Workbook

Sheet Base
A1: Nº | B1: N° Operación CMF | C1: Rut | D1: RUT | E1: DV | F1: Apellido paterno | G1: Apellido materno | H1: Nombres | I1: Género | J1: Segmento | K1: Pie | L1: Precio venta propiedad | M1: Subsidio | N1: Valor de tasación | O1: Tasa anual de emisión | P1: Tasa mensual de emisión | Q1: Plazo en meses | R1: Meses de gracia | S1: LTV | T1: Monto otorgado (UF) | U1: Valor cuota (UF) | V1: Valor última cuota (UF) | W1: Spread | X1: Tasa anual de endoso | Y1: Tasa mensual de endoso | Z1: Fecha de suscripción | AA1: Período primer aporte | AB1: Fecha de endoso | AC1: Fecha primer aporte a endosar | AD1: Fecha último aporte | AE1: Número de cuotas a endosar | AF1: VAN fecha endoso | AG1: Dirección | AH1: Comuna | AI1: Ciudad | AJ1: Region | AK1: Notaría | AL1: Dividendo/ Renta | AM1: Carga Financiera
A2: 1 | B2: 202401300028A033 | C2: 18028529-6 | D2: =LEFT(C2,LEN(C2)-2) -> 18028529 | E2: =RIGHT(C2,1) -> 6 | F2: Bobadilla | G2: Lopez | H2: Juan Pablo | I2: Masculino | J2: Subsidio | K2: 455 | L2: 2200 | M2: 375 | N2: 2400 | O2: 0.0783 | P2: 0.006301918 | Q2: 360 | R2: 5 | S2: 0.79318182 | T2: 1745 | U2: 12.71407 | V2: 13.752345 | W2: -0.004 | X2: 0.0743 | Y2: 0.0059903111 | Z2: 45321 | AA2: 45514 | AB2: 45351 | AC2: 45514 | AD2: 56290 | AE2: 355 | AF2: 1819.2749 | AG2: Camino La Vara 02600 , Edificio 3, Piso 2, Departamento 211, Estacionamiento 61 Uso y Goce | AH2: San Bernardo | AI2: Maipo | AJ2: Región Metropolitana de Santiago | AK2: María Soledad Lascar Merino | AL2: 0.25258541 | AM2: 0.48488599 | AN2: 5076 | AO2: OK
A3: 2 | B3: 202401310029A033 | C3: 17540548-8 | D3: =LEFT(C3,LEN(C3)-2) -> 17540548 | E3: =RIGHT(C3,1) -> 8 | F3: Carrillo | G3: Alarcon | H3: Francisco Javier | I3: Masculino | J3: Subsidio | K3: 440 | L3: 2200 | M3: 325 | N3: 2650 | O3: 0.0783 | P3: 0.006301918 | Q3: 360 | R3: 5 | S3: 0.8 | T3: 1760 | U3: 12.82336 | V3: 13.87056 | W3: -0.004 | X3: 0.0743 | Y3: 0.0059903111 | Z3: 45322 | AA3: 45514 | AB3: 45351 | AC3: 45514 | AD3: 56290 | AE3: 355 | AF3: 1835.0201 | AG3: Camino Segunda Faja Al Volcán 1260, Edificio ALLIPEN, Piso 4, Departamento 403, Estacionamiento 92 Uso y Goce | AH3: Villarrica | AI3: Cautín | AJ3: Región de La Araucanía | AK3: Elena Rosa Leyton Carvajal | AL3: 0.28239147 | AM3: 0.48306333 | AN3: 394 | AO3: OK
A4: 3 | B4: 202401310030A033 | C4: 18465199-8 | D4: =LEFT(C4,LEN(C4)-2) -> 18465199 | E4: =RIGHT(C4,1) -> 8 | F4: Mañan | G4: Valenzuela | H4: Vicente Tomas | I4: Masculino | J4: Subsidio | K4: 715 | L4: 2200 | M4: 625 | N4: 2200 | O4: 0.0783 | P4: 0.006301918 | Q4: 216 | R4: 5 | S4: 0.675 | T4: 1485 | U4: 13.15116 | V4: 12.92544 | W4: -0.004 | X4: 0.0743 | Y4: 0.0059903111 | Z4: 45322 | AA4: 45514 | AB4: 45351 | AC4: 45514 | AD4: 51907 | AE4: 211 | AF4: 1532.1686 | AG4: Avenida Santa Rosa 13240, Torre 3, Piso 1, Departamento 234 | AH4: La Pintana | AI4: Santiago | AJ4: Región Metropolitana de Santiago | AK4: María Soledad Lascar Merino | AL4: 0.13614764 | AM4: 0.27305764 | AN4: 5280 | AO4: OK
A5: 4 | B5: 202401310034A033 | C5: 15365153-1 | D5: =LEFT(C5,LEN(C5)-2) -> 15365153 | E5: =RIGHT(C5,1) -> 1 | F5: Jelves | G5: Sanchez | H5: Sebastian Andres | I5: Masculino | J5: Subsidio | K5: 893.66 | L5: 2400 | M5: 700 | N5: 2600 | O5: 0.0783 | P5: 0.006301918 | Q5: 360 | R5: 5 | S5: 0.62764167 | T5: 1506.34 | U5: 10.975193 | V5: 11.871466 | W5: -0.004 | X5: 0.0743 | Y5: 0.0059903111 | Z5: 45322 | AA5: 45514 | AB5: 45351 | AC5: 45514 | AD5: 56290 | AE5: 355 | AF5: 1571.6464 | AG5: Calle Miguel Campino 647, Mz D, Lote 5 | AH5: Paine | AI5: Maipo | AJ5: Región Metropolitana de Santiago | AK5: Wladimir Schramm López | AL5: 0.40079904 | AM5: 0.42389362 | AN5: 10574 | AO5: OK
A6: 5 | B6: 202401310036A033 | C6: 18187808-8 | D6: =LEFT(C6,LEN(C6)-2) -> 18187808 | E6: =RIGHT(C6,1) -> 8 | F6: Carvajal | G6: Guajardo | H6: Danahe Estefani | I6: Femenino | J6: Subsidio | K6: 780 | L6: 2065 | M6: 700 | N6: 2440 | O6: 0.0783 | P6: 0.006301918 | Q6: 360 | R6: 5 | S6: 0.62227603 | T6: 1285 | U6: 9.36251 | V6: 10.127085 | W6: -0.004 | X6: 0.0743 | Y6: 0.0059903111 | Z6: 45322 | AA6: 45514 | AB6: 45351 | AC6: 45514 | AD6: 56290 | AE6: 355 | AF6: 1339.7655 | AG6: Calle Del Toro 658, Mz D, Lote 33 | AH6: Paine | AI6: Maipo | AJ6: Región Metropolitana de Santiago | AK6: Wladimir Schramm López | AL6: 0.37717378 | AM6: 0.39792269 | AN6: 10563 | AO6: OK
A7: 6 | B7: 202401250039A033 | C7: 18245649-7 | D7: =LEFT(C7,LEN(C7)-2) -> 18245649 | E7: =RIGHT(C7,1) -> 7 | F7: Acevedo | G7: Monje | H7: Barbara Viviana | I7: Femenino | J7: Subsidio | K7: 494.87 | L7: 1400 | M7: 450 | N7: 1400 | O7: 0.0783 | P7: 0.006301918 | Q7: 180 | R7: 5 | S7: 0.64652143 | T7: 905.13 | U7: 8.825923 | V7: 8.777046 | W7: -0.004 | X7: 0.0743 | Y7: 0.0059903111 | Z7: 45316 | AA7: 45514 | AB7: 45351 | AC7: 45514 | AD7: 50811 | AE7: 175 | AF7: 931.14903 | AG7: Camino La Vara 02600, Torre 2, Piso 1, Departamento 101 | AH7: San Bernardo | AI7: Maipo | AJ7: Región Metropolitana de Santiago | AK7: María Soledad Lascar Merino | AL7: 0.41557874 | AM7: 0.4281181 | AN7: 4338 | AO7: OK
A8: 7 | B8: 202401310041A033 | C8: 15162947-4 | D8: =LEFT(C8,LEN(C8)-2) -> 15162947 | E8: =RIGHT(C8,1) -> 4 | F8: Palma | G8: Ponce | H8: Carola Del Carmen | I8: Femenino | J8: Subsidio | K8: 561.42 | L8: 1400 | M8: 500 | N8: 1800 | O8: 0.0783 | P8: 0.006301918 | Q8: 360 | R8: 5 | S8: 0.59898571 | T8: 838.58 | U8: 6.109894 | V8: 6.608849 | W8: -0.004 | X8: 0.0743 | Y8: 0.0059903111 | Z8: 45322 | AA8: 45514 | AB8: 45351 | AC8: 45514 | AD8: 56290 | AE8: 355 | AF8: 874.56881 | AG8: Rio Viejo 1123, Torre A, Piso 4, Departamento 407 A | AH8: Chillán | AI8: Diguillín | AJ8: Región de Ñuble | AK8: Luis Alvarez Diaz | AL8: 0.39962091 | AM8: 0.42110488 | AN8: 423 | AO8: OK
A9: 8 | B9: 202401310046A033 | C9: 16666807-7 | D9: =LEFT(C9,LEN(C9)-2) -> 16666807 | E9: =RIGHT(C9,1) -> 7 | F9: Acuña | G9: Mesías | H9: Kevin Joel | I9: Masculino | J9: Subsidio | K9: 979.93 | L9: 2325 | M9: 700 | N9: 2600 | O9: 0.0783 | P9: 0.006301918 | Q9: 144 | R9: 5 | S9: 0.57852473 | T9: 1345.07 | U9: 15.019052 | V9: 15.029812 | W9: -0.004 | X9: 0.0743 | Y9: 0.0059903111 | Z9: 45322 | AA9: 45514 | AB9: 45351 | AC9: 45514 | AD9: 49715 | AE9: 139 | AF9: 1377.8831 | AG9: Pasaje Copiapó Norte 071, Mz B, Lote 50 | AH9: Paine | AI9: Maipo | AJ9: Región Metropolitana de Santiago | AK9: Wladimir Schramm López | AL9: 0.37834186 | AM9: 0.40010103 | AN9: 10647 | AO9: OK
A10: 9 | B10: 202401310053A033 | C10: 14336994-3 | D10: =LEFT(C10,LEN(C10)-2) -> 14336994 | E10: =RIGHT(C10,1) -> 3 | F10: Valdes | G10: Molina | H10: Isabel Damari | I10: Femenino | J10: Subsidio | K10: 830 | L10: 1725 | M10: 750 | N10: 1725 | O10: 0.0783 | P10: 0.006301918 | Q10: 312 | R10: 5 | S10: 0.51884058 | T10: 895 | U10: 6.810055 | V10: 6.826165 | W10: -0.004 | X10: 0.0743 | Y10: 0.0059903111 | Z10: 45322 | AA10: 45514 | AB10: 45351 | AC10: 45514 | AD10: 54829 | AE10: 307 | AF10: 930.57378 | AG10: Pasaje Juan Vercellino Reginato 987, Mz E, Lote 9 | AH10: Rengo | AI10: Cachapoal | AJ10: Región del Libertador General Bernardo O'Higgins | AK10: Carla Silva Acharan | AL10: 0.2319673 | AM10: 0.25290877 | AN10: 280 | AO10: OK
A11: 10 | B11: 202401310054A033 | C11: 19580720-5 | D11: =LEFT(C11,LEN(C11)-2) -> 19580720 | E11: =RIGHT(C11,1) -> 5 | F11: Gonzalez | G11: Jaque | H11: Tabita Del Pilar | I11: Femenino | J11: Subsidio | K11: 830 | L11: 1725 | M11: 750 | N11: 1725 | O11: 0.0783 | P11: 0.006301918 | Q11: 228 | R11: 5 | S11: 0.51884058 | T11: 895 | U11: 7.722955 | V11: 7.72743 | W11: -0.004 | X11: 0.0743 | Y11: 0.0059903111 | Z11: 45322 | AA11: 45514 | AB11: 45351 | AC11: 45514 | AD11: 52272 | AE11: 223 | AF11: 924.16029 | AG11: Pasaje Elena Sanhueza Fajardo 794, Mz C, Lote 1 | AH11: Rengo | AI11: Cachapoal | AJ11: Región del Libertador General Bernardo O'Higgins | AK11: Carla Silva Acharan | AL11: 0.21381348 | AM11: 0.24493721 | AN11: 288 | AO11: OK
A12: 11 | B12: 202401310063A033 | C12: 14349421-7 | D12: =LEFT(C12,LEN(C12)-2) -> 14349421 | E12: =RIGHT(C12,1) -> 7 | F12: Ormeno | G12: Salazar | H12: Gino Rexner | I12: Masculino | J12: Subsidio | K12: 605 | L12: 2200 | M12: 525 | N12: 2325 | O12: 0.0783 | P12: 0.006301918 | Q12: 360 | R12: 5 | S12: 0.725 | T12: 1595 | U12: 11.62117 | V12: 12.570195 | W12: -0.004 | X12: 0.0743 | Y12: 0.0059903111 | Z12: 45322 | AA12: 45514 | AB12: 45351 | AC12: 45514 | AD12: 56290 | AE12: 355 | AF12: 1663.2551 | AG12: Pasaje La Cumbre 1 2505, Mz 8, Lote 4 | AH12: Los Ángeles | AI12: Biobío | AJ12: Región del Biobío | AK12: Maria Antonieta Carrillo Flores | AL12: 0.43872737 | AM12: 0.48266432 | AN12: 244 | AO12: OK
A13: 12 | B13: 202401310057A033 | C13: 14337194-8 | D13: =LEFT(C13,LEN(C13)-2) -> 14337194 | E13: =RIGHT(C13,1) -> 8 | F13: Osorio | G13: Briones | H13: Marcela Andrea | I13: Femenino | J13: Subsidio | K13: 830 | L13: 1725 | M13: 750 | N13: 1725 | O13: 0.0783 | P13: 0.006301918 | Q13: 348 | R13: 5 | S13: 0.51884058 | T13: 895 | U13: 6.58362 | V13: 6.391195 | W13: -0.004 | X13: 0.0743 | Y13: 0.0059903111 | Z13: 45322 | AA13: 45514 | AB13: 45351 | AC13: 45514 | AD13: 55925 | AE13: 343 | AF13: 932.21409 | AG13: Pasaje Raquel Labarca Urzua 759, Mz C, Lote 9 | AH13: Rengo | AI13: Cachapoal | AJ13: Región del Libertador General Bernardo O'Higgins | AK13: Carla Silva Acharan | AL13: 0.11836401 | AM13: 0.41558002 | AN13: 285 | AO13: OK
... A35: 34 | B35: 202402260086A033 | C35: 11392169-2 | D35: =LEFT(C35,LEN(C35)-2) -> 11392169 | E35: =RIGHT(C35,1) -> 2 | F35: Donoso | G35: Valdebenito | H35: Raul Cristian | I35: Masculino | J35: Subsidio | K35: 780 | L35: 2400 | M35: 700 | N35: 2600 | O35: 0.0759 | P35: 0.0061150813 | Q35: 300 | R35: 5 | S35: 0.675 | T35: 1620 | U35: 12.2391 | V35: 12.33468 | W35: -0.004 | X35: 0.0719 | Y35: 0.0058028362 | Z35: 45348 | AA35: 45545 | AB35: 45351 | AC35: 45545 | AD35: 54492 | AE35: 295 | AF35: 1673.7345 | AG35: CALLE DEL TORO 1306 | AH35: Paine | AI35: Maipo | AJ35: Región Metropolitana de Santiago | AK35: Wladimir Schramm López | AL35: 0.30137122 | AM35: 0.5317244 | AN35: 19368 | AO35: DD OK
A36: 35 | B36: 202402220087A033 | C36: 20039829-7 | D36: =LEFT(C36,LEN(C36)-2) -> 20039829 | E36: =RIGHT(C36,1) -> 7 | F36: Medel | G36: Bustos | H36: Pablo Andres | I36: Masculino | J36: Subsidio | K36: 680 | L36: 2400 | M36: 600 | N36: 2400 | O36: 0.0759 | P36: 0.0061150813 | Q36: 360 | R36: 5 | S36: 0.71666667 | T36: 1720 | U36: 12.24984 | V36: 12.6334 | W36: -0.004 | X36: 0.0719 | Y36: 0.0058028362 | Z36: 45344 | AA36: 45545 | AB36: 45351 | AC36: 45545 | AD36: 56318 | AE36: 355 | AF36: 1784.0307 | AG36: CALLE VICTOR MANUEL SAAVEDRA CAMPOS (DIRIGENTE) 412 | AH36: Rengo | AI36: Cachapoal | AJ36: Región del Libertador General Bernardo O'Higgins | AK36: Andrés Falcón Valencia | AL36: 0.30884557 | AM36: 0.3714098 | AN36: N/A | AO36: DD OK
A37: 36 | B37: 202402260088A033 | C37: 16377478-K | D37: =LEFT(C37,LEN(C37)-2) -> 16377478 | E37: =RIGHT(C37,1) -> K | F37: Parra | G37: Gálvez | H37: Angie Marcela | I37: Femenino | J37: Subsidio | K37: 743.35 | L37: 2325 | M37: 700 | N37: 2600 | O37: 0.0759 | P37: 0.0061150813 | Q37: 360 | R37: 5 | S37: 0.68027957 | T37: 1581.65 | U37: 11.264511 | V37: 11.617219 | W37: -0.004 | X37: 0.0719 | Y37: 0.0058028362 | Z37: 45348 | AA37: 45545 | AB37: 45351 | AC37: 45545 | AD37: 56318 | AE37: 355 | AF37: 1639.8532 | AG37: PASAJE COPIAPÓ NORTE 070 | AH37: Paine | AI37: Maipo | AJ37: Región Metropolitana de Santiago | AK37: Wladimir Schramm López | AL37: 0.22315429 | AM37: 0.35014293 | AN37: 19404 | AO37: DD OK
A38: 37 | B38: 202402270089A033 | C38: 16597475-1 | D38: =LEFT(C38,LEN(C38)-2) -> 16597475 | E38: =RIGHT(C38,1) -> 1 | F38: Cortes | G38: Rodriguez | H38: Ruben Alex | I38: Masculino | J38: Subsidio | K38: 470 | L38: 2100 | M38: 375 | N38: 2100 | O38: 0.0759 | P38: 0.0061150813 | Q38: 360 | R38: 5 | S38: 0.77619048 | T38: 1630 | U38: 11.60886 | V38: 11.97235 | W38: -0.004 | X38: 0.0719 | Y38: 0.0058028362 | Z38: 45349 | AA38: 45545 | AB38: 45351 | AC38: 45545 | AD38: 56318 | AE38: 355 | AF38: 1690.8242 | AG38: Alemania 30, Edificio 3 | AH38: Viña del Mar | AI38: Valparaíso | AJ38: Región de Valparaíso | AK38: Luis Enrique Fischer Yavar | AL38: 0.25436079 | AM38: 0.35435235 | AN38: 2024 | AO38: DD OK
A39: 38 | B39: 202402270090A033 | C39: 12406726-K | D39: =LEFT(C39,LEN(C39)-2) -> 12406726 | E39: =RIGHT(C39,1) -> K | F39: Morales | G39: Sanchez | H39: Ivonne Arlette | I39: Femenino | J39: Subsidio | K39: 504 | L39: 1400 | M39: 450 | N39: 1400 | O39: 0.0759 | P39: 0.0061150813 | Q39: 336 | R39: 5 | S39: 0.64 | T39: 896 | U39: 6.514816 | V39: 6.33472 | W39: -0.004 | X39: 0.0719 | Y39: 0.0058028362 | Z39: 45349 | AA39: 45545 | AB39: 45351 | AC39: 45545 | AD39: 55588 | AE39: 331 | AF39: 927.26287 | AG39: PASAJE EXEQUIEL SANCHEZ BALMACEDA (PROFESOR) 1708 | AH39: Rengo | AI39: Cachapoal | AJ39: Región del Libertador General Bernardo O'Higgins | AK39: Andrés Falcón Valencia | AL39: 0.18231278 | AM39: 0.30271257 | AN39: N/A | AO39: DD OK
A40: 39 | B40: 202402280091A033 | C40: 18452074-5 | D40: =LEFT(C40,LEN(C40)-2) -> 18452074 | E40: =RIGHT(C40,1) -> 5 | F40: Aguilera | G40: Benedetti | H40: Natalia Pamela | I40: Femenino | J40: Subsidio | K40: 540 | L40: 1400 | M40: 500 | N40: 1400 | O40: 0.0759 | P40: 0.0061150813 | Q40: 360 | R40: 5 | S40: 0.61428571 | T40: 860 | U40: 6.12492 | V40: 6.3167 | W40: -0.004 | X40: 0.0719 | Y40: 0.0058028362 | Z40: 45350 | AA40: 45545 | AB40: 45351 | AC40: 45545 | AD40: 56318 | AE40: 355 | AF40: 891.28843 | AG40: Camino Las Rosas 518, Edificio 12 | AH40: Chillán | AI40: Diguillín | AJ40: Región de Ñuble | AK40: Luis Álvarez Diaz | AL40: 0.091882356 | AM40: 0.25231874 | AN40: 842 | AO40: Firmada
A41: 40 | B41: 202402240093A033 | C41: 20614987-6 | D41: =LEFT(C41,LEN(C41)-2) -> 20614987 | E41: =RIGHT(C41,1) -> 6 | F41: Perez | G41: Avalos | H41: Belen Del Carmen | I41: Femenino | J41: Subsidio | K41: 780 | L41: 1990 | M41: 700 | N41: 2200 | O41: 0.0759 | P41: 0.0061150813 | Q41: 360 | R41: 5 | S41: 0.6080402 | T41: 1210 | U41: 8.61762 | V41: 8.88745 | W41: -0.004 | X41: 0.0719 | Y41: 0.0058028362 | Z41: 45346 | AA41: 45545 | AB41: 45351 | AC41: 45545 | AD41: 56318 | AE41: 355 | AF41: 1255.3754 | AG41: Matta Vial 635 | AH41: San Joaquín | AI41: Santiago | AJ41: Región Metropolitana de Santiago | AK41: Pablo Martínez Loaiza | AL41: 0.26464127 | AM41: 0.50420421 | AN41: 3957 | AO41: DD OK
A42: 41 | B42: 202402270094A033 | C42: 22607181-4 | D42: =LEFT(C42,LEN(C42)-2) -> 22607181 | E42: =RIGHT(C42,1) -> 4 | F42: Lopez | G42: Tineo | H42: Hector | I42: Masculino | J42: Subsidio | K42: 680 | L42: 2400 | M42: 600 | N42: 2400 | O42: 0.0759 | P42: 0.0061150813 | Q42: 360 | R42: 5 | S42: 0.71666667 | T42: 1720 | U42: 12.24984 | V42: 12.6334 | W42: -0.004 | X42: 0.0719 | Y42: 0.0058028362 | Z42: 45349 | AA42: 45545 | AB42: 45351 | AC42: 45545 | AD42: 56318 | AE42: 355 | AF42: 1784.0307 | AG42: PASAJE AGUSTO SANCHEZ BALMACEDA (PROFESOR) 1709 | AH42: Rengo | AI42: Cachapoal | AJ42: Región del Libertador General Bernardo O'Higgins | AK42: Andrés Falcón Valencia | AL42: 0.25324608 | AM42: 0.31799542 | AN42: N/A | AO42: DD OK
A43: 42 | B43: 202402260095A033 | C43: 18916005-4 | D43: =LEFT(C43,LEN(C43)-2) -> 18916005 | E43: =RIGHT(C43,1) -> 4 | F43: Espinoza | G43: Huerta | H43: Daniela Mackarena | I43: Femenino | J43: Subsidio | K43: 505 | L43: 1870 | M43: 425 | N43: 2100 | O43: 0.0759 | P43: 0.0061150813 | Q43: 216 | R43: 5 | S43: 0.72994652 | T43: 1365 | U43: 11.890515 | V43: 11.857755 | W43: -0.004 | X43: 0.0719 | Y43: 0.0058028362 | Z43: 45348 | AA43: 45545 | AB43: 45351 | AC43: 45545 | AD43: 51935 | AE43: 211 | AF43: 1400.3211 | AG43: San Enrique 1398, Edificio 2 | AH43: Villa Alemana | AI43: Marga Marga | AJ43: Región de Valparaíso | AK43: Luis Enrique Fischer Yavar | AL43: 0.21950803 | AM43: 0.34815283 | AN43: 2019 | AO43: Firmada

Sheet Valo FX
V1: valor Creditú
I2: Monto Crédito + Cap (UF) | P2: Tasa endoso | Q2: Fecha 1er Aporte a endosar | R2: Fecha Last Aporte | S2: Fecha Corte | U2: VPN | V2: Tasa mensual de endoso | X2: Tasacion | Y2: Precio Venta/Tasación | Z2: Tasa Endoso | AA2: Monto Dividendo | AB2: Dividendo/ Renta | AC2: Carga Financiera/ Renta
A3: Nº | B3: N° Operación | C3: Apellido paterno | D3: Apellido materno | E3: Nombres | F3: Rut | G3: DV | H3: Leasing o Mutuo | J3: Subsidio | K3: Pie | L3: Valor Vivienda | M3: Morosidad | N3: Nº Cuotas | O3: Primera cuota a endosar | T3: 45361 | U3: 45351 | W3: Saldo insoluto Teórico | AD3: Dirección de la Propiedad | AE3: Codigo Comuna | AF3: Comuna
A4: =+Base!A2 -> 1 | B4: =+Base!B2 -> 202401300028A033 | C4: =+Base!F2 -> Bobadilla | D4: =+Base!G2 -> Lopez | E4: =+Base!H2 -> Juan Pablo | F4: =+Base!D2 -> 18028529 | G4: =+Base!E2 -> 6 | H4: MHE | I4: =+Base!T2 -> 1745 | J4: =+Base!M2 -> 375 | K4: =+L4-J4-I4 -> 80 | L4: =+Base!L2 -> 2200 | M4: 0 | N4: =+Base!Q2 -> 360 | O4: =+Base!R2+1 -> 6 | P4: =+XIRR('Tabla desarrollo FX'!B3:MY3,'Tabla desarrollo FX'!$B$1:$MY$1) -> 0.07403166 | Q4: =+Base!AA2 -> 45514 | R4: =+Base!AD2 -> 56290 | S4: =T3 -> 45361 | T4: =+NPV(V4,'Tabla desarrollo FX'!D3:MY3) -> 1823.765 | U4: =+Base!AF2 -> 1819.2749 | V4: =+Base!Y2 -> 0.0059903111 | X4: =+Base!N2 -> 2400 | Y4: =+U4/X4 -> 0.7580312 | Z4: =+P4-Base!O2 -> -0.00426834 | AA4: =+Base!U2 -> 12.71407 | AB4: =+Base!AL2*100 -> 25.258541 | AC4: =+Base!AM2*100 -> 48.488599 | AD4: =+Base!AG2 -> Camino La Vara 02600 , Edificio 3, Piso 2, Departamento 211, Estacionamiento 61 Uso y Goce | AE4: 4103 | AF4: =+Base!AI2 -> Maipo
A5: =+Base!A3 -> 2 | B5: =+Base!B3 -> 202401310029A033 | C5: =+Base!F3 -> Carrillo | D5: =+Base!G3 -> Alarcon | E5: =+Base!H3 -> Francisco Javier | F5: =+Base!D3 -> 17540548 | G5: =+Base!E3 -> 8 | H5: MHE | I5: =+Base!T3 -> 1760 | J5: =+Base!M3 -> 325 | K5: =+L5-J5-I5 -> 115 | L5: =+Base!L3 -> 2200 | M5: 0 | N5: =+Base!Q3 -> 360 | O5: =+Base!R3+1 -> 6 | P5: =+XIRR('Tabla desarrollo FX'!B4:MY4,'Tabla desarrollo FX'!$B$1:$MY$1) -> 0.07403166 | Q5: =+Base!AA3 -> 45514 | R5: =+Base!AD3 -> 56290 | S5: =S4 -> 45361 | T5: =+NPV(V5,'Tabla desarrollo FX'!D4:MY4) -> 1839.4421 | U5: =+Base!AF3 -> 1835.0201 | V5: =+Base!Y3 -> 0.0059903111 | X5: =+Base!N3 -> 2650 | Y5: =+U5/X5 -> 0.69246041 | Z5: =+P5-Base!O3 -> -0.00426834 | AA5: =+Base!U3 -> 12.82336 | AB5: =+Base!AL3*100 -> 28.239147 | AC5: =+Base!AM3*100 -> 48.306333 | AD5: =+Base!AG3 -> Camino Segunda Faja Al Volcán 1260, Edificio ALLIPEN, Piso 4, Departamento 403, Estacionamiento 92 Uso y Goce | AE5: 4103 | AF5: =+Base!AI3 -> Cautín
A6: =+Base!A4 -> 3 | B6: =+Base!B4 -> 202401310030A033 | C6: =+Base!F4 -> Mañan | D6: =+Base!G4 -> Valenzuela | E6: =+Base!H4 -> Vicente Tomas | F6: =+Base!D4 -> 18465199 | G6: =+Base!E4 -> 8 | H6: MHE | I6: =+Base!T4 -> 1485 | J6: =+Base!M4 -> 625 | K6: =+L6-J6-I6 -> 90 | L6: =+Base!L4 -> 2200 | M6: 0 | N6: =+Base!Q4 -> 216 | O6: =+Base!R4+1 -> 6 | P6: =+XIRR('Tabla desarrollo FX'!B5:MY5,'Tabla desarrollo FX'!$B$1:$MY$1) -> 0.073945948 | Q6: =+Base!AA4 -> 45514 | R6: =+Base!AD4 -> 51907 | S6: =S5 -> 45361 | T6: =+NPV(V6,'Tabla desarrollo FX'!D5:MY5) -> 1535.5941 | U6: =+Base!AF4 -> 1532.1686 | V6: =+Base!Y4 -> 0.0059903111 | X6: =+Base!N4 -> 2200 | Y6: =+U6/X6 -> 0.69644028 | Z6: =+P6-Base!O4 -> -0.0043540515 | AA6: =+Base!U4 -> 13.15116 | AB6: =+Base!AL4*100 -> 13.614764 | AC6: =+Base!AM4*100 -> 27.305764 | AD6: =+Base!AG4 -> Avenida Santa Rosa 13240, Torre 3, Piso 1, Departamento 234 | AE6: 4103 | AF6: =+Base!AI4 -> Santiago
A7: =+Base!A5 -> 4 | B7: =+Base!B5 -> 202401310034A033 | C7: =+Base!F5 -> Jelves | D7: =+Base!G5 -> Sanchez | E7: =+Base!H5 -> Sebastian Andres | F7: =+Base!D5 -> 15365153 | G7: =+Base!E5 -> 1 | H7: MHE | I7: =+Base!T5 -> 1506.34 | J7: =+Base!M5 -> 700 | K7: =+L7-J7-I7 -> 193.66 | L7: =+Base!L5 -> 2400 | M7: 0 | N7: =+Base!Q5 -> 360 | O7: =+Base!R5+1 -> 6 | P7: =+XIRR('Tabla desarrollo FX'!B6:MY6,'Tabla desarrollo FX'!$B$1:$MY$1) -> 0.07403166 | Q7: =+Base!AA5 -> 45514 | R7: =+Base!AD5 -> 56290 | S7: =S6 -> 45361 | T7: =+NPV(V7,'Tabla desarrollo FX'!D6:MY6) -> 1574.3324 | U7: =+Base!AF5 -> 1571.6464 | V7: =+Base!Y5 -> 0.0059903111 | X7: =+Base!N5 -> 2600 | Y7: =+U7/X7 -> 0.60447938 | Z7: =+P7-Base!O5 -> -0.00426834 | AA7: =+Base!U5 -> 10.975193 | AB7: =+Base!AL5*100 -> 40.079904 | AC7: =+Base!AM5*100 -> 42.389362 | AD7: =+Base!AG5 -> Calle Miguel Campino 647, Mz D, Lote 5 | AE7: 4103 | AF7: =+Base!AI5 -> Maipo
A8: =+Base!A6 -> 5 | B8: =+Base!B6 -> 202401310036A033 | C8: =+Base!F6 -> Carvajal | D8: =+Base!G6 -> Guajardo | E8: =+Base!H6 -> Danahe Estefani | F8: =+Base!D6 -> 18187808 | G8: =+Base!E6 -> 8 | H8: MHE | I8: =+Base!T6 -> 1285 | J8: =+Base!M6 -> 700 | K8: =+L8-J8-I8 -> 80 | L8: =+Base!L6 -> 2065 | M8: 0 | N8: =+Base!Q6 -> 360 | O8: =+Base!R6+1 -> 6 | P8: =+XIRR('Tabla desarrollo FX'!B7:MY7,'Tabla desarrollo FX'!$B$1:$MY$1) -> 0.07403166 | Q8: =+Base!AA6 -> 45514 | R8: =+Base!AD6 -> 56290 | S8: =S7 -> 45361 | T8: =+NPV(V8,'Tabla desarrollo FX'!D7:MY7) -> 1343.0017 | U8: =+Base!AF6 -> 1339.7655 | V8: =+Base!Y6 -> 0.0059903111 | X8: =+Base!N6 -> 2440 | Y8: =+U8/X8 -> 0.5490842 | Z8: =+P8-Base!O6 -> -0.00426834 | AA8: =+Base!U6 -> 9.36251 | AB8: =+Base!AL6*100 -> 37.717378 | AC8: =+Base!AM6*100 -> 39.792269 | AD8: =+Base!AG6 -> Calle Del Toro 658, Mz D, Lote 33 | AE8: 4103 | AF8: =+Base!AI6 -> Maipo
A9: =+Base!A7 -> 6 | B9: =+Base!B7 -> 202401250039A033 | C9: =+Base!F7 -> Acevedo | D9: =+Base!G7 -> Monje | E9: =+Base!H7 -> Barbara Viviana | F9: =+Base!D7 -> 18245649 | G9: =+Base!E7 -> 7 | H9: MHE | I9: =+Base!T7 -> 905.13 | J9: =+Base!M7 -> 450 | K9: =+L9-J9-I9 -> 44.87 | L9: =+Base!L7 -> 1400 | M9: 0 | N9: =+Base!Q7 -> 180 | O9: =+Base!R7+1 -> 6 | P9: =+XIRR('Tabla desarrollo FX'!B8:MY8,'Tabla desarrollo FX'!$B$1:$MY$1) -> 0.073901585 | Q9: =+Base!AA7 -> 45514 | R9: =+Base!AD7 -> 50811 | S9: =S8 -> 45361 | T9: =+NPV(V9,'Tabla desarrollo FX'!D8:MY8) -> 932.71931 | U9: =+Base!AF7 -> 931.14903 | V9: =+Base!Y7 -> 0.0059903111 | X9: =+Base!N7 -> 1400 | Y9: =+U9/X9 -> 0.66510645 | Z9: =+P9-Base!O7 -> -0.0043984153 | AA9: =+Base!U7 -> 8.825923 | AB9: =+Base!AL7*100 -> 41.557874 | AC9: =+Base!AM7*100 -> 42.81181 | AD9: =+Base!AG7 -> Camino La Vara 02600, Torre 2, Piso 1, Departamento 101 | AE9: 4103 | AF9: =+Base!AI7 -> Maipo
A10: =+Base!A8 -> 7 | B10: =+Base!B8 -> 202401310041A033 | C10: =+Base!F8 -> Palma | D10: =+Base!G8 -> Ponce | E10: =+Base!H8 -> Carola Del Carmen | F10: =+Base!D8 -> 15162947 | G10: =+Base!E8 -> 4 | H10: MHE | I10: =+Base!T8 -> 838.58 | J10: =+Base!M8 -> 500 | K10: =+L10-J10-I10 -> 61.42 | L10: =+Base!L8 -> 1400 | M10: 0 | N10: =+Base!Q8 -> 360 | O10: =+Base!R8+1 -> 6 | P10: =+XIRR('Tabla desarrollo FX'!B9:MY9,'Tabla desarrollo FX'!$B$1:$MY$1) -> 0.07403166 | Q10: =+Base!AA8 -> 45514 | R10: =+Base!AD8 -> 56290 | S10: =S9 -> 45361 | T10: =+NPV(V10,'Tabla desarrollo FX'!D9:MY9) -> 876.43145 | U10: =+Base!AF8 -> 874.56881 | V10: =+Base!Y8 -> 0.0059903111 | X10: =+Base!N8 -> 1800 | Y10: =+U10/X10 -> 0.48587156 | Z10: =+P10-Base!O8 -> -0.00426834 | AA10: =+Base!U8 -> 6.109894 | AB10: =+Base!AL8*100 -> 39.962091 | AC10: =+Base!AM8*100 -> 42.110488 | AD10: =+Base!AG8 -> Rio Viejo 1123, Torre A, Piso 4, Departamento 407 A | AE10: 4103 | AF10: =+Base!AI8 -> Diguillín
A11: =+Base!A9 -> 8 | B11: =+Base!B9 -> 202401310046A033 | C11: =+Base!F9 -> Acuña | D11: =+Base!G9 -> Mesías | E11: =+Base!H9 -> Kevin Joel | F11: =+Base!D9 -> 16666807 | G11: =+Base!E9 -> 7 | H11: MHE | I11: =+Base!T9 -> 1345.07 | J11: =+Base!M9 -> 700 | K11: =+L11-J11-I11 -> 279.93 | L11: =+Base!L9 -> 2325 | M11: 0 | N11: =+Base!Q9 -> 144 | O11: =+Base!R9+1 -> 6 | P11: =+XIRR('Tabla desarrollo FX'!B10:MY10,'Tabla desarrollo FX'!$B$1:$MY$1) -> 0.073835269 | Q11: =+Base!AA9 -> 45514 | R11: =+Base!AD9 -> 49715 | S11: =S10 -> 45361 | T11: =+NPV(V11,'Tabla desarrollo FX'!D10:MY10) -> 1380.7573 | U11: =+Base!AF9 -> 1377.8831 | V11: =+Base!Y9 -> 0.0059903111 | X11: =+Base!N9 -> 2600 | Y11: =+U11/X11 -> 0.52995503 | Z11: =+P11-Base!O9 -> -0.0044647314 | AA11: =+Base!U9 -> 15.019052 | AB11: =+Base!AL9*100 -> 37.834186 | AC11: =+Base!AM9*100 -> 40.010103 | AD11: =+Base!AG9 -> Pasaje Copiapó Norte 071, Mz B, Lote 50 | AE11: 4103 | AF11: =+Base!AI9 -> Maipo
A12: =+Base!A10 -> 9 | B12: =+Base!B10 -> 202401310053A033 | C12: =+Base!F10 -> Valdes | D12: =+Base!G10 -> Molina | E12: =+Base!H10 -> Isabel Damari | F12: =+Base!D10 -> 14336994 | G12: =+Base!E10 -> 3 | H12: MHE | I12: =+Base!T10 -> 895 | J12: =+Base!M10 -> 750 | K12: =+L12-J12-I12 -> 80 | L12: =+Base!L10 -> 1725 | M12: 0 | N12: =+Base!Q10 -> 312 | O12: =+Base!R10+1 -> 6 | P12: =+XIRR('Tabla desarrollo FX'!B11:MY11,'Tabla desarrollo FX'!$B$1:$MY$1) -> 0.074012646 | Q12: =+Base!AA10 -> 45514 | R12: =+Base!AD10 -> 54829 | S12: =S11 -> 45361 | T12: =+NPV(V12,'Tabla desarrollo FX'!D11:MY11) -> 932.57912 | U12: =+Base!AF10 -> 930.57378 | V12: =+Base!Y10 -> 0.0059903111 | X12: =+Base!N10 -> 1725 | Y12: =+U12/X12 -> 0.53946306 | Z12: =+P12-Base!O10 -> -0.0042873539 | AA12: =+Base!U10 -> 6.810055 | AB12: =+Base!AL10*100 -> 23.19673 | AC12: =+Base!AM10*100 -> 25.290877 | AD12: =+Base!AG10 -> Pasaje Juan Vercellino Reginato 987, Mz E, Lote 9 | AE12: 4103 | AF12: =+Base!AI10 -> Cachapoal
A13: =+Base!A11 -> 10 | B13: =+Base!B11 -> 202401310054A033 | C13: =+Base!F11 -> Gonzalez | D13: =+Base!G11 -> Jaque | E13: =+Base!H11 -> Tabita Del Pilar | F13: =+Base!D11 -> 19580720 | G13: =+Base!E11 -> 5 | H13: MHE | I13: =+Base!T11 -> 895 | J13: =+Base!M11 -> 750 | K13: =+L13-J13-I13 -> 80 | L13: =+Base!L11 -> 1725 | M13: 0 | N13: =+Base!Q11 -> 228 | O13: =+Base!R11+1 -> 6 | P13: =+XIRR('Tabla desarrollo FX'!B12:MY12,'Tabla desarrollo FX'!$B$1:$MY$1) -> 0.073957667 | Q13: =+Base!AA11 -> 45514 | R13: =+Base!AD11 -> 52272 | S13: =S12 -> 45361 | T13: =+NPV(V13,'Tabla desarrollo FX'!D12:MY12) -> 926.49862 | U13: =+Base!AF11 -> 924.16029 | V13: =+Base!Y11 -> 0.0059903111 | X13: =+Base!N11 -> 1725 | Y13: =+U13/X13 -> 0.5357451 | Z13: =+P13-Base!O11 -> -0.0043423332 | AA13: =+Base!U11 -> 7.722955 | AB13: =+Base!AL11*100 -> 21.381348 | AC13: =+Base!AM11*100 -> 24.493721 | AD13: =+Base!AG11 -> Pasaje Elena Sanhueza Fajardo 794, Mz C, Lote 1 | AE13: 4103 | AF13: =+Base!AI11 -> Cachapoal
A14: =+Base!A12 -> 11 | B14: =+Base!B12 -> 202401310063A033 | C14: =+Base!F12 -> Ormeno | D14: =+Base!G12 -> Salazar | E14: =+Base!H12 -> Gino Rexner | F14: =+Base!D12 -> 14349421 | G14: =+Base!E12 -> 7 | H14: MHE | I14: =+Base!T12 -> 1595 | J14: =+Base!M12 -> 525 | K14: =+L14-J14-I14 -> 80 | L14: =+Base!L12 -> 2200 | M14: 0 | N14: =+Base!Q12 -> 360 | O14: =+Base!R12+1 -> 6 | P14: =+XIRR('Tabla desarrollo FX'!B13:MY13,'Tabla desarrollo FX'!$B$1:$MY$1) -> 0.07403166 | Q14: =+Base!AA12 -> 45514 | R14: =+Base!AD12 -> 56290 | S14: =S13 -> 45361 | T14: =+NPV(V14,'Tabla desarrollo FX'!D13:MY13) -> 1666.9944 | U14: =+Base!AF12 -> 1663.2551 | V14: =+Base!Y12 -> 0.0059903111 | X14: =+Base!N12 -> 2325 | Y14: =+U14/X14 -> 0.71537856 | Z14: =+P14-Base!O12 -> -0.00426834 | AA14: =+Base!U12 -> 11.62117 | AB14: =+Base!AL12*100 -> 43.872737 | AC14: =+Base!AM12*100 -> 48.266432 | AD14: =+Base!AG12 -> Pasaje La Cumbre 1 2505, Mz 8, Lote 4 | AE14: 4103 | AF14: =+Base!AI12 -> Biobío
A15: =+Base!A13 -> 12 | B15: =+Base!B13 -> 202401310057A033 | C15: =+Base!F13 -> Osorio | D15: =+Base!G13 -> Briones | E15: =+Base!H13 -> Marcela Andrea | F15: =+Base!D13 -> 14337194 | G15: =+Base!E13 -> 8 | H15: MHE | I15: =+Base!T13 -> 895 | J15: =+Base!M13 -> 750 | K15: =+L15-J15-I15 -> 80 | L15: =+Base!L13 -> 1725 | M15: 0 | N15: =+Base!Q13 -> 348 | O15: =+Base!R13+1 -> 6 | P15: =+XIRR('Tabla desarrollo FX'!B14:MY14,'Tabla desarrollo FX'!$B$1:$MY$1) -> 0.07402747 | Q15: =+Base!AA13 -> 45514 | R15: =+Base!AD13 -> 55925 | S15: =S14 -> 45361 | T15: =+NPV(V15,'Tabla desarrollo FX'!D14:MY14) -> 934.72947 | U15: =+Base!AF13 -> 932.21409 | V15: =+Base!Y13 -> 0.0059903111 | X15: =+Base!N13 -> 1725 | Y15: =+U15/X15 -> 0.54041396 | Z15: =+P15-Base!O13 -> -0.0042725302 | AA15: =+Base!U13 -> 6.58362 | AB15: =+Base!AL13*100 -> 11.836401 | AC15: =+Base!AM13*100 -> 41.558002 | AD15: =+Base!AG13 -> Pasaje Raquel Labarca Urzua 759, Mz C, Lote 9 | AE15: 4103 | AF15: =+Base!AI13 -> Cachapoal
A16: =+Base!A14 -> 13 | B16: =+Base!B14 -> 202401300058A033 | C16: =+Base!F14 -> Lopez | D16: =+Base!G14 -> Lopez | E16: =+Base!H14 -> Oscar Patricio | F16: =+Base!D14 -> 14009431 | G16: =+Base!E14 -> 5 | H16: MHE | I16: =+Base!T14 -> 1620 | J16: =+Base!M14 -> 700 | K16: =+L16-J16-I16 -> 80 | L16: =+Base!L14 -> 2400 | M16: 0 | N16: =+Base!Q14 -> 360 | O16: =+Base!R14+1 -> 6 | P16: =+XIRR('Tabla desarrollo FX'!B15:MY15,'Tabla desarrollo FX'!$B$1:$MY$1) -> 0.07403166 | Q16: =+Base!AA14 -> 45514 | R16: =+Base!AD14 -> 56290 | S16: =S15 -> 45361 | T16: =+NPV(V16,'Tabla desarrollo FX'!D15:MY15) -> 1693.1228 | U16: =+Base!AF14 -> 1689.0205 | V16: =+Base!Y14 -> 0.0059903111 | X16: =+Base!N14 -> 2600 | Y16: =+U16/X16 -> 0.64962326 | Z16: =+P16-Base!O14 -> -0.00426834 | AA16: =+Base!U14 -> 11.80332 | AB16: =+Base!AL14*100 -> 37.803514 | AC16: =+Base!AM14*100 -> 39.886891 | AD16: =+Base!AG14 -> Avenida Los Héroes 1328, Mz B, Lote 9 | AE16: 4103 | AF16: =+Base!AI14 -> Maipo
... A45: =+Base!A43 -> 42 | B45: =+Base!B43 -> 202402260095A033 | C45: =+Base!F43 -> Espinoza | D45: =+Base!G43 -> Huerta | E45: =+Base!H43 -> Daniela Mackarena | F45: =+Base!D43 -> 18916005 | G45: =+Base!E43 -> 4 | H45: MHE | I45: =+Base!T43 -> 1365 | J45: =+Base!M43 -> 425 | K45: =+L45-J45-I45 -> 80 | L45: =+Base!L43 -> 1870 | M45: 21 | N45: =+Base!Q43 -> 216 | O45: =+Base!R43+1 -> 6 | P45: =+XIRR('Tabla desarrollo FX'!B44:MY44,'Tabla desarrollo FX'!$B$1:$MY$1) -> 0.071563181 | Q45: =+Base!AA43 -> 45545 | R45: =+Base!AD43 -> 51935 | S45: =S44 -> 45361 | T45: =+NPV(V45,'Tabla desarrollo FX'!D44:MY44) -> 1403.4494 | U45: =+Base!AF43 -> 1400.3211 | V45: =+Base!Y43 -> 0.0058028362 | X45: =+Base!N43 -> 2100 | Y45: =+U45/X45 -> 0.66681958 | Z45: =+P45-Base!O43 -> -0.0043368187 | AA45: =+Base!U43 -> 11.890515 | AB45: =+Base!AL43*100 -> 21.950803 | AC45: =+Base!AM43*100 -> 34.815283 | AD45: =+Base!AG43 -> San Enrique 1398, Edificio 2 | AE45: 4103 | AF45: =+Base!AI43 -> Marga Marga

Sheet Valo
U1: =+SUM(U4:U45) -> 62799.219 | V1: 1 | X1: 1
I2: Monto Crédito + Cap (UF) | P2: Tasa endoso | Q2: Fecha 1er Aporte a endosar | R2: Fecha Last Aporte | S2: Fecha Corte | U2: VPN | V2: Tasa mensual de endoso | X2: Tasacion | Y2: Precio Venta/Tasación | Z2: Tasa Endoso | AA2: Monto Dividendo | AB2: Dividendo/ Renta | AC2: Carga Financiera/ Renta
A3: Nº | B3: N° Operación | C3: Apellido paterno | D3: Apellido materno | E3: Nombres | F3: Rut | G3: DV | H3: Leasing o Mutuo | J3: Subsidio | K3: Pie | L3: Valor Vivienda | M3: Morosidad | N3: Nº Cuotas | O3: Primera cuota a endosar | T3: 45332 | U3: 45351 | W3: Saldo insoluto Teórico | AD3: Dirección de la Propiedad | AE3: Codigo Comuna | AF3: Comuna
A4: 1 | B4: 202401300028A033 | C4: Bobadilla | D4: Lopez | E4: Juan Pablo | F4: 18028529 | G4: 6 | H4: MHE | I4: 1745 | J4: 375 | K4: 80 | L4: 2200 | M4: 0 | N4: 360 | O4: 6 | P4: 0.074653056 | Q4: 45514 | R4: 56290 | S4: 45332 | T4: 1812.9051 | U4: 1819.2749 | V4: 0.0059903111 | X4: 2400 | Y4: 0.7580312 | Z4: -0.0036469437 | AA4: 12.71407 | AB4: 25.258541 | AC4: 48.488599 | AD4: Camino La Vara 02600 , Edificio 3, Piso 2, Departamento 211, Estacionamiento 61 Uso y Goce | AE4: 4103 | AF4: Maipo
A5: 2 | B5: 202401310029A033 | C5: Carrillo | D5: Alarcon | E5: Francisco Javier | F5: 17540548 | G5: 8 | H5: MHE | I5: 1760 | J5: 325 | K5: 115 | L5: 2200 | M5: 0 | N5: 360 | O5: 6 | P5: 0.074653056 | Q5: 45514 | R5: 56290 | S5: 45332 | T5: 1828.4888 | U5: 1835.0201 | V5: 0.0059903111 | X5: 2650 | Y5: 0.69246041 | Z5: -0.0036469437 | AA5: 12.82336 | AB5: 28.239147 | AC5: 48.306333 | AD5: Camino Segunda Faja Al Volcán 1260, Edificio ALLIPEN, Piso 4, Departamento 403, Estacionamiento 92 Uso y Goce | AE5: 4103 | AF5: Cautín
A6: 3 | B6: 202401310030A033 | C6: Mañan | D6: Valenzuela | E6: Vicente Tomas | F6: 18465199 | G6: 8 | H6: MHE | I6: 1485 | J6: 625 | K6: 90 | L6: 2200 | M6: 0 | N6: 216 | O6: 6 | P6: 0.074813303 | Q6: 45514 | R6: 51907 | S6: 45332 | T6: 1526.4502 | U6: 1532.1686 | V6: 0.0059903111 | X6: 2200 | Y6: 0.69644028 | Z6: -0.0034866966 | AA6: 13.15116 | AB6: 13.614764 | AC6: 27.305764 | AD6: Avenida Santa Rosa 13240, Torre 3, Piso 1, Departamento 234 | AE6: 4103 | AF6: Santiago
A7: 4 | B7: 202401310034A033 | C7: Jelves | D7: Sanchez | E7: Sebastian Andres | F7: 15365153 | G7: 1 | H7: MHE | I7: 1506.34 | J7: 700 | K7: 193.66 | L7: 2400 | M7: 0 | N7: 360 | O7: 6 | P7: 0.074653056 | Q7: 45514 | R7: 56290 | S7: 45332 | T7: 1564.9579 | U7: 1571.6464 | V7: 0.0059903111 | X7: 2600 | Y7: 0.60447938 | Z7: -0.0036469437 | AA7: 10.975193 | AB7: 40.079904 | AC7: 42.389362 | AD7: Calle Miguel Campino 647, Mz D, Lote 5 | AE7: 4103 | AF7: Maipo
A8: 5 | B8: 202401310036A033 | C8: Carvajal | D8: Guajardo | E8: Danahe Estefani | F8: 18187808 | G8: 8 | H8: MHE | I8: 1285 | J8: 700 | K8: 80 | L8: 2065 | M8: 0 | N8: 360 | O8: 6 | P8: 0.074653056 | Q8: 45514 | R8: 56290 | S8: 45332 | T8: 1335.0046 | U8: 1339.7655 | V8: 0.0059903111 | X8: 2440 | Y8: 0.5490842 | Z8: -0.0036469437 | AA8: 9.36251 | AB8: 37.717378 | AC8: 39.792269 | AD8: Calle Del Toro 658, Mz D, Lote 33 | AE8: 4103 | AF8: Maipo
A9: 6 | B9: 202401250039A033 | C9: Acevedo | D9: Monje | E9: Barbara Viviana | F9: 18245649 | G9: 7 | H9: MHE | I9: 905.13 | J9: 450 | K9: 44.87 | L9: 1400 | M9: 0 | N9: 180 | O9: 6 | P9: 0.074896434 | Q9: 45514 | R9: 50811 | S9: 45332 | T9: 927.1653 | U9: 931.14903 | V9: 0.0059903111 | X9: 1400 | Y9: 0.66510645 | Z9: -0.0034035661 | AA9: 8.825923 | AB9: 41.557874 | AC9: 42.81181 | AD9: Camino La Vara 02600, Torre 2, Piso 1, Departamento 101 | AE9: 4103 | AF9: Maipo
A10: 7 | B10: 202401310041A033 | C10: Palma | D10: Ponce | E10: Carola Del Carmen | F10: 15162947 | G10: 4 | H10: MHE | I10: 838.58 | J10: 500 | K10: 61.42 | L10: 1400 | M10: 0 | N10: 360 | O10: 6 | P10: 0.074653056 | Q10: 45514 | R10: 56290 | S10: 45332 | T10: 871.21262 | U10: 874.56881 | V10: 0.0059903111 | X10: 1800 | Y10: 0.48587156 | Z10: -0.0036469437 | AA10: 6.109894 | AB10: 39.962091 | AC10: 42.110488 | AD10: Rio Viejo 1123, Torre A, Piso 4, Departamento 407 A | AE10: 4103 | AF10: Diguillín
A11: 8 | B11: 202401310046A033 | C11: Acuña | D11: Mesías | E11: Kevin Joel | F11: 16666807 | G11: 7 | H11: MHE | I11: 1345.07 | J11: 700 | K11: 279.93 | L11: 2325 | M11: 0 | N11: 144 | O11: 6 | P11: 0.075022426 | Q11: 45514 | R11: 49715 | S11: 45332 | T11: 1372.5354 | U11: 1377.8831 | V11: 0.0059903111 | X11: 2600 | Y11: 0.52995503 | Z11: -0.0032775738 | AA11: 15.019052 | AB11: 37.834186 | AC11: 40.010103 | AD11: Pasaje Copiapó Norte 071, Mz B, Lote 50 | AE11: 4103 | AF11: Maipo
A12: 9 | B12: 202401310053A033 | C12: Valdes | D12: Molina | E12: Isabel Damari | F12: 14336994 | G12: 3 | H12: MHE | I12: 895 | J12: 750 | K12: 80 | L12: 1725 | M12: 0 | N12: 312 | O12: 6 | P12: 0.074688664 | Q12: 45514 | R12: 54829 | S12: 45332 | T12: 927.02595 | U12: 930.57378 | V12: 0.0059903111 | X12: 1725 | Y12: 0.53946306 | Z12: -0.0036113359 | AA12: 6.810055 | AB12: 23.19673 | AC12: 25.290877 | AD12: Pasaje Juan Vercellino Reginato 987, Mz E, Lote 9 | AE12: 4103 | AF12: Cachapoal
A13: 10 | B13: 202401310054A033 | C13: Gonzalez | D13: Jaque | E13: Tabita Del Pilar | F13: 19580720 | G13: 5 | H13: MHE | I13: 895 | J13: 750 | K13: 80 | L13: 1725 | M13: 0 | N13: 228 | O13: 6 | P13: 0.074791661 | Q13: 45514 | R13: 52272 | S13: 45332 | T13: 920.98165 | U13: 924.16029 | V13: 0.0059903111 | X13: 1725 | Y13: 0.5357451 | Z13: -0.0035083391 | AA13: 7.722955 | AB13: 21.381348 | AC13: 24.493721 | AD13: Pasaje Elena Sanhueza Fajardo 794, Mz C, Lote 1 | AE13: 4103 | AF13: Cachapoal
A14: 11 | B14: 202401310063A033 | C14: Ormeno | D14: Salazar | E14: Gino Rexner | F14: 14349421 | G14: 7 | H14: MHE | I14: 1595 | J14: 525 | K14: 80 | L14: 2200 | M14: 0 | N14: 360 | O14: 6 | P14: 0.074653056 | Q14: 45514 | R14: 56290 | S14: 45332 | T14: 1657.068 | U14: 1663.2551 | V14: 0.0059903111 | X14: 2325 | Y14: 0.71537856 | Z14: -0.0036469437 | AA14: 11.62117 | AB14: 43.872737 | AC14: 48.266432 | AD14: Pasaje La Cumbre 1 2505, Mz 8, Lote 4 | AE14: 4103 | AF14: Biobío
A15: 12 | B15: 202401310057A033 | C15: Osorio | D15: Briones | E15: Marcela Andrea | F15: 14337194 | G15: 8 | H15: MHE | I15: 895 | J15: 750 | K15: 80 | L15: 1725 | M15: 0 | N15: 348 | O15: 6 | P15: 0.074661008 | Q15: 45514 | R15: 55925 | S15: 45332 | T15: 929.16349 | U15: 932.21409 | V15: 0.0059903111 | X15: 1725 | Y15: 0.54041396 | Z15: -0.0036389925 | AA15: 6.58362 | AB15: 11.836401 | AC15: 41.558002 | AD15: Pasaje Raquel Labarca Urzua 759, Mz C, Lote 9 | AE15: 4103 | AF15: Cachapoal
... A45: 42 | B45: 202402260095A033 | C45: Espinoza | D45: Huerta | E45: Daniela Mackarena | F45: 18916005 | G45: 4 | H45: MHE | I45: 1365 | J45: 425 | K45: 80 | L45: 1870 | M45: 21 | N45: 216 | O45: 6 | P45: 0.072386304 | Q45: 45545 | R45: 51935 | S45: 45332 | T45: 1395.3524 | U45: 1400.3211 | V45: 0.0058028362 | X45: 2100 | Y45: 0.66681958 | Z45: -0.0035136965 | AA45: 11.890515 | AB45: 21.950803 | AC45: 34.815283 | AD45: San Enrique 1398, Edificio 2 | AE45: 4103 | AF45: Marga Marga

Sheet Tabla desarrollo FX
B1: =+'Valo FX'!U3 -> 45351 | C1: ='Valo FX'!T3 -> 45361 | D1: =EDATE(C1,1) -> 45392 | E1: =EDATE(D1,1) -> 45422 | F1: =EDATE(E1,1) -> 45453 | G1: =EDATE(F1,1) -> 45483 | H1: =EDATE(G1,1) -> 45514 | I1: =EDATE(H1,1) -> 45545 | J1: =EDATE(I1,1) -> 45575 | K1: =EDATE(J1,1) -> 45606 | ... MY1: =EDATE(MX1,1) -> 56318
A2: Nº | B2: Primera cuota a endosar | C2: 1 | D2: =C2+1 -> 2 | E2: =D2+1 -> 3 | F2: =E2+1 -> 4 | G2: =F2+1 -> 5 | H2: =G2+1 -> 6 | I2: =H2+1 -> 7 | J2: =I2+1 -> 8 | K2: =J2+1 -> 9 | ... MY2: =MX2+1 -> 361
A3: =+'Valo FX'!A4 -> 1 | B3: =-'Valo FX'!T4 -> -1823.765 | C3: =IF(C$1<INDEX('Valo FX'!$Q:$Q,MATCH($A3,'Valo FX'!$A:$A,0)),0,IF(C$1<INDEX('Valo FX'!$R:$R,MATCH($A3,'Valo FX'!$A:$A,0)),INDEX(Base!$U:$U,MATCH($A3,Base!$A:$A,0)),IF(C$1=INDEX('Valo FX'!$R:$R,MATCH($A3,'Valo FX'!$A:$A,0)),INDEX(Base!$V:$V,MATCH($A3,Base!$A:$A,0)),0))) -> 0 | D3: =IF(D$1<INDEX('Valo FX'!$Q:$Q,MATCH($A3,'Valo FX'!$A:$A,0)),0,IF(D$1<INDEX('Valo FX'!$R:$R,MATCH($A3,'Valo FX'!$A:$A,0)),INDEX(Base!$U:$U,MATCH($A3,Base!$A:$A,0)),IF(D$1=INDEX('Valo FX'!$R:$R,MATCH($A3,'Valo FX'!$A:$A,0)),INDEX(Base!$V:$V,MATCH($A3,Base!$A:$A,0)),0))) -> 0 | E3: =IF(E$1<INDEX('Valo FX'!$Q:$Q,MATCH($A3,'Valo FX'!$A:$A,0)),0,IF(E$1<INDEX('Valo FX'!$R:$R,MATCH($A3,'Valo FX'!$A:$A,0)),INDEX(Base!$U:$U,MATCH($A3,Base!$A:$A,0)),IF(E$1=INDEX('Valo FX'!$R:$R,MATCH($A3,'Valo FX'!$A:$A,0)),INDEX(Base!$V:$V,MATCH($A3,Base!$A:$A,0)),0))) -> 0 | F3: =IF(F$1<INDEX('Valo FX'!$Q:$Q,MATCH($A3,'Valo FX'!$A:$A,0)),0,IF(F$1<INDEX('Valo FX'!$R:$R,MATCH($A3,'Valo FX'!$A:$A,0)),INDEX(Base!$U:$U,MATCH($A3,Base!$A:$A,0)),IF(F$1=INDEX('Valo FX'!$R:$R,MATCH($A3,'Valo FX'!$A:$A,0)),INDEX(Base!$V:$V,MATCH($A3,Base!$A:$A,0)),0))) -> 0 | G3: =IF(G$1<INDEX('Valo FX'!$Q:$Q,MATCH($A3,'Valo FX'!$A:$A,0)),0,IF(G$1<INDEX('Valo FX'!$R:$R,MATCH($A3,'Valo FX'!$A:$A,0)),INDEX(Base!$U:$U,MATCH($A3,Base!$A:$A,0)),IF(G$1=INDEX('Valo FX'!$R:$R,MATCH($A3,'Valo FX'!$A:$A,0)),INDEX(Base!$V:$V,MATCH($A3,Base!$A:$A,0)),0))) -> 0 | H3: =IF(H$1<INDEX('Valo FX'!$Q:$Q,MATCH($A3,'Valo FX'!$A:$A,0)),0,IF(H$1<INDEX('Valo FX'!$R:$R,MATCH($A3,'Valo FX'!$A:$A,0)),INDEX(Base!$U:$U,MATCH($A3,Base!$A:$A,0)),IF(H$1=INDEX('Valo FX'!$R:$R,MATCH($A3,'Valo FX'!$A:$A,0)),INDEX(Base!$V:$V,MATCH($A3,Base!$A:$A,0)),0))) -> 12.71407 | I3: =IF(I$1<INDEX('Valo FX'!$Q:$Q,MATCH($A3,'Valo FX'!$A:$A,0)),0,IF(I$1<INDEX('Valo FX'!$R:$R,MATCH($A3,'Valo FX'!$A:$A,0)),INDEX(Base!$U:$U,MATCH($A3,Base!$A:$A,0)),IF(I$1=INDEX('Valo FX'!$R:$R,MATCH($A3,'Valo FX'!$A:$A,0)),INDEX(Base!$V:$V,MATCH($A3,Base!$A:$A,0)),0))) -> 12.71407 | J3: =IF(J$1<INDEX('Valo FX'!$Q:$Q,MATCH($A3,'Valo FX'!$A:$A,0)),0,IF(J$1<INDEX('Valo FX'!$R:$R,MATCH($A3,'Valo FX'!$A:$A,0)),INDEX(Base!$U:$U,MATCH($A3,Base!$A:$A,0)),IF(J$1=INDEX('Valo FX'!$R:$R,MATCH($A3,'Valo FX'!$A:$A,0)),INDEX(Base!$V:$V,MATCH($A3,Base!$A:$A,0)),0))) -> 12.71407 | ... MY3: =IF(MY$1<INDEX('Valo FX'!$Q:$Q,MATCH($A3,'Valo FX'!$A:$A,0)),0,IF(MY$1<INDEX('Valo FX'!$R:$R,MATCH($A3,'Valo FX'!$A:$A,0)),INDEX(Base!$U:$U,MATCH($A3,Base!$A:$A,0)),IF(MY$1=INDEX('Valo FX'!$R:$R,MATCH($A3,'Valo FX'!$A:$A,0)),INDEX(Base!$V:$V,MATCH($A3,Base!$A:$A,0)),0))) -> 0
A4: =+'Valo FX'!A5 -> 2 | B4: =-'Valo FX'!T5 -> -1839.4421 | C4: =IF(C$1<INDEX('Valo FX'!$Q:$Q,MATCH($A4,'Valo FX'!$A:$A,0)),0,IF(C$1<INDEX('Valo FX'!$R:$R,MATCH($A4,'Valo FX'!$A:$A,0)),INDEX(Base!$U:$U,MATCH($A4,Base!$A:$A,0)),IF(C$1=INDEX('Valo FX'!$R:$R,MATCH($A4,'Valo FX'!$A:$A,0)),INDEX(Base!$V:$V,MATCH($A4,Base!$A:$A,0)),0))) -> 0 | D4: =IF(D$1<INDEX('Valo FX'!$Q:$Q,MATCH($A4,'Valo FX'!$A:$A,0)),0,IF(D$1<INDEX('Valo FX'!$R:$R,MATCH($A4,'Valo FX'!$A:$A,0)),INDEX(Base!$U:$U,MATCH($A4,Base!$A:$A,0)),IF(D$1=INDEX('Valo FX'!$R:$R,MATCH($A4,'Valo FX'!$A:$A,0)),INDEX(Base!$V:$V,MATCH($A4,Base!$A:$A,0)),0))) -> 0 | E4: =IF(E$1<INDEX('Valo FX'!$Q:$Q,MATCH($A4,'Valo FX'!$A:$A,0)),0,IF(E$1<INDEX('Valo FX'!$R:$R,MATCH($A4,'Valo FX'!$A:$A,0)),INDEX(Base!$U:$U,MATCH($A4,Base!$A:$A,0)),IF(E$1=INDEX('Valo FX'!$R:$R,MATCH($A4,'Valo FX'!$A:$A,0)),INDEX(Base!$V:$V,MATCH($A4,Base!$A:$A,0)),0))) -> 0 | F4: =IF(F$1<INDEX('Valo FX'!$Q:$Q,MATCH($A4,'Valo FX'!$A:$A,0)),0,IF(F$1<INDEX('Valo FX'!$R:$R,MATCH($A4,'Valo FX'!$A:$A,0)),INDEX(Base!$U:$U,MATCH($A4,Base!$A:$A,0)),IF(F$1=INDEX('Valo FX'!$R:$R,MATCH($A4,'Valo FX'!$A:$A,0)),INDEX(Base!$V:$V,MATCH($A4,Base!$A:$A,0)),0))) -> 0 | G4: =IF(G$1<INDEX('Valo FX'!$Q:$Q,MATCH($A4,'Valo FX'!$A:$A,0)),0,IF(G$1<INDEX('Valo FX'!$R:$R,MATCH($A4,'Valo FX'!$A:$A,0)),INDEX(Base!$U:$U,MATCH($A4,Base!$A:$A,0)),IF(G$1=INDEX('Valo FX'!$R:$R,MATCH($A4,'Valo FX'!$A:$A,0)),INDEX(Base!$V:$V,MATCH($A4,Base!$A:$A,0)),0))) -> 0 | H4: =IF(H$1<INDEX('Valo FX'!$Q:$Q,MATCH($A4,'Valo FX'!$A:$A,0)),0,IF(H$1<INDEX('Valo FX'!$R:$R,MATCH($A4,'Valo FX'!$A:$A,0)),INDEX(Base!$U:$U,MATCH($A4,Base!$A:$A,0)),IF(H$1=INDEX('Valo FX'!$R:$R,MATCH($A4,'Valo FX'!$A:$A,0)),INDEX(Base!$V:$V,MATCH($A4,Base!$A:$A,0)),0))) -> 12.82336 | I4: =IF(I$1<INDEX('Valo FX'!$Q:$Q,MATCH($A4,'Valo FX'!$A:$A,0)),0,IF(I$1<INDEX('Valo FX'!$R:$R,MATCH($A4,'Valo FX'!$A:$A,0)),INDEX(Base!$U:$U,MATCH($A4,Base!$A:$A,0)),IF(I$1=INDEX('Valo FX'!$R:$R,MATCH($A4,'Valo FX'!$A:$A,0)),INDEX(Base!$V:$V,MATCH($A4,Base!$A:$A,0)),0))) -> 12.82336 | J4: =IF(J$1<INDEX('Valo FX'!$Q:$Q,MATCH($A4,'Valo FX'!$A:$A,0)),0,IF(J$1<INDEX('Valo FX'!$R:$R,MATCH($A4,'Valo FX'!$A:$A,0)),INDEX(Base!$U:$U,MATCH($A4,Base!$A:$A,0)),IF(J$1=INDEX('Valo FX'!$R:$R,MATCH($A4,'Valo FX'!$A:$A,0)),INDEX(Base!$V:$V,MATCH($A4,Base!$A:$A,0)),0))) -> 12.82336 | ... MY4: =IF(MY$1<INDEX('Valo FX'!$Q:$Q,MATCH($A4,'Valo FX'!$A:$A,0)),0,IF(MY$1<INDEX('Valo FX'!$R:$R,MATCH($A4,'Valo FX'!$A:$A,0)),INDEX(Base!$U:$U,MATCH($A4,Base!$A:$A,0)),IF(MY$1=INDEX('Valo FX'!$R:$R,MATCH($A4,'Valo FX'!$A:$A,0)),INDEX(Base!$V:$V,MATCH($A4,Base!$A:$A,0)),0))) -> 0
A5: =+'Valo FX'!A6 -> 3 | B5: =-'Valo FX'!T6 -> -1535.5941 | C5: =IF(C$1<INDEX('Valo FX'!$Q:$Q,MATCH($A5,'Valo FX'!$A:$A,0)),0,IF(C$1<INDEX('Valo FX'!$R:$R,MATCH($A5,'Valo FX'!$A:$A,0)),INDEX(Base!$U:$U,MATCH($A5,Base!$A:$A,0)),IF(C$1=INDEX('Valo FX'!$R:$R,MATCH($A5,'Valo FX'!$A:$A,0)),INDEX(Base!$V:$V,MATCH($A5,Base!$A:$A,0)),0))) -> 0 | D5: =IF(D$1<INDEX('Valo FX'!$Q:$Q,MATCH($A5,'Valo FX'!$A:$A,0)),0,IF(D$1<INDEX('Valo FX'!$R:$R,MATCH($A5,'Valo FX'!$A:$A,0)),INDEX(Base!$U:$U,MATCH($A5,Base!$A:$A,0)),IF(D$1=INDEX('Valo FX'!$R:$R,MATCH($A5,'Valo FX'!$A:$A,0)),INDEX(Base!$V:$V,MATCH($A5,Base!$A:$A,0)),0))) -> 0 | E5: =IF(E$1<INDEX('Valo FX'!$Q:$Q,MATCH($A5,'Valo FX'!$A:$A,0)),0,IF(E$1<INDEX('Valo FX'!$R:$R,MATCH($A5,'Valo FX'!$A:$A,0)),INDEX(Base!$U:$U,MATCH($A5,Base!$A:$A,0)),IF(E$1=INDEX('Valo FX'!$R:$R,MATCH($A5,'Valo FX'!$A:$A,0)),INDEX(Base!$V:$V,MATCH($A5,Base!$A:$A,0)),0))) -> 0 | F5: =IF(F$1<INDEX('Valo FX'!$Q:$Q,MATCH($A5,'Valo FX'!$A:$A,0)),0,IF(F$1<INDEX('Valo FX'!$R:$R,MATCH($A5,'Valo FX'!$A:$A,0)),INDEX(Base!$U:$U,MATCH($A5,Base!$A:$A,0)),IF(F$1=INDEX('Valo FX'!$R:$R,MATCH($A5,'Valo FX'!$A:$A,0)),INDEX(Base!$V:$V,MATCH($A5,Base!$A:$A,0)),0))) -> 0 | G5: =IF(G$1<INDEX('Valo FX'!$Q:$Q,MATCH($A5,'Valo FX'!$A:$A,0)),0,IF(G$1<INDEX('Valo FX'!$R:$R,MATCH($A5,'Valo FX'!$A:$A,0)),INDEX(Base!$U:$U,MATCH($A5,Base!$A:$A,0)),IF(G$1=INDEX('Valo FX'!$R:$R,MATCH($A5,'Valo FX'!$A:$A,0)),INDEX(Base!$V:$V,MATCH($A5,Base!$A:$A,0)),0))) -> 0 | H5: =IF(H$1<INDEX('Valo FX'!$Q:$Q,MATCH($A5,'Valo FX'!$A:$A,0)),0,IF(H$1<INDEX('Valo FX'!$R:$R,MATCH($A5,'Valo FX'!$A:$A,0)),INDEX(Base!$U:$U,MATCH($A5,Base!$A:$A,0)),IF(H$1=INDEX('Valo FX'!$R:$R,MATCH($A5,'Valo FX'!$A:$A,0)),INDEX(Base!$V:$V,MATCH($A5,Base!$A:$A,0)),0))) -> 13.15116 | I5: =IF(I$1<INDEX('Valo FX'!$Q:$Q,MATCH($A5,'Valo FX'!$A:$A,0)),0,IF(I$1<INDEX('Valo FX'!$R:$R,MATCH($A5,'Valo FX'!$A:$A,0)),INDEX(Base!$U:$U,MATCH($A5,Base!$A:$A,0)),IF(I$1=INDEX('Valo FX'!$R:$R,MATCH($A5,'Valo FX'!$A:$A,0)),INDEX(Base!$V:$V,MATCH($A5,Base!$A:$A,0)),0))) -> 13.15116 | J5: =IF(J$1<INDEX('Valo FX'!$Q:$Q,MATCH($A5,'Valo FX'!$A:$A,0)),0,IF(J$1<INDEX('Valo FX'!$R:$R,MATCH($A5,'Valo FX'!$A:$A,0)),INDEX(Base!$U:$U,MATCH($A5,Base!$A:$A,0)),IF(J$1=INDEX('Valo FX'!$R:$R,MATCH($A5,'Valo FX'!$A:$A,0)),INDEX(Base!$V:$V,MATCH($A5,Base!$A:$A,0)),0))) -> 13.15116 | ... MY5: =IF(MY$1<INDEX('Valo FX'!$Q:$Q,MATCH($A5,'Valo FX'!$A:$A,0)),0,IF(MY$1<INDEX('Valo FX'!$R:$R,MATCH($A5,'Valo FX'!$A:$A,0)),INDEX(Base!$U:$U,MATCH($A5,Base!$A:$A,0)),IF(MY$1=INDEX('Valo FX'!$R:$R,MATCH($A5,'Valo FX'!$A:$A,0)),INDEX(Base!$V:$V,MATCH($A5,Base!$A:$A,0)),0))) -> 0
A6: =+'Valo FX'!A7 -> 4 | B6: =-'Valo FX'!T7 -> -1574.3324 | C6: =IF(C$1<INDEX('Valo FX'!$Q:$Q,MATCH($A6,'Valo FX'!$A:$A,0)),0,IF(C$1<INDEX('Valo FX'!$R:$R,MATCH($A6,'Valo FX'!$A:$A,0)),INDEX(Base!$U:$U,MATCH($A6,Base!$A:$A,0)),IF(C$1=INDEX('Valo FX'!$R:$R,MATCH($A6,'Valo FX'!$A:$A,0)),INDEX(Base!$V:$V,MATCH($A6,Base!$A:$A,0)),0))) -> 0 | D6: =IF(D$1<INDEX('Valo FX'!$Q:$Q,MATCH($A6,'Valo FX'!$A:$A,0)),0,IF(D$1<INDEX('Valo FX'!$R:$R,MATCH($A6,'Valo FX'!$A:$A,0)),INDEX(Base!$U:$U,MATCH($A6,Base!$A:$A,0)),IF(D$1=INDEX('Valo FX'!$R:$R,MATCH($A6,'Valo FX'!$A:$A,0)),INDEX(Base!$V:$V,MATCH($A6,Base!$A:$A,0)),0))) -> 0 | E6: =IF(E$1<INDEX('Valo FX'!$Q:$Q,MATCH($A6,'Valo FX'!$A:$A,0)),0,IF(E$1<INDEX('Valo FX'!$R:$R,MATCH($A6,'Valo FX'!$A:$A,0)),INDEX(Base!$U:$U,MATCH($A6,Base!$A:$A,0)),IF(E$1=INDEX('Valo FX'!$R:$R,MATCH($A6,'Valo FX'!$A:$A,0)),INDEX(Base!$V:$V,MATCH($A6,Base!$A:$A,0)),0))) -> 0 | F6: =IF(F$1<INDEX('Valo FX'!$Q:$Q,MATCH($A6,'Valo FX'!$A:$A,0)),0,IF(F$1<INDEX('Valo FX'!$R:$R,MATCH($A6,'Valo FX'!$A:$A,0)),INDEX(Base!$U:$U,MATCH($A6,Base!$A:$A,0)),IF(F$1=INDEX('Valo FX'!$R:$R,MATCH($A6,'Valo FX'!$A:$A,0)),INDEX(Base!$V:$V,MATCH($A6,Base!$A:$A,0)),0))) -> 0 | G6: =IF(G$1<INDEX('Valo FX'!$Q:$Q,MATCH($A6,'Valo FX'!$A:$A,0)),0,IF(G$1<INDEX('Valo FX'!$R:$R,MATCH($A6,'Valo FX'!$A:$A,0)),INDEX(Base!$U:$U,MATCH($A6,Base!$A:$A,0)),IF(G$1=INDEX('Valo FX'!$R:$R,MATCH($A6,'Valo FX'!$A:$A,0)),INDEX(Base!$V:$V,MATCH($A6,Base!$A:$A,0)),0))) -> 0 | H6: =IF(H$1<INDEX('Valo FX'!$Q:$Q,MATCH($A6,'Valo FX'!$A:$A,0)),0,IF(H$1<INDEX('Valo FX'!$R:$R,MATCH($A6,'Valo FX'!$A:$A,0)),INDEX(Base!$U:$U,MATCH($A6,Base!$A:$A,0)),IF(H$1=INDEX('Valo FX'!$R:$R,MATCH($A6,'Valo FX'!$A:$A,0)),INDEX(Base!$V:$V,MATCH($A6,Base!$A:$A,0)),0))) -> 10.975193 | I6: =IF(I$1<INDEX('Valo FX'!$Q:$Q,MATCH($A6,'Valo FX'!$A:$A,0)),0,IF(I$1<INDEX('Valo FX'!$R:$R,MATCH($A6,'Valo FX'!$A:$A,0)),INDEX(Base!$U:$U,MATCH($A6,Base!$A:$A,0)),IF(I$1=INDEX('Valo FX'!$R:$R,MATCH($A6,'Valo FX'!$A:$A,0)),INDEX(Base!$V:$V,MATCH($A6,Base!$A:$A,0)),0))) -> 10.975193 | J6: =IF(J$1<INDEX('Valo FX'!$Q:$Q,MATCH($A6,'Valo FX'!$A:$A,0)),0,IF(J$1<INDEX('Valo FX'!$R:$R,MATCH($A6,'Valo FX'!$A:$A,0)),INDEX(Base!$U:$U,MATCH($A6,Base!$A:$A,0)),IF(J$1=INDEX('Valo FX'!$R:$R,MATCH($A6,'Valo FX'!$A:$A,0)),INDEX(Base!$V:$V,MATCH($A6,Base!$A:$A,0)),0))) -> 10.975193 | ... MY6: =IF(MY$1<INDEX('Valo FX'!$Q:$Q,MATCH($A6,'Valo FX'!$A:$A,0)),0,IF(MY$1<INDEX('Valo FX'!$R:$R,MATCH($A6,'Valo FX'!$A:$A,0)),INDEX(Base!$U:$U,MATCH($A6,Base!$A:$A,0)),IF(MY$1=INDEX('Valo FX'!$R:$R,MATCH($A6,'Valo FX'!$A:$A,0)),INDEX(Base!$V:$V,MATCH($A6,Base!$A:$A,0)),0))) -> 0
A7: =+'Valo FX'!A8 -> 5 | B7: =-'Valo FX'!T8 -> -1343.0017 | C7: =IF(C$1<INDEX('Valo FX'!$Q:$Q,MATCH($A7,'Valo FX'!$A:$A,0)),0,IF(C$1<INDEX('Valo FX'!$R:$R,MATCH($A7,'Valo FX'!$A:$A,0)),INDEX(Base!$U:$U,MATCH($A7,Base!$A:$A,0)),IF(C$1=INDEX('Valo FX'!$R:$R,MATCH($A7,'Valo FX'!$A:$A,0)),INDEX(Base!$V:$V,MATCH($A7,Base!$A:$A,0)),0))) -> 0 | D7: =IF(D$1<INDEX('Valo FX'!$Q:$Q,MATCH($A7,'Valo FX'!$A:$A,0)),0,IF(D$1<INDEX('Valo FX'!$R:$R,MATCH($A7,'Valo FX'!$A:$A,0)),INDEX(Base!$U:$U,MATCH($A7,Base!$A:$A,0)),IF(D$1=INDEX('Valo FX'!$R:$R,MATCH($A7,'Valo FX'!$A:$A,0)),INDEX(Base!$V:$V,MATCH($A7,Base!$A:$A,0)),0))) -> 0 | E7: =IF(E$1<INDEX('Valo FX'!$Q:$Q,MATCH($A7,'Valo FX'!$A:$A,0)),0,IF(E$1<INDEX('Valo FX'!$R:$R,MATCH($A7,'Valo FX'!$A:$A,0)),INDEX(Base!$U:$U,MATCH($A7,Base!$A:$A,0)),IF(E$1=INDEX('Valo FX'!$R:$R,MATCH($A7,'Valo FX'!$A:$A,0)),INDEX(Base!$V:$V,MATCH($A7,Base!$A:$A,0)),0))) -> 0 | F7: =IF(F$1<INDEX('Valo FX'!$Q:$Q,MATCH($A7,'Valo FX'!$A:$A,0)),0,IF(F$1<INDEX('Valo FX'!$R:$R,MATCH($A7,'Valo FX'!$A:$A,0)),INDEX(Base!$U:$U,MATCH($A7,Base!$A:$A,0)),IF(F$1=INDEX('Valo FX'!$R:$R,MATCH($A7,'Valo FX'!$A:$A,0)),INDEX(Base!$V:$V,MATCH($A7,Base!$A:$A,0)),0))) -> 0 | G7: =IF(G$1<INDEX('Valo FX'!$Q:$Q,MATCH($A7,'Valo FX'!$A:$A,0)),0,IF(G$1<INDEX('Valo FX'!$R:$R,MATCH($A7,'Valo FX'!$A:$A,0)),INDEX(Base!$U:$U,MATCH($A7,Base!$A:$A,0)),IF(G$1=INDEX('Valo FX'!$R:$R,MATCH($A7,'Valo FX'!$A:$A,0)),INDEX(Base!$V:$V,MATCH($A7,Base!$A:$A,0)),0))) -> 0 | H7: =IF(H$1<INDEX('Valo FX'!$Q:$Q,MATCH($A7,'Valo FX'!$A:$A,0)),0,IF(H$1<INDEX('Valo FX'!$R:$R,MATCH($A7,'Valo FX'!$A:$A,0)),INDEX(Base!$U:$U,MATCH($A7,Base!$A:$A,0)),IF(H$1=INDEX('Valo FX'!$R:$R,MATCH($A7,'Valo FX'!$A:$A,0)),INDEX(Base!$V:$V,MATCH($A7,Base!$A:$A,0)),0))) -> 9.36251 | I7: =IF(I$1<INDEX('Valo FX'!$Q:$Q,MATCH($A7,'Valo FX'!$A:$A,0)),0,IF(I$1<INDEX('Valo FX'!$R:$R,MATCH($A7,'Valo FX'!$A:$A,0)),INDEX(Base!$U:$U,MATCH($A7,Base!$A:$A,0)),IF(I$1=INDEX('Valo FX'!$R:$R,MATCH($A7,'Valo FX'!$A:$A,0)),INDEX(Base!$V:$V,MATCH($A7,Base!$A:$A,0)),0))) -> 9.36251 | J7: =IF(J$1<INDEX('Valo FX'!$Q:$Q,MATCH($A7,'Valo FX'!$A:$A,0)),0,IF(J$1<INDEX('Valo FX'!$R:$R,MATCH($A7,'Valo FX'!$A:$A,0)),INDEX(Base!$U:$U,MATCH($A7,Base!$A:$A,0)),IF(J$1=INDEX('Valo FX'!$R:$R,MATCH($A7,'Valo FX'!$A:$A,0)),INDEX(Base!$V:$V,MATCH($A7,Base!$A:$A,0)),0))) -> 9.36251 | ... MY7: =IF(MY$1<INDEX('Valo FX'!$Q:$Q,MATCH($A7,'Valo FX'!$A:$A,0)),0,IF(MY$1<INDEX('Valo FX'!$R:$R,MATCH($A7,'Valo FX'!$A:$A,0)),INDEX(Base!$U:$U,MATCH($A7,Base!$A:$A,0)),IF(MY$1=INDEX('Valo FX'!$R:$R,MATCH($A7,'Valo FX'!$A:$A,0)),INDEX(Base!$V:$V,MATCH($A7,Base!$A:$A,0)),0))) -> 0
A8: =+'Valo FX'!A9 -> 6 | B8: =-'Valo FX'!T9 -> -932.71931 | C8: =IF(C$1<INDEX('Valo FX'!$Q:$Q,MATCH($A8,'Valo FX'!$A:$A,0)),0,IF(C$1<INDEX('Valo FX'!$R:$R,MATCH($A8,'Valo FX'!$A:$A,0)),INDEX(Base!$U:$U,MATCH($A8,Base!$A:$A,0)),IF(C$1=INDEX('Valo FX'!$R:$R,MATCH($A8,'Valo FX'!$A:$A,0)),INDEX(Base!$V:$V,MATCH($A8,Base!$A:$A,0)),0))) -> 0 | D8: =IF(D$1<INDEX('Valo FX'!$Q:$Q,MATCH($A8,'Valo FX'!$A:$A,0)),0,IF(D$1<INDEX('Valo FX'!$R:$R,MATCH($A8,'Valo FX'!$A:$A,0)),INDEX(Base!$U:$U,MATCH($A8,Base!$A:$A,0)),IF(D$1=INDEX('Valo FX'!$R:$R,MATCH($A8,'Valo FX'!$A:$A,0)),INDEX(Base!$V:$V,MATCH($A8,Base!$A:$A,0)),0))) -> 0 | E8: =IF(E$1<INDEX('Valo FX'!$Q:$Q,MATCH($A8,'Valo FX'!$A:$A,0)),0,IF(E$1<INDEX('Valo FX'!$R:$R,MATCH($A8,'Valo FX'!$A:$A,0)),INDEX(Base!$U:$U,MATCH($A8,Base!$A:$A,0)),IF(E$1=INDEX('Valo FX'!$R:$R,MATCH($A8,'Valo FX'!$A:$A,0)),INDEX(Base!$V:$V,MATCH($A8,Base!$A:$A,0)),0))) -> 0 | F8: =IF(F$1<INDEX('Valo FX'!$Q:$Q,MATCH($A8,'Valo FX'!$A:$A,0)),0,IF(F$1<INDEX('Valo FX'!$R:$R,MATCH($A8,'Valo FX'!$A:$A,0)),INDEX(Base!$U:$U,MATCH($A8,Base!$A:$A,0)),IF(F$1=INDEX('Valo FX'!$R:$R,MATCH($A8,'Valo FX'!$A:$A,0)),INDEX(Base!$V:$V,MATCH($A8,Base!$A:$A,0)),0))) -> 0 | G8: =IF(G$1<INDEX('Valo FX'!$Q:$Q,MATCH($A8,'Valo FX'!$A:$A,0)),0,IF(G$1<INDEX('Valo FX'!$R:$R,MATCH($A8,'Valo FX'!$A:$A,0)),INDEX(Base!$U:$U,MATCH($A8,Base!$A:$A,0)),IF(G$1=INDEX('Valo FX'!$R:$R,MATCH($A8,'Valo FX'!$A:$A,0)),INDEX(Base!$V:$V,MATCH($A8,Base!$A:$A,0)),0))) -> 0 | H8: =IF(H$1<INDEX('Valo FX'!$Q:$Q,MATCH($A8,'Valo FX'!$A:$A,0)),0,IF(H$1<INDEX('Valo FX'!$R:$R,MATCH($A8,'Valo FX'!$A:$A,0)),INDEX(Base!$U:$U,MATCH($A8,Base!$A:$A,0)),IF(H$1=INDEX('Valo FX'!$R:$R,MATCH($A8,'Valo FX'!$A:$A,0)),INDEX(Base!$V:$V,MATCH($A8,Base!$A:$A,0)),0))) -> 8.825923 | I8: =IF(I$1<INDEX('Valo FX'!$Q:$Q,MATCH($A8,'Valo FX'!$A:$A,0)),0,IF(I$1<INDEX('Valo FX'!$R:$R,MATCH($A8,'Valo FX'!$A:$A,0)),INDEX(Base!$U:$U,MATCH($A8,Base!$A:$A,0)),IF(I$1=INDEX('Valo FX'!$R:$R,MATCH($A8,'Valo FX'!$A:$A,0)),INDEX(Base!$V:$V,MATCH($A8,Base!$A:$A,0)),0))) -> 8.825923 | J8: =IF(J$1<INDEX('Valo FX'!$Q:$Q,MATCH($A8,'Valo FX'!$A:$A,0)),0,IF(J$1<INDEX('Valo FX'!$R:$R,MATCH($A8,'Valo FX'!$A:$A,0)),INDEX(Base!$U:$U,MATCH($A8,Base!$A:$A,0)),IF(J$1=INDEX('Valo FX'!$R:$R,MATCH($A8,'Valo FX'!$A:$A,0)),INDEX(Base!$V:$V,MATCH($A8,Base!$A:$A,0)),0))) -> 8.825923 | ... MY8: =IF(MY$1<INDEX('Valo FX'!$Q:$Q,MATCH($A8,'Valo FX'!$A:$A,0)),0,IF(MY$1<INDEX('Valo FX'!$R:$R,MATCH($A8,'Valo FX'!$A:$A,0)),INDEX(Base!$U:$U,MATCH($A8,Base!$A:$A,0)),IF(MY$1=INDEX('Valo FX'!$R:$R,MATCH($A8,'Valo FX'!$A:$A,0)),INDEX(Base!$V:$V,MATCH($A8,Base!$A:$A,0)),0))) -> 0
A9: =+'Valo FX'!A10 -> 7 | B9: =-'Valo FX'!T10 -> -876.43145 | C9: =IF(C$1<INDEX('Valo FX'!$Q:$Q,MATCH($A9,'Valo FX'!$A:$A,0)),0,IF(C$1<INDEX('Valo FX'!$R:$R,MATCH($A9,'Valo FX'!$A:$A,0)),INDEX(Base!$U:$U,MATCH($A9,Base!$A:$A,0)),IF(C$1=INDEX('Valo FX'!$R:$R,MATCH($A9,'Valo FX'!$A:$A,0)),INDEX(Base!$V:$V,MATCH($A9,Base!$A:$A,0)),0))) -> 0 | D9: =IF(D$1<INDEX('Valo FX'!$Q:$Q,MATCH($A9,'Valo FX'!$A:$A,0)),0,IF(D$1<INDEX('Valo FX'!$R:$R,MATCH($A9,'Valo FX'!$A:$A,0)),INDEX(Base!$U:$U,MATCH($A9,Base!$A:$A,0)),IF(D$1=INDEX('Valo FX'!$R:$R,MATCH($A9,'Valo FX'!$A:$A,0)),INDEX(Base!$V:$V,MATCH($A9,Base!$A:$A,0)),0))) -> 0 | E9: =IF(E$1<INDEX('Valo FX'!$Q:$Q,MATCH($A9,'Valo FX'!$A:$A,0)),0,IF(E$1<INDEX('Valo FX'!$R:$R,MATCH($A9,'Valo FX'!$A:$A,0)),INDEX(Base!$U:$U,MATCH($A9,Base!$A:$A,0)),IF(E$1=INDEX('Valo FX'!$R:$R,MATCH($A9,'Valo FX'!$A:$A,0)),INDEX(Base!$V:$V,MATCH($A9,Base!$A:$A,0)),0))) -> 0 | F9: =IF(F$1<INDEX('Valo FX'!$Q:$Q,MATCH($A9,'Valo FX'!$A:$A,0)),0,IF(F$1<INDEX('Valo FX'!$R:$R,MATCH($A9,'Valo FX'!$A:$A,0)),INDEX(Base!$U:$U,MATCH($A9,Base!$A:$A,0)),IF(F$1=INDEX('Valo FX'!$R:$R,MATCH($A9,'Valo FX'!$A:$A,0)),INDEX(Base!$V:$V,MATCH($A9,Base!$A:$A,0)),0))) -> 0 | G9: =IF(G$1<INDEX('Valo FX'!$Q:$Q,MATCH($A9,'Valo FX'!$A:$A,0)),0,IF(G$1<INDEX('Valo FX'!$R:$R,MATCH($A9,'Valo FX'!$A:$A,0)),INDEX(Base!$U:$U,MATCH($A9,Base!$A:$A,0)),IF(G$1=INDEX('Valo FX'!$R:$R,MATCH($A9,'Valo FX'!$A:$A,0)),INDEX(Base!$V:$V,MATCH($A9,Base!$A:$A,0)),0))) -> 0 | H9: =IF(H$1<INDEX('Valo FX'!$Q:$Q,MATCH($A9,'Valo FX'!$A:$A,0)),0,IF(H$1<INDEX('Valo FX'!$R:$R,MATCH($A9,'Valo FX'!$A:$A,0)),INDEX(Base!$U:$U,MATCH($A9,Base!$A:$A,0)),IF(H$1=INDEX('Valo FX'!$R:$R,MATCH($A9,'Valo FX'!$A:$A,0)),INDEX(Base!$V:$V,MATCH($A9,Base!$A:$A,0)),0))) -> 6.109894 | I9: =IF(I$1<INDEX('Valo FX'!$Q:$Q,MATCH($A9,'Valo FX'!$A:$A,0)),0,IF(I$1<INDEX('Valo FX'!$R:$R,MATCH($A9,'Valo FX'!$A:$A,0)),INDEX(Base!$U:$U,MATCH($A9,Base!$A:$A,0)),IF(I$1=INDEX('Valo FX'!$R:$R,MATCH($A9,'Valo FX'!$A:$A,0)),INDEX(Base!$V:$V,MATCH($A9,Base!$A:$A,0)),0))) -> 6.109894 | J9: =IF(J$1<INDEX('Valo FX'!$Q:$Q,MATCH($A9,'Valo FX'!$A:$A,0)),0,IF(J$1<INDEX('Valo FX'!$R:$R,MATCH($A9,'Valo FX'!$A:$A,0)),INDEX(Base!$U:$U,MATCH($A9,Base!$A:$A,0)),IF(J$1=INDEX('Valo FX'!$R:$R,MATCH($A9,'Valo FX'!$A:$A,0)),INDEX(Base!$V:$V,MATCH($A9,Base!$A:$A,0)),0))) -> 6.109894 | ... MY9: =IF(MY$1<INDEX('Valo FX'!$Q:$Q,MATCH($A9,'Valo FX'!$A:$A,0)),0,IF(MY$1<INDEX('Valo FX'!$R:$R,MATCH($A9,'Valo FX'!$A:$A,0)),INDEX(Base!$U:$U,MATCH($A9,Base!$A:$A,0)),IF(MY$1=INDEX('Valo FX'!$R:$R,MATCH($A9,'Valo FX'!$A:$A,0)),INDEX(Base!$V:$V,MATCH($A9,Base!$A:$A,0)),0))) -> 0
A10: =+'Valo FX'!A11 -> 8 | B10: =-'Valo FX'!T11 -> -1380.7573 | C10: =IF(C$1<INDEX('Valo FX'!$Q:$Q,MATCH($A10,'Valo FX'!$A:$A,0)),0,IF(C$1<INDEX('Valo FX'!$R:$R,MATCH($A10,'Valo FX'!$A:$A,0)),INDEX(Base!$U:$U,MATCH($A10,Base!$A:$A,0)),IF(C$1=INDEX('Valo FX'!$R:$R,MATCH($A10,'Valo FX'!$A:$A,0)),INDEX(Base!$V:$V,MATCH($A10,Base!$A:$A,0)),0))) -> 0 | D10: =IF(D$1<INDEX('Valo FX'!$Q:$Q,MATCH($A10,'Valo FX'!$A:$A,0)),0,IF(D$1<INDEX('Valo FX'!$R:$R,MATCH($A10,'Valo FX'!$A:$A,0)),INDEX(Base!$U:$U,MATCH($A10,Base!$A:$A,0)),IF(D$1=INDEX('Valo FX'!$R:$R,MATCH($A10,'Valo FX'!$A:$A,0)),INDEX(Base!$V:$V,MATCH($A10,Base!$A:$A,0)),0))) -> 0 | E10: =IF(E$1<INDEX('Valo FX'!$Q:$Q,MATCH($A10,'Valo FX'!$A:$A,0)),0,IF(E$1<INDEX('Valo FX'!$R:$R,MATCH($A10,'Valo FX'!$A:$A,0)),INDEX(Base!$U:$U,MATCH($A10,Base!$A:$A,0)),IF(E$1=INDEX('Valo FX'!$R:$R,MATCH($A10,'Valo FX'!$A:$A,0)),INDEX(Base!$V:$V,MATCH($A10,Base!$A:$A,0)),0))) -> 0 | F10: =IF(F$1<INDEX('Valo FX'!$Q:$Q,MATCH($A10,'Valo FX'!$A:$A,0)),0,IF(F$1<INDEX('Valo FX'!$R:$R,MATCH($A10,'Valo FX'!$A:$A,0)),INDEX(Base!$U:$U,MATCH($A10,Base!$A:$A,0)),IF(F$1=INDEX('Valo FX'!$R:$R,MATCH($A10,'Valo FX'!$A:$A,0)),INDEX(Base!$V:$V,MATCH($A10,Base!$A:$A,0)),0))) -> 0 | G10: =IF(G$1<INDEX('Valo FX'!$Q:$Q,MATCH($A10,'Valo FX'!$A:$A,0)),0,IF(G$1<INDEX('Valo FX'!$R:$R,MATCH($A10,'Valo FX'!$A:$A,0)),INDEX(Base!$U:$U,MATCH($A10,Base!$A:$A,0)),IF(G$1=INDEX('Valo FX'!$R:$R,MATCH($A10,'Valo FX'!$A:$A,0)),INDEX(Base!$V:$V,MATCH($A10,Base!$A:$A,0)),0))) -> 0 | H10: =IF(H$1<INDEX('Valo FX'!$Q:$Q,MATCH($A10,'Valo FX'!$A:$A,0)),0,IF(H$1<INDEX('Valo FX'!$R:$R,MATCH($A10,'Valo FX'!$A:$A,0)),INDEX(Base!$U:$U,MATCH($A10,Base!$A:$A,0)),IF(H$1=INDEX('Valo FX'!$R:$R,MATCH($A10,'Valo FX'!$A:$A,0)),INDEX(Base!$V:$V,MATCH($A10,Base!$A:$A,0)),0))) -> 15.019052 | I10: =IF(I$1<INDEX('Valo FX'!$Q:$Q,MATCH($A10,'Valo FX'!$A:$A,0)),0,IF(I$1<INDEX('Valo FX'!$R:$R,MATCH($A10,'Valo FX'!$A:$A,0)),INDEX(Base!$U:$U,MATCH($A10,Base!$A:$A,0)),IF(I$1=INDEX('Valo FX'!$R:$R,MATCH($A10,'Valo FX'!$A:$A,0)),INDEX(Base!$V:$V,MATCH($A10,Base!$A:$A,0)),0))) -> 15.019052 | J10: =IF(J$1<INDEX('Valo FX'!$Q:$Q,MATCH($A10,'Valo FX'!$A:$A,0)),0,IF(J$1<INDEX('Valo FX'!$R:$R,MATCH($A10,'Valo FX'!$A:$A,0)),INDEX(Base!$U:$U,MATCH($A10,Base!$A:$A,0)),IF(J$1=INDEX('Valo FX'!$R:$R,MATCH($A10,'Valo FX'!$A:$A,0)),INDEX(Base!$V:$V,MATCH($A10,Base!$A:$A,0)),0))) -> 15.019052 | ... MY10: =IF(MY$1<INDEX('Valo FX'!$Q:$Q,MATCH($A10,'Valo FX'!$A:$A,0)),0,IF(MY$1<INDEX('Valo FX'!$R:$R,MATCH($A10,'Valo FX'!$A:$A,0)),INDEX(Base!$U:$U,MATCH($A10,Base!$A:$A,0)),IF(MY$1=INDEX('Valo FX'!$R:$R,MATCH($A10,'Valo FX'!$A:$A,0)),INDEX(Base!$V:$V,MATCH($A10,Base!$A:$A,0)),0))) -> 0
A11: =+'Valo FX'!A12 -> 9 | B11: =-'Valo FX'!T12 -> -932.57912 | C11: =IF(C$1<INDEX('Valo FX'!$Q:$Q,MATCH($A11,'Valo FX'!$A:$A,0)),0,IF(C$1<INDEX('Valo FX'!$R:$R,MATCH($A11,'Valo FX'!$A:$A,0)),INDEX(Base!$U:$U,MATCH($A11,Base!$A:$A,0)),IF(C$1=INDEX('Valo FX'!$R:$R,MATCH($A11,'Valo FX'!$A:$A,0)),INDEX(Base!$V:$V,MATCH($A11,Base!$A:$A,0)),0))) -> 0 | D11: =IF(D$1<INDEX('Valo FX'!$Q:$Q,MATCH($A11,'Valo FX'!$A:$A,0)),0,IF(D$1<INDEX('Valo FX'!$R:$R,MATCH($A11,'Valo FX'!$A:$A,0)),INDEX(Base!$U:$U,MATCH($A11,Base!$A:$A,0)),IF(D$1=INDEX('Valo FX'!$R:$R,MATCH($A11,'Valo FX'!$A:$A,0)),INDEX(Base!$V:$V,MATCH($A11,Base!$A:$A,0)),0))) -> 0 | E11: =IF(E$1<INDEX('Valo FX'!$Q:$Q,MATCH($A11,'Valo FX'!$A:$A,0)),0,IF(E$1<INDEX('Valo FX'!$R:$R,MATCH($A11,'Valo FX'!$A:$A,0)),INDEX(Base!$U:$U,MATCH($A11,Base!$A:$A,0)),IF(E$1=INDEX('Valo FX'!$R:$R,MATCH($A11,'Valo FX'!$A:$A,0)),INDEX(Base!$V:$V,MATCH($A11,Base!$A:$A,0)),0))) -> 0 | F11: =IF(F$1<INDEX('Valo FX'!$Q:$Q,MATCH($A11,'Valo FX'!$A:$A,0)),0,IF(F$1<INDEX('Valo FX'!$R:$R,MATCH($A11,'Valo FX'!$A:$A,0)),INDEX(Base!$U:$U,MATCH($A11,Base!$A:$A,0)),IF(F$1=INDEX('Valo FX'!$R:$R,MATCH($A11,'Valo FX'!$A:$A,0)),INDEX(Base!$V:$V,MATCH($A11,Base!$A:$A,0)),0))) -> 0 | G11: =IF(G$1<INDEX('Valo FX'!$Q:$Q,MATCH($A11,'Valo FX'!$A:$A,0)),0,IF(G$1<INDEX('Valo FX'!$R:$R,MATCH($A11,'Valo FX'!$A:$A,0)),INDEX(Base!$U:$U,MATCH($A11,Base!$A:$A,0)),IF(G$1=INDEX('Valo FX'!$R:$R,MATCH($A11,'Valo FX'!$A:$A,0)),INDEX(Base!$V:$V,MATCH($A11,Base!$A:$A,0)),0))) -> 0 | H11: =IF(H$1<INDEX('Valo FX'!$Q:$Q,MATCH($A11,'Valo FX'!$A:$A,0)),0,IF(H$1<INDEX('Valo FX'!$R:$R,MATCH($A11,'Valo FX'!$A:$A,0)),INDEX(Base!$U:$U,MATCH($A11,Base!$A:$A,0)),IF(H$1=INDEX('Valo FX'!$R:$R,MATCH($A11,'Valo FX'!$A:$A,0)),INDEX(Base!$V:$V,MATCH($A11,Base!$A:$A,0)),0))) -> 6.810055 | I11: =IF(I$1<INDEX('Valo FX'!$Q:$Q,MATCH($A11,'Valo FX'!$A:$A,0)),0,IF(I$1<INDEX('Valo FX'!$R:$R,MATCH($A11,'Valo FX'!$A:$A,0)),INDEX(Base!$U:$U,MATCH($A11,Base!$A:$A,0)),IF(I$1=INDEX('Valo FX'!$R:$R,MATCH($A11,'Valo FX'!$A:$A,0)),INDEX(Base!$V:$V,MATCH($A11,Base!$A:$A,0)),0))) -> 6.810055 | J11: =IF(J$1<INDEX('Valo FX'!$Q:$Q,MATCH($A11,'Valo FX'!$A:$A,0)),0,IF(J$1<INDEX('Valo FX'!$R:$R,MATCH($A11,'Valo FX'!$A:$A,0)),INDEX(Base!$U:$U,MATCH($A11,Base!$A:$A,0)),IF(J$1=INDEX('Valo FX'!$R:$R,MATCH($A11,'Valo FX'!$A:$A,0)),INDEX(Base!$V:$V,MATCH($A11,Base!$A:$A,0)),0))) -> 6.810055 | ... MY11: =IF(MY$1<INDEX('Valo FX'!$Q:$Q,MATCH($A11,'Valo FX'!$A:$A,0)),0,IF(MY$1<INDEX('Valo FX'!$R:$R,MATCH($A11,'Valo FX'!$A:$A,0)),INDEX(Base!$U:$U,MATCH($A11,Base!$A:$A,0)),IF(MY$1=INDEX('Valo FX'!$R:$R,MATCH($A11,'Valo FX'!$A:$A,0)),INDEX(Base!$V:$V,MATCH($A11,Base!$A:$A,0)),0))) -> 0
A12: =+'Valo FX'!A13 -> 10 | B12: =-'Valo FX'!T13 -> -926.49862 | C12: =IF(C$1<INDEX('Valo FX'!$Q:$Q,MATCH($A12,'Valo FX'!$A:$A,0)),0,IF(C$1<INDEX('Valo FX'!$R:$R,MATCH($A12,'Valo FX'!$A:$A,0)),INDEX(Base!$U:$U,MATCH($A12,Base!$A:$A,0)),IF(C$1=INDEX('Valo FX'!$R:$R,MATCH($A12,'Valo FX'!$A:$A,0)),INDEX(Base!$V:$V,MATCH($A12,Base!$A:$A,0)),0))) -> 0 | D12: =IF(D$1<INDEX('Valo FX'!$Q:$Q,MATCH($A12,'Valo FX'!$A:$A,0)),0,IF(D$1<INDEX('Valo FX'!$R:$R,MATCH($A12,'Valo FX'!$A:$A,0)),INDEX(Base!$U:$U,MATCH($A12,Base!$A:$A,0)),IF(D$1=INDEX('Valo FX'!$R:$R,MATCH($A12,'Valo FX'!$A:$A,0)),INDEX(Base!$V:$V,MATCH($A12,Base!$A:$A,0)),0))) -> 0 | E12: =IF(E$1<INDEX('Valo FX'!$Q:$Q,MATCH($A12,'Valo FX'!$A:$A,0)),0,IF(E$1<INDEX('Valo FX'!$R:$R,MATCH($A12,'Valo FX'!$A:$A,0)),INDEX(Base!$U:$U,MATCH($A12,Base!$A:$A,0)),IF(E$1=INDEX('Valo FX'!$R:$R,MATCH($A12,'Valo FX'!$A:$A,0)),INDEX(Base!$V:$V,MATCH($A12,Base!$A:$A,0)),0))) -> 0 | F12: =IF(F$1<INDEX('Valo FX'!$Q:$Q,MATCH($A12,'Valo FX'!$A:$A,0)),0,IF(F$1<INDEX('Valo FX'!$R:$R,MATCH($A12,'Valo FX'!$A:$A,0)),INDEX(Base!$U:$U,MATCH($A12,Base!$A:$A,0)),IF(F$1=INDEX('Valo FX'!$R:$R,MATCH($A12,'Valo FX'!$A:$A,0)),INDEX(Base!$V:$V,MATCH($A12,Base!$A:$A,0)),0))) -> 0 | G12: =IF(G$1<INDEX('Valo FX'!$Q:$Q,MATCH($A12,'Valo FX'!$A:$A,0)),0,IF(G$1<INDEX('Valo FX'!$R:$R,MATCH($A12,'Valo FX'!$A:$A,0)),INDEX(Base!$U:$U,MATCH($A12,Base!$A:$A,0)),IF(G$1=INDEX('Valo FX'!$R:$R,MATCH($A12,'Valo FX'!$A:$A,0)),INDEX(Base!$V:$V,MATCH($A12,Base!$A:$A,0)),0))) -> 0 | H12: =IF(H$1<INDEX('Valo FX'!$Q:$Q,MATCH($A12,'Valo FX'!$A:$A,0)),0,IF(H$1<INDEX('Valo FX'!$R:$R,MATCH($A12,'Valo FX'!$A:$A,0)),INDEX(Base!$U:$U,MATCH($A12,Base!$A:$A,0)),IF(H$1=INDEX('Valo FX'!$R:$R,MATCH($A12,'Valo FX'!$A:$A,0)),INDEX(Base!$V:$V,MATCH($A12,Base!$A:$A,0)),0))) -> 7.722955 | I12: =IF(I$1<INDEX('Valo FX'!$Q:$Q,MATCH($A12,'Valo FX'!$A:$A,0)),0,IF(I$1<INDEX('Valo FX'!$R:$R,MATCH($A12,'Valo FX'!$A:$A,0)),INDEX(Base!$U:$U,MATCH($A12,Base!$A:$A,0)),IF(I$1=INDEX('Valo FX'!$R:$R,MATCH($A12,'Valo FX'!$A:$A,0)),INDEX(Base!$V:$V,MATCH($A12,Base!$A:$A,0)),0))) -> 7.722955 | J12: =IF(J$1<INDEX('Valo FX'!$Q:$Q,MATCH($A12,'Valo FX'!$A:$A,0)),0,IF(J$1<INDEX('Valo FX'!$R:$R,MATCH($A12,'Valo FX'!$A:$A,0)),INDEX(Base!$U:$U,MATCH($A12,Base!$A:$A,0)),IF(J$1=INDEX('Valo FX'!$R:$R,MATCH($A12,'Valo FX'!$A:$A,0)),INDEX(Base!$V:$V,MATCH($A12,Base!$A:$A,0)),0))) -> 7.722955 | ... MY12: =IF(MY$1<INDEX('Valo FX'!$Q:$Q,MATCH($A12,'Valo FX'!$A:$A,0)),0,IF(MY$1<INDEX('Valo FX'!$R:$R,MATCH($A12,'Valo FX'!$A:$A,0)),INDEX(Base!$U:$U,MATCH($A12,Base!$A:$A,0)),IF(MY$1=INDEX('Valo FX'!$R:$R,MATCH($A12,'Valo FX'!$A:$A,0)),INDEX(Base!$V:$V,MATCH($A12,Base!$A:$A,0)),0))) -> 0
A13: =+'Valo FX'!A14 -> 11 | B13: =-'Valo FX'!T14 -> -1666.9944 | C13: =IF(C$1<INDEX('Valo FX'!$Q:$Q,MATCH($A13,'Valo FX'!$A:$A,0)),0,IF(C$1<INDEX('Valo FX'!$R:$R,MATCH($A13,'Valo FX'!$A:$A,0)),INDEX(Base!$U:$U,MATCH($A13,Base!$A:$A,0)),IF(C$1=INDEX('Valo FX'!$R:$R,MATCH($A13,'Valo FX'!$A:$A,0)),INDEX(Base!$V:$V,MATCH($A13,Base!$A:$A,0)),0))) -> 0 | D13: =IF(D$1<INDEX('Valo FX'!$Q:$Q,MATCH($A13,'Valo FX'!$A:$A,0)),0,IF(D$1<INDEX('Valo FX'!$R:$R,MATCH($A13,'Valo FX'!$A:$A,0)),INDEX(Base!$U:$U,MATCH($A13,Base!$A:$A,0)),IF(D$1=INDEX('Valo FX'!$R:$R,MATCH($A13,'Valo FX'!$A:$A,0)),INDEX(Base!$V:$V,MATCH($A13,Base!$A:$A,0)),0))) -> 0 | E13: =IF(E$1<INDEX('Valo FX'!$Q:$Q,MATCH($A13,'Valo FX'!$A:$A,0)),0,IF(E$1<INDEX('Valo FX'!$R:$R,MATCH($A13,'Valo FX'!$A:$A,0)),INDEX(Base!$U:$U,MATCH($A13,Base!$A:$A,0)),IF(E$1=INDEX('Valo FX'!$R:$R,MATCH($A13,'Valo FX'!$A:$A,0)),INDEX(Base!$V:$V,MATCH($A13,Base!$A:$A,0)),0))) -> 0 | F13: =IF(F$1<INDEX('Valo FX'!$Q:$Q,MATCH($A13,'Valo FX'!$A:$A,0)),0,IF(F$1<INDEX('Valo FX'!$R:$R,MATCH($A13,'Valo FX'!$A:$A,0)),INDEX(Base!$U:$U,MATCH($A13,Base!$A:$A,0)),IF(F$1=INDEX('Valo FX'!$R:$R,MATCH($A13,'Valo FX'!$A:$A,0)),INDEX(Base!$V:$V,MATCH($A13,Base!$A:$A,0)),0))) -> 0 | G13: =IF(G$1<INDEX('Valo FX'!$Q:$Q,MATCH($A13,'Valo FX'!$A:$A,0)),0,IF(G$1<INDEX('Valo FX'!$R:$R,MATCH($A13,'Valo FX'!$A:$A,0)),INDEX(Base!$U:$U,MATCH($A13,Base!$A:$A,0)),IF(G$1=INDEX('Valo FX'!$R:$R,MATCH($A13,'Valo FX'!$A:$A,0)),INDEX(Base!$V:$V,MATCH($A13,Base!$A:$A,0)),0))) -> 0 | H13: =IF(H$1<INDEX('Valo FX'!$Q:$Q,MATCH($A13,'Valo FX'!$A:$A,0)),0,IF(H$1<INDEX('Valo FX'!$R:$R,MATCH($A13,'Valo FX'!$A:$A,0)),INDEX(Base!$U:$U,MATCH($A13,Base!$A:$A,0)),IF(H$1=INDEX('Valo FX'!$R:$R,MATCH($A13,'Valo FX'!$A:$A,0)),INDEX(Base!$V:$V,MATCH($A13,Base!$A:$A,0)),0))) -> 11.62117 | I13: =IF(I$1<INDEX('Valo FX'!$Q:$Q,MATCH($A13,'Valo FX'!$A:$A,0)),0,IF(I$1<INDEX('Valo FX'!$R:$R,MATCH($A13,'Valo FX'!$A:$A,0)),INDEX(Base!$U:$U,MATCH($A13,Base!$A:$A,0)),IF(I$1=INDEX('Valo FX'!$R:$R,MATCH($A13,'Valo FX'!$A:$A,0)),INDEX(Base!$V:$V,MATCH($A13,Base!$A:$A,0)),0))) -> 11.62117 | J13: =IF(J$1<INDEX('Valo FX'!$Q:$Q,MATCH($A13,'Valo FX'!$A:$A,0)),0,IF(J$1<INDEX('Valo FX'!$R:$R,MATCH($A13,'Valo FX'!$A:$A,0)),INDEX(Base!$U:$U,MATCH($A13,Base!$A:$A,0)),IF(J$1=INDEX('Valo FX'!$R:$R,MATCH($A13,'Valo FX'!$A:$A,0)),INDEX(Base!$V:$V,MATCH($A13,Base!$A:$A,0)),0))) -> 11.62117 | ... MY13: =IF(MY$1<INDEX('Valo FX'!$Q:$Q,MATCH($A13,'Valo FX'!$A:$A,0)),0,IF(MY$1<INDEX('Valo FX'!$R:$R,MATCH($A13,'Valo FX'!$A:$A,0)),INDEX(Base!$U:$U,MATCH($A13,Base!$A:$A,0)),IF(MY$1=INDEX('Valo FX'!$R:$R,MATCH($A13,'Valo FX'!$A:$A,0)),INDEX(Base!$V:$V,MATCH($A13,Base!$A:$A,0)),0))) -> 0
A14: =+'Valo FX'!A15 -> 12 | B14: =-'Valo FX'!T15 -> -934.72947 | C14: =IF(C$1<INDEX('Valo FX'!$Q:$Q,MATCH($A14,'Valo FX'!$A:$A,0)),0,IF(C$1<INDEX('Valo FX'!$R:$R,MATCH($A14,'Valo FX'!$A:$A,0)),INDEX(Base!$U:$U,MATCH($A14,Base!$A:$A,0)),IF(C$1=INDEX('Valo FX'!$R:$R,MATCH($A14,'Valo FX'!$A:$A,0)),INDEX(Base!$V:$V,MATCH($A14,Base!$A:$A,0)),0))) -> 0 | D14: =IF(D$1<INDEX('Valo FX'!$Q:$Q,MATCH($A14,'Valo FX'!$A:$A,0)),0,IF(D$1<INDEX('Valo FX'!$R:$R,MATCH($A14,'Valo FX'!$A:$A,0)),INDEX(Base!$U:$U,MATCH($A14,Base!$A:$A,0)),IF(D$1=INDEX('Valo FX'!$R:$R,MATCH($A14,'Valo FX'!$A:$A,0)),INDEX(Base!$V:$V,MATCH($A14,Base!$A:$A,0)),0))) -> 0 | E14: =IF(E$1<INDEX('Valo FX'!$Q:$Q,MATCH($A14,'Valo FX'!$A:$A,0)),0,IF(E$1<INDEX('Valo FX'!$R:$R,MATCH($A14,'Valo FX'!$A:$A,0)),INDEX(Base!$U:$U,MATCH($A14,Base!$A:$A,0)),IF(E$1=INDEX('Valo FX'!$R:$R,MATCH($A14,'Valo FX'!$A:$A,0)),INDEX(Base!$V:$V,MATCH($A14,Base!$A:$A,0)),0))) -> 0 | F14: =IF(F$1<INDEX('Valo FX'!$Q:$Q,MATCH($A14,'Valo FX'!$A:$A,0)),0,IF(F$1<INDEX('Valo FX'!$R:$R,MATCH($A14,'Valo FX'!$A:$A,0)),INDEX(Base!$U:$U,MATCH($A14,Base!$A:$A,0)),IF(F$1=INDEX('Valo FX'!$R:$R,MATCH($A14,'Valo FX'!$A:$A,0)),INDEX(Base!$V:$V,MATCH($A14,Base!$A:$A,0)),0))) -> 0 | G14: =IF(G$1<INDEX('Valo FX'!$Q:$Q,MATCH($A14,'Valo FX'!$A:$A,0)),0,IF(G$1<INDEX('Valo FX'!$R:$R,MATCH($A14,'Valo FX'!$A:$A,0)),INDEX(Base!$U:$U,MATCH($A14,Base!$A:$A,0)),IF(G$1=INDEX('Valo FX'!$R:$R,MATCH($A14,'Valo FX'!$A:$A,0)),INDEX(Base!$V:$V,MATCH($A14,Base!$A:$A,0)),0))) -> 0 | H14: =IF(H$1<INDEX('Valo FX'!$Q:$Q,MATCH($A14,'Valo FX'!$A:$A,0)),0,IF(H$1<INDEX('Valo FX'!$R:$R,MATCH($A14,'Valo FX'!$A:$A,0)),INDEX(Base!$U:$U,MATCH($A14,Base!$A:$A,0)),IF(H$1=INDEX('Valo FX'!$R:$R,MATCH($A14,'Valo FX'!$A:$A,0)),INDEX(Base!$V:$V,MATCH($A14,Base!$A:$A,0)),0))) -> 6.58362 | I14: =IF(I$1<INDEX('Valo FX'!$Q:$Q,MATCH($A14,'Valo FX'!$A:$A,0)),0,IF(I$1<INDEX('Valo FX'!$R:$R,MATCH($A14,'Valo FX'!$A:$A,0)),INDEX(Base!$U:$U,MATCH($A14,Base!$A:$A,0)),IF(I$1=INDEX('Valo FX'!$R:$R,MATCH($A14,'Valo FX'!$A:$A,0)),INDEX(Base!$V:$V,MATCH($A14,Base!$A:$A,0)),0))) -> 6.58362 | J14: =IF(J$1<INDEX('Valo FX'!$Q:$Q,MATCH($A14,'Valo FX'!$A:$A,0)),0,IF(J$1<INDEX('Valo FX'!$R:$R,MATCH($A14,'Valo FX'!$A:$A,0)),INDEX(Base!$U:$U,MATCH($A14,Base!$A:$A,0)),IF(J$1=INDEX('Valo FX'!$R:$R,MATCH($A14,'Valo FX'!$A:$A,0)),INDEX(Base!$V:$V,MATCH($A14,Base!$A:$A,0)),0))) -> 6.58362 | ... MY14: =IF(MY$1<INDEX('Valo FX'!$Q:$Q,MATCH($A14,'Valo FX'!$A:$A,0)),0,IF(MY$1<INDEX('Valo FX'!$R:$R,MATCH($A14,'Valo FX'!$A:$A,0)),INDEX(Base!$U:$U,MATCH($A14,Base!$A:$A,0)),IF(MY$1=INDEX('Valo FX'!$R:$R,MATCH($A14,'Valo FX'!$A:$A,0)),INDEX(Base!$V:$V,MATCH($A14,Base!$A:$A,0)),0))) -> 0
... A23: =+'Valo FX'!A24 -> 21 | B23: =-'Valo FX'!T24 -> -1646.2706 | C23: =IF(C$1<INDEX('Valo FX'!$Q:$Q,MATCH($A23,'Valo FX'!$A:$A,0)),0,IF(C$1<INDEX('Valo FX'!$R:$R,MATCH($A23,'Valo FX'!$A:$A,0)),INDEX(Base!$U:$U,MATCH($A23,Base!$A:$A,0)),IF(C$1=INDEX('Valo FX'!$R:$R,MATCH($A23,'Valo FX'!$A:$A,0)),INDEX(Base!$V:$V,MATCH($A23,Base!$A:$A,0)),0))) -> 0 | D23: =IF(D$1<INDEX('Valo FX'!$Q:$Q,MATCH($A23,'Valo FX'!$A:$A,0)),0,IF(D$1<INDEX('Valo FX'!$R:$R,MATCH($A23,'Valo FX'!$A:$A,0)),INDEX(Base!$U:$U,MATCH($A23,Base!$A:$A,0)),IF(D$1=INDEX('Valo FX'!$R:$R,MATCH($A23,'Valo FX'!$A:$A,0)),INDEX(Base!$V:$V,MATCH($A23,Base!$A:$A,0)),0))) -> 0 | E23: =IF(E$1<INDEX('Valo FX'!$Q:$Q,MATCH($A23,'Valo FX'!$A:$A,0)),0,IF(E$1<INDEX('Valo FX'!$R:$R,MATCH($A23,'Valo FX'!$A:$A,0)),INDEX(Base!$U:$U,MATCH($A23,Base!$A:$A,0)),IF(E$1=INDEX('Valo FX'!$R:$R,MATCH($A23,'Valo FX'!$A:$A,0)),INDEX(Base!$V:$V,MATCH($A23,Base!$A:$A,0)),0))) -> 0 | F23: =IF(F$1<INDEX('Valo FX'!$Q:$Q,MATCH($A23,'Valo FX'!$A:$A,0)),0,IF(F$1<INDEX('Valo FX'!$R:$R,MATCH($A23,'Valo FX'!$A:$A,0)),INDEX(Base!$U:$U,MATCH($A23,Base!$A:$A,0)),IF(F$1=INDEX('Valo FX'!$R:$R,MATCH($A23,'Valo FX'!$A:$A,0)),INDEX(Base!$V:$V,MATCH($A23,Base!$A:$A,0)),0))) -> 0 | G23: =IF(G$1<INDEX('Valo FX'!$Q:$Q,MATCH($A23,'Valo FX'!$A:$A,0)),0,IF(G$1<INDEX('Valo FX'!$R:$R,MATCH($A23,'Valo FX'!$A:$A,0)),INDEX(Base!$U:$U,MATCH($A23,Base!$A:$A,0)),IF(G$1=INDEX('Valo FX'!$R:$R,MATCH($A23,'Valo FX'!$A:$A,0)),INDEX(Base!$V:$V,MATCH($A23,Base!$A:$A,0)),0))) -> 0 | H23: =IF(H$1<INDEX('Valo FX'!$Q:$Q,MATCH($A23,'Valo FX'!$A:$A,0)),0,IF(H$1<INDEX('Valo FX'!$R:$R,MATCH($A23,'Valo FX'!$A:$A,0)),INDEX(Base!$U:$U,MATCH($A23,Base!$A:$A,0)),IF(H$1=INDEX('Valo FX'!$R:$R,MATCH($A23,'Valo FX'!$A:$A,0)),INDEX(Base!$V:$V,MATCH($A23,Base!$A:$A,0)),0))) -> 0 | I23: =IF(I$1<INDEX('Valo FX'!$Q:$Q,MATCH($A23,'Valo FX'!$A:$A,0)),0,IF(I$1<INDEX('Valo FX'!$R:$R,MATCH($A23,'Valo FX'!$A:$A,0)),INDEX(Base!$U:$U,MATCH($A23,Base!$A:$A,0)),IF(I$1=INDEX('Valo FX'!$R:$R,MATCH($A23,'Valo FX'!$A:$A,0)),INDEX(Base!$V:$V,MATCH($A23,Base!$A:$A,0)),0))) -> 12.012828 | J23: =IF(J$1<INDEX('Valo FX'!$Q:$Q,MATCH($A23,'Valo FX'!$A:$A,0)),0,IF(J$1<INDEX('Valo FX'!$R:$R,MATCH($A23,'Valo FX'!$A:$A,0)),INDEX(Base!$U:$U,MATCH($A23,Base!$A:$A,0)),IF(J$1=INDEX('Valo FX'!$R:$R,MATCH($A23,'Valo FX'!$A:$A,0)),INDEX(Base!$V:$V,MATCH($A23,Base!$A:$A,0)),0))) -> 12.012828 | ... MY23: =IF(MY$1<INDEX('Valo FX'!$Q:$Q,MATCH($A23,'Valo FX'!$A:$A,0)),0,IF(MY$1<INDEX('Valo FX'!$R:$R,MATCH($A23,'Valo FX'!$A:$A,0)),INDEX(Base!$U:$U,MATCH($A23,Base!$A:$A,0)),IF(MY$1=INDEX('Valo FX'!$R:$R,MATCH($A23,'Valo FX'!$A:$A,0)),INDEX(Base!$V:$V,MATCH($A23,Base!$A:$A,0)),0))) -> 0
A24: =+A23+1 -> 22 | B24: =-'Valo FX'!T25 -> -1438.1085 | C24: =IF(C$1<INDEX('Valo FX'!$Q:$Q,MATCH($A24,'Valo FX'!$A:$A,0)),0,IF(C$1<INDEX('Valo FX'!$R:$R,MATCH($A24,'Valo FX'!$A:$A,0)),INDEX(Base!$U:$U,MATCH($A24,Base!$A:$A,0)),IF(C$1=INDEX('Valo FX'!$R:$R,MATCH($A24,'Valo FX'!$A:$A,0)),INDEX(Base!$V:$V,MATCH($A24,Base!$A:$A,0)),0))) -> 0 | D24: =IF(D$1<INDEX('Valo FX'!$Q:$Q,MATCH($A24,'Valo FX'!$A:$A,0)),0,IF(D$1<INDEX('Valo FX'!$R:$R,MATCH($A24,'Valo FX'!$A:$A,0)),INDEX(Base!$U:$U,MATCH($A24,Base!$A:$A,0)),IF(D$1=INDEX('Valo FX'!$R:$R,MATCH($A24,'Valo FX'!$A:$A,0)),INDEX(Base!$V:$V,MATCH($A24,Base!$A:$A,0)),0))) -> 0 | E24: =IF(E$1<INDEX('Valo FX'!$Q:$Q,MATCH($A24,'Valo FX'!$A:$A,0)),0,IF(E$1<INDEX('Valo FX'!$R:$R,MATCH($A24,'Valo FX'!$A:$A,0)),INDEX(Base!$U:$U,MATCH($A24,Base!$A:$A,0)),IF(E$1=INDEX('Valo FX'!$R:$R,MATCH($A24,'Valo FX'!$A:$A,0)),INDEX(Base!$V:$V,MATCH($A24,Base!$A:$A,0)),0))) -> 0 | F24: =IF(F$1<INDEX('Valo FX'!$Q:$Q,MATCH($A24,'Valo FX'!$A:$A,0)),0,IF(F$1<INDEX('Valo FX'!$R:$R,MATCH($A24,'Valo FX'!$A:$A,0)),INDEX(Base!$U:$U,MATCH($A24,Base!$A:$A,0)),IF(F$1=INDEX('Valo FX'!$R:$R,MATCH($A24,'Valo FX'!$A:$A,0)),INDEX(Base!$V:$V,MATCH($A24,Base!$A:$A,0)),0))) -> 0 | G24: =IF(G$1<INDEX('Valo FX'!$Q:$Q,MATCH($A24,'Valo FX'!$A:$A,0)),0,IF(G$1<INDEX('Valo FX'!$R:$R,MATCH($A24,'Valo FX'!$A:$A,0)),INDEX(Base!$U:$U,MATCH($A24,Base!$A:$A,0)),IF(G$1=INDEX('Valo FX'!$R:$R,MATCH($A24,'Valo FX'!$A:$A,0)),INDEX(Base!$V:$V,MATCH($A24,Base!$A:$A,0)),0))) -> 0 | H24: =IF(H$1<INDEX('Valo FX'!$Q:$Q,MATCH($A24,'Valo FX'!$A:$A,0)),0,IF(H$1<INDEX('Valo FX'!$R:$R,MATCH($A24,'Valo FX'!$A:$A,0)),INDEX(Base!$U:$U,MATCH($A24,Base!$A:$A,0)),IF(H$1=INDEX('Valo FX'!$R:$R,MATCH($A24,'Valo FX'!$A:$A,0)),INDEX(Base!$V:$V,MATCH($A24,Base!$A:$A,0)),0))) -> 0 | I24: =IF(I$1<INDEX('Valo FX'!$Q:$Q,MATCH($A24,'Valo FX'!$A:$A,0)),0,IF(I$1<INDEX('Valo FX'!$R:$R,MATCH($A24,'Valo FX'!$A:$A,0)),INDEX(Base!$U:$U,MATCH($A24,Base!$A:$A,0)),IF(I$1=INDEX('Valo FX'!$R:$R,MATCH($A24,'Valo FX'!$A:$A,0)),INDEX(Base!$V:$V,MATCH($A24,Base!$A:$A,0)),0))) -> 10.200271 | J24: =IF(J$1<INDEX('Valo FX'!$Q:$Q,MATCH($A24,'Valo FX'!$A:$A,0)),0,IF(J$1<INDEX('Valo FX'!$R:$R,MATCH($A24,'Valo FX'!$A:$A,0)),INDEX(Base!$U:$U,MATCH($A24,Base!$A:$A,0)),IF(J$1=INDEX('Valo FX'!$R:$R,MATCH($A24,'Valo FX'!$A:$A,0)),INDEX(Base!$V:$V,MATCH($A24,Base!$A:$A,0)),0))) -> 10.200271 | ... MY24: =IF(MY$1<INDEX('Valo FX'!$Q:$Q,MATCH($A24,'Valo FX'!$A:$A,0)),0,IF(MY$1<INDEX('Valo FX'!$R:$R,MATCH($A24,'Valo FX'!$A:$A,0)),INDEX(Base!$U:$U,MATCH($A24,Base!$A:$A,0)),IF(MY$1=INDEX('Valo FX'!$R:$R,MATCH($A24,'Valo FX'!$A:$A,0)),INDEX(Base!$V:$V,MATCH($A24,Base!$A:$A,0)),0))) -> 0
A25: =+A24+1 -> 23 | B25: =-'Valo FX'!T26 -> -1628.2509 | C25: =IF(C$1<INDEX('Valo FX'!$Q:$Q,MATCH($A25,'Valo FX'!$A:$A,0)),0,IF(C$1<INDEX('Valo FX'!$R:$R,MATCH($A25,'Valo FX'!$A:$A,0)),INDEX(Base!$U:$U,MATCH($A25,Base!$A:$A,0)),IF(C$1=INDEX('Valo FX'!$R:$R,MATCH($A25,'Valo FX'!$A:$A,0)),INDEX(Base!$V:$V,MATCH($A25,Base!$A:$A,0)),0))) -> 0 | D25: =IF(D$1<INDEX('Valo FX'!$Q:$Q,MATCH($A25,'Valo FX'!$A:$A,0)),0,IF(D$1<INDEX('Valo FX'!$R:$R,MATCH($A25,'Valo FX'!$A:$A,0)),INDEX(Base!$U:$U,MATCH($A25,Base!$A:$A,0)),IF(D$1=INDEX('Valo FX'!$R:$R,MATCH($A25,'Valo FX'!$A:$A,0)),INDEX(Base!$V:$V,MATCH($A25,Base!$A:$A,0)),0))) -> 0 | E25: =IF(E$1<INDEX('Valo FX'!$Q:$Q,MATCH($A25,'Valo FX'!$A:$A,0)),0,IF(E$1<INDEX('Valo FX'!$R:$R,MATCH($A25,'Valo FX'!$A:$A,0)),INDEX(Base!$U:$U,MATCH($A25,Base!$A:$A,0)),IF(E$1=INDEX('Valo FX'!$R:$R,MATCH($A25,'Valo FX'!$A:$A,0)),INDEX(Base!$V:$V,MATCH($A25,Base!$A:$A,0)),0))) -> 0 | F25: =IF(F$1<INDEX('Valo FX'!$Q:$Q,MATCH($A25,'Valo FX'!$A:$A,0)),0,IF(F$1<INDEX('Valo FX'!$R:$R,MATCH($A25,'Valo FX'!$A:$A,0)),INDEX(Base!$U:$U,MATCH($A25,Base!$A:$A,0)),IF(F$1=INDEX('Valo FX'!$R:$R,MATCH($A25,'Valo FX'!$A:$A,0)),INDEX(Base!$V:$V,MATCH($A25,Base!$A:$A,0)),0))) -> 0 | G25: =IF(G$1<INDEX('Valo FX'!$Q:$Q,MATCH($A25,'Valo FX'!$A:$A,0)),0,IF(G$1<INDEX('Valo FX'!$R:$R,MATCH($A25,'Valo FX'!$A:$A,0)),INDEX(Base!$U:$U,MATCH($A25,Base!$A:$A,0)),IF(G$1=INDEX('Valo FX'!$R:$R,MATCH($A25,'Valo FX'!$A:$A,0)),INDEX(Base!$V:$V,MATCH($A25,Base!$A:$A,0)),0))) -> 0 | H25: =IF(H$1<INDEX('Valo FX'!$Q:$Q,MATCH($A25,'Valo FX'!$A:$A,0)),0,IF(H$1<INDEX('Valo FX'!$R:$R,MATCH($A25,'Valo FX'!$A:$A,0)),INDEX(Base!$U:$U,MATCH($A25,Base!$A:$A,0)),IF(H$1=INDEX('Valo FX'!$R:$R,MATCH($A25,'Valo FX'!$A:$A,0)),INDEX(Base!$V:$V,MATCH($A25,Base!$A:$A,0)),0))) -> 0 | I25: =IF(I$1<INDEX('Valo FX'!$Q:$Q,MATCH($A25,'Valo FX'!$A:$A,0)),0,IF(I$1<INDEX('Valo FX'!$R:$R,MATCH($A25,'Valo FX'!$A:$A,0)),INDEX(Base!$U:$U,MATCH($A25,Base!$A:$A,0)),IF(I$1=INDEX('Valo FX'!$R:$R,MATCH($A25,'Valo FX'!$A:$A,0)),INDEX(Base!$V:$V,MATCH($A25,Base!$A:$A,0)),0))) -> 11.54892 | J25: =IF(J$1<INDEX('Valo FX'!$Q:$Q,MATCH($A25,'Valo FX'!$A:$A,0)),0,IF(J$1<INDEX('Valo FX'!$R:$R,MATCH($A25,'Valo FX'!$A:$A,0)),INDEX(Base!$U:$U,MATCH($A25,Base!$A:$A,0)),IF(J$1=INDEX('Valo FX'!$R:$R,MATCH($A25,'Valo FX'!$A:$A,0)),INDEX(Base!$V:$V,MATCH($A25,Base!$A:$A,0)),0))) -> 11.54892 | ... MY25: =IF(MY$1<INDEX('Valo FX'!$Q:$Q,MATCH($A25,'Valo FX'!$A:$A,0)),0,IF(MY$1<INDEX('Valo FX'!$R:$R,MATCH($A25,'Valo FX'!$A:$A,0)),INDEX(Base!$U:$U,MATCH($A25,Base!$A:$A,0)),IF(MY$1=INDEX('Valo FX'!$R:$R,MATCH($A25,'Valo FX'!$A:$A,0)),INDEX(Base!$V:$V,MATCH($A25,Base!$A:$A,0)),0))) -> 0
A26: =+A25+1 -> 24 | B26: =-'Valo FX'!T27 -> -1787.9164 | C26: =IF(C$1<INDEX('Valo FX'!$Q:$Q,MATCH($A26,'Valo FX'!$A:$A,0)),0,IF(C$1<INDEX('Valo FX'!$R:$R,MATCH($A26,'Valo FX'!$A:$A,0)),INDEX(Base!$U:$U,MATCH($A26,Base!$A:$A,0)),IF(C$1=INDEX('Valo FX'!$R:$R,MATCH($A26,'Valo FX'!$A:$A,0)),INDEX(Base!$V:$V,MATCH($A26,Base!$A:$A,0)),0))) -> 0 | D26: =IF(D$1<INDEX('Valo FX'!$Q:$Q,MATCH($A26,'Valo FX'!$A:$A,0)),0,IF(D$1<INDEX('Valo FX'!$R:$R,MATCH($A26,'Valo FX'!$A:$A,0)),INDEX(Base!$U:$U,MATCH($A26,Base!$A:$A,0)),IF(D$1=INDEX('Valo FX'!$R:$R,MATCH($A26,'Valo FX'!$A:$A,0)),INDEX(Base!$V:$V,MATCH($A26,Base!$A:$A,0)),0))) -> 0 | E26: =IF(E$1<INDEX('Valo FX'!$Q:$Q,MATCH($A26,'Valo FX'!$A:$A,0)),0,IF(E$1<INDEX('Valo FX'!$R:$R,MATCH($A26,'Valo FX'!$A:$A,0)),INDEX(Base!$U:$U,MATCH($A26,Base!$A:$A,0)),IF(E$1=INDEX('Valo FX'!$R:$R,MATCH($A26,'Valo FX'!$A:$A,0)),INDEX(Base!$V:$V,MATCH($A26,Base!$A:$A,0)),0))) -> 0 | F26: =IF(F$1<INDEX('Valo FX'!$Q:$Q,MATCH($A26,'Valo FX'!$A:$A,0)),0,IF(F$1<INDEX('Valo FX'!$R:$R,MATCH($A26,'Valo FX'!$A:$A,0)),INDEX(Base!$U:$U,MATCH($A26,Base!$A:$A,0)),IF(F$1=INDEX('Valo FX'!$R:$R,MATCH($A26,'Valo FX'!$A:$A,0)),INDEX(Base!$V:$V,MATCH($A26,Base!$A:$A,0)),0))) -> 0 | G26: =IF(G$1<INDEX('Valo FX'!$Q:$Q,MATCH($A26,'Valo FX'!$A:$A,0)),0,IF(G$1<INDEX('Valo FX'!$R:$R,MATCH($A26,'Valo FX'!$A:$A,0)),INDEX(Base!$U:$U,MATCH($A26,Base!$A:$A,0)),IF(G$1=INDEX('Valo FX'!$R:$R,MATCH($A26,'Valo FX'!$A:$A,0)),INDEX(Base!$V:$V,MATCH($A26,Base!$A:$A,0)),0))) -> 0 | H26: =IF(H$1<INDEX('Valo FX'!$Q:$Q,MATCH($A26,'Valo FX'!$A:$A,0)),0,IF(H$1<INDEX('Valo FX'!$R:$R,MATCH($A26,'Valo FX'!$A:$A,0)),INDEX(Base!$U:$U,MATCH($A26,Base!$A:$A,0)),IF(H$1=INDEX('Valo FX'!$R:$R,MATCH($A26,'Valo FX'!$A:$A,0)),INDEX(Base!$V:$V,MATCH($A26,Base!$A:$A,0)),0))) -> 0 | I26: =IF(I$1<INDEX('Valo FX'!$Q:$Q,MATCH($A26,'Valo FX'!$A:$A,0)),0,IF(I$1<INDEX('Valo FX'!$R:$R,MATCH($A26,'Valo FX'!$A:$A,0)),INDEX(Base!$U:$U,MATCH($A26,Base!$A:$A,0)),IF(I$1=INDEX('Valo FX'!$R:$R,MATCH($A26,'Valo FX'!$A:$A,0)),INDEX(Base!$V:$V,MATCH($A26,Base!$A:$A,0)),0))) -> 12.24984 | J26: =IF(J$1<INDEX('Valo FX'!$Q:$Q,MATCH($A26,'Valo FX'!$A:$A,0)),0,IF(J$1<INDEX('Valo FX'!$R:$R,MATCH($A26,'Valo FX'!$A:$A,0)),INDEX(Base!$U:$U,MATCH($A26,Base!$A:$A,0)),IF(J$1=INDEX('Valo FX'!$R:$R,MATCH($A26,'Valo FX'!$A:$A,0)),INDEX(Base!$V:$V,MATCH($A26,Base!$A:$A,0)),0))) -> 12.24984 | ... MY26: =IF(MY$1<INDEX('Valo FX'!$Q:$Q,MATCH($A26,'Valo FX'!$A:$A,0)),0,IF(MY$1<INDEX('Valo FX'!$R:$R,MATCH($A26,'Valo FX'!$A:$A,0)),INDEX(Base!$U:$U,MATCH($A26,Base!$A:$A,0)),IF(MY$1=INDEX('Valo FX'!$R:$R,MATCH($A26,'Valo FX'!$A:$A,0)),INDEX(Base!$V:$V,MATCH($A26,Base!$A:$A,0)),0))) -> 12.6334
A27: =+A26+1 -> 25 | B27: =-'Valo FX'!T28 -> -1758.8108 | C27: =IF(C$1<INDEX('Valo FX'!$Q:$Q,MATCH($A27,'Valo FX'!$A:$A,0)),0,IF(C$1<INDEX('Valo FX'!$R:$R,MATCH($A27,'Valo FX'!$A:$A,0)),INDEX(Base!$U:$U,MATCH($A27,Base!$A:$A,0)),IF(C$1=INDEX('Valo FX'!$R:$R,MATCH($A27,'Valo FX'!$A:$A,0)),INDEX(Base!$V:$V,MATCH($A27,Base!$A:$A,0)),0))) -> 0 | D27: =IF(D$1<INDEX('Valo FX'!$Q:$Q,MATCH($A27,'Valo FX'!$A:$A,0)),0,IF(D$1<INDEX('Valo FX'!$R:$R,MATCH($A27,'Valo FX'!$A:$A,0)),INDEX(Base!$U:$U,MATCH($A27,Base!$A:$A,0)),IF(D$1=INDEX('Valo FX'!$R:$R,MATCH($A27,'Valo FX'!$A:$A,0)),INDEX(Base!$V:$V,MATCH($A27,Base!$A:$A,0)),0))) -> 0 | E27: =IF(E$1<INDEX('Valo FX'!$Q:$Q,MATCH($A27,'Valo FX'!$A:$A,0)),0,IF(E$1<INDEX('Valo FX'!$R:$R,MATCH($A27,'Valo FX'!$A:$A,0)),INDEX(Base!$U:$U,MATCH($A27,Base!$A:$A,0)),IF(E$1=INDEX('Valo FX'!$R:$R,MATCH($A27,'Valo FX'!$A:$A,0)),INDEX(Base!$V:$V,MATCH($A27,Base!$A:$A,0)),0))) -> 0 | F27: =IF(F$1<INDEX('Valo FX'!$Q:$Q,MATCH($A27,'Valo FX'!$A:$A,0)),0,IF(F$1<INDEX('Valo FX'!$R:$R,MATCH($A27,'Valo FX'!$A:$A,0)),INDEX(Base!$U:$U,MATCH($A27,Base!$A:$A,0)),IF(F$1=INDEX('Valo FX'!$R:$R,MATCH($A27,'Valo FX'!$A:$A,0)),INDEX(Base!$V:$V,MATCH($A27,Base!$A:$A,0)),0))) -> 0 | G27: =IF(G$1<INDEX('Valo FX'!$Q:$Q,MATCH($A27,'Valo FX'!$A:$A,0)),0,IF(G$1<INDEX('Valo FX'!$R:$R,MATCH($A27,'Valo FX'!$A:$A,0)),INDEX(Base!$U:$U,MATCH($A27,Base!$A:$A,0)),IF(G$1=INDEX('Valo FX'!$R:$R,MATCH($A27,'Valo FX'!$A:$A,0)),INDEX(Base!$V:$V,MATCH($A27,Base!$A:$A,0)),0))) -> 0 | H27: =IF(H$1<INDEX('Valo FX'!$Q:$Q,MATCH($A27,'Valo FX'!$A:$A,0)),0,IF(H$1<INDEX('Valo FX'!$R:$R,MATCH($A27,'Valo FX'!$A:$A,0)),INDEX(Base!$U:$U,MATCH($A27,Base!$A:$A,0)),IF(H$1=INDEX('Valo FX'!$R:$R,MATCH($A27,'Valo FX'!$A:$A,0)),INDEX(Base!$V:$V,MATCH($A27,Base!$A:$A,0)),0))) -> 0 | I27: =IF(I$1<INDEX('Valo FX'!$Q:$Q,MATCH($A27,'Valo FX'!$A:$A,0)),0,IF(I$1<INDEX('Valo FX'!$R:$R,MATCH($A27,'Valo FX'!$A:$A,0)),INDEX(Base!$U:$U,MATCH($A27,Base!$A:$A,0)),IF(I$1=INDEX('Valo FX'!$R:$R,MATCH($A27,'Valo FX'!$A:$A,0)),INDEX(Base!$V:$V,MATCH($A27,Base!$A:$A,0)),0))) -> 12.050424 | J27: =IF(J$1<INDEX('Valo FX'!$Q:$Q,MATCH($A27,'Valo FX'!$A:$A,0)),0,IF(J$1<INDEX('Valo FX'!$R:$R,MATCH($A27,'Valo FX'!$A:$A,0)),INDEX(Base!$U:$U,MATCH($A27,Base!$A:$A,0)),IF(J$1=INDEX('Valo FX'!$R:$R,MATCH($A27,'Valo FX'!$A:$A,0)),INDEX(Base!$V:$V,MATCH($A27,Base!$A:$A,0)),0))) -> 12.050424 | ... MY27: =IF(MY$1<INDEX('Valo FX'!$Q:$Q,MATCH($A27,'Valo FX'!$A:$A,0)),0,IF(MY$1<INDEX('Valo FX'!$R:$R,MATCH($A27,'Valo FX'!$A:$A,0)),INDEX(Base!$U:$U,MATCH($A27,Base!$A:$A,0)),IF(MY$1=INDEX('Valo FX'!$R:$R,MATCH($A27,'Valo FX'!$A:$A,0)),INDEX(Base!$V:$V,MATCH($A27,Base!$A:$A,0)),0))) -> 12.42774
A28: =+A27+1 -> 26 | B28: =-'Valo FX'!T29 -> -1787.9164 | C28: =IF(C$1<INDEX('Valo FX'!$Q:$Q,MATCH($A28,'Valo FX'!$A:$A,0)),0,IF(C$1<INDEX('Valo FX'!$R:$R,MATCH($A28,'Valo FX'!$A:$A,0)),INDEX(Base!$U:$U,MATCH($A28,Base!$A:$A,0)),IF(C$1=INDEX('Valo FX'!$R:$R,MATCH($A28,'Valo FX'!$A:$A,0)),INDEX(Base!$V:$V,MATCH($A28,Base!$A:$A,0)),0))) -> 0 | D28: =IF(D$1<INDEX('Valo FX'!$Q:$Q,MATCH($A28,'Valo FX'!$A:$A,0)),0,IF(D$1<INDEX('Valo FX'!$R:$R,MATCH($A28,'Valo FX'!$A:$A,0)),INDEX(Base!$U:$U,MATCH($A28,Base!$A:$A,0)),IF(D$1=INDEX('Valo FX'!$R:$R,MATCH($A28,'Valo FX'!$A:$A,0)),INDEX(Base!$V:$V,MATCH($A28,Base!$A:$A,0)),0))) -> 0 | E28: =IF(E$1<INDEX('Valo FX'!$Q:$Q,MATCH($A28,'Valo FX'!$A:$A,0)),0,IF(E$1<INDEX('Valo FX'!$R:$R,MATCH($A28,'Valo FX'!$A:$A,0)),INDEX(Base!$U:$U,MATCH($A28,Base!$A:$A,0)),IF(E$1=INDEX('Valo FX'!$R:$R,MATCH($A28,'Valo FX'!$A:$A,0)),INDEX(Base!$V:$V,MATCH($A28,Base!$A:$A,0)),0))) -> 0 | F28: =IF(F$1<INDEX('Valo FX'!$Q:$Q,MATCH($A28,'Valo FX'!$A:$A,0)),0,IF(F$1<INDEX('Valo FX'!$R:$R,MATCH($A28,'Valo FX'!$A:$A,0)),INDEX(Base!$U:$U,MATCH($A28,Base!$A:$A,0)),IF(F$1=INDEX('Valo FX'!$R:$R,MATCH($A28,'Valo FX'!$A:$A,0)),INDEX(Base!$V:$V,MATCH($A28,Base!$A:$A,0)),0))) -> 0 | G28: =IF(G$1<INDEX('Valo FX'!$Q:$Q,MATCH($A28,'Valo FX'!$A:$A,0)),0,IF(G$1<INDEX('Valo FX'!$R:$R,MATCH($A28,'Valo FX'!$A:$A,0)),INDEX(Base!$U:$U,MATCH($A28,Base!$A:$A,0)),IF(G$1=INDEX('Valo FX'!$R:$R,MATCH($A28,'Valo FX'!$A:$A,0)),INDEX(Base!$V:$V,MATCH($A28,Base!$A:$A,0)),0))) -> 0 | H28: =IF(H$1<INDEX('Valo FX'!$Q:$Q,MATCH($A28,'Valo FX'!$A:$A,0)),0,IF(H$1<INDEX('Valo FX'!$R:$R,MATCH($A28,'Valo FX'!$A:$A,0)),INDEX(Base!$U:$U,MATCH($A28,Base!$A:$A,0)),IF(H$1=INDEX('Valo FX'!$R:$R,MATCH($A28,'Valo FX'!$A:$A,0)),INDEX(Base!$V:$V,MATCH($A28,Base!$A:$A,0)),0))) -> 0 | I28: =IF(I$1<INDEX('Valo FX'!$Q:$Q,MATCH($A28,'Valo FX'!$A:$A,0)),0,IF(I$1<INDEX('Valo FX'!$R:$R,MATCH($A28,'Valo FX'!$A:$A,0)),INDEX(Base!$U:$U,MATCH($A28,Base!$A:$A,0)),IF(I$1=INDEX('Valo FX'!$R:$R,MATCH($A28,'Valo FX'!$A:$A,0)),INDEX(Base!$V:$V,MATCH($A28,Base!$A:$A,0)),0))) -> 12.24984 | J28: =IF(J$1<INDEX('Valo FX'!$Q:$Q,MATCH($A28,'Valo FX'!$A:$A,0)),0,IF(J$1<INDEX('Valo FX'!$R:$R,MATCH($A28,'Valo FX'!$A:$A,0)),INDEX(Base!$U:$U,MATCH($A28,Base!$A:$A,0)),IF(J$1=INDEX('Valo FX'!$R:$R,MATCH($A28,'Valo FX'!$A:$A,0)),INDEX(Base!$V:$V,MATCH($A28,Base!$A:$A,0)),0))) -> 12.24984 | ... MY28: =IF(MY$1<INDEX('Valo FX'!$Q:$Q,MATCH($A28,'Valo FX'!$A:$A,0)),0,IF(MY$1<INDEX('Valo FX'!$R:$R,MATCH($A28,'Valo FX'!$A:$A,0)),INDEX(Base!$U:$U,MATCH($A28,Base!$A:$A,0)),IF(MY$1=INDEX('Valo FX'!$R:$R,MATCH($A28,'Valo FX'!$A:$A,0)),INDEX(Base!$V:$V,MATCH($A28,Base!$A:$A,0)),0))) -> 12.6334
A29: =+A28+1 -> 27 | B29: =-'Valo FX'!T30 -> -893.63596 | C29: =IF(C$1<INDEX('Valo FX'!$Q:$Q,MATCH($A29,'Valo FX'!$A:$A,0)),0,IF(C$1<INDEX('Valo FX'!$R:$R,MATCH($A29,'Valo FX'!$A:$A,0)),INDEX(Base!$U:$U,MATCH($A29,Base!$A:$A,0)),IF(C$1=INDEX('Valo FX'!$R:$R,MATCH($A29,'Valo FX'!$A:$A,0)),INDEX(Base!$V:$V,MATCH($A29,Base!$A:$A,0)),0))) -> 0 | D29: =IF(D$1<INDEX('Valo FX'!$Q:$Q,MATCH($A29,'Valo FX'!$A:$A,0)),0,IF(D$1<INDEX('Valo FX'!$R:$R,MATCH($A29,'Valo FX'!$A:$A,0)),INDEX(Base!$U:$U,MATCH($A29,Base!$A:$A,0)),IF(D$1=INDEX('Valo FX'!$R:$R,MATCH($A29,'Valo FX'!$A:$A,0)),INDEX(Base!$V:$V,MATCH($A29,Base!$A:$A,0)),0))) -> 0 | E29: =IF(E$1<INDEX('Valo FX'!$Q:$Q,MATCH($A29,'Valo FX'!$A:$A,0)),0,IF(E$1<INDEX('Valo FX'!$R:$R,MATCH($A29,'Valo FX'!$A:$A,0)),INDEX(Base!$U:$U,MATCH($A29,Base!$A:$A,0)),IF(E$1=INDEX('Valo FX'!$R:$R,MATCH($A29,'Valo FX'!$A:$A,0)),INDEX(Base!$V:$V,MATCH($A29,Base!$A:$A,0)),0))) -> 0 | F29: =IF(F$1<INDEX('Valo FX'!$Q:$Q,MATCH($A29,'Valo FX'!$A:$A,0)),0,IF(F$1<INDEX('Valo FX'!$R:$R,MATCH($A29,'Valo FX'!$A:$A,0)),INDEX(Base!$U:$U,MATCH($A29,Base!$A:$A,0)),IF(F$1=INDEX('Valo FX'!$R:$R,MATCH($A29,'Valo FX'!$A:$A,0)),INDEX(Base!$V:$V,MATCH($A29,Base!$A:$A,0)),0))) -> 0 | G29: =IF(G$1<INDEX('Valo FX'!$Q:$Q,MATCH($A29,'Valo FX'!$A:$A,0)),0,IF(G$1<INDEX('Valo FX'!$R:$R,MATCH($A29,'Valo FX'!$A:$A,0)),INDEX(Base!$U:$U,MATCH($A29,Base!$A:$A,0)),IF(G$1=INDEX('Valo FX'!$R:$R,MATCH($A29,'Valo FX'!$A:$A,0)),INDEX(Base!$V:$V,MATCH($A29,Base!$A:$A,0)),0))) -> 0 | H29: =IF(H$1<INDEX('Valo FX'!$Q:$Q,MATCH($A29,'Valo FX'!$A:$A,0)),0,IF(H$1<INDEX('Valo FX'!$R:$R,MATCH($A29,'Valo FX'!$A:$A,0)),INDEX(Base!$U:$U,MATCH($A29,Base!$A:$A,0)),IF(H$1=INDEX('Valo FX'!$R:$R,MATCH($A29,'Valo FX'!$A:$A,0)),INDEX(Base!$V:$V,MATCH($A29,Base!$A:$A,0)),0))) -> 0 | I29: =IF(I$1<INDEX('Valo FX'!$Q:$Q,MATCH($A29,'Valo FX'!$A:$A,0)),0,IF(I$1<INDEX('Valo FX'!$R:$R,MATCH($A29,'Valo FX'!$A:$A,0)),INDEX(Base!$U:$U,MATCH($A29,Base!$A:$A,0)),IF(I$1=INDEX('Valo FX'!$R:$R,MATCH($A29,'Valo FX'!$A:$A,0)),INDEX(Base!$V:$V,MATCH($A29,Base!$A:$A,0)),0))) -> 6.122712 | J29: =IF(J$1<INDEX('Valo FX'!$Q:$Q,MATCH($A29,'Valo FX'!$A:$A,0)),0,IF(J$1<INDEX('Valo FX'!$R:$R,MATCH($A29,'Valo FX'!$A:$A,0)),INDEX(Base!$U:$U,MATCH($A29,Base!$A:$A,0)),IF(J$1=INDEX('Valo FX'!$R:$R,MATCH($A29,'Valo FX'!$A:$A,0)),INDEX(Base!$V:$V,MATCH($A29,Base!$A:$A,0)),0))) -> 6.122712 | ... MY29: =IF(MY$1<INDEX('Valo FX'!$Q:$Q,MATCH($A29,'Valo FX'!$A:$A,0)),0,IF(MY$1<INDEX('Valo FX'!$R:$R,MATCH($A29,'Valo FX'!$A:$A,0)),INDEX(Base!$U:$U,MATCH($A29,Base!$A:$A,0)),IF(MY$1=INDEX('Valo FX'!$R:$R,MATCH($A29,'Valo FX'!$A:$A,0)),INDEX(Base!$V:$V,MATCH($A29,Base!$A:$A,0)),0))) -> 6.314423
A30: =+A29+1 -> 28 | B30: =-'Valo FX'!T31 -> -1657.9807 | C30: =IF(C$1<INDEX('Valo FX'!$Q:$Q,MATCH($A30,'Valo FX'!$A:$A,0)),0,IF(C$1<INDEX('Valo FX'!$R:$R,MATCH($A30,'Valo FX'!$A:$A,0)),INDEX(Base!$U:$U,MATCH($A30,Base!$A:$A,0)),IF(C$1=INDEX('Valo FX'!$R:$R,MATCH($A30,'Valo FX'!$A:$A,0)),INDEX(Base!$V:$V,MATCH($A30,Base!$A:$A,0)),0))) -> 0 | D30: =IF(D$1<INDEX('Valo FX'!$Q:$Q,MATCH($A30,'Valo FX'!$A:$A,0)),0,IF(D$1<INDEX('Valo FX'!$R:$R,MATCH($A30,'Valo FX'!$A:$A,0)),INDEX(Base!$U:$U,MATCH($A30,Base!$A:$A,0)),IF(D$1=INDEX('Valo FX'!$R:$R,MATCH($A30,'Valo FX'!$A:$A,0)),INDEX(Base!$V:$V,MATCH($A30,Base!$A:$A,0)),0))) -> 0 | E30: =IF(E$1<INDEX('Valo FX'!$Q:$Q,MATCH($A30,'Valo FX'!$A:$A,0)),0,IF(E$1<INDEX('Valo FX'!$R:$R,MATCH($A30,'Valo FX'!$A:$A,0)),INDEX(Base!$U:$U,MATCH($A30,Base!$A:$A,0)),IF(E$1=INDEX('Valo FX'!$R:$R,MATCH($A30,'Valo FX'!$A:$A,0)),INDEX(Base!$V:$V,MATCH($A30,Base!$A:$A,0)),0))) -> 0 | F30: =IF(F$1<INDEX('Valo FX'!$Q:$Q,MATCH($A30,'Valo FX'!$A:$A,0)),0,IF(F$1<INDEX('Valo FX'!$R:$R,MATCH($A30,'Valo FX'!$A:$A,0)),INDEX(Base!$U:$U,MATCH($A30,Base!$A:$A,0)),IF(F$1=INDEX('Valo FX'!$R:$R,MATCH($A30,'Valo FX'!$A:$A,0)),INDEX(Base!$V:$V,MATCH($A30,Base!$A:$A,0)),0))) -> 0 | G30: =IF(G$1<INDEX('Valo FX'!$Q:$Q,MATCH($A30,'Valo FX'!$A:$A,0)),0,IF(G$1<INDEX('Valo FX'!$R:$R,MATCH($A30,'Valo FX'!$A:$A,0)),INDEX(Base!$U:$U,MATCH($A30,Base!$A:$A,0)),IF(G$1=INDEX('Valo FX'!$R:$R,MATCH($A30,'Valo FX'!$A:$A,0)),INDEX(Base!$V:$V,MATCH($A30,Base!$A:$A,0)),0))) -> 0 | H30: =IF(H$1<INDEX('Valo FX'!$Q:$Q,MATCH($A30,'Valo FX'!$A:$A,0)),0,IF(H$1<INDEX('Valo FX'!$R:$R,MATCH($A30,'Valo FX'!$A:$A,0)),INDEX(Base!$U:$U,MATCH($A30,Base!$A:$A,0)),IF(H$1=INDEX('Valo FX'!$R:$R,MATCH($A30,'Valo FX'!$A:$A,0)),INDEX(Base!$V:$V,MATCH($A30,Base!$A:$A,0)),0))) -> 0 | I30: =IF(I$1<INDEX('Valo FX'!$Q:$Q,MATCH($A30,'Valo FX'!$A:$A,0)),0,IF(I$1<INDEX('Valo FX'!$R:$R,MATCH($A30,'Valo FX'!$A:$A,0)),INDEX(Base!$U:$U,MATCH($A30,Base!$A:$A,0)),IF(I$1=INDEX('Valo FX'!$R:$R,MATCH($A30,'Valo FX'!$A:$A,0)),INDEX(Base!$V:$V,MATCH($A30,Base!$A:$A,0)),0))) -> 11.35959 | J30: =IF(J$1<INDEX('Valo FX'!$Q:$Q,MATCH($A30,'Valo FX'!$A:$A,0)),0,IF(J$1<INDEX('Valo FX'!$R:$R,MATCH($A30,'Valo FX'!$A:$A,0)),INDEX(Base!$U:$U,MATCH($A30,Base!$A:$A,0)),IF(J$1=INDEX('Valo FX'!$R:$R,MATCH($A30,'Valo FX'!$A:$A,0)),INDEX(Base!$V:$V,MATCH($A30,Base!$A:$A,0)),0))) -> 11.35959 | ... MY30: =IF(MY$1<INDEX('Valo FX'!$Q:$Q,MATCH($A30,'Valo FX'!$A:$A,0)),0,IF(MY$1<INDEX('Valo FX'!$R:$R,MATCH($A30,'Valo FX'!$A:$A,0)),INDEX(Base!$U:$U,MATCH($A30,Base!$A:$A,0)),IF(MY$1=INDEX('Valo FX'!$R:$R,MATCH($A30,'Valo FX'!$A:$A,0)),INDEX(Base!$V:$V,MATCH($A30,Base!$A:$A,0)),0))) -> 11.715275
A31: =+A30+1 -> 29 | B31: =-'Valo FX'!T32 -> -1917.8522 | C31: =IF(C$1<INDEX('Valo FX'!$Q:$Q,MATCH($A31,'Valo FX'!$A:$A,0)),0,IF(C$1<INDEX('Valo FX'!$R:$R,MATCH($A31,'Valo FX'!$A:$A,0)),INDEX(Base!$U:$U,MATCH($A31,Base!$A:$A,0)),IF(C$1=INDEX('Valo FX'!$R:$R,MATCH($A31,'Valo FX'!$A:$A,0)),INDEX(Base!$V:$V,MATCH($A31,Base!$A:$A,0)),0))) -> 0 | D31: =IF(D$1<INDEX('Valo FX'!$Q:$Q,MATCH($A31,'Valo FX'!$A:$A,0)),0,IF(D$1<INDEX('Valo FX'!$R:$R,MATCH($A31,'Valo FX'!$A:$A,0)),INDEX(Base!$U:$U,MATCH($A31,Base!$A:$A,0)),IF(D$1=INDEX('Valo FX'!$R:$R,MATCH($A31,'Valo FX'!$A:$A,0)),INDEX(Base!$V:$V,MATCH($A31,Base!$A:$A,0)),0))) -> 0 | E31: =IF(E$1<INDEX('Valo FX'!$Q:$Q,MATCH($A31,'Valo FX'!$A:$A,0)),0,IF(E$1<INDEX('Valo FX'!$R:$R,MATCH($A31,'Valo FX'!$A:$A,0)),INDEX(Base!$U:$U,MATCH($A31,Base!$A:$A,0)),IF(E$1=INDEX('Valo FX'!$R:$R,MATCH($A31,'Valo FX'!$A:$A,0)),INDEX(Base!$V:$V,MATCH($A31,Base!$A:$A,0)),0))) -> 0 | F31: =IF(F$1<INDEX('Valo FX'!$Q:$Q,MATCH($A31,'Valo FX'!$A:$A,0)),0,IF(F$1<INDEX('Valo FX'!$R:$R,MATCH($A31,'Valo FX'!$A:$A,0)),INDEX(Base!$U:$U,MATCH($A31,Base!$A:$A,0)),IF(F$1=INDEX('Valo FX'!$R:$R,MATCH($A31,'Valo FX'!$A:$A,0)),INDEX(Base!$V:$V,MATCH($A31,Base!$A:$A,0)),0))) -> 0 | G31: =IF(G$1<INDEX('Valo FX'!$Q:$Q,MATCH($A31,'Valo FX'!$A:$A,0)),0,IF(G$1<INDEX('Valo FX'!$R:$R,MATCH($A31,'Valo FX'!$A:$A,0)),INDEX(Base!$U:$U,MATCH($A31,Base!$A:$A,0)),IF(G$1=INDEX('Valo FX'!$R:$R,MATCH($A31,'Valo FX'!$A:$A,0)),INDEX(Base!$V:$V,MATCH($A31,Base!$A:$A,0)),0))) -> 0 | H31: =IF(H$1<INDEX('Valo FX'!$Q:$Q,MATCH($A31,'Valo FX'!$A:$A,0)),0,IF(H$1<INDEX('Valo FX'!$R:$R,MATCH($A31,'Valo FX'!$A:$A,0)),INDEX(Base!$U:$U,MATCH($A31,Base!$A:$A,0)),IF(H$1=INDEX('Valo FX'!$R:$R,MATCH($A31,'Valo FX'!$A:$A,0)),INDEX(Base!$V:$V,MATCH($A31,Base!$A:$A,0)),0))) -> 0 | I31: =IF(I$1<INDEX('Valo FX'!$Q:$Q,MATCH($A31,'Valo FX'!$A:$A,0)),0,IF(I$1<INDEX('Valo FX'!$R:$R,MATCH($A31,'Valo FX'!$A:$A,0)),INDEX(Base!$U:$U,MATCH($A31,Base!$A:$A,0)),IF(I$1=INDEX('Valo FX'!$R:$R,MATCH($A31,'Valo FX'!$A:$A,0)),INDEX(Base!$V:$V,MATCH($A31,Base!$A:$A,0)),0))) -> 13.14009 | J31: =IF(J$1<INDEX('Valo FX'!$Q:$Q,MATCH($A31,'Valo FX'!$A:$A,0)),0,IF(J$1<INDEX('Valo FX'!$R:$R,MATCH($A31,'Valo FX'!$A:$A,0)),INDEX(Base!$U:$U,MATCH($A31,Base!$A:$A,0)),IF(J$1=INDEX('Valo FX'!$R:$R,MATCH($A31,'Valo FX'!$A:$A,0)),INDEX(Base!$V:$V,MATCH($A31,Base!$A:$A,0)),0))) -> 13.14009 | ... MY31: =IF(MY$1<INDEX('Valo FX'!$Q:$Q,MATCH($A31,'Valo FX'!$A:$A,0)),0,IF(MY$1<INDEX('Valo FX'!$R:$R,MATCH($A31,'Valo FX'!$A:$A,0)),INDEX(Base!$U:$U,MATCH($A31,Base!$A:$A,0)),IF(MY$1=INDEX('Valo FX'!$R:$R,MATCH($A31,'Valo FX'!$A:$A,0)),INDEX(Base!$V:$V,MATCH($A31,Base!$A:$A,0)),0))) -> 13.551525
A32: =+A31+1 -> 30 | B32: =-'Valo FX'!T33 -> -1574.7768 | C32: =IF(C$1<INDEX('Valo FX'!$Q:$Q,MATCH($A32,'Valo FX'!$A:$A,0)),0,IF(C$1<INDEX('Valo FX'!$R:$R,MATCH($A32,'Valo FX'!$A:$A,0)),INDEX(Base!$U:$U,MATCH($A32,Base!$A:$A,0)),IF(C$1=INDEX('Valo FX'!$R:$R,MATCH($A32,'Valo FX'!$A:$A,0)),INDEX(Base!$V:$V,MATCH($A32,Base!$A:$A,0)),0))) -> 0 | D32: =IF(D$1<INDEX('Valo FX'!$Q:$Q,MATCH($A32,'Valo FX'!$A:$A,0)),0,IF(D$1<INDEX('Valo FX'!$R:$R,MATCH($A32,'Valo FX'!$A:$A,0)),INDEX(Base!$U:$U,MATCH($A32,Base!$A:$A,0)),IF(D$1=INDEX('Valo FX'!$R:$R,MATCH($A32,'Valo FX'!$A:$A,0)),INDEX(Base!$V:$V,MATCH($A32,Base!$A:$A,0)),0))) -> 0 | E32: =IF(E$1<INDEX('Valo FX'!$Q:$Q,MATCH($A32,'Valo FX'!$A:$A,0)),0,IF(E$1<INDEX('Valo FX'!$R:$R,MATCH($A32,'Valo FX'!$A:$A,0)),INDEX(Base!$U:$U,MATCH($A32,Base!$A:$A,0)),IF(E$1=INDEX('Valo FX'!$R:$R,MATCH($A32,'Valo FX'!$A:$A,0)),INDEX(Base!$V:$V,MATCH($A32,Base!$A:$A,0)),0))) -> 0 | F32: =IF(F$1<INDEX('Valo FX'!$Q:$Q,MATCH($A32,'Valo FX'!$A:$A,0)),0,IF(F$1<INDEX('Valo FX'!$R:$R,MATCH($A32,'Valo FX'!$A:$A,0)),INDEX(Base!$U:$U,MATCH($A32,Base!$A:$A,0)),IF(F$1=INDEX('Valo FX'!$R:$R,MATCH($A32,'Valo FX'!$A:$A,0)),INDEX(Base!$V:$V,MATCH($A32,Base!$A:$A,0)),0))) -> 0 | G32: =IF(G$1<INDEX('Valo FX'!$Q:$Q,MATCH($A32,'Valo FX'!$A:$A,0)),0,IF(G$1<INDEX('Valo FX'!$R:$R,MATCH($A32,'Valo FX'!$A:$A,0)),INDEX(Base!$U:$U,MATCH($A32,Base!$A:$A,0)),IF(G$1=INDEX('Valo FX'!$R:$R,MATCH($A32,'Valo FX'!$A:$A,0)),INDEX(Base!$V:$V,MATCH($A32,Base!$A:$A,0)),0))) -> 0 | H32: =IF(H$1<INDEX('Valo FX'!$Q:$Q,MATCH($A32,'Valo FX'!$A:$A,0)),0,IF(H$1<INDEX('Valo FX'!$R:$R,MATCH($A32,'Valo FX'!$A:$A,0)),INDEX(Base!$U:$U,MATCH($A32,Base!$A:$A,0)),IF(H$1=INDEX('Valo FX'!$R:$R,MATCH($A32,'Valo FX'!$A:$A,0)),INDEX(Base!$V:$V,MATCH($A32,Base!$A:$A,0)),0))) -> 0 | I32: =IF(I$1<INDEX('Valo FX'!$Q:$Q,MATCH($A32,'Valo FX'!$A:$A,0)),0,IF(I$1<INDEX('Valo FX'!$R:$R,MATCH($A32,'Valo FX'!$A:$A,0)),INDEX(Base!$U:$U,MATCH($A32,Base!$A:$A,0)),IF(I$1=INDEX('Valo FX'!$R:$R,MATCH($A32,'Valo FX'!$A:$A,0)),INDEX(Base!$V:$V,MATCH($A32,Base!$A:$A,0)),0))) -> 11.323285 | J32: =IF(J$1<INDEX('Valo FX'!$Q:$Q,MATCH($A32,'Valo FX'!$A:$A,0)),0,IF(J$1<INDEX('Valo FX'!$R:$R,MATCH($A32,'Valo FX'!$A:$A,0)),INDEX(Base!$U:$U,MATCH($A32,Base!$A:$A,0)),IF(J$1=INDEX('Valo FX'!$R:$R,MATCH($A32,'Valo FX'!$A:$A,0)),INDEX(Base!$V:$V,MATCH($A32,Base!$A:$A,0)),0))) -> 11.323285 | ... MY32: =IF(MY$1<INDEX('Valo FX'!$Q:$Q,MATCH($A32,'Valo FX'!$A:$A,0)),0,IF(MY$1<INDEX('Valo FX'!$R:$R,MATCH($A32,'Valo FX'!$A:$A,0)),INDEX(Base!$U:$U,MATCH($A32,Base!$A:$A,0)),IF(MY$1=INDEX('Valo FX'!$R:$R,MATCH($A32,'Valo FX'!$A:$A,0)),INDEX(Base!$V:$V,MATCH($A32,Base!$A:$A,0)),0))) -> 0
A33: =+A32+1 -> 31 | B33: =-'Valo FX'!T34 -> -1995.2211 | C33: =IF(C$1<INDEX('Valo FX'!$Q:$Q,MATCH($A33,'Valo FX'!$A:$A,0)),0,IF(C$1<INDEX('Valo FX'!$R:$R,MATCH($A33,'Valo FX'!$A:$A,0)),INDEX(Base!$U:$U,MATCH($A33,Base!$A:$A,0)),IF(C$1=INDEX('Valo FX'!$R:$R,MATCH($A33,'Valo FX'!$A:$A,0)),INDEX(Base!$V:$V,MATCH($A33,Base!$A:$A,0)),0))) -> 0 | D33: =IF(D$1<INDEX('Valo FX'!$Q:$Q,MATCH($A33,'Valo FX'!$A:$A,0)),0,IF(D$1<INDEX('Valo FX'!$R:$R,MATCH($A33,'Valo FX'!$A:$A,0)),INDEX(Base!$U:$U,MATCH($A33,Base!$A:$A,0)),IF(D$1=INDEX('Valo FX'!$R:$R,MATCH($A33,'Valo FX'!$A:$A,0)),INDEX(Base!$V:$V,MATCH($A33,Base!$A:$A,0)),0))) -> 0 | E33: =IF(E$1<INDEX('Valo FX'!$Q:$Q,MATCH($A33,'Valo FX'!$A:$A,0)),0,IF(E$1<INDEX('Valo FX'!$R:$R,MATCH($A33,'Valo FX'!$A:$A,0)),INDEX(Base!$U:$U,MATCH($A33,Base!$A:$A,0)),IF(E$1=INDEX('Valo FX'!$R:$R,MATCH($A33,'Valo FX'!$A:$A,0)),INDEX(Base!$V:$V,MATCH($A33,Base!$A:$A,0)),0))) -> 0 | F33: =IF(F$1<INDEX('Valo FX'!$Q:$Q,MATCH($A33,'Valo FX'!$A:$A,0)),0,IF(F$1<INDEX('Valo FX'!$R:$R,MATCH($A33,'Valo FX'!$A:$A,0)),INDEX(Base!$U:$U,MATCH($A33,Base!$A:$A,0)),IF(F$1=INDEX('Valo FX'!$R:$R,MATCH($A33,'Valo FX'!$A:$A,0)),INDEX(Base!$V:$V,MATCH($A33,Base!$A:$A,0)),0))) -> 0 | G33: =IF(G$1<INDEX('Valo FX'!$Q:$Q,MATCH($A33,'Valo FX'!$A:$A,0)),0,IF(G$1<INDEX('Valo FX'!$R:$R,MATCH($A33,'Valo FX'!$A:$A,0)),INDEX(Base!$U:$U,MATCH($A33,Base!$A:$A,0)),IF(G$1=INDEX('Valo FX'!$R:$R,MATCH($A33,'Valo FX'!$A:$A,0)),INDEX(Base!$V:$V,MATCH($A33,Base!$A:$A,0)),0))) -> 0 | H33: =IF(H$1<INDEX('Valo FX'!$Q:$Q,MATCH($A33,'Valo FX'!$A:$A,0)),0,IF(H$1<INDEX('Valo FX'!$R:$R,MATCH($A33,'Valo FX'!$A:$A,0)),INDEX(Base!$U:$U,MATCH($A33,Base!$A:$A,0)),IF(H$1=INDEX('Valo FX'!$R:$R,MATCH($A33,'Valo FX'!$A:$A,0)),INDEX(Base!$V:$V,MATCH($A33,Base!$A:$A,0)),0))) -> 0 | I33: =IF(I$1<INDEX('Valo FX'!$Q:$Q,MATCH($A33,'Valo FX'!$A:$A,0)),0,IF(I$1<INDEX('Valo FX'!$R:$R,MATCH($A33,'Valo FX'!$A:$A,0)),INDEX(Base!$U:$U,MATCH($A33,Base!$A:$A,0)),IF(I$1=INDEX('Valo FX'!$R:$R,MATCH($A33,'Valo FX'!$A:$A,0)),INDEX(Base!$V:$V,MATCH($A33,Base!$A:$A,0)),0))) -> 13.67018 | J33: =IF(J$1<INDEX('Valo FX'!$Q:$Q,MATCH($A33,'Valo FX'!$A:$A,0)),0,IF(J$1<INDEX('Valo FX'!$R:$R,MATCH($A33,'Valo FX'!$A:$A,0)),INDEX(Base!$U:$U,MATCH($A33,Base!$A:$A,0)),IF(J$1=INDEX('Valo FX'!$R:$R,MATCH($A33,'Valo FX'!$A:$A,0)),INDEX(Base!$V:$V,MATCH($A33,Base!$A:$A,0)),0))) -> 13.67018 | ... MY33: =IF(MY$1<INDEX('Valo FX'!$Q:$Q,MATCH($A33,'Valo FX'!$A:$A,0)),0,IF(MY$1<INDEX('Valo FX'!$R:$R,MATCH($A33,'Valo FX'!$A:$A,0)),INDEX(Base!$U:$U,MATCH($A33,Base!$A:$A,0)),IF(MY$1=INDEX('Valo FX'!$R:$R,MATCH($A33,'Valo FX'!$A:$A,0)),INDEX(Base!$V:$V,MATCH($A33,Base!$A:$A,0)),0))) -> 14.098213
A34: =+A33+1 -> 32 | B34: =-'Valo FX'!T35 -> -1813.9036 | C34: =IF(C$1<INDEX('Valo FX'!$Q:$Q,MATCH($A34,'Valo FX'!$A:$A,0)),0,IF(C$1<INDEX('Valo FX'!$R:$R,MATCH($A34,'Valo FX'!$A:$A,0)),INDEX(Base!$U:$U,MATCH($A34,Base!$A:$A,0)),IF(C$1=INDEX('Valo FX'!$R:$R,MATCH($A34,'Valo FX'!$A:$A,0)),INDEX(Base!$V:$V,MATCH($A34,Base!$A:$A,0)),0))) -> 0 | D34: =IF(D$1<INDEX('Valo FX'!$Q:$Q,MATCH($A34,'Valo FX'!$A:$A,0)),0,IF(D$1<INDEX('Valo FX'!$R:$R,MATCH($A34,'Valo FX'!$A:$A,0)),INDEX(Base!$U:$U,MATCH($A34,Base!$A:$A,0)),IF(D$1=INDEX('Valo FX'!$R:$R,MATCH($A34,'Valo FX'!$A:$A,0)),INDEX(Base!$V:$V,MATCH($A34,Base!$A:$A,0)),0))) -> 0 | E34: =IF(E$1<INDEX('Valo FX'!$Q:$Q,MATCH($A34,'Valo FX'!$A:$A,0)),0,IF(E$1<INDEX('Valo FX'!$R:$R,MATCH($A34,'Valo FX'!$A:$A,0)),INDEX(Base!$U:$U,MATCH($A34,Base!$A:$A,0)),IF(E$1=INDEX('Valo FX'!$R:$R,MATCH($A34,'Valo FX'!$A:$A,0)),INDEX(Base!$V:$V,MATCH($A34,Base!$A:$A,0)),0))) -> 0 | F34: =IF(F$1<INDEX('Valo FX'!$Q:$Q,MATCH($A34,'Valo FX'!$A:$A,0)),0,IF(F$1<INDEX('Valo FX'!$R:$R,MATCH($A34,'Valo FX'!$A:$A,0)),INDEX(Base!$U:$U,MATCH($A34,Base!$A:$A,0)),IF(F$1=INDEX('Valo FX'!$R:$R,MATCH($A34,'Valo FX'!$A:$A,0)),INDEX(Base!$V:$V,MATCH($A34,Base!$A:$A,0)),0))) -> 0 | G34: =IF(G$1<INDEX('Valo FX'!$Q:$Q,MATCH($A34,'Valo FX'!$A:$A,0)),0,IF(G$1<INDEX('Valo FX'!$R:$R,MATCH($A34,'Valo FX'!$A:$A,0)),INDEX(Base!$U:$U,MATCH($A34,Base!$A:$A,0)),IF(G$1=INDEX('Valo FX'!$R:$R,MATCH($A34,'Valo FX'!$A:$A,0)),INDEX(Base!$V:$V,MATCH($A34,Base!$A:$A,0)),0))) -> 0 | H34: =IF(H$1<INDEX('Valo FX'!$Q:$Q,MATCH($A34,'Valo FX'!$A:$A,0)),0,IF(H$1<INDEX('Valo FX'!$R:$R,MATCH($A34,'Valo FX'!$A:$A,0)),INDEX(Base!$U:$U,MATCH($A34,Base!$A:$A,0)),IF(H$1=INDEX('Valo FX'!$R:$R,MATCH($A34,'Valo FX'!$A:$A,0)),INDEX(Base!$V:$V,MATCH($A34,Base!$A:$A,0)),0))) -> 0 | I34: =IF(I$1<INDEX('Valo FX'!$Q:$Q,MATCH($A34,'Valo FX'!$A:$A,0)),0,IF(I$1<INDEX('Valo FX'!$R:$R,MATCH($A34,'Valo FX'!$A:$A,0)),INDEX(Base!$U:$U,MATCH($A34,Base!$A:$A,0)),IF(I$1=INDEX('Valo FX'!$R:$R,MATCH($A34,'Valo FX'!$A:$A,0)),INDEX(Base!$V:$V,MATCH($A34,Base!$A:$A,0)),0))) -> 12.42789 | J34: =IF(J$1<INDEX('Valo FX'!$Q:$Q,MATCH($A34,'Valo FX'!$A:$A,0)),0,IF(J$1<INDEX('Valo FX'!$R:$R,MATCH($A34,'Valo FX'!$A:$A,0)),INDEX(Base!$U:$U,MATCH($A34,Base!$A:$A,0)),IF(J$1=INDEX('Valo FX'!$R:$R,MATCH($A34,'Valo FX'!$A:$A,0)),INDEX(Base!$V:$V,MATCH($A34,Base!$A:$A,0)),0))) -> 12.42789 | ... MY34: =IF(MY$1<INDEX('Valo FX'!$Q:$Q,MATCH($A34,'Valo FX'!$A:$A,0)),0,IF(MY$1<INDEX('Valo FX'!$R:$R,MATCH($A34,'Valo FX'!$A:$A,0)),INDEX(Base!$U:$U,MATCH($A34,Base!$A:$A,0)),IF(MY$1=INDEX('Valo FX'!$R:$R,MATCH($A34,'Valo FX'!$A:$A,0)),INDEX(Base!$V:$V,MATCH($A34,Base!$A:$A,0)),0))) -> 12.817025
A35: =+A34+1 -> 33 | B35: =-'Valo FX'!T36 -> -1335.7399 | C35: =IF(C$1<INDEX('Valo FX'!$Q:$Q,MATCH($A35,'Valo FX'!$A:$A,0)),0,IF(C$1<INDEX('Valo FX'!$R:$R,MATCH($A35,'Valo FX'!$A:$A,0)),INDEX(Base!$U:$U,MATCH($A35,Base!$A:$A,0)),IF(C$1=INDEX('Valo FX'!$R:$R,MATCH($A35,'Valo FX'!$A:$A,0)),INDEX(Base!$V:$V,MATCH($A35,Base!$A:$A,0)),0))) -> 0 | D35: =IF(D$1<INDEX('Valo FX'!$Q:$Q,MATCH($A35,'Valo FX'!$A:$A,0)),0,IF(D$1<INDEX('Valo FX'!$R:$R,MATCH($A35,'Valo FX'!$A:$A,0)),INDEX(Base!$U:$U,MATCH($A35,Base!$A:$A,0)),IF(D$1=INDEX('Valo FX'!$R:$R,MATCH($A35,'Valo FX'!$A:$A,0)),INDEX(Base!$V:$V,MATCH($A35,Base!$A:$A,0)),0))) -> 0 | E35: =IF(E$1<INDEX('Valo FX'!$Q:$Q,MATCH($A35,'Valo FX'!$A:$A,0)),0,IF(E$1<INDEX('Valo FX'!$R:$R,MATCH($A35,'Valo FX'!$A:$A,0)),INDEX(Base!$U:$U,MATCH($A35,Base!$A:$A,0)),IF(E$1=INDEX('Valo FX'!$R:$R,MATCH($A35,'Valo FX'!$A:$A,0)),INDEX(Base!$V:$V,MATCH($A35,Base!$A:$A,0)),0))) -> 0 | F35: =IF(F$1<INDEX('Valo FX'!$Q:$Q,MATCH($A35,'Valo FX'!$A:$A,0)),0,IF(F$1<INDEX('Valo FX'!$R:$R,MATCH($A35,'Valo FX'!$A:$A,0)),INDEX(Base!$U:$U,MATCH($A35,Base!$A:$A,0)),IF(F$1=INDEX('Valo FX'!$R:$R,MATCH($A35,'Valo FX'!$A:$A,0)),INDEX(Base!$V:$V,MATCH($A35,Base!$A:$A,0)),0))) -> 0 | G35: =IF(G$1<INDEX('Valo FX'!$Q:$Q,MATCH($A35,'Valo FX'!$A:$A,0)),0,IF(G$1<INDEX('Valo FX'!$R:$R,MATCH($A35,'Valo FX'!$A:$A,0)),INDEX(Base!$U:$U,MATCH($A35,Base!$A:$A,0)),IF(G$1=INDEX('Valo FX'!$R:$R,MATCH($A35,'Valo FX'!$A:$A,0)),INDEX(Base!$V:$V,MATCH($A35,Base!$A:$A,0)),0))) -> 0 | H35: =IF(H$1<INDEX('Valo FX'!$Q:$Q,MATCH($A35,'Valo FX'!$A:$A,0)),0,IF(H$1<INDEX('Valo FX'!$R:$R,MATCH($A35,'Valo FX'!$A:$A,0)),INDEX(Base!$U:$U,MATCH($A35,Base!$A:$A,0)),IF(H$1=INDEX('Valo FX'!$R:$R,MATCH($A35,'Valo FX'!$A:$A,0)),INDEX(Base!$V:$V,MATCH($A35,Base!$A:$A,0)),0))) -> 0 | I35: =IF(I$1<INDEX('Valo FX'!$Q:$Q,MATCH($A35,'Valo FX'!$A:$A,0)),0,IF(I$1<INDEX('Valo FX'!$R:$R,MATCH($A35,'Valo FX'!$A:$A,0)),INDEX(Base!$U:$U,MATCH($A35,Base!$A:$A,0)),IF(I$1=INDEX('Valo FX'!$R:$R,MATCH($A35,'Valo FX'!$A:$A,0)),INDEX(Base!$V:$V,MATCH($A35,Base!$A:$A,0)),0))) -> 9.15177 | J35: =IF(J$1<INDEX('Valo FX'!$Q:$Q,MATCH($A35,'Valo FX'!$A:$A,0)),0,IF(J$1<INDEX('Valo FX'!$R:$R,MATCH($A35,'Valo FX'!$A:$A,0)),INDEX(Base!$U:$U,MATCH($A35,Base!$A:$A,0)),IF(J$1=INDEX('Valo FX'!$R:$R,MATCH($A35,'Valo FX'!$A:$A,0)),INDEX(Base!$V:$V,MATCH($A35,Base!$A:$A,0)),0))) -> 9.15177 | ... MY35: =IF(MY$1<INDEX('Valo FX'!$Q:$Q,MATCH($A35,'Valo FX'!$A:$A,0)),0,IF(MY$1<INDEX('Valo FX'!$R:$R,MATCH($A35,'Valo FX'!$A:$A,0)),INDEX(Base!$U:$U,MATCH($A35,Base!$A:$A,0)),IF(MY$1=INDEX('Valo FX'!$R:$R,MATCH($A35,'Valo FX'!$A:$A,0)),INDEX(Base!$V:$V,MATCH($A35,Base!$A:$A,0)),0))) -> 9.438325
... A44: =+A43+1 -> 42 | B44: =-'Valo FX'!T45 -> -1403.4494 | C44: =IF(C$1<INDEX('Valo FX'!$Q:$Q,MATCH($A44,'Valo FX'!$A:$A,0)),0,IF(C$1<INDEX('Valo FX'!$R:$R,MATCH($A44,'Valo FX'!$A:$A,0)),INDEX(Base!$U:$U,MATCH($A44,Base!$A:$A,0)),IF(C$1=INDEX('Valo FX'!$R:$R,MATCH($A44,'Valo FX'!$A:$A,0)),INDEX(Base!$V:$V,MATCH($A44,Base!$A:$A,0)),0))) -> 0 | D44: =IF(D$1<INDEX('Valo FX'!$Q:$Q,MATCH($A44,'Valo FX'!$A:$A,0)),0,IF(D$1<INDEX('Valo FX'!$R:$R,MATCH($A44,'Valo FX'!$A:$A,0)),INDEX(Base!$U:$U,MATCH($A44,Base!$A:$A,0)),IF(D$1=INDEX('Valo FX'!$R:$R,MATCH($A44,'Valo FX'!$A:$A,0)),INDEX(Base!$V:$V,MATCH($A44,Base!$A:$A,0)),0))) -> 0 | E44: =IF(E$1<INDEX('Valo FX'!$Q:$Q,MATCH($A44,'Valo FX'!$A:$A,0)),0,IF(E$1<INDEX('Valo FX'!$R:$R,MATCH($A44,'Valo FX'!$A:$A,0)),INDEX(Base!$U:$U,MATCH($A44,Base!$A:$A,0)),IF(E$1=INDEX('Valo FX'!$R:$R,MATCH($A44,'Valo FX'!$A:$A,0)),INDEX(Base!$V:$V,MATCH($A44,Base!$A:$A,0)),0))) -> 0 | F44: =IF(F$1<INDEX('Valo FX'!$Q:$Q,MATCH($A44,'Valo FX'!$A:$A,0)),0,IF(F$1<INDEX('Valo FX'!$R:$R,MATCH($A44,'Valo FX'!$A:$A,0)),INDEX(Base!$U:$U,MATCH($A44,Base!$A:$A,0)),IF(F$1=INDEX('Valo FX'!$R:$R,MATCH($A44,'Valo FX'!$A:$A,0)),INDEX(Base!$V:$V,MATCH($A44,Base!$A:$A,0)),0))) -> 0 | G44: =IF(G$1<INDEX('Valo FX'!$Q:$Q,MATCH($A44,'Valo FX'!$A:$A,0)),0,IF(G$1<INDEX('Valo FX'!$R:$R,MATCH($A44,'Valo FX'!$A:$A,0)),INDEX(Base!$U:$U,MATCH($A44,Base!$A:$A,0)),IF(G$1=INDEX('Valo FX'!$R:$R,MATCH($A44,'Valo FX'!$A:$A,0)),INDEX(Base!$V:$V,MATCH($A44,Base!$A:$A,0)),0))) -> 0 | H44: =IF(H$1<INDEX('Valo FX'!$Q:$Q,MATCH($A44,'Valo FX'!$A:$A,0)),0,IF(H$1<INDEX('Valo FX'!$R:$R,MATCH($A44,'Valo FX'!$A:$A,0)),INDEX(Base!$U:$U,MATCH($A44,Base!$A:$A,0)),IF(H$1=INDEX('Valo FX'!$R:$R,MATCH($A44,'Valo FX'!$A:$A,0)),INDEX(Base!$V:$V,MATCH($A44,Base!$A:$A,0)),0))) -> 0 | I44: =IF(I$1<INDEX('Valo FX'!$Q:$Q,MATCH($A44,'Valo FX'!$A:$A,0)),0,IF(I$1<INDEX('Valo FX'!$R:$R,MATCH($A44,'Valo FX'!$A:$A,0)),INDEX(Base!$U:$U,MATCH($A44,Base!$A:$A,0)),IF(I$1=INDEX('Valo FX'!$R:$R,MATCH($A44,'Valo FX'!$A:$A,0)),INDEX(Base!$V:$V,MATCH($A44,Base!$A:$A,0)),0))) -> 11.890515 | J44: =IF(J$1<INDEX('Valo FX'!$Q:$Q,MATCH($A44,'Valo FX'!$A:$A,0)),0,IF(J$1<INDEX('Valo FX'!$R:$R,MATCH($A44,'Valo FX'!$A:$A,0)),INDEX(Base!$U:$U,MATCH($A44,Base!$A:$A,0)),IF(J$1=INDEX('Valo FX'!$R:$R,MATCH($A44,'Valo FX'!$A:$A,0)),INDEX(Base!$V:$V,MATCH($A44,Base!$A:$A,0)),0))) -> 11.890515 | ... MY44: =IF(MY$1<INDEX('Valo FX'!$Q:$Q,MATCH($A44,'Valo FX'!$A:$A,0)),0,IF(MY$1<INDEX('Valo FX'!$R:$R,MATCH($A44,'Valo FX'!$A:$A,0)),INDEX(Base!$U:$U,MATCH($A44,Base!$A:$A,0)),IF(MY$1=INDEX('Valo FX'!$R:$R,MATCH($A44,'Valo FX'!$A:$A,0)),INDEX(Base!$V:$V,MATCH($A44,Base!$A:$A,0)),0))) -> 0

Sheet Tabla desarrollo
D1: 45332 | E1: 45361 | F1: 45392 | G1: 45422 | H1: 45453 | I1: 45483 | J1: 45514 | K1: 45545 | L1: 45575 | M1: 45606 | N1: 45636 | O1: 45667 | P1: 45698 | Q1: 45726 | R1: 45757 | S1: 45787 | T1: 45818 | U1: 45848 | V1: 45879 | W1: 45910 | X1: 45940 | Y1: 45971 | Z1: 46001 | AA1: 46032 | AB1: 46063 | AC1: 46091 | AD1: 46122 | AE1: 46152 | AF1: 46183 | AG1: 46213 | AH1: 46244 | AI1: 46275 | AJ1: 46305 | AK1: 46336 | AL1: 46366 | AM1: 46397 | AN1: 46428 | AO1: 46456 | AP1: 46487 | AQ1: 46517 | AR1: 46548 | AS1: 46578 | AT1: 46609 | AU1: 46640 | AV1: 46670 | AW1: 46701 | AX1: 46731 | AY1: 46762 | AZ1: 46793 | BA1: 46822 | BB1: 46853 | BC1: 46883 | BD1: 46914 | BE1: 46944 | BF1: 46975 | BG1: 47006 | BH1: 47036 | BI1: 47067 | BJ1: 47097 | BK1: 47128 | BL1: 47159 | BM1: 47187 | BN1: 47218 | BO1: 47248 | BP1: 47279 | BQ1: 47309 | BR1: 47340 | BS1: 47371 | BT1: 47401 | BU1: 47432 | BV1: 47462 | BW1: 47493 | BX1: 47524 | BY1: 47552 | BZ1: 47583 | CA1: 47613 | CB1: 47644 | CC1: 47674 | CD1: 47705 | CE1: 47736 | CF1: 47766 | CG1: 47797 | CH1: 47827 | CI1: 47858 | CJ1: 47889 | CK1: 47917 | CL1: 47948 | CM1: 47978 | CN1: 48009 | CO1: 48039 | CP1: 48070 | CQ1: 48101 | CR1: 48131 | CS1: 48162 | CT1: 48192 | CU1: 48223 | CV1: 48254 | CW1: 48283 | CX1: 48314 | CY1: 48344 | CZ1: 48375 | DA1: 48405 | DB1: 48436 | DC1: 48467 | DD1: 48497 | DE1: 48528 | DF1: 48558 | DG1: 48589 | DH1: 48620 | DI1: 48648 | DJ1: 48679 | DK1: 48709 | DL1: 48740 | DM1: 48770 | DN1: 48801 | DO1: 48832 | DP1: 48862 | DQ1: 48893 | DR1: 48923 | DS1: 48954 | DT1: 48985 | DU1: 49013 | DV1: 49044 | DW1: 49074 | DX1: 49105 | DY1: 49135 | DZ1: 49166 | EA1: 49197 | EB1: 49227 | EC1: 49258 | ED1: 49288 | EE1: 49319 | EF1: 49350 | EG1: 49378 | EH1: 49409 | EI1: 49439 | EJ1: 49470 | EK1: 49500 | EL1: 49531 | EM1: 49562 | EN1: 49592 | EO1: 49623 | EP1: 49653 | EQ1: 49684 | ER1: 49715 | ES1: 49744 | ET1: 49775 | EU1: 49805 | EV1: 49836 | EW1: 49866 | EX1: 49897 | EY1: 49928 | EZ1: 49958 | FA1: 49989 | FB1: 50019 | FC1: 50050 | FD1: 50081 | FE1: 50109 | FF1: 50140 | FG1: 50170 | FH1: 50201 | FI1: 50231 | FJ1: 50262 | FK1: 50293 | FL1: 50323 | FM1: 50354 | FN1: 50384 | FO1: 50415 | FP1: 50446 | FQ1: 50474 | FR1: 50505 | FS1: 50535 | FT1: 50566 | FU1: 50596 | FV1: 50627 | FW1: 50658 | FX1: 50688 | FY1: 50719 | FZ1: 50749 | GA1: 50780 | GB1: 50811 | GC1: 50839 | GD1: 50870 | GE1: 50900 | GF1: 50931 | GG1: 50961 | GH1: 50992 | GI1: 51023 | GJ1: 51053 | GK1: 51084 | GL1: 51114 | GM1: 51145 | GN1: 51176 | GO1: 51205 | GP1: 51236 | GQ1: 51266 | GR1: 51297 | GS1: 51327 | GT1: 51358 | GU1: 51389 | GV1: 51419 | GW1: 51450 | GX1: 51480 | GY1: 51511 | GZ1: 51542 | HA1: 51570 | HB1: 51601 | HC1: 51631 | HD1: 51662 | HE1: 51692 | HF1: 51723 | HG1: 51754 | HH1: 51784 | HI1: 51815 | HJ1: 51845 | HK1: 51876 | HL1: 51907 | HM1: 51935 | HN1: 51966 | HO1: 51996 | HP1: 52027 | HQ1: 52057 | HR1: 52088 | HS1: 52119 | HT1: 52149 | HU1: 52180 | HV1: 52210 | HW1: 52241 | HX1: 52272 | HY1: 52300 | HZ1: 52331 | IA1: 52361 | IB1: 52392 | IC1: 52422 | ID1: 52453 | IE1: 52484 | IF1: 52514 | IG1: 52545 | IH1: 52575 | II1: 52606 | IJ1: 52637 | IK1: 52666 | IL1: 52697 | IM1: 52727 | IN1: 52758 | IO1: 52788 | IP1: 52819 | IQ1: 52850 | IR1: 52880 | IS1: 52911 | IT1: 52941 | IU1: 52972 | IV1: 53003 | IW1: 53031 | IX1: 53062 | IY1: 53092 | IZ1: 53123 | JA1: 53153 | JB1: 53184 | JC1: 53215 | JD1: 53245 | JE1: 53276 | JF1: 53306 | JG1: 53337 | JH1: 53368 | JI1: 53396 | JJ1: 53427 | JK1: 53457 | JL1: 53488 | JM1: 53518 | JN1: 53549 | JO1: 53580 | JP1: 53610 | JQ1: 53641 | JR1: 53671 | JS1: 53702 | JT1: 53733 | JU1: 53761 | JV1: 53792 | JW1: 53822 | JX1: 53853 | JY1: 53883 | JZ1: 53914 | KA1: 53945 | KB1: 53975 | KC1: 54006 | KD1: 54036 | KE1: 54067 | KF1: 54098 | KG1: 54127 | KH1: 54158 | KI1: 54188 | KJ1: 54219 | KK1: 54249 | KL1: 54280 | KM1: 54311 | KN1: 54341 | KO1: 54372 | KP1: 54402 | KQ1: 54433 | KR1: 54464 | KS1: 54492 | KT1: 54523 | KU1: 54553 | KV1: 54584 | KW1: 54614 | KX1: 54645 | KY1: 54676 | KZ1: 54706 | LA1: 54737 | LB1: 54767 | LC1: 54798 | LD1: 54829 | LE1: 54857 | LF1: 54888 | LG1: 54918 | LH1: 54949 | LI1: 54979 | LJ1: 55010 | LK1: 55041 | LL1: 55071 | LM1: 55102 | LN1: 55132 | LO1: 55163 | LP1: 55194 | LQ1: 55222 | LR1: 55253 | LS1: 55283 | LT1: 55314 | LU1: 55344 | LV1: 55375 | LW1: 55406 | LX1: 55436 | LY1: 55467 | LZ1: 55497 | MA1: 55528 | MB1: 55559 | MC1: 55588 | MD1: 55619 | ME1: 55649 | MF1: 55680 | MG1: 55710 | MH1: 55741 | MI1: 55772 | MJ1: 55802 | MK1: 55833 | ML1: 55863 | MM1: 55894 | MN1: 55925 | MO1: 55953 | MP1: 55984 | MQ1: 56014 | MR1: 56045 | MS1: 56075 | MT1: 56106 | MU1: 56137 | MV1: 56167 | MW1: 56198 | MX1: 56228 | MY1: 56259 | MZ1: 56290
A2: Nº | B2: N° Operación | C2: Primera cuota a endosar | D2: 1 | E2: 2 | F2: 3 | G2: 4 | H2: 5 | I2: 6 | J2: 7 | K2: 8 | L2: 9 | M2: 10 | N2: 11 | O2: 12 | P2: 13 | Q2: 14 | R2: 15 | S2: 16 | T2: 17 | U2: 18 | V2: 19 | W2: 20 | X2: 21 | Y2: 22 | Z2: 23 | AA2: 24 | AB2: 25 | AC2: 26 | AD2: 27 | AE2: 28 | AF2: 29 | AG2: 30 | AH2: 31 | AI2: 32 | AJ2: 33 | AK2: 34 | AL2: 35 | AM2: 36 | AN2: 37 | AO2: 38 | AP2: 39 | AQ2: 40 | AR2: 41 | AS2: 42 | AT2: 43 | AU2: 44 | AV2: 45 | AW2: 46 | AX2: 47 | AY2: 48 | AZ2: 49 | BA2: 50 | BB2: 51 | BC2: 52 | BD2: 53 | BE2: 54 | BF2: 55 | BG2: 56 | BH2: 57 | BI2: 58 | BJ2: 59 | BK2: 60 | BL2: 61 | BM2: 62 | BN2: 63 | BO2: 64 | BP2: 65 | BQ2: 66 | BR2: 67 | BS2: 68 | BT2: 69 | BU2: 70 | BV2: 71 | BW2: 72 | BX2: 73 | BY2: 74 | BZ2: 75 | CA2: 76 | CB2: 77 | CC2: 78 | CD2: 79 | CE2: 80 | CF2: 81 | CG2: 82 | CH2: 83 | CI2: 84 | CJ2: 85 | CK2: 86 | CL2: 87 | CM2: 88 | CN2: 89 | CO2: 90 | CP2: 91 | CQ2: 92 | CR2: 93 | CS2: 94 | CT2: 95 | CU2: 96 | CV2: 97 | CW2: 98 | CX2: 99 | CY2: 100 | CZ2: 101 | DA2: 102 | DB2: 103 | DC2: 104 | DD2: 105 | DE2: 106 | DF2: 107 | DG2: 108 | DH2: 109 | DI2: 110 | DJ2: 111 | DK2: 112 | DL2: 113 | DM2: 114 | DN2: 115 | DO2: 116 | DP2: 117 | DQ2: 118 | DR2: 119 | DS2: 120 | DT2: 121 | DU2: 122 | DV2: 123 | DW2: 124 | DX2: 125 | DY2: 126 | DZ2: 127 | EA2: 128 | EB2: 129 | EC2: 130 | ED2: 131 | EE2: 132 | EF2: 133 | EG2: 134 | EH2: 135 | EI2: 136 | EJ2: 137 | EK2: 138 | EL2: 139 | EM2: 140 | EN2: 141 | EO2: 142 | EP2: 143 | EQ2: 144 | ER2: 145 | ES2: 146 | ET2: 147 | EU2: 148 | EV2: 149 | EW2: 150 | EX2: 151 | EY2: 152 | EZ2: 153 | FA2: 154 | FB2: 155 | FC2: 156 | FD2: 157 | FE2: 158 | FF2: 159 | FG2: 160 | FH2: 161 | FI2: 162 | FJ2: 163 | FK2: 164 | FL2: 165 | FM2: 166 | FN2: 167 | FO2: 168 | FP2: 169 | FQ2: 170 | FR2: 171 | FS2: 172 | FT2: 173 | FU2: 174 | FV2: 175 | FW2: 176 | FX2: 177 | FY2: 178 | FZ2: 179 | GA2: 180 | GB2: 181 | GC2: 182 | GD2: 183 | GE2: 184 | GF2: 185 | GG2: 186 | GH2: 187 | GI2: 188 | GJ2: 189 | GK2: 190 | GL2: 191 | GM2: 192 | GN2: 193 | GO2: 194 | GP2: 195 | GQ2: 196 | GR2: 197 | GS2: 198 | GT2: 199 | GU2: 200 | GV2: 201 | GW2: 202 | GX2: 203 | GY2: 204 | GZ2: 205 | HA2: 206 | HB2: 207 | HC2: 208 | HD2: 209 | HE2: 210 | HF2: 211 | HG2: 212 | HH2: 213 | HI2: 214 | HJ2: 215 | HK2: 216 | HL2: 217 | HM2: 218 | HN2: 219 | HO2: 220 | HP2: 221 | HQ2: 222 | HR2: 223 | HS2: 224 | HT2: 225 | HU2: 226 | HV2: 227 | HW2: 228 | HX2: 229 | HY2: 230 | HZ2: 231 | IA2: 232 | IB2: 233 | IC2: 234 | ID2: 235 | IE2: 236 | IF2: 237 | IG2: 238 | IH2: 239 | II2: 240 | IJ2: 241 | IK2: 242 | IL2: 243 | IM2: 244 | IN2: 245 | IO2: 246 | IP2: 247 | IQ2: 248 | IR2: 249 | IS2: 250 | IT2: 251 | IU2: 252 | IV2: 253 | IW2: 254 | IX2: 255 | IY2: 256 | IZ2: 257 | JA2: 258 | JB2: 259 | JC2: 260 | JD2: 261 | JE2: 262 | JF2: 263 | JG2: 264 | JH2: 265 | JI2: 266 | JJ2: 267 | JK2: 268 | JL2: 269 | JM2: 270 | JN2: 271 | JO2: 272 | JP2: 273 | JQ2: 274 | JR2: 275 | JS2: 276 | JT2: 277 | JU2: 278 | JV2: 279 | JW2: 280 | JX2: 281 | JY2: 282 | JZ2: 283 | KA2: 284 | KB2: 285 | KC2: 286 | KD2: 287 | KE2: 288 | KF2: 289 | KG2: 290 | KH2: 291 | KI2: 292 | KJ2: 293 | KK2: 294 | KL2: 295 | KM2: 296 | KN2: 297 | KO2: 298 | KP2: 299 | KQ2: 300 | KR2: 301 | KS2: 302 | KT2: 303 | KU2: 304 | KV2: 305 | KW2: 306 | KX2: 307 | KY2: 308 | KZ2: 309 | LA2: 310 | LB2: 311 | LC2: 312 | LD2: 313 | LE2: 314 | LF2: 315 | LG2: 316 | LH2: 317 | LI2: 318 | LJ2: 319 | LK2: 320 | LL2: 321 | LM2: 322 | LN2: 323 | LO2: 324 | LP2: 325 | LQ2: 326 | LR2: 327 | LS2: 328 | LT2: 329 | LU2: 330 | LV2: 331 | LW2: 332 | LX2: 333 | LY2: 334 | LZ2: 335 | MA2: 336 | MB2: 337 | MC2: 338 | MD2: 339 | ME2: 340 | MF2: 341 | MG2: 342 | MH2: 343 | MI2: 344 | MJ2: 345 | MK2: 346 | ML2: 347 | MM2: 348 | MN2: 349 | MO2: 350 | MP2: 351 | MQ2: 352 | MR2: 353 | MS2: 354 | MT2: 355 | MU2: 356 | MV2: 357 | MW2: 358 | MX2: 359 | MY2: 360 | MZ2: 361
A3: =+'Valo FX'!A4 -> 1 | B3: =+Base!B1 -> N° Operación CMF | C3: 6 | D3: 0 | E3: 0 | F3: 0 | G3: 0 | H3: 0 | I3: 0 | J3: 12.71407 | K3: 12.71407 | L3: 12.71407 | M3: 12.71407 | N3: 12.71407 | O3: 12.71407 | P3: 12.71407 | Q3: 12.71407 | R3: 12.71407 | S3: 12.71407 | T3: 12.71407 | U3: 12.71407 | V3: 12.71407 | W3: 12.71407 | X3: 12.71407 | Y3: 12.71407 | Z3: 12.71407 | AA3: 12.71407 | AB3: 12.71407 | AC3: 12.71407 | AD3: 12.71407 | AE3: 12.71407 | AF3: 12.71407 | AG3: 12.71407 | AH3: 12.71407 | AI3: 12.71407 | AJ3: 12.71407 | AK3: 12.71407 | AL3: 12.71407 | AM3: 12.71407 | AN3: 12.71407 | AO3: 12.71407 | AP3: 12.71407 | AQ3: 12.71407 | AR3: 12.71407 | AS3: 12.71407 | AT3: 12.71407 | AU3: 12.71407 | AV3: 12.71407 | AW3: 12.71407 | AX3: 12.71407 | AY3: 12.71407 | AZ3: 12.71407 | BA3: 12.71407 | BB3: 12.71407 | BC3: 12.71407 | BD3: 12.71407 | BE3: 12.71407 | BF3: 12.71407 | BG3: 12.71407 | BH3: 12.71407 | BI3: 12.71407 | BJ3: 12.71407 | BK3: 12.71407 | BL3: 12.71407 | BM3: 12.71407 | BN3: 12.71407 | BO3: 12.71407 | BP3: 12.71407 | BQ3: 12.71407 | BR3: 12.71407 | BS3: 12.71407 | BT3: 12.71407 | BU3: 12.71407 | BV3: 12.71407 | BW3: 12.71407 | BX3: 12.71407 | BY3: 12.71407 | BZ3: 12.71407 | CA3: 12.71407 | CB3: 12.71407 | CC3: 12.71407 | CD3: 12.71407 | CE3: 12.71407 | CF3: 12.71407 | CG3: 12.71407 | CH3: 12.71407 | CI3: 12.71407 | CJ3: 12.71407 | CK3: 12.71407 | CL3: 12.71407 | CM3: 12.71407 | CN3: 12.71407 | CO3: 12.71407 | CP3: 12.71407 | CQ3: 12.71407 | CR3: 12.71407 | CS3: 12.71407 | CT3: 12.71407 | CU3: 12.71407 | CV3: 12.71407 | CW3: 12.71407 | CX3: 12.71407 | CY3: 12.71407 | CZ3: 12.71407 | DA3: 12.71407 | DB3: 12.71407 | DC3: 12.71407 | DD3: 12.71407 | DE3: 12.71407 | DF3: 12.71407 | DG3: 12.71407 | DH3: 12.71407 | DI3: 12.71407 | DJ3: 12.71407 | DK3: 12.71407 | DL3: 12.71407 | DM3: 12.71407 | DN3: 12.71407 | DO3: 12.71407 | DP3: 12.71407 | DQ3: 12.71407 | DR3: 12.71407 | DS3: 12.71407 | DT3: 12.71407 | DU3: 12.71407 | DV3: 12.71407 | DW3: 12.71407 | DX3: 12.71407 | DY3: 12.71407 | DZ3: 12.71407 | EA3: 12.71407 | EB3: 12.71407 | EC3: 12.71407 | ED3: 12.71407 | EE3: 12.71407 | EF3: 12.71407 | EG3: 12.71407 | EH3: 12.71407 | EI3: 12.71407 | EJ3: 12.71407 | EK3: 12.71407 | EL3: 12.71407 | EM3: 12.71407 | EN3: 12.71407 | EO3: 12.71407 | EP3: 12.71407 | EQ3: 12.71407 | ER3: 12.71407 | ES3: 12.71407 | ET3: 12.71407 | EU3: 12.71407 | EV3: 12.71407 | EW3: 12.71407 | EX3: 12.71407 | EY3: 12.71407 | EZ3: 12.71407 | FA3: 12.71407 | FB3: 12.71407 | FC3: 12.71407 | FD3: 12.71407 | FE3: 12.71407 | FF3: 12.71407 | FG3: 12.71407 | FH3: 12.71407 | FI3: 12.71407 | FJ3: 12.71407 | FK3: 12.71407 | FL3: 12.71407 | FM3: 12.71407 | FN3: 12.71407 | FO3: 12.71407 | FP3: 12.71407 | FQ3: 12.71407 | FR3: 12.71407 | FS3: 12.71407 | FT3: 12.71407 | FU3: 12.71407 | FV3: 12.71407 | FW3: 12.71407 | FX3: 12.71407 | FY3: 12.71407 | FZ3: 12.71407 | GA3: 12.71407 | GB3: 12.71407 | GC3: 12.71407 | GD3: 12.71407 | GE3: 12.71407 | GF3: 12.71407 | GG3: 12.71407 | GH3: 12.71407 | GI3: 12.71407 | GJ3: 12.71407 | GK3: 12.71407 | GL3: 12.71407 | GM3: 12.71407 | GN3: 12.71407 | GO3: 12.71407 | GP3: 12.71407 | GQ3: 12.71407 | GR3: 12.71407 | GS3: 12.71407 | GT3: 12.71407 | GU3: 12.71407 | GV3: 12.71407 | GW3: 12.71407 | GX3: 12.71407 | GY3: 12.71407 | GZ3: 12.71407 | HA3: 12.71407 | HB3: 12.71407 | HC3: 12.71407 | HD3: 12.71407 | HE3: 12.71407 | HF3: 12.71407 | HG3: 12.71407 | HH3: 12.71407 | HI3: 12.71407 | HJ3: 12.71407 | HK3: 12.71407 | HL3: 12.71407 | HM3: 12.71407 | HN3: 12.71407 | HO3: 12.71407 | HP3: 12.71407 | HQ3: 12.71407 | HR3: 12.71407 | HS3: 12.71407 | HT3: 12.71407 | HU3: 12.71407 | HV3: 12.71407 | HW3: 12.71407 | HX3: 12.71407 | HY3: 12.71407 | HZ3: 12.71407 | IA3: 12.71407 | IB3: 12.71407 | IC3: 12.71407 | ID3: 12.71407 | IE3: 12.71407 | IF3: 12.71407 | IG3: 12.71407 | IH3: 12.71407 | II3: 12.71407 | IJ3: 12.71407 | IK3: 12.71407 | IL3: 12.71407 | IM3: 12.71407 | IN3: 12.71407 | IO3: 12.71407 | IP3: 12.71407 | IQ3: 12.71407 | IR3: 12.71407 | IS3: 12.71407 | IT3: 12.71407 | IU3: 12.71407 | IV3: 12.71407 | IW3: 12.71407 | IX3: 12.71407 | IY3: 12.71407 | IZ3: 12.71407 | JA3: 12.71407 | JB3: 12.71407 | JC3: 12.71407 | JD3: 12.71407 | JE3: 12.71407 | JF3: 12.71407 | JG3: 12.71407 | JH3: 12.71407 | JI3: 12.71407 | JJ3: 12.71407 | JK3: 12.71407 | JL3: 12.71407 | JM3: 12.71407 | JN3: 12.71407 | JO3: 12.71407 | JP3: 12.71407 | JQ3: 12.71407 | JR3: 12.71407 | JS3: 12.71407 | JT3: 12.71407 | JU3: 12.71407 | JV3: 12.71407 | JW3: 12.71407 | JX3: 12.71407 | JY3: 12.71407 | JZ3: 12.71407 | KA3: 12.71407 | KB3: 12.71407 | KC3: 12.71407 | KD3: 12.71407 | KE3: 12.71407 | KF3: 12.71407 | KG3: 12.71407 | KH3: 12.71407 | KI3: 12.71407 | KJ3: 12.71407 | KK3: 12.71407 | KL3: 12.71407 | KM3: 12.71407 | KN3: 12.71407 | KO3: 12.71407 | KP3: 12.71407 | KQ3: 12.71407 | KR3: 12.71407 | KS3: 12.71407 | KT3: 12.71407 | KU3: 12.71407 | KV3: 12.71407 | KW3: 12.71407 | KX3: 12.71407 | KY3: 12.71407 | KZ3: 12.71407 | LA3: 12.71407 | LB3: 12.71407 | LC3: 12.71407 | LD3: 12.71407 | LE3: 12.71407 | LF3: 12.71407 | LG3: 12.71407 | LH3: 12.71407 | LI3: 12.71407 | LJ3: 12.71407 | LK3: 12.71407 | LL3: 12.71407 | LM3: 12.71407 | LN3: 12.71407 | LO3: 12.71407 | LP3: 12.71407 | LQ3: 12.71407 | LR3: 12.71407 | LS3: 12.71407 | LT3: 12.71407 | LU3: 12.71407 | LV3: 12.71407 | LW3: 12.71407 | LX3: 12.71407 | LY3: 12.71407 | LZ3: 12.71407 | MA3: 12.71407 | MB3: 12.71407 | MC3: 12.71407 | MD3: 12.71407 | ME3: 12.71407 | MF3: 12.71407 | MG3: 12.71407 | MH3: 12.71407 | MI3: 12.71407 | MJ3: 12.71407 | MK3: 12.71407 | ML3: 12.71407 | MM3: 12.71407 | MN3: 12.71407 | MO3: 12.71407 | MP3: 12.71407 | MQ3: 12.71407 | MR3: 12.71407 | MS3: 12.71407 | MT3: 12.71407 | MU3: 12.71407 | MV3: 12.71407 | MW3: 12.71407 | MX3: 12.71407 | MY3: 12.71407 | MZ3: 13.752345
A4: =+'Valo FX'!A5 -> 2 | B4: =+Base!B2 -> 202401300028A033 | C4: 6 | D4: 0 | E4: 0 | F4: 0 | G4: 0 | H4: 0 | I4: 0 | J4: 12.82336 | K4: 12.82336 | L4: 12.82336 | M4: 12.82336 | N4: 12.82336 | O4: 12.82336 | P4: 12.82336 | Q4: 12.82336 | R4: 12.82336 | S4: 12.82336 | T4: 12.82336 | U4: 12.82336 | V4: 12.82336 | W4: 12.82336 | X4: 12.82336 | Y4: 12.82336 | Z4: 12.82336 | AA4: 12.82336 | AB4: 12.82336 | AC4: 12.82336 | AD4: 12.82336 | AE4: 12.82336 | AF4: 12.82336 | AG4: 12.82336 | AH4: 12.82336 | AI4: 12.82336 | AJ4: 12.82336 | AK4: 12.82336 | AL4: 12.82336 | AM4: 12.82336 | AN4: 12.82336 | AO4: 12.82336 | AP4: 12.82336 | AQ4: 12.82336 | AR4: 12.82336 | AS4: 12.82336 | AT4: 12.82336 | AU4: 12.82336 | AV4: 12.82336 | AW4: 12.82336 | AX4: 12.82336 | AY4: 12.82336 | AZ4: 12.82336 | BA4: 12.82336 | BB4: 12.82336 | BC4: 12.82336 | BD4: 12.82336 | BE4: 12.82336 | BF4: 12.82336 | BG4: 12.82336 | BH4: 12.82336 | BI4: 12.82336 | BJ4: 12.82336 | BK4: 12.82336 | BL4: 12.82336 | BM4: 12.82336 | BN4: 12.82336 | BO4: 12.82336 | BP4: 12.82336 | BQ4: 12.82336 | BR4: 12.82336 | BS4: 12.82336 | BT4: 12.82336 | BU4: 12.82336 | BV4: 12.82336 | BW4: 12.82336 | BX4: 12.82336 | BY4: 12.82336 | BZ4: 12.82336 | CA4: 12.82336 | CB4: 12.82336 | CC4: 12.82336 | CD4: 12.82336 | CE4: 12.82336 | CF4: 12.82336 | CG4: 12.82336 | CH4: 12.82336 | CI4: 12.82336 | CJ4: 12.82336 | CK4: 12.82336 | CL4: 12.82336 | CM4: 12.82336 | CN4: 12.82336 | CO4: 12.82336 | CP4: 12.82336 | CQ4: 12.82336 | CR4: 12.82336 | CS4: 12.82336 | CT4: 12.82336 | CU4: 12.82336 | CV4: 12.82336 | CW4: 12.82336 | CX4: 12.82336 | CY4: 12.82336 | CZ4: 12.82336 | DA4: 12.82336 | DB4: 12.82336 | DC4: 12.82336 | DD4: 12.82336 | DE4: 12.82336 | DF4: 12.82336 | DG4: 12.82336 | DH4: 12.82336 | DI4: 12.82336 | DJ4: 12.82336 | DK4: 12.82336 | DL4: 12.82336 | DM4: 12.82336 | DN4: 12.82336 | DO4: 12.82336 | DP4: 12.82336 | DQ4: 12.82336 | DR4: 12.82336 | DS4: 12.82336 | DT4: 12.82336 | DU4: 12.82336 | DV4: 12.82336 | DW4: 12.82336 | DX4: 12.82336 | DY4: 12.82336 | DZ4: 12.82336 | EA4: 12.82336 | EB4: 12.82336 | EC4: 12.82336 | ED4: 12.82336 | EE4: 12.82336 | EF4: 12.82336 | EG4: 12.82336 | EH4: 12.82336 | EI4: 12.82336 | EJ4: 12.82336 | EK4: 12.82336 | EL4: 12.82336 | EM4: 12.82336 | EN4: 12.82336 | EO4: 12.82336 | EP4: 12.82336 | EQ4: 12.82336 | ER4: 12.82336 | ES4: 12.82336 | ET4: 12.82336 | EU4: 12.82336 | EV4: 12.82336 | EW4: 12.82336 | EX4: 12.82336 | EY4: 12.82336 | EZ4: 12.82336 | FA4: 12.82336 | FB4: 12.82336 | FC4: 12.82336 | FD4: 12.82336 | FE4: 12.82336 | FF4: 12.82336 | FG4: 12.82336 | FH4: 12.82336 | FI4: 12.82336 | FJ4: 12.82336 | FK4: 12.82336 | FL4: 12.82336 | FM4: 12.82336 | FN4: 12.82336 | FO4: 12.82336 | FP4: 12.82336 | FQ4: 12.82336 | FR4: 12.82336 | FS4: 12.82336 | FT4: 12.82336 | FU4: 12.82336 | FV4: 12.82336 | FW4: 12.82336 | FX4: 12.82336 | FY4: 12.82336 | FZ4: 12.82336 | GA4: 12.82336 | GB4: 12.82336 | GC4: 12.82336 | GD4: 12.82336 | GE4: 12.82336 | GF4: 12.82336 | GG4: 12.82336 | GH4: 12.82336 | GI4: 12.82336 | GJ4: 12.82336 | GK4: 12.82336 | GL4: 12.82336 | GM4: 12.82336 | GN4: 12.82336 | GO4: 12.82336 | GP4: 12.82336 | GQ4: 12.82336 | GR4: 12.82336 | GS4: 12.82336 | GT4: 12.82336 | GU4: 12.82336 | GV4: 12.82336 | GW4: 12.82336 | GX4: 12.82336 | GY4: 12.82336 | GZ4: 12.82336 | HA4: 12.82336 | HB4: 12.82336 | HC4: 12.82336 | HD4: 12.82336 | HE4: 12.82336 | HF4: 12.82336 | HG4: 12.82336 | HH4: 12.82336 | HI4: 12.82336 | HJ4: 12.82336 | HK4: 12.82336 | HL4: 12.82336 | HM4: 12.82336 | HN4: 12.82336 | HO4: 12.82336 | HP4: 12.82336 | HQ4: 12.82336 | HR4: 12.82336 | HS4: 12.82336 | HT4: 12.82336 | HU4: 12.82336 | HV4: 12.82336 | HW4: 12.82336 | HX4: 12.82336 | HY4: 12.82336 | HZ4: 12.82336 | IA4: 12.82336 | IB4: 12.82336 | IC4: 12.82336 | ID4: 12.82336 | IE4: 12.82336 | IF4: 12.82336 | IG4: 12.82336 | IH4: 12.82336 | II4: 12.82336 | IJ4: 12.82336 | IK4: 12.82336 | IL4: 12.82336 | IM4: 12.82336 | IN4: 12.82336 | IO4: 12.82336 | IP4: 12.82336 | IQ4: 12.82336 | IR4: 12.82336 | IS4: 12.82336 | IT4: 12.82336 | IU4: 12.82336 | IV4: 12.82336 | IW4: 12.82336 | IX4: 12.82336 | IY4: 12.82336 | IZ4: 12.82336 | JA4: 12.82336 | JB4: 12.82336 | JC4: 12.82336 | JD4: 12.82336 | JE4: 12.82336 | JF4: 12.82336 | JG4: 12.82336 | JH4: 12.82336 | JI4: 12.82336 | JJ4: 12.82336 | JK4: 12.82336 | JL4: 12.82336 | JM4: 12.82336 | JN4: 12.82336 | JO4: 12.82336 | JP4: 12.82336 | JQ4: 12.82336 | JR4: 12.82336 | JS4: 12.82336 | JT4: 12.82336 | JU4: 12.82336 | JV4: 12.82336 | JW4: 12.82336 | JX4: 12.82336 | JY4: 12.82336 | JZ4: 12.82336 | KA4: 12.82336 | KB4: 12.82336 | KC4: 12.82336 | KD4: 12.82336 | KE4: 12.82336 | KF4: 12.82336 | KG4: 12.82336 | KH4: 12.82336 | KI4: 12.82336 | KJ4: 12.82336 | KK4: 12.82336 | KL4: 12.82336 | KM4: 12.82336 | KN4: 12.82336 | KO4: 12.82336 | KP4: 12.82336 | KQ4: 12.82336 | KR4: 12.82336 | KS4: 12.82336 | KT4: 12.82336 | KU4: 12.82336 | KV4: 12.82336 | KW4: 12.82336 | KX4: 12.82336 | KY4: 12.82336 | KZ4: 12.82336 | LA4: 12.82336 | LB4: 12.82336 | LC4: 12.82336 | LD4: 12.82336 | LE4: 12.82336 | LF4: 12.82336 | LG4: 12.82336 | LH4: 12.82336 | LI4: 12.82336 | LJ4: 12.82336 | LK4: 12.82336 | LL4: 12.82336 | LM4: 12.82336 | LN4: 12.82336 | LO4: 12.82336 | LP4: 12.82336 | LQ4: 12.82336 | LR4: 12.82336 | LS4: 12.82336 | LT4: 12.82336 | LU4: 12.82336 | LV4: 12.82336 | LW4: 12.82336 | LX4: 12.82336 | LY4: 12.82336 | LZ4: 12.82336 | MA4: 12.82336 | MB4: 12.82336 | MC4: 12.82336 | MD4: 12.82336 | ME4: 12.82336 | MF4: 12.82336 | MG4: 12.82336 | MH4: 12.82336 | MI4: 12.82336 | MJ4: 12.82336 | MK4: 12.82336 | ML4: 12.82336 | MM4: 12.82336 | MN4: 12.82336 | MO4: 12.82336 | MP4: 12.82336 | MQ4: 12.82336 | MR4: 12.82336 | MS4: 12.82336 | MT4: 12.82336 | MU4: 12.82336 | MV4: 12.82336 | MW4: 12.82336 | MX4: 12.82336 | MY4: 12.82336 | MZ4: 13.87056
A5: =+'Valo FX'!A6 -> 3 | B5: =+Base!B3 -> 202401310029A033 | C5: 6 | D5: 0 | E5: 0 | F5: 0 | G5: 0 | H5: 0 | I5: 0 | J5: 13.15116 | K5: 13.15116 | L5: 13.15116 | M5: 13.15116 | N5: 13.15116 | O5: 13.15116 | P5: 13.15116 | Q5: 13.15116 | R5: 13.15116 | S5: 13.15116 | T5: 13.15116 | U5: 13.15116 | V5: 13.15116 | W5: 13.15116 | X5: 13.15116 | Y5: 13.15116 | Z5: 13.15116 | AA5: 13.15116 | AB5: 13.15116 | AC5: 13.15116 | AD5: 13.15116 | AE5: 13.15116 | AF5: 13.15116 | AG5: 13.15116 | AH5: 13.15116 | AI5: 13.15116 | AJ5: 13.15116 | AK5: 13.15116 | AL5: 13.15116 | AM5: 13.15116 | AN5: 13.15116 | AO5: 13.15116 | AP5: 13.15116 | AQ5: 13.15116 | AR5: 13.15116 | AS5: 13.15116 | AT5: 13.15116 | AU5: 13.15116 | AV5: 13.15116 | AW5: 13.15116 | AX5: 13.15116 | AY5: 13.15116 | AZ5: 13.15116 | BA5: 13.15116 | BB5: 13.15116 | BC5: 13.15116 | BD5: 13.15116 | BE5: 13.15116 | BF5: 13.15116 | BG5: 13.15116 | BH5: 13.15116 | BI5: 13.15116 | BJ5: 13.15116 | BK5: 13.15116 | BL5: 13.15116 | BM5: 13.15116 | BN5: 13.15116 | BO5: 13.15116 | BP5: 13.15116 | BQ5: 13.15116 | BR5: 13.15116 | BS5: 13.15116 | BT5: 13.15116 | BU5: 13.15116 | BV5: 13.15116 | BW5: 13.15116 | BX5: 13.15116 | BY5: 13.15116 | BZ5: 13.15116 | CA5: 13.15116 | CB5: 13.15116 | CC5: 13.15116 | CD5: 13.15116 | CE5: 13.15116 | CF5: 13.15116 | CG5: 13.15116 | CH5: 13.15116 | CI5: 13.15116 | CJ5: 13.15116 | CK5: 13.15116 | CL5: 13.15116 | CM5: 13.15116 | CN5: 13.15116 | CO5: 13.15116 | CP5: 13.15116 | CQ5: 13.15116 | CR5: 13.15116 | CS5: 13.15116 | CT5: 13.15116 | CU5: 13.15116 | CV5: 13.15116 | CW5: 13.15116 | CX5: 13.15116 | CY5: 13.15116 | CZ5: 13.15116 | DA5: 13.15116 | DB5: 13.15116 | DC5: 13.15116 | DD5: 13.15116 | DE5: 13.15116 | DF5: 13.15116 | DG5: 13.15116 | DH5: 13.15116 | DI5: 13.15116 | DJ5: 13.15116 | DK5: 13.15116 | DL5: 13.15116 | DM5: 13.15116 | DN5: 13.15116 | DO5: 13.15116 | DP5: 13.15116 | DQ5: 13.15116 | DR5: 13.15116 | DS5: 13.15116 | DT5: 13.15116 | DU5: 13.15116 | DV5: 13.15116 | DW5: 13.15116 | DX5: 13.15116 | DY5: 13.15116 | DZ5: 13.15116 | EA5: 13.15116 | EB5: 13.15116 | EC5: 13.15116 | ED5: 13.15116 | EE5: 13.15116 | EF5: 13.15116 | EG5: 13.15116 | EH5: 13.15116 | EI5: 13.15116 | EJ5: 13.15116 | EK5: 13.15116 | EL5: 13.15116 | EM5: 13.15116 | EN5: 13.15116 | EO5: 13.15116 | EP5: 13.15116 | EQ5: 13.15116 | ER5: 13.15116 | ES5: 13.15116 | ET5: 13.15116 | EU5: 13.15116 | EV5: 13.15116 | EW5: 13.15116 | EX5: 13.15116 | EY5: 13.15116 | EZ5: 13.15116 | FA5: 13.15116 | FB5: 13.15116 | FC5: 13.15116 | FD5: 13.15116 | FE5: 13.15116 | FF5: 13.15116 | FG5: 13.15116 | FH5: 13.15116 | FI5: 13.15116 | FJ5: 13.15116 | FK5: 13.15116 | FL5: 13.15116 | FM5: 13.15116 | FN5: 13.15116 | FO5: 13.15116 | FP5: 13.15116 | FQ5: 13.15116 | FR5: 13.15116 | FS5: 13.15116 | FT5: 13.15116 | FU5: 13.15116 | FV5: 13.15116 | FW5: 13.15116 | FX5: 13.15116 | FY5: 13.15116 | FZ5: 13.15116 | GA5: 13.15116 | GB5: 13.15116 | GC5: 13.15116 | GD5: 13.15116 | GE5: 13.15116 | GF5: 13.15116 | GG5: 13.15116 | GH5: 13.15116 | GI5: 13.15116 | GJ5: 13.15116 | GK5: 13.15116 | GL5: 13.15116 | GM5: 13.15116 | GN5: 13.15116 | GO5: 13.15116 | GP5: 13.15116 | GQ5: 13.15116 | GR5: 13.15116 | GS5: 13.15116 | GT5: 13.15116 | GU5: 13.15116 | GV5: 13.15116 | GW5: 13.15116 | GX5: 13.15116 | GY5: 13.15116 | GZ5: 13.15116 | HA5: 13.15116 | HB5: 13.15116 | HC5: 13.15116 | HD5: 13.15116 | HE5: 13.15116 | HF5: 13.15116 | HG5: 13.15116 | HH5: 13.15116 | HI5: 13.15116 | HJ5: 13.15116 | HK5: 13.15116 | HL5: 12.92544 | HM5: 0 | HN5: 0 | HO5: 0 | HP5: 0 | HQ5: 0 | HR5: 0 | HS5: 0 | HT5: 0 | HU5: 0 | HV5: 0 | HW5: 0 | HX5: 0 | HY5: 0 | HZ5: 0 | IA5: 0 | IB5: 0 | IC5: 0 | ID5: 0 | IE5: 0 | IF5: 0 | IG5: 0 | IH5: 0 | II5: 0 | IJ5: 0 | IK5: 0 | IL5: 0 | IM5: 0 | IN5: 0 | IO5: 0 | IP5: 0 | IQ5: 0 | IR5: 0 | IS5: 0 | IT5: 0 | IU5: 0 | IV5: 0 | IW5: 0 | IX5: 0 | IY5: 0 | IZ5: 0 | JA5: 0 | JB5: 0 | JC5: 0 | JD5: 0 | JE5: 0 | JF5: 0 | JG5: 0 | JH5: 0 | JI5: 0 | JJ5: 0 | JK5: 0 | JL5: 0 | JM5: 0 | JN5: 0 | JO5: 0 | JP5: 0 | JQ5: 0 | JR5: 0 | JS5: 0 | JT5: 0 | JU5: 0 | JV5: 0 | JW5: 0 | JX5: 0 | JY5: 0 | JZ5: 0 | KA5: 0 | KB5: 0 | KC5: 0 | KD5: 0 | KE5: 0 | KF5: 0 | KG5: 0 | KH5: 0 | KI5: 0 | KJ5: 0 | KK5: 0 | KL5: 0 | KM5: 0 | KN5: 0 | KO5: 0 | KP5: 0 | KQ5: 0 | KR5: 0 | KS5: 0 | KT5: 0 | KU5: 0 | KV5: 0 | KW5: 0 | KX5: 0 | KY5: 0 | KZ5: 0 | LA5: 0 | LB5: 0 | LC5: 0 | LD5: 0 | LE5: 0 | LF5: 0 | LG5: 0 | LH5: 0 | LI5: 0 | LJ5: 0 | LK5: 0 | LL5: 0 | LM5: 0 | LN5: 0 | LO5: 0 | LP5: 0 | LQ5: 0 | LR5: 0 | LS5: 0 | LT5: 0 | LU5: 0 | LV5: 0 | LW5: 0 | LX5: 0 | LY5: 0 | LZ5: 0 | MA5: 0 | MB5: 0 | MC5: 0 | MD5: 0 | ME5: 0 | MF5: 0 | MG5: 0 | MH5: 0 | MI5: 0 | MJ5: 0 | MK5: 0 | ML5: 0 | MM5: 0 | MN5: 0 | MO5: 0 | MP5: 0 | MQ5: 0 | MR5: 0 | MS5: 0 | MT5: 0 | MU5: 0 | MV5: 0 | MW5: 0 | MX5: 0 | MY5: 0 | MZ5: 0
A6: =+'Valo FX'!A7 -> 4 | B6: =+Base!B4 -> 202401310030A033 | C6: 6 | D6: 0 | E6: 0 | F6: 0 | G6: 0 | H6: 0 | I6: 0 | J6: 10.975193 | K6: 10.975193 | L6: 10.975193 | M6: 10.975193 | N6: 10.975193 | O6: 10.975193 | P6: 10.975193 | Q6: 10.975193 | R6: 10.975193 | S6: 10.975193 | T6: 10.975193 | U6: 10.975193 | V6: 10.975193 | W6: 10.975193 | X6: 10.975193 | Y6: 10.975193 | Z6: 10.975193 | AA6: 10.975193 | AB6: 10.975193 | AC6: 10.975193 | AD6: 10.975193 | AE6: 10.975193 | AF6: 10.975193 | AG6: 10.975193 | AH6: 10.975193 | AI6: 10.975193 | AJ6: 10.975193 | AK6: 10.975193 | AL6: 10.975193 | AM6: 10.975193 | AN6: 10.975193 | AO6: 10.975193 | AP6: 10.975193 | AQ6: 10.975193 | AR6: 10.975193 | AS6: 10.975193 | AT6: 10.975193 | AU6: 10.975193 | AV6: 10.975193 | AW6: 10.975193 | AX6: 10.975193 | AY6: 10.975193 | AZ6: 10.975193 | BA6: 10.975193 | BB6: 10.975193 | BC6: 10.975193 | BD6: 10.975193 | BE6: 10.975193 | BF6: 10.975193 | BG6: 10.975193 | BH6: 10.975193 | BI6: 10.975193 | BJ6: 10.975193 | BK6: 10.975193 | BL6: 10.975193 | BM6: 10.975193 | BN6: 10.975193 | BO6: 10.975193 | BP6: 10.975193 | BQ6: 10.975193 | BR6: 10.975193 | BS6: 10.975193 | BT6: 10.975193 | BU6: 10.975193 | BV6: 10.975193 | BW6: 10.975193 | BX6: 10.975193 | BY6: 10.975193 | BZ6: 10.975193 | CA6: 10.975193 | CB6: 10.975193 | CC6: 10.975193 | CD6: 10.975193 | CE6: 10.975193 | CF6: 10.975193 | CG6: 10.975193 | CH6: 10.975193 | CI6: 10.975193 | CJ6: 10.975193 | CK6: 10.975193 | CL6: 10.975193 | CM6: 10.975193 | CN6: 10.975193 | CO6: 10.975193 | CP6: 10.975193 | CQ6: 10.975193 | CR6: 10.975193 | CS6: 10.975193 | CT6: 10.975193 | CU6: 10.975193 | CV6: 10.975193 | CW6: 10.975193 | CX6: 10.975193 | CY6: 10.975193 | CZ6: 10.975193 | DA6: 10.975193 | DB6: 10.975193 | DC6: 10.975193 | DD6: 10.975193 | DE6: 10.975193 | DF6: 10.975193 | DG6: 10.975193 | DH6: 10.975193 | DI6: 10.975193 | DJ6: 10.975193 | DK6: 10.975193 | DL6: 10.975193 | DM6: 10.975193 | DN6: 10.975193 | DO6: 10.975193 | DP6: 10.975193 | DQ6: 10.975193 | DR6: 10.975193 | DS6: 10.975193 | DT6: 10.975193 | DU6: 10.975193 | DV6: 10.975193 | DW6: 10.975193 | DX6: 10.975193 | DY6: 10.975193 | DZ6: 10.975193 | EA6: 10.975193 | EB6: 10.975193 | EC6: 10.975193 | ED6: 10.975193 | EE6: 10.975193 | EF6: 10.975193 | EG6: 10.975193 | EH6: 10.975193 | EI6: 10.975193 | EJ6: 10.975193 | EK6: 10.975193 | EL6: 10.975193 | EM6: 10.975193 | EN6: 10.975193 | EO6: 10.975193 | EP6: 10.975193 | EQ6: 10.975193 | ER6: 10.975193 | ES6: 10.975193 | ET6: 10.975193 | EU6: 10.975193 | EV6: 10.975193 | EW6: 10.975193 | EX6: 10.975193 | EY6: 10.975193 | EZ6: 10.975193 | FA6: 10.975193 | FB6: 10.975193 | FC6: 10.975193 | FD6: 10.975193 | FE6: 10.975193 | FF6: 10.975193 | FG6: 10.975193 | FH6: 10.975193 | FI6: 10.975193 | FJ6: 10.975193 | FK6: 10.975193 | FL6: 10.975193 | FM6: 10.975193 | FN6: 10.975193 | FO6: 10.975193 | FP6: 10.975193 | FQ6: 10.975193 | FR6: 10.975193 | FS6: 10.975193 | FT6: 10.975193 | FU6: 10.975193 | FV6: 10.975193 | FW6: 10.975193 | FX6: 10.975193 | FY6: 10.975193 | FZ6: 10.975193 | GA6: 10.975193 | GB6: 10.975193 | GC6: 10.975193 | GD6: 10.975193 | GE6: 10.975193 | GF6: 10.975193 | GG6: 10.975193 | GH6: 10.975193 | GI6: 10.975193 | GJ6: 10.975193 | GK6: 10.975193 | GL6: 10.975193 | GM6: 10.975193 | GN6: 10.975193 | GO6: 10.975193 | GP6: 10.975193 | GQ6: 10.975193 | GR6: 10.975193 | GS6: 10.975193 | GT6: 10.975193 | GU6: 10.975193 | GV6: 10.975193 | GW6: 10.975193 | GX6: 10.975193 | GY6: 10.975193 | GZ6: 10.975193 | HA6: 10.975193 | HB6: 10.975193 | HC6: 10.975193 | HD6: 10.975193 | HE6: 10.975193 | HF6: 10.975193 | HG6: 10.975193 | HH6: 10.975193 | HI6: 10.975193 | HJ6: 10.975193 | HK6: 10.975193 | HL6: 10.975193 | HM6: 10.975193 | HN6: 10.975193 | HO6: 10.975193 | HP6: 10.975193 | HQ6: 10.975193 | HR6: 10.975193 | HS6: 10.975193 | HT6: 10.975193 | HU6: 10.975193 | HV6: 10.975193 | HW6: 10.975193 | HX6: 10.975193 | HY6: 10.975193 | HZ6: 10.975193 | IA6: 10.975193 | IB6: 10.975193 | IC6: 10.975193 | ID6: 10.975193 | IE6: 10.975193 | IF6: 10.975193 | IG6: 10.975193 | IH6: 10.975193 | II6: 10.975193 | IJ6: 10.975193 | IK6: 10.975193 | IL6: 10.975193 | IM6: 10.975193 | IN6: 10.975193 | IO6: 10.975193 | IP6: 10.975193 | IQ6: 10.975193 | IR6: 10.975193 | IS6: 10.975193 | IT6: 10.975193 | IU6: 10.975193 | IV6: 10.975193 | IW6: 10.975193 | IX6: 10.975193 | IY6: 10.975193 | IZ6: 10.975193 | JA6: 10.975193 | JB6: 10.975193 | JC6: 10.975193 | JD6: 10.975193 | JE6: 10.975193 | JF6: 10.975193 | JG6: 10.975193 | JH6: 10.975193 | JI6: 10.975193 | JJ6: 10.975193 | JK6: 10.975193 | JL6: 10.975193 | JM6: 10.975193 | JN6: 10.975193 | JO6: 10.975193 | JP6: 10.975193 | JQ6: 10.975193 | JR6: 10.975193 | JS6: 10.975193 | JT6: 10.975193 | JU6: 10.975193 | JV6: 10.975193 | JW6: 10.975193 | JX6: 10.975193 | JY6: 10.975193 | JZ6: 10.975193 | KA6: 10.975193 | KB6: 10.975193 | KC6: 10.975193 | KD6: 10.975193 | KE6: 10.975193 | KF6: 10.975193 | KG6: 10.975193 | KH6: 10.975193 | KI6: 10.975193 | KJ6: 10.975193 | KK6: 10.975193 | KL6: 10.975193 | KM6: 10.975193 | KN6: 10.975193 | KO6: 10.975193 | KP6: 10.975193 | KQ6: 10.975193 | KR6: 10.975193 | KS6: 10.975193 | KT6: 10.975193 | KU6: 10.975193 | KV6: 10.975193 | KW6: 10.975193 | KX6: 10.975193 | KY6: 10.975193 | KZ6: 10.975193 | LA6: 10.975193 | LB6: 10.975193 | LC6: 10.975193 | LD6: 10.975193 | LE6: 10.975193 | LF6: 10.975193 | LG6: 10.975193 | LH6: 10.975193 | LI6: 10.975193 | LJ6: 10.975193 | LK6: 10.975193 | LL6: 10.975193 | LM6: 10.975193 | LN6: 10.975193 | LO6: 10.975193 | LP6: 10.975193 | LQ6: 10.975193 | LR6: 10.975193 | LS6: 10.975193 | LT6: 10.975193 | LU6: 10.975193 | LV6: 10.975193 | LW6: 10.975193 | LX6: 10.975193 | LY6: 10.975193 | LZ6: 10.975193 | MA6: 10.975193 | MB6: 10.975193 | MC6: 10.975193 | MD6: 10.975193 | ME6: 10.975193 | MF6: 10.975193 | MG6: 10.975193 | MH6: 10.975193 | MI6: 10.975193 | MJ6: 10.975193 | MK6: 10.975193 | ML6: 10.975193 | MM6: 10.975193 | MN6: 10.975193 | MO6: 10.975193 | MP6: 10.975193 | MQ6: 10.975193 | MR6: 10.975193 | MS6: 10.975193 | MT6: 10.975193 | MU6: 10.975193 | MV6: 10.975193 | MW6: 10.975193 | MX6: 10.975193 | MY6: 10.975193 | MZ6: 11.871466
A7: =+'Valo FX'!A8 -> 5 | B7: =+Base!B5 -> 202401310034A033 | C7: 6 | D7: 0 | E7: 0 | F7: 0 | G7: 0 | H7: 0 | I7: 0 | J7: 9.36251 | K7: 9.36251 | L7: 9.36251 | M7: 9.36251 | N7: 9.36251 | O7: 9.36251 | P7: 9.36251 | Q7: 9.36251 | R7: 9.36251 | S7: 9.36251 | T7: 9.36251 | U7: 9.36251 | V7: 9.36251 | W7: 9.36251 | X7: 9.36251 | Y7: 9.36251 | Z7: 9.36251 | AA7: 9.36251 | AB7: 9.36251 | AC7: 9.36251 | AD7: 9.36251 | AE7: 9.36251 | AF7: 9.36251 | AG7: 9.36251 | AH7: 9.36251 | AI7: 9.36251 | AJ7: 9.36251 | AK7: 9.36251 | AL7: 9.36251 | AM7: 9.36251 | AN7: 9.36251 | AO7: 9.36251 | AP7: 9.36251 | AQ7: 9.36251 | AR7: 9.36251 | AS7: 9.36251 | AT7: 9.36251 | AU7: 9.36251 | AV7: 9.36251 | AW7: 9.36251 | AX7: 9.36251 | AY7: 9.36251 | AZ7: 9.36251 | BA7: 9.36251 | BB7: 9.36251 | BC7: 9.36251 | BD7: 9.36251 | BE7: 9.36251 | BF7: 9.36251 | BG7: 9.36251 | BH7: 9.36251 | BI7: 9.36251 | BJ7: 9.36251 | BK7: 9.36251 | BL7: 9.36251 | BM7: 9.36251 | BN7: 9.36251 | BO7: 9.36251 | BP7: 9.36251 | BQ7: 9.36251 | BR7: 9.36251 | BS7: 9.36251 | BT7: 9.36251 | BU7: 9.36251 | BV7: 9.36251 | BW7: 9.36251 | BX7: 9.36251 | BY7: 9.36251 | BZ7: 9.36251 | CA7: 9.36251 | CB7: 9.36251 | CC7: 9.36251 | CD7: 9.36251 | CE7: 9.36251 | CF7: 9.36251 | CG7: 9.36251 | CH7: 9.36251 | CI7: 9.36251 | CJ7: 9.36251 | CK7: 9.36251 | CL7: 9.36251 | CM7: 9.36251 | CN7: 9.36251 | CO7: 9.36251 | CP7: 9.36251 | CQ7: 9.36251 | CR7: 9.36251 | CS7: 9.36251 | CT7: 9.36251 | CU7: 9.36251 | CV7: 9.36251 | CW7: 9.36251 | CX7: 9.36251 | CY7: 9.36251 | CZ7: 9.36251 | DA7: 9.36251 | DB7: 9.36251 | DC7: 9.36251 | DD7: 9.36251 | DE7: 9.36251 | DF7: 9.36251 | DG7: 9.36251 | DH7: 9.36251 | DI7: 9.36251 | DJ7: 9.36251 | DK7: 9.36251 | DL7: 9.36251 | DM7: 9.36251 | DN7: 9.36251 | DO7: 9.36251 | DP7: 9.36251 | DQ7: 9.36251 | DR7: 9.36251 | DS7: 9.36251 | DT7: 9.36251 | DU7: 9.36251 | DV7: 9.36251 | DW7: 9.36251 | DX7: 9.36251 | DY7: 9.36251 | DZ7: 9.36251 | EA7: 9.36251 | EB7: 9.36251 | EC7: 9.36251 | ED7: 9.36251 | EE7: 9.36251 | EF7: 9.36251 | EG7: 9.36251 | EH7: 9.36251 | EI7: 9.36251 | EJ7: 9.36251 | EK7: 9.36251 | EL7: 9.36251 | EM7: 9.36251 | EN7: 9.36251 | EO7: 9.36251 | EP7: 9.36251 | EQ7: 9.36251 | ER7: 9.36251 | ES7: 9.36251 | ET7: 9.36251 | EU7: 9.36251 | EV7: 9.36251 | EW7: 9.36251 | EX7: 9.36251 | EY7: 9.36251 | EZ7: 9.36251 | FA7: 9.36251 | FB7: 9.36251 | FC7: 9.36251 | FD7: 9.36251 | FE7: 9.36251 | FF7: 9.36251 | FG7: 9.36251 | FH7: 9.36251 | FI7: 9.36251 | FJ7: 9.36251 | FK7: 9.36251 | FL7: 9.36251 | FM7: 9.36251 | FN7: 9.36251 | FO7: 9.36251 | FP7: 9.36251 | FQ7: 9.36251 | FR7: 9.36251 | FS7: 9.36251 | FT7: 9.36251 | FU7: 9.36251 | FV7: 9.36251 | FW7: 9.36251 | FX7: 9.36251 | FY7: 9.36251 | FZ7: 9.36251 | GA7: 9.36251 | GB7: 9.36251 | GC7: 9.36251 | GD7: 9.36251 | GE7: 9.36251 | GF7: 9.36251 | GG7: 9.36251 | GH7: 9.36251 | GI7: 9.36251 | GJ7: 9.36251 | GK7: 9.36251 | GL7: 9.36251 | GM7: 9.36251 | GN7: 9.36251 | GO7: 9.36251 | GP7: 9.36251 | GQ7: 9.36251 | GR7: 9.36251 | GS7: 9.36251 | GT7: 9.36251 | GU7: 9.36251 | GV7: 9.36251 | GW7: 9.36251 | GX7: 9.36251 | GY7: 9.36251 | GZ7: 9.36251 | HA7: 9.36251 | HB7: 9.36251 | HC7: 9.36251 | HD7: 9.36251 | HE7: 9.36251 | HF7: 9.36251 | HG7: 9.36251 | HH7: 9.36251 | HI7: 9.36251 | HJ7: 9.36251 | HK7: 9.36251 | HL7: 9.36251 | HM7: 9.36251 | HN7: 9.36251 | HO7: 9.36251 | HP7: 9.36251 | HQ7: 9.36251 | HR7: 9.36251 | HS7: 9.36251 | HT7: 9.36251 | HU7: 9.36251 | HV7: 9.36251 | HW7: 9.36251 | HX7: 9.36251 | HY7: 9.36251 | HZ7: 9.36251 | IA7: 9.36251 | IB7: 9.36251 | IC7: 9.36251 | ID7: 9.36251 | IE7: 9.36251 | IF7: 9.36251 | IG7: 9.36251 | IH7: 9.36251 | II7: 9.36251 | IJ7: 9.36251 | IK7: 9.36251 | IL7: 9.36251 | IM7: 9.36251 | IN7: 9.36251 | IO7: 9.36251 | IP7: 9.36251 | IQ7: 9.36251 | IR7: 9.36251 | IS7: 9.36251 | IT7: 9.36251 | IU7: 9.36251 | IV7: 9.36251 | IW7: 9.36251 | IX7: 9.36251 | IY7: 9.36251 | IZ7: 9.36251 | JA7: 9.36251 | JB7: 9.36251 | JC7: 9.36251 | JD7: 9.36251 | JE7: 9.36251 | JF7: 9.36251 | JG7: 9.36251 | JH7: 9.36251 | JI7: 9.36251 | JJ7: 9.36251 | JK7: 9.36251 | JL7: 9.36251 | JM7: 9.36251 | JN7: 9.36251 | JO7: 9.36251 | JP7: 9.36251 | JQ7: 9.36251 | JR7: 9.36251 | JS7: 9.36251 | JT7: 9.36251 | JU7: 9.36251 | JV7: 9.36251 | JW7: 9.36251 | JX7: 9.36251 | JY7: 9.36251 | JZ7: 9.36251 | KA7: 9.36251 | KB7: 9.36251 | KC7: 9.36251 | KD7: 9.36251 | KE7: 9.36251 | KF7: 9.36251 | KG7: 9.36251 | KH7: 9.36251 | KI7: 9.36251 | KJ7: 9.36251 | KK7: 9.36251 | KL7: 9.36251 | KM7: 9.36251 | KN7: 9.36251 | KO7: 9.36251 | KP7: 9.36251 | KQ7: 9.36251 | KR7: 9.36251 | KS7: 9.36251 | KT7: 9.36251 | KU7: 9.36251 | KV7: 9.36251 | KW7: 9.36251 | KX7: 9.36251 | KY7: 9.36251 | KZ7: 9.36251 | LA7: 9.36251 | LB7: 9.36251 | LC7: 9.36251 | LD7: 9.36251 | LE7: 9.36251 | LF7: 9.36251 | LG7: 9.36251 | LH7: 9.36251 | LI7: 9.36251 | LJ7: 9.36251 | LK7: 9.36251 | LL7: 9.36251 | LM7: 9.36251 | LN7: 9.36251 | LO7: 9.36251 | LP7: 9.36251 | LQ7: 9.36251 | LR7: 9.36251 | LS7: 9.36251 | LT7: 9.36251 | LU7: 9.36251 | LV7: 9.36251 | LW7: 9.36251 | LX7: 9.36251 | LY7: 9.36251 | LZ7: 9.36251 | MA7: 9.36251 | MB7: 9.36251 | MC7: 9.36251 | MD7: 9.36251 | ME7: 9.36251 | MF7: 9.36251 | MG7: 9.36251 | MH7: 9.36251 | MI7: 9.36251 | MJ7: 9.36251 | MK7: 9.36251 | ML7: 9.36251 | MM7: 9.36251 | MN7: 9.36251 | MO7: 9.36251 | MP7: 9.36251 | MQ7: 9.36251 | MR7: 9.36251 | MS7: 9.36251 | MT7: 9.36251 | MU7: 9.36251 | MV7: 9.36251 | MW7: 9.36251 | MX7: 9.36251 | MY7: 9.36251 | MZ7: 10.127085
A8: =+'Valo FX'!A9 -> 6 | B8: =+Base!B6 -> 202401310036A033 | C8: 6 | D8: 0 | E8: 0 | F8: 0 | G8: 0 | H8: 0 | I8: 0 | J8: 8.825923 | K8: 8.825923 | L8: 8.825923 | M8: 8.825923 | N8: 8.825923 | O8: 8.825923 | P8: 8.825923 | Q8: 8.825923 | R8: 8.825923 | S8: 8.825923 | T8: 8.825923 | U8: 8.825923 | V8: 8.825923 | W8: 8.825923 | X8: 8.825923 | Y8: 8.825923 | Z8: 8.825923 | AA8: 8.825923 | AB8: 8.825923 | AC8: 8.825923 | AD8: 8.825923 | AE8: 8.825923 | AF8: 8.825923 | AG8: 8.825923 | AH8: 8.825923 | AI8: 8.825923 | AJ8: 8.825923 | AK8: 8.825923 | AL8: 8.825923 | AM8: 8.825923 | AN8: 8.825923 | AO8: 8.825923 | AP8: 8.825923 | AQ8: 8.825923 | AR8: 8.825923 | AS8: 8.825923 | AT8: 8.825923 | AU8: 8.825923 | AV8: 8.825923 | AW8: 8.825923 | AX8: 8.825923 | AY8: 8.825923 | AZ8: 8.825923 | BA8: 8.825923 | BB8: 8.825923 | BC8: 8.825923 | BD8: 8.825923 | BE8: 8.825923 | BF8: 8.825923 | BG8: 8.825923 | BH8: 8.825923 | BI8: 8.825923 | BJ8: 8.825923 | BK8: 8.825923 | BL8: 8.825923 | BM8: 8.825923 | BN8: 8.825923 | BO8: 8.825923 | BP8: 8.825923 | BQ8: 8.825923 | BR8: 8.825923 | BS8: 8.825923 | BT8: 8.825923 | BU8: 8.825923 | BV8: 8.825923 | BW8: 8.825923 | BX8: 8.825923 | BY8: 8.825923 | BZ8: 8.825923 | CA8: 8.825923 | CB8: 8.825923 | CC8: 8.825923 | CD8: 8.825923 | CE8: 8.825923 | CF8: 8.825923 | CG8: 8.825923 | CH8: 8.825923 | CI8: 8.825923 | CJ8: 8.825923 | CK8: 8.825923 | CL8: 8.825923 | CM8: 8.825923 | CN8: 8.825923 | CO8: 8.825923 | CP8: 8.825923 | CQ8: 8.825923 | CR8: 8.825923 | CS8: 8.825923 | CT8: 8.825923 | CU8: 8.825923 | CV8: 8.825923 | CW8: 8.825923 | CX8: 8.825923 | CY8: 8.825923 | CZ8: 8.825923 | DA8: 8.825923 | DB8: 8.825923 | DC8: 8.825923 | DD8: 8.825923 | DE8: 8.825923 | DF8: 8.825923 | DG8: 8.825923 | DH8: 8.825923 | DI8: 8.825923 | DJ8: 8.825923 | DK8: 8.825923 | DL8: 8.825923 | DM8: 8.825923 | DN8: 8.825923 | DO8: 8.825923 | DP8: 8.825923 | DQ8: 8.825923 | DR8: 8.825923 | DS8: 8.825923 | DT8: 8.825923 | DU8: 8.825923 | DV8: 8.825923 | DW8: 8.825923 | DX8: 8.825923 | DY8: 8.825923 | DZ8: 8.825923 | EA8: 8.825923 | EB8: 8.825923 | EC8: 8.825923 | ED8: 8.825923 | EE8: 8.825923 | EF8: 8.825923 | EG8: 8.825923 | EH8: 8.825923 | EI8: 8.825923 | EJ8: 8.825923 | EK8: 8.825923 | EL8: 8.825923 | EM8: 8.825923 | EN8: 8.825923 | EO8: 8.825923 | EP8: 8.825923 | EQ8: 8.825923 | ER8: 8.825923 | ES8: 8.825923 | ET8: 8.825923 | EU8: 8.825923 | EV8: 8.825923 | EW8: 8.825923 | EX8: 8.825923 | EY8: 8.825923 | EZ8: 8.825923 | FA8: 8.825923 | FB8: 8.825923 | FC8: 8.825923 | FD8: 8.825923 | FE8: 8.825923 | FF8: 8.825923 | FG8: 8.825923 | FH8: 8.825923 | FI8: 8.825923 | FJ8: 8.825923 | FK8: 8.825923 | FL8: 8.825923 | FM8: 8.825923 | FN8: 8.825923 | FO8: 8.825923 | FP8: 8.825923 | FQ8: 8.825923 | FR8: 8.825923 | FS8: 8.825923 | FT8: 8.825923 | FU8: 8.825923 | FV8: 8.825923 | FW8: 8.825923 | FX8: 8.825923 | FY8: 8.825923 | FZ8: 8.825923 | GA8: 8.825923 | GB8: 8.777046 | GC8: 0 | GD8: 0 | GE8: 0 | GF8: 0 | GG8: 0 | GH8: 0 | GI8: 0 | GJ8: 0 | GK8: 0 | GL8: 0 | GM8: 0 | GN8: 0 | GO8: 0 | GP8: 0 | GQ8: 0 | GR8: 0 | GS8: 0 | GT8: 0 | GU8: 0 | GV8: 0 | GW8: 0 | GX8: 0 | GY8: 0 | GZ8: 0 | HA8: 0 | HB8: 0 | HC8: 0 | HD8: 0 | HE8: 0 | HF8: 0 | HG8: 0 | HH8: 0 | HI8: 0 | HJ8: 0 | HK8: 0 | HL8: 0 | HM8: 0 | HN8: 0 | HO8: 0 | HP8: 0 | HQ8: 0 | HR8: 0 | HS8: 0 | HT8: 0 | HU8: 0 | HV8: 0 | HW8: 0 | HX8: 0 | HY8: 0 | HZ8: 0 | IA8: 0 | IB8: 0 | IC8: 0 | ID8: 0 | IE8: 0 | IF8: 0 | IG8: 0 | IH8: 0 | II8: 0 | IJ8: 0 | IK8: 0 | IL8: 0 | IM8: 0 | IN8: 0 | IO8: 0 | IP8: 0 | IQ8: 0 | IR8: 0 | IS8: 0 | IT8: 0 | IU8: 0 | IV8: 0 | IW8: 0 | IX8: 0 | IY8: 0 | IZ8: 0 | JA8: 0 | JB8: 0 | JC8: 0 | JD8: 0 | JE8: 0 | JF8: 0 | JG8: 0 | JH8: 0 | JI8: 0 | JJ8: 0 | JK8: 0 | JL8: 0 | JM8: 0 | JN8: 0 | JO8: 0 | JP8: 0 | JQ8: 0 | JR8: 0 | JS8: 0 | JT8: 0 | JU8: 0 | JV8: 0 | JW8: 0 | JX8: 0 | JY8: 0 | JZ8: 0 | KA8: 0 | KB8: 0 | KC8: 0 | KD8: 0 | KE8: 0 | KF8: 0 | KG8: 0 | KH8: 0 | KI8: 0 | KJ8: 0 | KK8: 0 | KL8: 0 | KM8: 0 | KN8: 0 | KO8: 0 | KP8: 0 | KQ8: 0 | KR8: 0 | KS8: 0 | KT8: 0 | KU8: 0 | KV8: 0 | KW8: 0 | KX8: 0 | KY8: 0 | KZ8: 0 | LA8: 0 | LB8: 0 | LC8: 0 | LD8: 0 | LE8: 0 | LF8: 0 | LG8: 0 | LH8: 0 | LI8: 0 | LJ8: 0 | LK8: 0 | LL8: 0 | LM8: 0 | LN8: 0 | LO8: 0 | LP8: 0 | LQ8: 0 | LR8: 0 | LS8: 0 | LT8: 0 | LU8: 0 | LV8: 0 | LW8: 0 | LX8: 0 | LY8: 0 | LZ8: 0 | MA8: 0 | MB8: 0 | MC8: 0 | MD8: 0 | ME8: 0 | MF8: 0 | MG8: 0 | MH8: 0 | MI8: 0 | MJ8: 0 | MK8: 0 | ML8: 0 | MM8: 0 | MN8: 0 | MO8: 0 | MP8: 0 | MQ8: 0 | MR8: 0 | MS8: 0 | MT8: 0 | MU8: 0 | MV8: 0 | MW8: 0 | MX8: 0 | MY8: 0 | MZ8: 0
A9: =+'Valo FX'!A10 -> 7 | B9: =+Base!B7 -> 202401250039A033 | C9: 6 | D9: 0 | E9: 0 | F9: 0 | G9: 0 | H9: 0 | I9: 0 | J9: 6.109894 | K9: 6.109894 | L9: 6.109894 | M9: 6.109894 | N9: 6.109894 | O9: 6.109894 | P9: 6.109894 | Q9: 6.109894 | R9: 6.109894 | S9: 6.109894 | T9: 6.109894 | U9: 6.109894 | V9: 6.109894 | W9: 6.109894 | X9: 6.109894 | Y9: 6.109894 | Z9: 6.109894 | AA9: 6.109894 | AB9: 6.109894 | AC9: 6.109894 | AD9: 6.109894 | AE9: 6.109894 | AF9: 6.109894 | AG9: 6.109894 | AH9: 6.109894 | AI9: 6.109894 | AJ9: 6.109894 | AK9: 6.109894 | AL9: 6.109894 | AM9: 6.109894 | AN9: 6.109894 | AO9: 6.109894 | AP9: 6.109894 | AQ9: 6.109894 | AR9: 6.109894 | AS9: 6.109894 | AT9: 6.109894 | AU9: 6.109894 | AV9: 6.109894 | AW9: 6.109894 | AX9: 6.109894 | AY9: 6.109894 | AZ9: 6.109894 | BA9: 6.109894 | BB9: 6.109894 | BC9: 6.109894 | BD9: 6.109894 | BE9: 6.109894 | BF9: 6.109894 | BG9: 6.109894 | BH9: 6.109894 | BI9: 6.109894 | BJ9: 6.109894 | BK9: 6.109894 | BL9: 6.109894 | BM9: 6.109894 | BN9: 6.109894 | BO9: 6.109894 | BP9: 6.109894 | BQ9: 6.109894 | BR9: 6.109894 | BS9: 6.109894 | BT9: 6.109894 | BU9: 6.109894 | BV9: 6.109894 | BW9: 6.109894 | BX9: 6.109894 | BY9: 6.109894 | BZ9: 6.109894 | CA9: 6.109894 | CB9: 6.109894 | CC9: 6.109894 | CD9: 6.109894 | CE9: 6.109894 | CF9: 6.109894 | CG9: 6.109894 | CH9: 6.109894 | CI9: 6.109894 | CJ9: 6.109894 | CK9: 6.109894 | CL9: 6.109894 | CM9: 6.109894 | CN9: 6.109894 | CO9: 6.109894 | CP9: 6.109894 | CQ9: 6.109894 | CR9: 6.109894 | CS9: 6.109894 | CT9: 6.109894 | CU9: 6.109894 | CV9: 6.109894 | CW9: 6.109894 | CX9: 6.109894 | CY9: 6.109894 | CZ9: 6.109894 | DA9: 6.109894 | DB9: 6.109894 | DC9: 6.109894 | DD9: 6.109894 | DE9: 6.109894 | DF9: 6.109894 | DG9: 6.109894 | DH9: 6.109894 | DI9: 6.109894 | DJ9: 6.109894 | DK9: 6.109894 | DL9: 6.109894 | DM9: 6.109894 | DN9: 6.109894 | DO9: 6.109894 | DP9: 6.109894 | DQ9: 6.109894 | DR9: 6.109894 | DS9: 6.109894 | DT9: 6.109894 | DU9: 6.109894 | DV9: 6.109894 | DW9: 6.109894 | DX9: 6.109894 | DY9: 6.109894 | DZ9: 6.109894 | EA9: 6.109894 | EB9: 6.109894 | EC9: 6.109894 | ED9: 6.109894 | EE9: 6.109894 | EF9: 6.109894 | EG9: 6.109894 | EH9: 6.109894 | EI9: 6.109894 | EJ9: 6.109894 | EK9: 6.109894 | EL9: 6.109894 | EM9: 6.109894 | EN9: 6.109894 | EO9: 6.109894 | EP9: 6.109894 | EQ9: 6.109894 | ER9: 6.109894 | ES9: 6.109894 | ET9: 6.109894 | EU9: 6.109894 | EV9: 6.109894 | EW9: 6.109894 | EX9: 6.109894 | EY9: 6.109894 | EZ9: 6.109894 | FA9: 6.109894 | FB9: 6.109894 | FC9: 6.109894 | FD9: 6.109894 | FE9: 6.109894 | FF9: 6.109894 | FG9: 6.109894 | FH9: 6.109894 | FI9: 6.109894 | FJ9: 6.109894 | FK9: 6.109894 | FL9: 6.109894 | FM9: 6.109894 | FN9: 6.109894 | FO9: 6.109894 | FP9: 6.109894 | FQ9: 6.109894 | FR9: 6.109894 | FS9: 6.109894 | FT9: 6.109894 | FU9: 6.109894 | FV9: 6.109894 | FW9: 6.109894 | FX9: 6.109894 | FY9: 6.109894 | FZ9: 6.109894 | GA9: 6.109894 | GB9: 6.109894 | GC9: 6.109894 | GD9: 6.109894 | GE9: 6.109894 | GF9: 6.109894 | GG9: 6.109894 | GH9: 6.109894 | GI9: 6.109894 | GJ9: 6.109894 | GK9: 6.109894 | GL9: 6.109894 | GM9: 6.109894 | GN9: 6.109894 | GO9: 6.109894 | GP9: 6.109894 | GQ9: 6.109894 | GR9: 6.109894 | GS9: 6.109894 | GT9: 6.109894 | GU9: 6.109894 | GV9: 6.109894 | GW9: 6.109894 | GX9: 6.109894 | GY9: 6.109894 | GZ9: 6.109894 | HA9: 6.109894 | HB9: 6.109894 | HC9: 6.109894 | HD9: 6.109894 | HE9: 6.109894 | HF9: 6.109894 | HG9: 6.109894 | HH9: 6.109894 | HI9: 6.109894 | HJ9: 6.109894 | HK9: 6.109894 | HL9: 6.109894 | HM9: 6.109894 | HN9: 6.109894 | HO9: 6.109894 | HP9: 6.109894 | HQ9: 6.109894 | HR9: 6.109894 | HS9: 6.109894 | HT9: 6.109894 | HU9: 6.109894 | HV9: 6.109894 | HW9: 6.109894 | HX9: 6.109894 | HY9: 6.109894 | HZ9: 6.109894 | IA9: 6.109894 | IB9: 6.109894 | IC9: 6.109894 | ID9: 6.109894 | IE9: 6.109894 | IF9: 6.109894 | IG9: 6.109894 | IH9: 6.109894 | II9: 6.109894 | IJ9: 6.109894 | IK9: 6.109894 | IL9: 6.109894 | IM9: 6.109894 | IN9: 6.109894 | IO9: 6.109894 | IP9: 6.109894 | IQ9: 6.109894 | IR9: 6.109894 | IS9: 6.109894 | IT9: 6.109894 | IU9: 6.109894 | IV9: 6.109894 | IW9: 6.109894 | IX9: 6.109894 | IY9: 6.109894 | IZ9: 6.109894 | JA9: 6.109894 | JB9: 6.109894 | JC9: 6.109894 | JD9: 6.109894 | JE9: 6.109894 | JF9: 6.109894 | JG9: 6.109894 | JH9: 6.109894 | JI9: 6.109894 | JJ9: 6.109894 | JK9: 6.109894 | JL9: 6.109894 | JM9: 6.109894 | JN9: 6.109894 | JO9: 6.109894 | JP9: 6.109894 | JQ9: 6.109894 | JR9: 6.109894 | JS9: 6.109894 | JT9: 6.109894 | JU9: 6.109894 | JV9: 6.109894 | JW9: 6.109894 | JX9: 6.109894 | JY9: 6.109894 | JZ9: 6.109894 | KA9: 6.109894 | KB9: 6.109894 | KC9: 6.109894 | KD9: 6.109894 | KE9: 6.109894 | KF9: 6.109894 | KG9: 6.109894 | KH9: 6.109894 | KI9: 6.109894 | KJ9: 6.109894 | KK9: 6.109894 | KL9: 6.109894 | KM9: 6.109894 | KN9: 6.109894 | KO9: 6.109894 | KP9: 6.109894 | KQ9: 6.109894 | KR9: 6.109894 | KS9: 6.109894 | KT9: 6.109894 | KU9: 6.109894 | KV9: 6.109894 | KW9: 6.109894 | KX9: 6.109894 | KY9: 6.109894 | KZ9: 6.109894 | LA9: 6.109894 | LB9: 6.109894 | LC9: 6.109894 | LD9: 6.109894 | LE9: 6.109894 | LF9: 6.109894 | LG9: 6.109894 | LH9: 6.109894 | LI9: 6.109894 | LJ9: 6.109894 | LK9: 6.109894 | LL9: 6.109894 | LM9: 6.109894 | LN9: 6.109894 | LO9: 6.109894 | LP9: 6.109894 | LQ9: 6.109894 | LR9: 6.109894 | LS9: 6.109894 | LT9: 6.109894 | LU9: 6.109894 | LV9: 6.109894 | LW9: 6.109894 | LX9: 6.109894 | LY9: 6.109894 | LZ9: 6.109894 | MA9: 6.109894 | MB9: 6.109894 | MC9: 6.109894 | MD9: 6.109894 | ME9: 6.109894 | MF9: 6.109894 | MG9: 6.109894 | MH9: 6.109894 | MI9: 6.109894 | MJ9: 6.109894 | MK9: 6.109894 | ML9: 6.109894 | MM9: 6.109894 | MN9: 6.109894 | MO9: 6.109894 | MP9: 6.109894 | MQ9: 6.109894 | MR9: 6.109894 | MS9: 6.109894 | MT9: 6.109894 | MU9: 6.109894 | MV9: 6.109894 | MW9: 6.109894 | MX9: 6.109894 | MY9: 6.109894 | MZ9: 6.608849
A10: =+'Valo FX'!A11 -> 8 | B10: =+Base!B8 -> 202401310041A033 | C10: 6 | D10: 0 | E10: 0 | F10: 0 | G10: 0 | H10: 0 | I10: 0 | J10: 15.019052 | K10: 15.019052 | L10: 15.019052 | M10: 15.019052 | N10: 15.019052 | O10: 15.019052 | P10: 15.019052 | Q10: 15.019052 | R10: 15.019052 | S10: 15.019052 | T10: 15.019052 | U10: 15.019052 | V10: 15.019052 | W10: 15.019052 | X10: 15.019052 | Y10: 15.019052 | Z10: 15.019052 | AA10: 15.019052 | AB10: 15.019052 | AC10: 15.019052 | AD10: 15.019052 | AE10: 15.019052 | AF10: 15.019052 | AG10: 15.019052 | AH10: 15.019052 | AI10: 15.019052 | AJ10: 15.019052 | AK10: 15.019052 | AL10: 15.019052 | AM10: 15.019052 | AN10: 15.019052 | AO10: 15.019052 | AP10: 15.019052 | AQ10: 15.019052 | AR10: 15.019052 | AS10: 15.019052 | AT10: 15.019052 | AU10: 15.019052 | AV10: 15.019052 | AW10: 15.019052 | AX10: 15.019052 | AY10: 15.019052 | AZ10: 15.019052 | BA10: 15.019052 | BB10: 15.019052 | BC10: 15.019052 | BD10: 15.019052 | BE10: 15.019052 | BF10: 15.019052 | BG10: 15.019052 | BH10: 15.019052 | BI10: 15.019052 | BJ10: 15.019052 | BK10: 15.019052 | BL10: 15.019052 | BM10: 15.019052 | BN10: 15.019052 | BO10: 15.019052 | BP10: 15.019052 | BQ10: 15.019052 | BR10: 15.019052 | BS10: 15.019052 | BT10: 15.019052 | BU10: 15.019052 | BV10: 15.019052 | BW10: 15.019052 | BX10: 15.019052 | BY10: 15.019052 | BZ10: 15.019052 | CA10: 15.019052 | CB10: 15.019052 | CC10: 15.019052 | CD10: 15.019052 | CE10: 15.019052 | CF10: 15.019052 | CG10: 15.019052 | CH10: 15.019052 | CI10: 15.019052 | CJ10: 15.019052 | CK10: 15.019052 | CL10: 15.019052 | CM10: 15.019052 | CN10: 15.019052 | CO10: 15.019052 | CP10: 15.019052 | CQ10: 15.019052 | CR10: 15.019052 | CS10: 15.019052 | CT10: 15.019052 | CU10: 15.019052 | CV10: 15.019052 | CW10: 15.019052 | CX10: 15.019052 | CY10: 15.019052 | CZ10: 15.019052 | DA10: 15.019052 | DB10: 15.019052 | DC10: 15.019052 | DD10: 15.019052 | DE10: 15.019052 | DF10: 15.019052 | DG10: 15.019052 | DH10: 15.019052 | DI10: 15.019052 | DJ10: 15.019052 | DK10: 15.019052 | DL10: 15.019052 | DM10: 15.019052 | DN10: 15.019052 | DO10: 15.019052 | DP10: 15.019052 | DQ10: 15.019052 | DR10: 15.019052 | DS10: 15.019052 | DT10: 15.019052 | DU10: 15.019052 | DV10: 15.019052 | DW10: 15.019052 | DX10: 15.019052 | DY10: 15.019052 | DZ10: 15.019052 | EA10: 15.019052 | EB10: 15.019052 | EC10: 15.019052 | ED10: 15.019052 | EE10: 15.019052 | EF10: 15.019052 | EG10: 15.019052 | EH10: 15.019052 | EI10: 15.019052 | EJ10: 15.019052 | EK10: 15.019052 | EL10: 15.019052 | EM10: 15.019052 | EN10: 15.019052 | EO10: 15.019052 | EP10: 15.019052 | EQ10: 15.019052 | ER10: 15.029812 | ES10: 0 | ET10: 0 | EU10: 0 | EV10: 0 | EW10: 0 | EX10: 0 | EY10: 0 | EZ10: 0 | FA10: 0 | FB10: 0 | FC10: 0 | FD10: 0 | FE10: 0 | FF10: 0 | FG10: 0 | FH10: 0 | FI10: 0 | FJ10: 0 | FK10: 0 | FL10: 0 | FM10: 0 | FN10: 0 | FO10: 0 | FP10: 0 | FQ10: 0 | FR10: 0 | FS10: 0 | FT10: 0 | FU10: 0 | FV10: 0 | FW10: 0 | FX10: 0 | FY10: 0 | FZ10: 0 | GA10: 0 | GB10: 0 | GC10: 0 | GD10: 0 | GE10: 0 | GF10: 0 | GG10: 0 | GH10: 0 | GI10: 0 | GJ10: 0 | GK10: 0 | GL10: 0 | GM10: 0 | GN10: 0 | GO10: 0 | GP10: 0 | GQ10: 0 | GR10: 0 | GS10: 0 | GT10: 0 | GU10: 0 | GV10: 0 | GW10: 0 | GX10: 0 | GY10: 0 | GZ10: 0 | HA10: 0 | HB10: 0 | HC10: 0 | HD10: 0 | HE10: 0 | HF10: 0 | HG10: 0 | HH10: 0 | HI10: 0 | HJ10: 0 | HK10: 0 | HL10: 0 | HM10: 0 | HN10: 0 | HO10: 0 | HP10: 0 | HQ10: 0 | HR10: 0 | HS10: 0 | HT10: 0 | HU10: 0 | HV10: 0 | HW10: 0 | HX10: 0 | HY10: 0 | HZ10: 0 | IA10: 0 | IB10: 0 | IC10: 0 | ID10: 0 | IE10: 0 | IF10: 0 | IG10: 0 | IH10: 0 | II10: 0 | IJ10: 0 | IK10: 0 | IL10: 0 | IM10: 0 | IN10: 0 | IO10: 0 | IP10: 0 | IQ10: 0 | IR10: 0 | IS10: 0 | IT10: 0 | IU10: 0 | IV10: 0 | IW10: 0 | IX10: 0 | IY10: 0 | IZ10: 0 | JA10: 0 | JB10: 0 | JC10: 0 | JD10: 0 | JE10: 0 | JF10: 0 | JG10: 0 | JH10: 0 | JI10: 0 | JJ10: 0 | JK10: 0 | JL10: 0 | JM10: 0 | JN10: 0 | JO10: 0 | JP10: 0 | JQ10: 0 | JR10: 0 | JS10: 0 | JT10: 0 | JU10: 0 | JV10: 0 | JW10: 0 | JX10: 0 | JY10: 0 | JZ10: 0 | KA10: 0 | KB10: 0 | KC10: 0 | KD10: 0 | KE10: 0 | KF10: 0 | KG10: 0 | KH10: 0 | KI10: 0 | KJ10: 0 | KK10: 0 | KL10: 0 | KM10: 0 | KN10: 0 | KO10: 0 | KP10: 0 | KQ10: 0 | KR10: 0 | KS10: 0 | KT10: 0 | KU10: 0 | KV10: 0 | KW10: 0 | KX10: 0 | KY10: 0 | KZ10: 0 | LA10: 0 | LB10: 0 | LC10: 0 | LD10: 0 | LE10: 0 | LF10: 0 | LG10: 0 | LH10: 0 | LI10: 0 | LJ10: 0 | LK10: 0 | LL10: 0 | LM10: 0 | LN10: 0 | LO10: 0 | LP10: 0 | LQ10: 0 | LR10: 0 | LS10: 0 | LT10: 0 | LU10: 0 | LV10: 0 | LW10: 0 | LX10: 0 | LY10: 0 | LZ10: 0 | MA10: 0 | MB10: 0 | MC10: 0 | MD10: 0 | ME10: 0 | MF10: 0 | MG10: 0 | MH10: 0 | MI10: 0 | MJ10: 0 | MK10: 0 | ML10: 0 | MM10: 0 | MN10: 0 | MO10: 0 | MP10: 0 | MQ10: 0 | MR10: 0 | MS10: 0 | MT10: 0 | MU10: 0 | MV10: 0 | MW10: 0 | MX10: 0 | MY10: 0 | MZ10: 0
A11: =+'Valo FX'!A12 -> 9 | B11: =+Base!B9 -> 202401310046A033 | C11: 6 | D11: 0 | E11: 0 | F11: 0 | G11: 0 | H11: 0 | I11: 0 | J11: 6.810055 | K11: 6.810055 | L11: 6.810055 | M11: 6.810055 | N11: 6.810055 | O11: 6.810055 | P11: 6.810055 | Q11: 6.810055 | R11: 6.810055 | S11: 6.810055 | T11: 6.810055 | U11: 6.810055 | V11: 6.810055 | W11: 6.810055 | X11: 6.810055 | Y11: 6.810055 | Z11: 6.810055 | AA11: 6.810055 | AB11: 6.810055 | AC11: 6.810055 | AD11: 6.810055 | AE11: 6.810055 | AF11: 6.810055 | AG11: 6.810055 | AH11: 6.810055 | AI11: 6.810055 | AJ11: 6.810055 | AK11: 6.810055 | AL11: 6.810055 | AM11: 6.810055 | AN11: 6.810055 | AO11: 6.810055 | AP11: 6.810055 | AQ11: 6.810055 | AR11: 6.810055 | AS11: 6.810055 | AT11: 6.810055 | AU11: 6.810055 | AV11: 6.810055 | AW11: 6.810055 | AX11: 6.810055 | AY11: 6.810055 | AZ11: 6.810055 | BA11: 6.810055 | BB11: 6.810055 | BC11: 6.810055 | BD11: 6.810055 | BE11: 6.810055 | BF11: 6.810055 | BG11: 6.810055 | BH11: 6.810055 | BI11: 6.810055 | BJ11: 6.810055 | BK11: 6.810055 | BL11: 6.810055 | BM11: 6.810055 | BN11: 6.810055 | BO11: 6.810055 | BP11: 6.810055 | BQ11: 6.810055 | BR11: 6.810055 | BS11: 6.810055 | BT11: 6.810055 | BU11: 6.810055 | BV11: 6.810055 | BW11: 6.810055 | BX11: 6.810055 | BY11: 6.810055 | BZ11: 6.810055 | CA11: 6.810055 | CB11: 6.810055 | CC11: 6.810055 | CD11: 6.810055 | CE11: 6.810055 | CF11: 6.810055 | CG11: 6.810055 | CH11: 6.810055 | CI11: 6.810055 | CJ11: 6.810055 | CK11: 6.810055 | CL11: 6.810055 | CM11: 6.810055 | CN11: 6.810055 | CO11: 6.810055 | CP11: 6.810055 | CQ11: 6.810055 | CR11: 6.810055 | CS11: 6.810055 | CT11: 6.810055 | CU11: 6.810055 | CV11: 6.810055 | CW11: 6.810055 | CX11: 6.810055 | CY11: 6.810055 | CZ11: 6.810055 | DA11: 6.810055 | DB11: 6.810055 | DC11: 6.810055 | DD11: 6.810055 | DE11: 6.810055 | DF11: 6.810055 | DG11: 6.810055 | DH11: 6.810055 | DI11: 6.810055 | DJ11: 6.810055 | DK11: 6.810055 | DL11: 6.810055 | DM11: 6.810055 | DN11: 6.810055 | DO11: 6.810055 | DP11: 6.810055 | DQ11: 6.810055 | DR11: 6.810055 | DS11: 6.810055 | DT11: 6.810055 | DU11: 6.810055 | DV11: 6.810055 | DW11: 6.810055 | DX11: 6.810055 | DY11: 6.810055 | DZ11: 6.810055 | EA11: 6.810055 | EB11: 6.810055 | EC11: 6.810055 | ED11: 6.810055 | EE11: 6.810055 | EF11: 6.810055 | EG11: 6.810055 | EH11: 6.810055 | EI11: 6.810055 | EJ11: 6.810055 | EK11: 6.810055 | EL11: 6.810055 | EM11: 6.810055 | EN11: 6.810055 | EO11: 6.810055 | EP11: 6.810055 | EQ11: 6.810055 | ER11: 6.810055 | ES11: 6.810055 | ET11: 6.810055 | EU11: 6.810055 | EV11: 6.810055 | EW11: 6.810055 | EX11: 6.810055 | EY11: 6.810055 | EZ11: 6.810055 | FA11: 6.810055 | FB11: 6.810055 | FC11: 6.810055 | FD11: 6.810055 | FE11: 6.810055 | FF11: 6.810055 | FG11: 6.810055 | FH11: 6.810055 | FI11: 6.810055 | FJ11: 6.810055 | FK11: 6.810055 | FL11: 6.810055 | FM11: 6.810055 | FN11: 6.810055 | FO11: 6.810055 | FP11: 6.810055 | FQ11: 6.810055 | FR11: 6.810055 | FS11: 6.810055 | FT11: 6.810055 | FU11: 6.810055 | FV11: 6.810055 | FW11: 6.810055 | FX11: 6.810055 | FY11: 6.810055 | FZ11: 6.810055 | GA11: 6.810055 | GB11: 6.810055 | GC11: 6.810055 | GD11: 6.810055 | GE11: 6.810055 | GF11: 6.810055 | GG11: 6.810055 | GH11: 6.810055 | GI11: 6.810055 | GJ11: 6.810055 | GK11: 6.810055 | GL11: 6.810055 | GM11: 6.810055 | GN11: 6.810055 | GO11: 6.810055 | GP11: 6.810055 | GQ11: 6.810055 | GR11: 6.810055 | GS11: 6.810055 | GT11: 6.810055 | GU11: 6.810055 | GV11: 6.810055 | GW11: 6.810055 | GX11: 6.810055 | GY11: 6.810055 | GZ11: 6.810055 | HA11: 6.810055 | HB11: 6.810055 | HC11: 6.810055 | HD11: 6.810055 | HE11: 6.810055 | HF11: 6.810055 | HG11: 6.810055 | HH11: 6.810055 | HI11: 6.810055 | HJ11: 6.810055 | HK11: 6.810055 | HL11: 6.810055 | HM11: 6.810055 | HN11: 6.810055 | HO11: 6.810055 | HP11: 6.810055 | HQ11: 6.810055 | HR11: 6.810055 | HS11: 6.810055 | HT11: 6.810055 | HU11: 6.810055 | HV11: 6.810055 | HW11: 6.810055 | HX11: 6.810055 | HY11: 6.810055 | HZ11: 6.810055 | IA11: 6.810055 | IB11: 6.810055 | IC11: 6.810055 | ID11: 6.810055 | IE11: 6.810055 | IF11: 6.810055 | IG11: 6.810055 | IH11: 6.810055 | II11: 6.810055 | IJ11: 6.810055 | IK11: 6.810055 | IL11: 6.810055 | IM11: 6.810055 | IN11: 6.810055 | IO11: 6.810055 | IP11: 6.810055 | IQ11: 6.810055 | IR11: 6.810055 | IS11: 6.810055 | IT11: 6.810055 | IU11: 6.810055 | IV11: 6.810055 | IW11: 6.810055 | IX11: 6.810055 | IY11: 6.810055 | IZ11: 6.810055 | JA11: 6.810055 | JB11: 6.810055 | JC11: 6.810055 | JD11: 6.810055 | JE11: 6.810055 | JF11: 6.810055 | JG11: 6.810055 | JH11: 6.810055 | JI11: 6.810055 | JJ11: 6.810055 | JK11: 6.810055 | JL11: 6.810055 | JM11: 6.810055 | JN11: 6.810055 | JO11: 6.810055 | JP11: 6.810055 | JQ11: 6.810055 | JR11: 6.810055 | JS11: 6.810055 | JT11: 6.810055 | JU11: 6.810055 | JV11: 6.810055 | JW11: 6.810055 | JX11: 6.810055 | JY11: 6.810055 | JZ11: 6.810055 | KA11: 6.810055 | KB11: 6.810055 | KC11: 6.810055 | KD11: 6.810055 | KE11: 6.810055 | KF11: 6.810055 | KG11: 6.810055 | KH11: 6.810055 | KI11: 6.810055 | KJ11: 6.810055 | KK11: 6.810055 | KL11: 6.810055 | KM11: 6.810055 | KN11: 6.810055 | KO11: 6.810055 | KP11: 6.810055 | KQ11: 6.810055 | KR11: 6.810055 | KS11: 6.810055 | KT11: 6.810055 | KU11: 6.810055 | KV11: 6.810055 | KW11: 6.810055 | KX11: 6.810055 | KY11: 6.810055 | KZ11: 6.810055 | LA11: 6.810055 | LB11: 6.810055 | LC11: 6.810055 | LD11: 6.826165 | LE11: 0 | LF11: 0 | LG11: 0 | LH11: 0 | LI11: 0 | LJ11: 0 | LK11: 0 | LL11: 0 | LM11: 0 | LN11: 0 | LO11: 0 | LP11: 0 | LQ11: 0 | LR11: 0 | LS11: 0 | LT11: 0 | LU11: 0 | LV11: 0 | LW11: 0 | LX11: 0 | LY11: 0 | LZ11: 0 | MA11: 0 | MB11: 0 | MC11: 0 | MD11: 0 | ME11: 0 | MF11: 0 | MG11: 0 | MH11: 0 | MI11: 0 | MJ11: 0 | MK11: 0 | ML11: 0 | MM11: 0 | MN11: 0 | MO11: 0 | MP11: 0 | MQ11: 0 | MR11: 0 | MS11: 0 | MT11: 0 | MU11: 0 | MV11: 0 | MW11: 0 | MX11: 0 | MY11: 0 | MZ11: 0
A12: =+'Valo FX'!A13 -> 10 | B12: =+Base!B10 -> 202401310053A033 | C12: 6 | D12: 0 | E12: 0 | F12: 0 | G12: 0 | H12: 0 | I12: 0 | J12: 7.722955 | K12: 7.722955 | L12: 7.722955 | M12: 7.722955 | N12: 7.722955 | O12: 7.722955 | P12: 7.722955 | Q12: 7.722955 | R12: 7.722955 | S12: 7.722955 | T12: 7.722955 | U12: 7.722955 | V12: 7.722955 | W12: 7.722955 | X12: 7.722955 | Y12: 7.722955 | Z12: 7.722955 | AA12: 7.722955 | AB12: 7.722955 | AC12: 7.722955 | AD12: 7.722955 | AE12: 7.722955 | AF12: 7.722955 | AG12: 7.722955 | AH12: 7.722955 | AI12: 7.722955 | AJ12: 7.722955 | AK12: 7.722955 | AL12: 7.722955 | AM12: 7.722955 | AN12: 7.722955 | AO12: 7.722955 | AP12: 7.722955 | AQ12: 7.722955 | AR12: 7.722955 | AS12: 7.722955 | AT12: 7.722955 | AU12: 7.722955 | AV12: 7.722955 | AW12: 7.722955 | AX12: 7.722955 | AY12: 7.722955 | AZ12: 7.722955 | BA12: 7.722955 | BB12: 7.722955 | BC12: 7.722955 | BD12: 7.722955 | BE12: 7.722955 | BF12: 7.722955 | BG12: 7.722955 | BH12: 7.722955 | BI12: 7.722955 | BJ12: 7.722955 | BK12: 7.722955 | BL12: 7.722955 | BM12: 7.722955 | BN12: 7.722955 | BO12: 7.722955 | BP12: 7.722955 | BQ12: 7.722955 | BR12: 7.722955 | BS12: 7.722955 | BT12: 7.722955 | BU12: 7.722955 | BV12: 7.722955 | BW12: 7.722955 | BX12: 7.722955 | BY12: 7.722955 | BZ12: 7.722955 | CA12: 7.722955 | CB12: 7.722955 | CC12: 7.722955 | CD12: 7.722955 | CE12: 7.722955 | CF12: 7.722955 | CG12: 7.722955 | CH12: 7.722955 | CI12: 7.722955 | CJ12: 7.722955 | CK12: 7.722955 | CL12: 7.722955 | CM12: 7.722955 | CN12: 7.722955 | CO12: 7.722955 | CP12: 7.722955 | CQ12: 7.722955 | CR12: 7.722955 | CS12: 7.722955 | CT12: 7.722955 | CU12: 7.722955 | CV12: 7.722955 | CW12: 7.722955 | CX12: 7.722955 | CY12: 7.722955 | CZ12: 7.722955 | DA12: 7.722955 | DB12: 7.722955 | DC12: 7.722955 | DD12: 7.722955 | DE12: 7.722955 | DF12: 7.722955 | DG12: 7.722955 | DH12: 7.722955 | DI12: 7.722955 | DJ12: 7.722955 | DK12: 7.722955 | DL12: 7.722955 | DM12: 7.722955 | DN12: 7.722955 | DO12: 7.722955 | DP12: 7.722955 | DQ12: 7.722955 | DR12: 7.722955 | DS12: 7.722955 | DT12: 7.722955 | DU12: 7.722955 | DV12: 7.722955 | DW12: 7.722955 | DX12: 7.722955 | DY12: 7.722955 | DZ12: 7.722955 | EA12: 7.722955 | EB12: 7.722955 | EC12: 7.722955 | ED12: 7.722955 | EE12: 7.722955 | EF12: 7.722955 | EG12: 7.722955 | EH12: 7.722955 | EI12: 7.722955 | EJ12: 7.722955 | EK12: 7.722955 | EL12: 7.722955 | EM12: 7.722955 | EN12: 7.722955 | EO12: 7.722955 | EP12: 7.722955 | EQ12: 7.722955 | ER12: 7.722955 | ES12: 7.722955 | ET12: 7.722955 | EU12: 7.722955 | EV12: 7.722955 | EW12: 7.722955 | EX12: 7.722955 | EY12: 7.722955 | EZ12: 7.722955 | FA12: 7.722955 | FB12: 7.722955 | FC12: 7.722955 | FD12: 7.722955 | FE12: 7.722955 | FF12: 7.722955 | FG12: 7.722955 | FH12: 7.722955 | FI12: 7.722955 | FJ12: 7.722955 | FK12: 7.722955 | FL12: 7.722955 | FM12: 7.722955 | FN12: 7.722955 | FO12: 7.722955 | FP12: 7.722955 | FQ12: 7.722955 | FR12: 7.722955 | FS12: 7.722955 | FT12: 7.722955 | FU12: 7.722955 | FV12: 7.722955 | FW12: 7.722955 | FX12: 7.722955 | FY12: 7.722955 | FZ12: 7.722955 | GA12: 7.722955 | GB12: 7.722955 | GC12: 7.722955 | GD12: 7.722955 | GE12: 7.722955 | GF12: 7.722955 | GG12: 7.722955 | GH12: 7.722955 | GI12: 7.722955 | GJ12: 7.722955 | GK12: 7.722955 | GL12: 7.722955 | GM12: 7.722955 | GN12: 7.722955 | GO12: 7.722955 | GP12: 7.722955 | GQ12: 7.722955 | GR12: 7.722955 | GS12: 7.722955 | GT12: 7.722955 | GU12: 7.722955 | GV12: 7.722955 | GW12: 7.722955 | GX12: 7.722955 | GY12: 7.722955 | GZ12: 7.722955 | HA12: 7.722955 | HB12: 7.722955 | HC12: 7.722955 | HD12: 7.722955 | HE12: 7.722955 | HF12: 7.722955 | HG12: 7.722955 | HH12: 7.722955 | HI12: 7.722955 | HJ12: 7.722955 | HK12: 7.722955 | HL12: 7.722955 | HM12: 7.722955 | HN12: 7.722955 | HO12: 7.722955 | HP12: 7.722955 | HQ12: 7.722955 | HR12: 7.722955 | HS12: 7.722955 | HT12: 7.722955 | HU12: 7.722955 | HV12: 7.722955 | HW12: 7.722955 | HX12: 7.72743 | HY12: 0 | HZ12: 0 | IA12: 0 | IB12: 0 | IC12: 0 | ID12: 0 | IE12: 0 | IF12: 0 | IG12: 0 | IH12: 0 | II12: 0 | IJ12: 0 | IK12: 0 | IL12: 0 | IM12: 0 | IN12: 0 | IO12: 0 | IP12: 0 | IQ12: 0 | IR12: 0 | IS12: 0 | IT12: 0 | IU12: 0 | IV12: 0 | IW12: 0 | IX12: 0 | IY12: 0 | IZ12: 0 | JA12: 0 | JB12: 0 | JC12: 0 | JD12: 0 | JE12: 0 | JF12: 0 | JG12: 0 | JH12: 0 | JI12: 0 | JJ12: 0 | JK12: 0 | JL12: 0 | JM12: 0 | JN12: 0 | JO12: 0 | JP12: 0 | JQ12: 0 | JR12: 0 | JS12: 0 | JT12: 0 | JU12: 0 | JV12: 0 | JW12: 0 | JX12: 0 | JY12: 0 | JZ12: 0 | KA12: 0 | KB12: 0 | KC12: 0 | KD12: 0 | KE12: 0 | KF12: 0 | KG12: 0 | KH12: 0 | KI12: 0 | KJ12: 0 | KK12: 0 | KL12: 0 | KM12: 0 | KN12: 0 | KO12: 0 | KP12: 0 | KQ12: 0 | KR12: 0 | KS12: 0 | KT12: 0 | KU12: 0 | KV12: 0 | KW12: 0 | KX12: 0 | KY12: 0 | KZ12: 0 | LA12: 0 | LB12: 0 | LC12: 0 | LD12: 0 | LE12: 0 | LF12: 0 | LG12: 0 | LH12: 0 | LI12: 0 | LJ12: 0 | LK12: 0 | LL12: 0 | LM12: 0 | LN12: 0 | LO12: 0 | LP12: 0 | LQ12: 0 | LR12: 0 | LS12: 0 | LT12: 0 | LU12: 0 | LV12: 0 | LW12: 0 | LX12: 0 | LY12: 0 | LZ12: 0 | MA12: 0 | MB12: 0 | MC12: 0 | MD12: 0 | ME12: 0 | MF12: 0 | MG12: 0 | MH12: 0 | MI12: 0 | MJ12: 0 | MK12: 0 | ML12: 0 | MM12: 0 | MN12: 0 | MO12: 0 | MP12: 0 | MQ12: 0 | MR12: 0 | MS12: 0 | MT12: 0 | MU12: 0 | MV12: 0 | MW12: 0 | MX12: 0 | MY12: 0 | MZ12: 0
A13: =+'Valo FX'!A14 -> 11 | B13: =+Base!B11 -> 202401310054A033 | C13: 6 | D13: 0 | E13: 0 | F13: 0 | G13: 0 | H13: 0 | I13: 0 | J13: 11.62117 | K13: 11.62117 | L13: 11.62117 | M13: 11.62117 | N13: 11.62117 | O13: 11.62117 | P13: 11.62117 | Q13: 11.62117 | R13: 11.62117 | S13: 11.62117 | T13: 11.62117 | U13: 11.62117 | V13: 11.62117 | W13: 11.62117 | X13: 11.62117 | Y13: 11.62117 | Z13: 11.62117 | AA13: 11.62117 | AB13: 11.62117 | AC13: 11.62117 | AD13: 11.62117 | AE13: 11.62117 | AF13: 11.62117 | AG13: 11.62117 | AH13: 11.62117 | AI13: 11.62117 | AJ13: 11.62117 | AK13: 11.62117 | AL13: 11.62117 | AM13: 11.62117 | AN13: 11.62117 | AO13: 11.62117 | AP13: 11.62117 | AQ13: 11.62117 | AR13: 11.62117 | AS13: 11.62117 | AT13: 11.62117 | AU13: 11.62117 | AV13: 11.62117 | AW13: 11.62117 | AX13: 11.62117 | AY13: 11.62117 | AZ13: 11.62117 | BA13: 11.62117 | BB13: 11.62117 | BC13: 11.62117 | BD13: 11.62117 | BE13: 11.62117 | BF13: 11.62117 | BG13: 11.62117 | BH13: 11.62117 | BI13: 11.62117 | BJ13: 11.62117 | BK13: 11.62117 | BL13: 11.62117 | BM13: 11.62117 | BN13: 11.62117 | BO13: 11.62117 | BP13: 11.62117 | BQ13: 11.62117 | BR13: 11.62117 | BS13: 11.62117 | BT13: 11.62117 | BU13: 11.62117 | BV13: 11.62117 | BW13: 11.62117 | BX13: 11.62117 | BY13: 11.62117 | BZ13: 11.62117 | CA13: 11.62117 | CB13: 11.62117 | CC13: 11.62117 | CD13: 11.62117 | CE13: 11.62117 | CF13: 11.62117 | CG13: 11.62117 | CH13: 11.62117 | CI13: 11.62117 | CJ13: 11.62117 | CK13: 11.62117 | CL13: 11.62117 | CM13: 11.62117 | CN13: 11.62117 | CO13: 11.62117 | CP13: 11.62117 | CQ13: 11.62117 | CR13: 11.62117 | CS13: 11.62117 | CT13: 11.62117 | CU13: 11.62117 | CV13: 11.62117 | CW13: 11.62117 | CX13: 11.62117 | CY13: 11.62117 | CZ13: 11.62117 | DA13: 11.62117 | DB13: 11.62117 | DC13: 11.62117 | DD13: 11.62117 | DE13: 11.62117 | DF13: 11.62117 | DG13: 11.62117 | DH13: 11.62117 | DI13: 11.62117 | DJ13: 11.62117 | DK13: 11.62117 | DL13: 11.62117 | DM13: 11.62117 | DN13: 11.62117 | DO13: 11.62117 | DP13: 11.62117 | DQ13: 11.62117 | DR13: 11.62117 | DS13: 11.62117 | DT13: 11.62117 | DU13: 11.62117 | DV13: 11.62117 | DW13: 11.62117 | DX13: 11.62117 | DY13: 11.62117 | DZ13: 11.62117 | EA13: 11.62117 | EB13: 11.62117 | EC13: 11.62117 | ED13: 11.62117 | EE13: 11.62117 | EF13: 11.62117 | EG13: 11.62117 | EH13: 11.62117 | EI13: 11.62117 | EJ13: 11.62117 | EK13: 11.62117 | EL13: 11.62117 | EM13: 11.62117 | EN13: 11.62117 | EO13: 11.62117 | EP13: 11.62117 | EQ13: 11.62117 | ER13: 11.62117 | ES13: 11.62117 | ET13: 11.62117 | EU13: 11.62117 | EV13: 11.62117 | EW13: 11.62117 | EX13: 11.62117 | EY13: 11.62117 | EZ13: 11.62117 | FA13: 11.62117 | FB13: 11.62117 | FC13: 11.62117 | FD13: 11.62117 | FE13: 11.62117 | FF13: 11.62117 | FG13: 11.62117 | FH13: 11.62117 | FI13: 11.62117 | FJ13: 11.62117 | FK13: 11.62117 | FL13: 11.62117 | FM13: 11.62117 | FN13: 11.62117 | FO13: 11.62117 | FP13: 11.62117 | FQ13: 11.62117 | FR13: 11.62117 | FS13: 11.62117 | FT13: 11.62117 | FU13: 11.62117 | FV13: 11.62117 | FW13: 11.62117 | FX13: 11.62117 | FY13: 11.62117 | FZ13: 11.62117 | GA13: 11.62117 | GB13: 11.62117 | GC13: 11.62117 | GD13: 11.62117 | GE13: 11.62117 | GF13: 11.62117 | GG13: 11.62117 | GH13: 11.62117 | GI13: 11.62117 | GJ13: 11.62117 | GK13: 11.62117 | GL13: 11.62117 | GM13: 11.62117 | GN13: 11.62117 | GO13: 11.62117 | GP13: 11.62117 | GQ13: 11.62117 | GR13: 11.62117 | GS13: 11.62117 | GT13: 11.62117 | GU13: 11.62117 | GV13: 11.62117 | GW13: 11.62117 | GX13: 11.62117 | GY13: 11.62117 | GZ13: 11.62117 | HA13: 11.62117 | HB13: 11.62117 | HC13: 11.62117 | HD13: 11.62117 | HE13: 11.62117 | HF13: 11.62117 | HG13: 11.62117 | HH13: 11.62117 | HI13: 11.62117 | HJ13: 11.62117 | HK13: 11.62117 | HL13: 11.62117 | HM13: 11.62117 | HN13: 11.62117 | HO13: 11.62117 | HP13: 11.62117 | HQ13: 11.62117 | HR13: 11.62117 | HS13: 11.62117 | HT13: 11.62117 | HU13: 11.62117 | HV13: 11.62117 | HW13: 11.62117 | HX13: 11.62117 | HY13: 11.62117 | HZ13: 11.62117 | IA13: 11.62117 | IB13: 11.62117 | IC13: 11.62117 | ID13: 11.62117 | IE13: 11.62117 | IF13: 11.62117 | IG13: 11.62117 | IH13: 11.62117 | II13: 11.62117 | IJ13: 11.62117 | IK13: 11.62117 | IL13: 11.62117 | IM13: 11.62117 | IN13: 11.62117 | IO13: 11.62117 | IP13: 11.62117 | IQ13: 11.62117 | IR13: 11.62117 | IS13: 11.62117 | IT13: 11.62117 | IU13: 11.62117 | IV13: 11.62117 | IW13: 11.62117 | IX13: 11.62117 | IY13: 11.62117 | IZ13: 11.62117 | JA13: 11.62117 | JB13: 11.62117 | JC13: 11.62117 | JD13: 11.62117 | JE13: 11.62117 | JF13: 11.62117 | JG13: 11.62117 | JH13: 11.62117 | JI13: 11.62117 | JJ13: 11.62117 | JK13: 11.62117 | JL13: 11.62117 | JM13: 11.62117 | JN13: 11.62117 | JO13: 11.62117 | JP13: 11.62117 | JQ13: 11.62117 | JR13: 11.62117 | JS13: 11.62117 | JT13: 11.62117 | JU13: 11.62117 | JV13: 11.62117 | JW13: 11.62117 | JX13: 11.62117 | JY13: 11.62117 | JZ13: 11.62117 | KA13: 11.62117 | KB13: 11.62117 | KC13: 11.62117 | KD13: 11.62117 | KE13: 11.62117 | KF13: 11.62117 | KG13: 11.62117 | KH13: 11.62117 | KI13: 11.62117 | KJ13: 11.62117 | KK13: 11.62117 | KL13: 11.62117 | KM13: 11.62117 | KN13: 11.62117 | KO13: 11.62117 | KP13: 11.62117 | KQ13: 11.62117 | KR13: 11.62117 | KS13: 11.62117 | KT13: 11.62117 | KU13: 11.62117 | KV13: 11.62117 | KW13: 11.62117 | KX13: 11.62117 | KY13: 11.62117 | KZ13: 11.62117 | LA13: 11.62117 | LB13: 11.62117 | LC13: 11.62117 | LD13: 11.62117 | LE13: 11.62117 | LF13: 11.62117 | LG13: 11.62117 | LH13: 11.62117 | LI13: 11.62117 | LJ13: 11.62117 | LK13: 11.62117 | LL13: 11.62117 | LM13: 11.62117 | LN13: 11.62117 | LO13: 11.62117 | LP13: 11.62117 | LQ13: 11.62117 | LR13: 11.62117 | LS13: 11.62117 | LT13: 11.62117 | LU13: 11.62117 | LV13: 11.62117 | LW13: 11.62117 | LX13: 11.62117 | LY13: 11.62117 | LZ13: 11.62117 | MA13: 11.62117 | MB13: 11.62117 | MC13: 11.62117 | MD13: 11.62117 | ME13: 11.62117 | MF13: 11.62117 | MG13: 11.62117 | MH13: 11.62117 | MI13: 11.62117 | MJ13: 11.62117 | MK13: 11.62117 | ML13: 11.62117 | MM13: 11.62117 | MN13: 11.62117 | MO13: 11.62117 | MP13: 11.62117 | MQ13: 11.62117 | MR13: 11.62117 | MS13: 11.62117 | MT13: 11.62117 | MU13: 11.62117 | MV13: 11.62117 | MW13: 11.62117 | MX13: 11.62117 | MY13: 11.62117 | MZ13: 12.570195
A14: =+'Valo FX'!A15 -> 12 | B14: =+Base!B12 -> 202401310063A033 | C14: 6 | D14: 0 | E14: 0 | F14: 0 | G14: 0 | H14: 0 | I14: 0 | J14: 6.58362 | K14: 6.58362 | L14: 6.58362 | M14: 6.58362 | N14: 6.58362 | O14: 6.58362 | P14: 6.58362 | Q14: 6.58362 | R14: 6.58362 | S14: 6.58362 | T14: 6.58362 | U14: 6.58362 | V14: 6.58362 | W14: 6.58362 | X14: 6.58362 | Y14: 6.58362 | Z14: 6.58362 | AA14: 6.58362 | AB14: 6.58362 | AC14: 6.58362 | AD14: 6.58362 | AE14: 6.58362 | AF14: 6.58362 | AG14: 6.58362 | AH14: 6.58362 | AI14: 6.58362 | AJ14: 6.58362 | AK14: 6.58362 | AL14: 6.58362 | AM14: 6.58362 | AN14: 6.58362 | AO14: 6.58362 | AP14: 6.58362 | AQ14: 6.58362 | AR14: 6.58362 | AS14: 6.58362 | AT14: 6.58362 | AU14: 6.58362 | AV14: 6.58362 | AW14: 6.58362 | AX14: 6.58362 | AY14: 6.58362 | AZ14: 6.58362 | BA14: 6.58362 | BB14: 6.58362 | BC14: 6.58362 | BD14: 6.58362 | BE14: 6.58362 | BF14: 6.58362 | BG14: 6.58362 | BH14: 6.58362 | BI14: 6.58362 | BJ14: 6.58362 | BK14: 6.58362 | BL14: 6.58362 | BM14: 6.58362 | BN14: 6.58362 | BO14: 6.58362 | BP14: 6.58362 | BQ14: 6.58362 | BR14: 6.58362 | BS14: 6.58362 | BT14: 6.58362 | BU14: 6.58362 | BV14: 6.58362 | BW14: 6.58362 | BX14: 6.58362 | BY14: 6.58362 | BZ14: 6.58362 | CA14: 6.58362 | CB14: 6.58362 | CC14: 6.58362 | CD14: 6.58362 | CE14: 6.58362 | CF14: 6.58362 | CG14: 6.58362 | CH14: 6.58362 | CI14: 6.58362 | CJ14: 6.58362 | CK14: 6.58362 | CL14: 6.58362 | CM14: 6.58362 | CN14: 6.58362 | CO14: 6.58362 | CP14: 6.58362 | CQ14: 6.58362 | CR14: 6.58362 | CS14: 6.58362 | CT14: 6.58362 | CU14: 6.58362 | CV14: 6.58362 | CW14: 6.58362 | CX14: 6.58362 | CY14: 6.58362 | CZ14: 6.58362 | DA14: 6.58362 | DB14: 6.58362 | DC14: 6.58362 | DD14: 6.58362 | DE14: 6.58362 | DF14: 6.58362 | DG14: 6.58362 | DH14: 6.58362 | DI14: 6.58362 | DJ14: 6.58362 | DK14: 6.58362 | DL14: 6.58362 | DM14: 6.58362 | DN14: 6.58362 | DO14: 6.58362 | DP14: 6.58362 | DQ14: 6.58362 | DR14: 6.58362 | DS14: 6.58362 | DT14: 6.58362 | DU14: 6.58362 | DV14: 6.58362 | DW14: 6.58362 | DX14: 6.58362 | DY14: 6.58362 | DZ14: 6.58362 | EA14: 6.58362 | EB14: 6.58362 | EC14: 6.58362 | ED14: 6.58362 | EE14: 6.58362 | EF14: 6.58362 | EG14: 6.58362 | EH14: 6.58362 | EI14: 6.58362 | EJ14: 6.58362 | EK14: 6.58362 | EL14: 6.58362 | EM14: 6.58362 | EN14: 6.58362 | EO14: 6.58362 | EP14: 6.58362 | EQ14: 6.58362 | ER14: 6.58362 | ES14: 6.58362 | ET14: 6.58362 | EU14: 6.58362 | EV14: 6.58362 | EW14: 6.58362 | EX14: 6.58362 | EY14: 6.58362 | EZ14: 6.58362 | FA14: 6.58362 | FB14: 6.58362 | FC14: 6.58362 | FD14: 6.58362 | FE14: 6.58362 | FF14: 6.58362 | FG14: 6.58362 | FH14: 6.58362 | FI14: 6.58362 | FJ14: 6.58362 | FK14: 6.58362 | FL14: 6.58362 | FM14: 6.58362 | FN14: 6.58362 | FO14: 6.58362 | FP14: 6.58362 | FQ14: 6.58362 | FR14: 6.58362 | FS14: 6.58362 | FT14: 6.58362 | FU14: 6.58362 | FV14: 6.58362 | FW14: 6.58362 | FX14: 6.58362 | FY14: 6.58362 | FZ14: 6.58362 | GA14: 6.58362 | GB14: 6.58362 | GC14: 6.58362 | GD14: 6.58362 | GE14: 6.58362 | GF14: 6.58362 | GG14: 6.58362 | GH14: 6.58362 | GI14: 6.58362 | GJ14: 6.58362 | GK14: 6.58362 | GL14: 6.58362 | GM14: 6.58362 | GN14: 6.58362 | GO14: 6.58362 | GP14: 6.58362 | GQ14: 6.58362 | GR14: 6.58362 | GS14: 6.58362 | GT14: 6.58362 | GU14: 6.58362 | GV14: 6.58362 | GW14: 6.58362 | GX14: 6.58362 | GY14: 6.58362 | GZ14: 6.58362 | HA14: 6.58362 | HB14: 6.58362 | HC14: 6.58362 | HD14: 6.58362 | HE14: 6.58362 | HF14: 6.58362 | HG14: 6.58362 | HH14: 6.58362 | HI14: 6.58362 | HJ14: 6.58362 | HK14: 6.58362 | HL14: 6.58362 | HM14: 6.58362 | HN14: 6.58362 | HO14: 6.58362 | HP14: 6.58362 | HQ14: 6.58362 | HR14: 6.58362 | HS14: 6.58362 | HT14: 6.58362 | HU14: 6.58362 | HV14: 6.58362 | HW14: 6.58362 | HX14: 6.58362 | HY14: 6.58362 | HZ14: 6.58362 | IA14: 6.58362 | IB14: 6.58362 | IC14: 6.58362 | ID14: 6.58362 | IE14: 6.58362 | IF14: 6.58362 | IG14: 6.58362 | IH14: 6.58362 | II14: 6.58362 | IJ14: 6.58362 | IK14: 6.58362 | IL14: 6.58362 | IM14: 6.58362 | IN14: 6.58362 | IO14: 6.58362 | IP14: 6.58362 | IQ14: 6.58362 | IR14: 6.58362 | IS14: 6.58362 | IT14: 6.58362 | IU14: 6.58362 | IV14: 6.58362 | IW14: 6.58362 | IX14: 6.58362 | IY14: 6.58362 | IZ14: 6.58362 | JA14: 6.58362 | JB14: 6.58362 | JC14: 6.58362 | JD14: 6.58362 | JE14: 6.58362 | JF14: 6.58362 | JG14: 6.58362 | JH14: 6.58362 | JI14: 6.58362 | JJ14: 6.58362 | JK14: 6.58362 | JL14: 6.58362 | JM14: 6.58362 | JN14: 6.58362 | JO14: 6.58362 | JP14: 6.58362 | JQ14: 6.58362 | JR14: 6.58362 | JS14: 6.58362 | JT14: 6.58362 | JU14: 6.58362 | JV14: 6.58362 | JW14: 6.58362 | JX14: 6.58362 | JY14: 6.58362 | JZ14: 6.58362 | KA14: 6.58362 | KB14: 6.58362 | KC14: 6.58362 | KD14: 6.58362 | KE14: 6.58362 | KF14: 6.58362 | KG14: 6.58362 | KH14: 6.58362 | KI14: 6.58362 | KJ14: 6.58362 | KK14: 6.58362 | KL14: 6.58362 | KM14: 6.58362 | KN14: 6.58362 | KO14: 6.58362 | KP14: 6.58362 | KQ14: 6.58362 | KR14: 6.58362 | KS14: 6.58362 | KT14: 6.58362 | KU14: 6.58362 | KV14: 6.58362 | KW14: 6.58362 | KX14: 6.58362 | KY14: 6.58362 | KZ14: 6.58362 | LA14: 6.58362 | LB14: 6.58362 | LC14: 6.58362 | LD14: 6.58362 | LE14: 6.58362 | LF14: 6.58362 | LG14: 6.58362 | LH14: 6.58362 | LI14: 6.58362 | LJ14: 6.58362 | LK14: 6.58362 | LL14: 6.58362 | LM14: 6.58362 | LN14: 6.58362 | LO14: 6.58362 | LP14: 6.58362 | LQ14: 6.58362 | LR14: 6.58362 | LS14: 6.58362 | LT14: 6.58362 | LU14: 6.58362 | LV14: 6.58362 | LW14: 6.58362 | LX14: 6.58362 | LY14: 6.58362 | LZ14: 6.58362 | MA14: 6.58362 | MB14: 6.58362 | MC14: 6.58362 | MD14: 6.58362 | ME14: 6.58362 | MF14: 6.58362 | MG14: 6.58362 | MH14: 6.58362 | MI14: 6.58362 | MJ14: 6.58362 | MK14: 6.58362 | ML14: 6.58362 | MM14: 6.58362 | MN14: 6.391195 | MO14: 0 | MP14: 0 | MQ14: 0 | MR14: 0 | MS14: 0 | MT14: 0 | MU14: 0 | MV14: 0 | MW14: 0 | MX14: 0 | MY14: 0 | MZ14: 0
... A23: =+'Valo FX'!A24 -> 21 | B23: =+Base!B21 -> 202402140071A033 | C23: 6 | D23: 0 | E23: 0 | F23: 0 | G23: 0 | H23: 0 | I23: 0 | J23: 0 | K23: 12.012828 | L23: 12.012828 | M23: 12.012828 | N23: 12.012828 | O23: 12.012828 | P23: 12.012828 | Q23: 12.012828 | R23: 12.012828 | S23: 12.012828 | T23: 12.012828 | U23: 12.012828 | V23: 12.012828 | W23: 12.012828 | X23: 12.012828 | Y23: 12.012828 | Z23: 12.012828 | AA23: 12.012828 | AB23: 12.012828 | AC23: 12.012828 | AD23: 12.012828 | AE23: 12.012828 | AF23: 12.012828 | AG23: 12.012828 | AH23: 12.012828 | AI23: 12.012828 | AJ23: 12.012828 | AK23: 12.012828 | AL23: 12.012828 | AM23: 12.012828 | AN23: 12.012828 | AO23: 12.012828 | AP23: 12.012828 | AQ23: 12.012828 | AR23: 12.012828 | AS23: 12.012828 | AT23: 12.012828 | AU23: 12.012828 | AV23: 12.012828 | AW23: 12.012828 | AX23: 12.012828 | AY23: 12.012828 | AZ23: 12.012828 | BA23: 12.012828 | BB23: 12.012828 | BC23: 12.012828 | BD23: 12.012828 | BE23: 12.012828 | BF23: 12.012828 | BG23: 12.012828 | BH23: 12.012828 | BI23: 12.012828 | BJ23: 12.012828 | BK23: 12.012828 | BL23: 12.012828 | BM23: 12.012828 | BN23: 12.012828 | BO23: 12.012828 | BP23: 12.012828 | BQ23: 12.012828 | BR23: 12.012828 | BS23: 12.012828 | BT23: 12.012828 | BU23: 12.012828 | BV23: 12.012828 | BW23: 12.012828 | BX23: 12.012828 | BY23: 12.012828 | BZ23: 12.012828 | CA23: 12.012828 | CB23: 12.012828 | CC23: 12.012828 | CD23: 12.012828 | CE23: 12.012828 | CF23: 12.012828 | CG23: 12.012828 | CH23: 12.012828 | CI23: 12.012828 | CJ23: 12.012828 | CK23: 12.012828 | CL23: 12.012828 | CM23: 12.012828 | CN23: 12.012828 | CO23: 12.012828 | CP23: 12.012828 | CQ23: 12.012828 | CR23: 12.012828 | CS23: 12.012828 | CT23: 12.012828 | CU23: 12.012828 | CV23: 12.012828 | CW23: 12.012828 | CX23: 12.012828 | CY23: 12.012828 | CZ23: 12.012828 | DA23: 12.012828 | DB23: 12.012828 | DC23: 12.012828 | DD23: 12.012828 | DE23: 12.012828 | DF23: 12.012828 | DG23: 12.012828 | DH23: 12.012828 | DI23: 12.012828 | DJ23: 12.012828 | DK23: 12.012828 | DL23: 12.012828 | DM23: 12.012828 | DN23: 12.012828 | DO23: 12.012828 | DP23: 12.012828 | DQ23: 12.012828 | DR23: 12.012828 | DS23: 12.012828 | DT23: 12.012828 | DU23: 12.012828 | DV23: 12.012828 | DW23: 12.012828 | DX23: 12.012828 | DY23: 12.012828 | DZ23: 12.012828 | EA23: 12.012828 | EB23: 12.012828 | EC23: 12.012828 | ED23: 12.012828 | EE23: 12.012828 | EF23: 12.012828 | EG23: 12.012828 | EH23: 12.012828 | EI23: 12.012828 | EJ23: 12.012828 | EK23: 12.012828 | EL23: 12.012828 | EM23: 12.012828 | EN23: 12.012828 | EO23: 12.012828 | EP23: 12.012828 | EQ23: 12.012828 | ER23: 12.012828 | ES23: 12.012828 | ET23: 12.012828 | EU23: 12.012828 | EV23: 12.012828 | EW23: 12.012828 | EX23: 12.012828 | EY23: 12.012828 | EZ23: 12.012828 | FA23: 12.012828 | FB23: 12.012828 | FC23: 12.012828 | FD23: 12.012828 | FE23: 12.012828 | FF23: 12.012828 | FG23: 12.012828 | FH23: 12.012828 | FI23: 12.012828 | FJ23: 12.012828 | FK23: 12.012828 | FL23: 12.012828 | FM23: 12.012828 | FN23: 12.012828 | FO23: 12.012828 | FP23: 12.012828 | FQ23: 12.012828 | FR23: 12.012828 | FS23: 12.012828 | FT23: 12.012828 | FU23: 12.012828 | FV23: 12.012828 | FW23: 12.012828 | FX23: 12.012828 | FY23: 12.012828 | FZ23: 12.012828 | GA23: 12.012828 | GB23: 12.012828 | GC23: 12.012828 | GD23: 12.012828 | GE23: 12.012828 | GF23: 12.012828 | GG23: 12.012828 | GH23: 12.012828 | GI23: 12.012828 | GJ23: 12.012828 | GK23: 12.012828 | GL23: 12.012828 | GM23: 12.012828 | GN23: 12.012828 | GO23: 12.012828 | GP23: 12.012828 | GQ23: 12.012828 | GR23: 12.012828 | GS23: 12.012828 | GT23: 12.012828 | GU23: 12.012828 | GV23: 12.012828 | GW23: 12.012828 | GX23: 12.012828 | GY23: 12.012828 | GZ23: 12.012828 | HA23: 12.012828 | HB23: 12.012828 | HC23: 12.012828 | HD23: 12.012828 | HE23: 12.012828 | HF23: 12.012828 | HG23: 12.012828 | HH23: 12.012828 | HI23: 12.012828 | HJ23: 12.012828 | HK23: 12.012828 | HL23: 12.012828 | HM23: 12.012828 | HN23: 12.012828 | HO23: 12.012828 | HP23: 12.012828 | HQ23: 12.012828 | HR23: 12.012828 | HS23: 12.012828 | HT23: 12.012828 | HU23: 12.012828 | HV23: 12.012828 | HW23: 12.012828 | HX23: 12.012828 | HY23: 12.012828 | HZ23: 12.012828 | IA23: 12.012828 | IB23: 12.012828 | IC23: 12.012828 | ID23: 12.012828 | IE23: 12.012828 | IF23: 12.012828 | IG23: 12.012828 | IH23: 12.012828 | II23: 12.012828 | IJ23: 12.012828 | IK23: 12.012828 | IL23: 12.012828 | IM23: 12.012828 | IN23: 12.012828 | IO23: 12.012828 | IP23: 12.012828 | IQ23: 12.012828 | IR23: 12.012828 | IS23: 12.012828 | IT23: 12.012828 | IU23: 12.012828 | IV23: 12.012828 | IW23: 12.012828 | IX23: 12.012828 | IY23: 12.012828 | IZ23: 12.012828 | JA23: 12.012828 | JB23: 12.012828 | JC23: 12.012828 | JD23: 12.012828 | JE23: 12.012828 | JF23: 12.012828 | JG23: 12.012828 | JH23: 12.012828 | JI23: 12.012828 | JJ23: 12.012828 | JK23: 12.012828 | JL23: 12.012828 | JM23: 12.012828 | JN23: 12.012828 | JO23: 12.012828 | JP23: 12.012828 | JQ23: 12.012828 | JR23: 12.012828 | JS23: 12.012828 | JT23: 12.012828 | JU23: 12.012828 | JV23: 12.012828 | JW23: 12.012828 | JX23: 12.012828 | JY23: 12.012828 | JZ23: 12.012828 | KA23: 12.012828 | KB23: 12.012828 | KC23: 12.012828 | KD23: 12.012828 | KE23: 12.012828 | KF23: 12.012828 | KG23: 12.012828 | KH23: 12.012828 | KI23: 12.012828 | KJ23: 12.012828 | KK23: 12.012828 | KL23: 12.012828 | KM23: 12.012828 | KN23: 12.012828 | KO23: 12.012828 | KP23: 12.012828 | KQ23: 12.012828 | KR23: 12.012828 | KS23: 12.106641 | KT23: 0 | KU23: 0 | KV23: 0 | KW23: 0 | KX23: 0 | KY23: 0 | KZ23: 0 | LA23: 0 | LB23: 0 | LC23: 0 | LD23: 0 | LE23: 0 | LF23: 0 | LG23: 0 | LH23: 0 | LI23: 0 | LJ23: 0 | LK23: 0 | LL23: 0 | LM23: 0 | LN23: 0 | LO23: 0 | LP23: 0 | LQ23: 0 | LR23: 0 | LS23: 0 | LT23: 0 | LU23: 0 | LV23: 0 | LW23: 0 | LX23: 0 | LY23: 0 | LZ23: 0 | MA23: 0 | MB23: 0 | MC23: 0 | MD23: 0 | ME23: 0 | MF23: 0 | MG23: 0 | MH23: 0 | MI23: 0 | MJ23: 0 | MK23: 0 | ML23: 0 | MM23: 0 | MN23: 0 | MO23: 0 | MP23: 0 | MQ23: 0 | MR23: 0 | MS23: 0 | MT23: 0 | MU23: 0 | MV23: 0 | MW23: 0 | MX23: 0 | MY23: 0 | MZ23: 0
A24: =+A23+1 -> 22 | B24: =+Base!B22 -> 202402270073A033 | C24: 6 | D24: 0 | E24: 0 | F24: 0 | G24: 0 | H24: 0 | I24: 0 | J24: 0 | K24: 10.200271 | L24: 10.200271 | M24: 10.200271 | N24: 10.200271 | O24: 10.200271 | P24: 10.200271 | Q24: 10.200271 | R24: 10.200271 | S24: 10.200271 | T24: 10.200271 | U24: 10.200271 | V24: 10.200271 | W24: 10.200271 | X24: 10.200271 | Y24: 10.200271 | Z24: 10.200271 | AA24: 10.200271 | AB24: 10.200271 | AC24: 10.200271 | AD24: 10.200271 | AE24: 10.200271 | AF24: 10.200271 | AG24: 10.200271 | AH24: 10.200271 | AI24: 10.200271 | AJ24: 10.200271 | AK24: 10.200271 | AL24: 10.200271 | AM24: 10.200271 | AN24: 10.200271 | AO24: 10.200271 | AP24: 10.200271 | AQ24: 10.200271 | AR24: 10.200271 | AS24: 10.200271 | AT24: 10.200271 | AU24: 10.200271 | AV24: 10.200271 | AW24: 10.200271 | AX24: 10.200271 | AY24: 10.200271 | AZ24: 10.200271 | BA24: 10.200271 | BB24: 10.200271 | BC24: 10.200271 | BD24: 10.200271 | BE24: 10.200271 | BF24: 10.200271 | BG24: 10.200271 | BH24: 10.200271 | BI24: 10.200271 | BJ24: 10.200271 | BK24: 10.200271 | BL24: 10.200271 | BM24: 10.200271 | BN24: 10.200271 | BO24: 10.200271 | BP24: 10.200271 | BQ24: 10.200271 | BR24: 10.200271 | BS24: 10.200271 | BT24: 10.200271 | BU24: 10.200271 | BV24: 10.200271 | BW24: 10.200271 | BX24: 10.200271 | BY24: 10.200271 | BZ24: 10.200271 | CA24: 10.200271 | CB24: 10.200271 | CC24: 10.200271 | CD24: 10.200271 | CE24: 10.200271 | CF24: 10.200271 | CG24: 10.200271 | CH24: 10.200271 | CI24: 10.200271 | CJ24: 10.200271 | CK24: 10.200271 | CL24: 10.200271 | CM24: 10.200271 | CN24: 10.200271 | CO24: 10.200271 | CP24: 10.200271 | CQ24: 10.200271 | CR24: 10.200271 | CS24: 10.200271 | CT24: 10.200271 | CU24: 10.200271 | CV24: 10.200271 | CW24: 10.200271 | CX24: 10.200271 | CY24: 10.200271 | CZ24: 10.200271 | DA24: 10.200271 | DB24: 10.200271 | DC24: 10.200271 | DD24: 10.200271 | DE24: 10.200271 | DF24: 10.200271 | DG24: 10.200271 | DH24: 10.200271 | DI24: 10.200271 | DJ24: 10.200271 | DK24: 10.200271 | DL24: 10.200271 | DM24: 10.200271 | DN24: 10.200271 | DO24: 10.200271 | DP24: 10.200271 | DQ24: 10.200271 | DR24: 10.200271 | DS24: 10.200271 | DT24: 10.200271 | DU24: 10.200271 | DV24: 10.200271 | DW24: 10.200271 | DX24: 10.200271 | DY24: 10.200271 | DZ24: 10.200271 | EA24: 10.200271 | EB24: 10.200271 | EC24: 10.200271 | ED24: 10.200271 | EE24: 10.200271 | EF24: 10.200271 | EG24: 10.200271 | EH24: 10.200271 | EI24: 10.200271 | EJ24: 10.200271 | EK24: 10.200271 | EL24: 10.200271 | EM24: 10.200271 | EN24: 10.200271 | EO24: 10.200271 | EP24: 10.200271 | EQ24: 10.200271 | ER24: 10.200271 | ES24: 10.200271 | ET24: 10.200271 | EU24: 10.200271 | EV24: 10.200271 | EW24: 10.200271 | EX24: 10.200271 | EY24: 10.200271 | EZ24: 10.200271 | FA24: 10.200271 | FB24: 10.200271 | FC24: 10.200271 | FD24: 10.200271 | FE24: 10.200271 | FF24: 10.200271 | FG24: 10.200271 | FH24: 10.200271 | FI24: 10.200271 | FJ24: 10.200271 | FK24: 10.200271 | FL24: 10.200271 | FM24: 10.200271 | FN24: 10.200271 | FO24: 10.200271 | FP24: 10.200271 | FQ24: 10.200271 | FR24: 10.200271 | FS24: 10.200271 | FT24: 10.200271 | FU24: 10.200271 | FV24: 10.200271 | FW24: 10.200271 | FX24: 10.200271 | FY24: 10.200271 | FZ24: 10.200271 | GA24: 10.200271 | GB24: 10.200271 | GC24: 10.200271 | GD24: 10.200271 | GE24: 10.200271 | GF24: 10.200271 | GG24: 10.200271 | GH24: 10.200271 | GI24: 10.200271 | GJ24: 10.200271 | GK24: 10.200271 | GL24: 10.200271 | GM24: 10.200271 | GN24: 10.200271 | GO24: 10.200271 | GP24: 10.200271 | GQ24: 10.200271 | GR24: 10.200271 | GS24: 10.200271 | GT24: 10.200271 | GU24: 10.200271 | GV24: 10.200271 | GW24: 10.200271 | GX24: 10.200271 | GY24: 10.200271 | GZ24: 10.200271 | HA24: 10.200271 | HB24: 10.200271 | HC24: 10.200271 | HD24: 10.200271 | HE24: 10.200271 | HF24: 10.200271 | HG24: 10.200271 | HH24: 10.200271 | HI24: 10.200271 | HJ24: 10.200271 | HK24: 10.200271 | HL24: 10.200271 | HM24: 10.200271 | HN24: 10.200271 | HO24: 10.200271 | HP24: 10.200271 | HQ24: 10.200271 | HR24: 10.200271 | HS24: 10.200271 | HT24: 10.200271 | HU24: 10.200271 | HV24: 10.200271 | HW24: 10.200271 | HX24: 10.200271 | HY24: 10.200271 | HZ24: 10.200271 | IA24: 10.200271 | IB24: 10.200271 | IC24: 10.200271 | ID24: 10.200271 | IE24: 10.200271 | IF24: 10.200271 | IG24: 10.200271 | IH24: 10.200271 | II24: 10.200271 | IJ24: 10.200271 | IK24: 10.200271 | IL24: 10.200271 | IM24: 10.200271 | IN24: 10.200271 | IO24: 10.200271 | IP24: 10.200271 | IQ24: 10.200271 | IR24: 10.200271 | IS24: 10.200271 | IT24: 10.200271 | IU24: 10.200271 | IV24: 10.200271 | IW24: 10.200271 | IX24: 10.200271 | IY24: 10.200271 | IZ24: 10.200271 | JA24: 10.200271 | JB24: 10.200271 | JC24: 10.200271 | JD24: 10.200271 | JE24: 10.200271 | JF24: 10.200271 | JG24: 10.200271 | JH24: 10.200271 | JI24: 10.200271 | JJ24: 10.200271 | JK24: 10.200271 | JL24: 10.200271 | JM24: 10.200271 | JN24: 10.200271 | JO24: 10.200271 | JP24: 10.200271 | JQ24: 10.200271 | JR24: 10.200271 | JS24: 10.200271 | JT24: 10.200271 | JU24: 10.200271 | JV24: 10.200271 | JW24: 10.200271 | JX24: 10.200271 | JY24: 10.200271 | JZ24: 10.200271 | KA24: 10.200271 | KB24: 10.200271 | KC24: 10.200271 | KD24: 10.200271 | KE24: 10.200271 | KF24: 10.200271 | KG24: 10.200271 | KH24: 10.200271 | KI24: 10.200271 | KJ24: 10.200271 | KK24: 10.200271 | KL24: 10.200271 | KM24: 10.200271 | KN24: 10.200271 | KO24: 10.200271 | KP24: 10.200271 | KQ24: 10.200271 | KR24: 10.200271 | KS24: 10.200271 | KT24: 10.200271 | KU24: 10.200271 | KV24: 10.200271 | KW24: 10.200271 | KX24: 10.200271 | KY24: 10.200271 | KZ24: 10.200271 | LA24: 10.200271 | LB24: 10.200271 | LC24: 10.200271 | LD24: 10.200271 | LE24: 10.200271 | LF24: 10.200271 | LG24: 10.200271 | LH24: 10.200271 | LI24: 10.200271 | LJ24: 10.200271 | LK24: 10.200271 | LL24: 10.200271 | LM24: 10.200271 | LN24: 10.200271 | LO24: 10.200271 | LP24: 10.200271 | LQ24: 10.718882 | LR24: 0 | LS24: 0 | LT24: 0 | LU24: 0 | LV24: 0 | LW24: 0 | LX24: 0 | LY24: 0 | LZ24: 0 | MA24: 0 | MB24: 0 | MC24: 0 | MD24: 0 | ME24: 0 | MF24: 0 | MG24: 0 | MH24: 0 | MI24: 0 | MJ24: 0 | MK24: 0 | ML24: 0 | MM24: 0 | MN24: 0 | MO24: 0 | MP24: 0 | MQ24: 0 | MR24: 0 | MS24: 0 | MT24: 0 | MU24: 0 | MV24: 0 | MW24: 0 | MX24: 0 | MY24: 0 | MZ24: 0
A25: =+A24+1 -> 23 | B25: =+Base!B23 -> 202402260074A033 | C25: 6 | D25: 0 | E25: 0 | F25: 0 | G25: 0 | H25: 0 | I25: 0 | J25: 0 | K25: 11.54892 | L25: 11.54892 | M25: 11.54892 | N25: 11.54892 | O25: 11.54892 | P25: 11.54892 | Q25: 11.54892 | R25: 11.54892 | S25: 11.54892 | T25: 11.54892 | U25: 11.54892 | V25: 11.54892 | W25: 11.54892 | X25: 11.54892 | Y25: 11.54892 | Z25: 11.54892 | AA25: 11.54892 | AB25: 11.54892 | AC25: 11.54892 | AD25: 11.54892 | AE25: 11.54892 | AF25: 11.54892 | AG25: 11.54892 | AH25: 11.54892 | AI25: 11.54892 | AJ25: 11.54892 | AK25: 11.54892 | AL25: 11.54892 | AM25: 11.54892 | AN25: 11.54892 | AO25: 11.54892 | AP25: 11.54892 | AQ25: 11.54892 | AR25: 11.54892 | AS25: 11.54892 | AT25: 11.54892 | AU25: 11.54892 | AV25: 11.54892 | AW25: 11.54892 | AX25: 11.54892 | AY25: 11.54892 | AZ25: 11.54892 | BA25: 11.54892 | BB25: 11.54892 | BC25: 11.54892 | BD25: 11.54892 | BE25: 11.54892 | BF25: 11.54892 | BG25: 11.54892 | BH25: 11.54892 | BI25: 11.54892 | BJ25: 11.54892 | BK25: 11.54892 | BL25: 11.54892 | BM25: 11.54892 | BN25: 11.54892 | BO25: 11.54892 | BP25: 11.54892 | BQ25: 11.54892 | BR25: 11.54892 | BS25: 11.54892 | BT25: 11.54892 | BU25: 11.54892 | BV25: 11.54892 | BW25: 11.54892 | BX25: 11.54892 | BY25: 11.54892 | BZ25: 11.54892 | CA25: 11.54892 | CB25: 11.54892 | CC25: 11.54892 | CD25: 11.54892 | CE25: 11.54892 | CF25: 11.54892 | CG25: 11.54892 | CH25: 11.54892 | CI25: 11.54892 | CJ25: 11.54892 | CK25: 11.54892 | CL25: 11.54892 | CM25: 11.54892 | CN25: 11.54892 | CO25: 11.54892 | CP25: 11.54892 | CQ25: 11.54892 | CR25: 11.54892 | CS25: 11.54892 | CT25: 11.54892 | CU25: 11.54892 | CV25: 11.54892 | CW25: 11.54892 | CX25: 11.54892 | CY25: 11.54892 | CZ25: 11.54892 | DA25: 11.54892 | DB25: 11.54892 | DC25: 11.54892 | DD25: 11.54892 | DE25: 11.54892 | DF25: 11.54892 | DG25: 11.54892 | DH25: 11.54892 | DI25: 11.54892 | DJ25: 11.54892 | DK25: 11.54892 | DL25: 11.54892 | DM25: 11.54892 | DN25: 11.54892 | DO25: 11.54892 | DP25: 11.54892 | DQ25: 11.54892 | DR25: 11.54892 | DS25: 11.54892 | DT25: 11.54892 | DU25: 11.54892 | DV25: 11.54892 | DW25: 11.54892 | DX25: 11.54892 | DY25: 11.54892 | DZ25: 11.54892 | EA25: 11.54892 | EB25: 11.54892 | EC25: 11.54892 | ED25: 11.54892 | EE25: 11.54892 | EF25: 11.54892 | EG25: 11.54892 | EH25: 11.54892 | EI25: 11.54892 | EJ25: 11.54892 | EK25: 11.54892 | EL25: 11.54892 | EM25: 11.54892 | EN25: 11.54892 | EO25: 11.54892 | EP25: 11.54892 | EQ25: 11.54892 | ER25: 11.54892 | ES25: 11.54892 | ET25: 11.54892 | EU25: 11.54892 | EV25: 11.54892 | EW25: 11.54892 | EX25: 11.54892 | EY25: 11.54892 | EZ25: 11.54892 | FA25: 11.54892 | FB25: 11.54892 | FC25: 11.54892 | FD25: 11.54892 | FE25: 11.54892 | FF25: 11.54892 | FG25: 11.54892 | FH25: 11.54892 | FI25: 11.54892 | FJ25: 11.54892 | FK25: 11.54892 | FL25: 11.54892 | FM25: 11.54892 | FN25: 11.54892 | FO25: 11.54892 | FP25: 11.54892 | FQ25: 11.54892 | FR25: 11.54892 | FS25: 11.54892 | FT25: 11.54892 | FU25: 11.54892 | FV25: 11.54892 | FW25: 11.54892 | FX25: 11.54892 | FY25: 11.54892 | FZ25: 11.54892 | GA25: 11.54892 | GB25: 11.54892 | GC25: 11.54892 | GD25: 11.54892 | GE25: 11.54892 | GF25: 11.54892 | GG25: 11.54892 | GH25: 11.54892 | GI25: 11.54892 | GJ25: 11.54892 | GK25: 11.54892 | GL25: 11.54892 | GM25: 11.54892 | GN25: 11.54892 | GO25: 11.54892 | GP25: 11.54892 | GQ25: 11.54892 | GR25: 11.54892 | GS25: 11.54892 | GT25: 11.54892 | GU25: 11.54892 | GV25: 11.54892 | GW25: 11.54892 | GX25: 11.54892 | GY25: 11.54892 | GZ25: 11.54892 | HA25: 11.54892 | HB25: 11.54892 | HC25: 11.54892 | HD25: 11.54892 | HE25: 11.54892 | HF25: 11.54892 | HG25: 11.54892 | HH25: 11.54892 | HI25: 11.54892 | HJ25: 11.54892 | HK25: 11.54892 | HL25: 11.54892 | HM25: 11.54892 | HN25: 11.54892 | HO25: 11.54892 | HP25: 11.54892 | HQ25: 11.54892 | HR25: 11.54892 | HS25: 11.54892 | HT25: 11.54892 | HU25: 11.54892 | HV25: 11.54892 | HW25: 11.54892 | HX25: 11.54892 | HY25: 11.54892 | HZ25: 11.54892 | IA25: 11.54892 | IB25: 11.54892 | IC25: 11.54892 | ID25: 11.54892 | IE25: 11.54892 | IF25: 11.54892 | IG25: 11.54892 | IH25: 11.54892 | II25: 11.54892 | IJ25: 11.54892 | IK25: 11.54892 | IL25: 11.54892 | IM25: 11.54892 | IN25: 11.54892 | IO25: 11.54892 | IP25: 11.54892 | IQ25: 11.54892 | IR25: 11.54892 | IS25: 11.54892 | IT25: 11.54892 | IU25: 11.54892 | IV25: 11.54892 | IW25: 11.54892 | IX25: 11.54892 | IY25: 11.54892 | IZ25: 11.54892 | JA25: 11.54892 | JB25: 11.54892 | JC25: 11.54892 | JD25: 11.54892 | JE25: 11.54892 | JF25: 11.54892 | JG25: 11.54892 | JH25: 11.54892 | JI25: 11.54892 | JJ25: 11.54892 | JK25: 11.54892 | JL25: 11.54892 | JM25: 11.54892 | JN25: 11.54892 | JO25: 11.54892 | JP25: 11.54892 | JQ25: 11.54892 | JR25: 11.54892 | JS25: 11.54892 | JT25: 11.54892 | JU25: 11.54892 | JV25: 11.54892 | JW25: 11.54892 | JX25: 11.54892 | JY25: 11.54892 | JZ25: 11.54892 | KA25: 11.54892 | KB25: 11.54892 | KC25: 11.54892 | KD25: 11.54892 | KE25: 11.54892 | KF25: 11.54892 | KG25: 11.54892 | KH25: 11.54892 | KI25: 11.54892 | KJ25: 11.54892 | KK25: 11.54892 | KL25: 11.54892 | KM25: 11.54892 | KN25: 11.54892 | KO25: 11.54892 | KP25: 11.54892 | KQ25: 11.54892 | KR25: 11.54892 | KS25: 11.54892 | KT25: 11.54892 | KU25: 11.54892 | KV25: 11.54892 | KW25: 11.54892 | KX25: 11.54892 | KY25: 11.54892 | KZ25: 11.54892 | LA25: 11.54892 | LB25: 11.54892 | LC25: 11.54892 | LD25: 11.54892 | LE25: 11.54892 | LF25: 11.54892 | LG25: 11.54892 | LH25: 11.54892 | LI25: 11.54892 | LJ25: 11.54892 | LK25: 11.54892 | LL25: 11.54892 | LM25: 11.54892 | LN25: 11.54892 | LO25: 11.54892 | LP25: 11.54892 | LQ25: 12.1361 | LR25: 0 | LS25: 0 | LT25: 0 | LU25: 0 | LV25: 0 | LW25: 0 | LX25: 0 | LY25: 0 | LZ25: 0 | MA25: 0 | MB25: 0 | MC25: 0 | MD25: 0 | ME25: 0 | MF25: 0 | MG25: 0 | MH25: 0 | MI25: 0 | MJ25: 0 | MK25: 0 | ML25: 0 | MM25: 0 | MN25: 0 | MO25: 0 | MP25: 0 | MQ25: 0 | MR25: 0 | MS25: 0 | MT25: 0 | MU25: 0 | MV25: 0 | MW25: 0 | MX25: 0 | MY25: 0 | MZ25: 0
