Workbook

Sheet Base
A1: Nº | B1: N° Operación CMF | C1: Rut | D1: RUT | E1: DV | F1: Apellido paterno | G1: Apellido materno | H1: Nombres | I1: Género | J1: Segmento | K1: Pie | L1: Precio venta propiedad | M1: Subsidio | N1: Valor de tasación | O1: Tasa anual de emisión | P1: Tasa mensual de emisión | Q1: Plazo en meses | R1: Meses de gracia | S1: LTV | T1: Monto otorgado (UF) | U1: Valor cuota (UF) | V1: Valor última cuota (UF) | W1: Spread | X1: Tasa anual de endoso | Y1: Tasa mensual de endoso | Z1: Fecha de suscripción | AA1: Período primer aporte | AB1: Fecha de endoso | AC1: Fecha primer aporte a endosar | AD1: Fecha último aporte | AE1: Número de cuotas a endosar | AF1: VAN fecha endoso | AG1: Dirección | AH1: Comuna | AI1: Ciudad | AJ1: Region | AK1: Notaría | AL1: Dividendo/ Renta | AM1: Carga Financiera
A2: 1 | B2: 202403250103A033 | C2: 18803188-9 | D2: =LEFT(C2,LEN(C2)-2) -> 18803188 | E2: =RIGHT(C2,1) -> 9 | F2: Diaz | G2: Zuñiga | H2: Joel Alejandro | I2: Masculino | J2: Subsidio | K2: 605 | L2: 2200 | M2: 525 | N2: 2325 | O2: 0.0753 | P2: 0.0060683124 | Q2: 300 | R2: 5 | S2: 0.725 | T2: 1595 | U2: 11.98802 | V2: 11.919435 | W2: -0.004 | X2: 0.0713 | Y2: 0.0057559073 | Z2: 45376 | AA2: 45575 | AB2: 45379 | AC2: 45575 | AD2: 54523 | AE2: 295 | AF2: 1647.6019 | AG2: Calle 8 Sur Poniente 351,casa 351 | AH2: Los Ángeles | AI2: Biobío | AJ2: Región del Biobío | AK2: María Antonieta Carrillo Flores | AL2: 0.25914525 | AM2: 0.32831376 | AN2: 682 | AO2: OK | AP2: Firmada
A3: =A2+1 -> 2 | B3: 202403260104A033 | C3: 16265854-9 | D3: =LEFT(C3,LEN(C3)-2) -> 16265854 | E3: =RIGHT(C3,1) -> 9 | F3: Hultazo | G3: Novoa | H3: Daniela Del Carmen | I3: Femenino | J3: Subsidio | K3: 750 | L3: 2200 | M3: 550 | N3: 2560 | O3: 0.0753 | P3: 0.0060683124 | Q3: 360 | R3: 5 | S3: 0.67294545 | T3: 1480.48 | U3: 10.483279 | V3: 10.761609 | W3: -0.004 | X3: 0.0713 | Y3: 0.0057559073 | Z3: 45377 | AA3: 45575 | AB3: 45379 | AC3: 45575 | AD3: 56349 | AE3: 355 | AF3: 1534.7211 | AG3: ADRIANA GARCIA IBAÑEZ 2030, Edificio G,departamento 303 | AH3: San Javier | AI3: Linares | AJ3: Región del Maule | AK3: Gabriel Guerrero González | AL3: 0.17374483 | AM3: 0.46168658 | AN3: 1136 | AO3: OK | AP3: Firmada
A4: =A3+1 -> 3 | B4: 202403250105A033 | C4: 24585394-7 | D4: =LEFT(C4,LEN(C4)-2) -> 24585394 | E4: =RIGHT(C4,1) -> 7 | F4: Salazar | G4: Carvajal | H4: Nedier Graciela | I4: Femenino | J4: Subsidio | K4: 536.04 | L4: 1400 | M4: 450 | N4: 1400 | O4: 0.0753 | P4: 0.0060683124 | Q4: 312 | R4: 5 | S4: 0.61711429 | T4: 863.96 | U4: 6.402808 | V4: 6.596335 | W4: -0.004 | X4: 0.0713 | Y4: 0.0057559073 | Z4: 45376 | AA4: 45575 | AB4: 45379 | AC4: 45575 | AD4: 54888 | AE4: 307 | AF4: 892.6874 | AG4: Camino La Vara 02600, Torre 1,departamento 406 | AH4: San Bernardo | AI4: Maipo | AJ4: Región Metropolitana de Santiago | AK4: Pablo Martínez Loaiza | AL4: 0.34565539 | AM4: 0.54730716 | AN4: 5481 | AO4: OK | AP4: Firmada
A5: =A4+1 -> 4 | B5: 202403260108A033 | C5: 26537872-2 | D5: =LEFT(C5,LEN(C5)-2) -> 26537872 | E5: =RIGHT(C5,1) -> 2 | F5: Vasquez | G5: Sanchez | H5: Bertha Ramona | I5: Femenino | J5: Subsidio | K5: 583 | L5: 2300 | M5: 475 | N5: 2300 | O5: 0.0753 | P5: 0.0060683124 | Q5: 264 | R5: 5 | S5: 0.74652174 | T5: 1717 | U5: 13.571168 | V5: 13.454412 | W5: -0.004 | X5: 0.0713 | Y5: 0.0057559073 | Z5: 45377 | AA5: 45575 | AB5: 45379 | AC5: 45575 | AD5: 53427 | AE5: 259 | AF5: 1768.2353 | AG5: Calle 38 Oriente 350, Torre 8,departamento 2804 | AH5: Talca | AI5: Talca | AJ5: Región del Maule | AK5: Teodoro Durán Palma | AL5: 0.36411949 | AM5: 0.41283351 | AN5: 1753 | AO5: OK | AP5: Firmada
A6: =A5+1 -> 5 | B6: 202403250112A033 | C6: 18188333-2 | D6: =LEFT(C6,LEN(C6)-2) -> 18188333 | E6: =RIGHT(C6,1) -> 2 | F6: Huenchul | G6: Colihuinca | H6: César Antonio | I6: Masculino | J6: Subsidio | K6: 518.4 | L6: 2070 | M6: 375 | N6: 2400 | O6: 0.0753 | P6: 0.0060683124 | Q6: 360 | R6: 5 | S6: 0.74956522 | T6: 1551.6 | U6: 10.98688 | V6: 11.27858 | W6: -0.004 | X6: 0.0713 | Y6: 0.0057559073 | Z6: 45376 | AA6: 45575 | AB6: 45379 | AC6: 45575 | AD6: 56349 | AE6: 355 | AF6: 1609.4065 | AG6: Camino La Vara 02600, TORRE 2,departamento 412 | AH6: San Bernardo | AI6: Maipo | AJ6: Región Metropolitana de Santiago | AK6: Pablo Martínez Loaiza | AL6: 0.40025143 | AM6: 0.42269568 | AN6: 5560 | AO6: OK | AP6: Firmada
A7: =A6+1 -> 6 | B7: 202403260115A033 | C7: 18250306-1 | D7: =LEFT(C7,LEN(C7)-2) -> 18250306 | E7: =RIGHT(C7,1) -> 1 | F7: Rojas | G7: Diaz | H7: Claudio Sebastian | I7: Masculino | J7: Subsidio | K7: 1035.77 | L7: 2700 | M7: 700 | N7: 2700 | O7: 0.0753 | P7: 0.0060683124 | Q7: 300 | R7: 5 | S7: 0.61638148 | T7: 1664.23 | U7: 12.508353 | V7: 12.436791 | W7: -0.004 | X7: 0.0713 | Y7: 0.0057559073 | Z7: 45377 | AA7: 45575 | AB7: 45379 | AC7: 45575 | AD7: 54523 | AE7: 295 | AF7: 1719.0581 | AG7: Los Libertadores 4733, Edificio F,departamento 106 | AH7: Cerrillos | AI7: Santiago | AJ7: Región Metropolitana de Santiago | AK7: Pablo Martínez Loaiza | AL7: 0.16448389 | AM7: 0.37966625 | AN7: 5566 | AO7: OK | AP7: Firmada
A8: =A7+1 -> 7 | B8: 202403260117A033 | C8: 17747816-4 | D8: =LEFT(C8,LEN(C8)-2) -> 17747816 | E8: =RIGHT(C8,1) -> 4 | F8: Lagos | G8: Muñoz | H8: Pablo Daniel | I8: Masculino | J8: Subsidio | K8: 650 | L8: 2250 | M8: 550 | N8: 2460 | O8: 0.0753 | P8: 0.0060683124 | Q8: 360 | R8: 5 | S8: 0.72487778 | T8: 1630.975 | U8: 11.548934 | V8: 11.855557 | W8: -0.004 | X8: 0.0713 | Y8: 0.0057559073 | Z8: 45377 | AA8: 45575 | AB8: 45379 | AC8: 45575 | AD8: 56349 | AE8: 355 | AF8: 1691.4151 | AG8: ADRIANA GARCIA IBAÑEZ 2030, Torre B,departamento 401 | AH8: San Javier | AI8: Linares | AJ8: Región del Maule | AK8: Gabriel Guerrero González | AL8: 0.33391403 | AM8: 0.49056281 | AN8: 1134 | AO8: OK | AP8: Firmada
A9: =A8+1 -> 8 | B9: 202403220119A033 | C9: 17137105-8 | D9: =LEFT(C9,LEN(C9)-2) -> 17137105 | E9: =RIGHT(C9,1) -> 8 | F9: Jaña | G9: Avila | H9: Francisco Javier | I9: Masculino | J9: Subsidio | K9: 618.63 | L9: 1400 | M9: 400 | N9: 1410 | O9: 0.0753 | P9: 0.0060683124 | Q9: 360 | R9: 5 | S9: 0.55812143 | T9: 781.37 | U9: 5.532881 | V9: 5.679779 | W9: -0.004 | X9: 0.0713 | Y9: 0.0057559073 | Z9: 45373 | AA9: 45575 | AB9: 45379 | AC9: 45575 | AD9: 56349 | AE9: 355 | AF9: 809.82925 | AG9: Av. El Valle 199, Torre B,departamento 101 | AH9: Rancagua | AI9: Cachapoal | AJ9: Región del Libertador General Bernardo O'Higgins | AK9: Gerardo Carvallo Castillo | AL9: 0.38354014 | AM9: 0.50324471 | AN9: 789 | AO9: OK | AP9: Firmada
A10: =A9+1 -> 9 | B10: 202403260120A033 | C10: 16995140-3 | D10: =LEFT(C10,LEN(C10)-2) -> 16995140 | E10: =RIGHT(C10,1) -> 3 | F10: Oñate | G10: Muñoz | H10: Pablo Enrique | I10: Masculino | J10: Subsidio | K10: 640 | L10: 1400 | M10: 600 | N10: 1600 | O10: 0.0753 | P10: 0.0060683124 | Q10: 216 | R10: 5 | S10: 0.54285714 | T10: 760 | U10: 6.593 | V10: 6.50864 | W10: -0.004 | X10: 0.0713 | Y10: 0.0057559073 | Z10: 45377 | AA10: 45575 | AB10: 45379 | AC10: 45575 | AD10: 51966 | AE10: 211 | AF10: 779.0959 | AG10: PROFESOR PASCUAL PEREIRA 1324,casa 1324 | AH10: Nacimiento | AI10: Biobío | AJ10: Región del Biobío | AK10: Cristian Camilla Sandoval | AL10: 0.1583457 | AM10: 0.40708554 | AN10: 851 | AO10: OK | AP10: Firmada
A11: =A10+1 -> 10 | B11: 202403250121A033 | C11: 18645373-5 | D11: =LEFT(C11,LEN(C11)-2) -> 18645373 | E11: =RIGHT(C11,1) -> 5 | F11: Aranguiz | G11: Arevalo | H11: Macarena Andrea Del Carmen | I11: Femenino | J11: Subsidio | K11: 418 | L11: 2090 | M11: 325 | N11: 2200 | O11: 0.0753 | P11: 0.0060683124 | Q11: 360 | R11: 5 | S11: 0.8 | T11: 1672 | U11: 11.839432 | V11: 12.153768 | W11: -0.004 | X11: 0.0713 | Y11: 0.0057559073 | Z11: 45376 | AA11: 45575 | AB11: 45379 | AC11: 45575 | AD11: 56349 | AE11: 355 | AF11: 1733.8826 | AG11: Av El Valle 199, Torre B,departamento 407 | AH11: Rancagua | AI11: Cachapoal | AJ11: Región del Libertador General Bernardo O'Higgins | AK11: Gerardo Carvallo Castillo | AL11: 0.24855131 | AM11: 0.39683384 | AN11: 808 | AO11: OK | AP11: Firmada
A12: =A11+1 -> 11 | B12: 202403250123A033 | C12: 16681463-4 | D12: =LEFT(C12,LEN(C12)-2) -> 16681463 | E12: =RIGHT(C12,1) -> 4 | F12: Moraga | G12: Carrasco | H12: Jenny Alejandra | I12: Femenino | J12: Subsidio | K12: 522.22 | L12: 1400 | M12: 450 | N12: 1400 | O12: 0.0753 | P12: 0.0060683124 | Q12: 240 | R12: 5 | S12: 0.62698571 | T12: 877.78 | U12: 7.236418 | V12: 7.068762 | W12: -0.004 | X12: 0.0713 | Y12: 0.0057559073 | Z12: 45376 | AA12: 45575 | AB12: 45379 | AC12: 45575 | AD12: 52697 | AE12: 235 | AF12: 902.65751 | AG12: PASAJE DEMOFILA TORREALBA (PROFESORA) 1744,casa 1744 | AH12: Rengo | AI12: Cachapoal | AJ12: Región del Libertador General Bernardo O'Higgins | AK12: Andrés Falcón Valencia | AL12: 0.27580802 | AM12: 0.28908034 | AN12: N/A | AO12: OK | AP12: Firmada
A13: =A12+1 -> 12 | B13: 202403250125A033 | C13: 24243822-1 | D13: =LEFT(C13,LEN(C13)-2) -> 24243822 | E13: =RIGHT(C13,1) -> 1 | F13: Pozo | G13: Salvatierra | H13: Eufronia | I13: Femenino | J13: Subsidio | K13: 933.25 | L13: 1700 | M13: 737.5 | N13: 1700 | O13: 0.0753 | P13: 0.0060683124 | Q13: 204 | R13: 5 | S13: 0.45102941 | T13: 766.75 | U13: 6.850911 | V13: 6.893849 | W13: -0.004 | X13: 0.0713 | Y13: 0.0057559073 | Z13: 45376 | AA13: 45575 | AB13: 45379 | AC13: 45575 | AD13: 51601 | AE13: 199 | AF13: 785.37074 | AG13: Los Libertadores 4733, Edificio F,departamento 808 | AH13: Cerrillos | AI13: Santiago | AJ13: Región Metropolitana de Santiago | AK13: Pablo Martínez Loaiza | AL13: 0.41766992 | AM13: 0.44378192 | AN13: 5557 | AO13: OK | AP13: Firmada
A14: =A13+1 -> 13 | B14: 202403270128A033 | C14: 10745032-7 | D14: =LEFT(C14,LEN(C14)-2) -> 10745032 | E14: =RIGHT(C14,1) -> 7 | F14: Herrera | G14: Labarca | H14: Ester Lorena | I14: Femenino | J14: Subsidio | K14: 903.54 | L14: 1600 | M14: 675 | N14: 1600 | O14: 0.0753 | P14: 0.0060683124 | Q14: 240 | R14: 5 | S14: 0.448725 | T14: 717.96 | U14: 5.918862 | V14: 5.781732 | W14: -0.004 | X14: 0.0713 | Y14: 0.0057559073 | Z14: 45378 | AA14: 45575 | AB14: 45379 | AC14: 45575 | AD14: 52697 | AE14: 235 | AF14: 738.08434 | AG14: EMMA GOLDMAN 3456,casa 3456 | AH14: Coquimbo | AI14: Elqui | AJ14: Región de Coquimbo | AK14: Juan Carlos Maturana | AL14: 0.24192368 | AM14: 0.28928929 | AN14: N/A | AO14: OK | AP14: Firmada
A15: =A14+1 -> 14 | B15: 202403250129A033 | C15: 18429503-2 | D15: =LEFT(C15,LEN(C15)-2) -> 18429503 | E15: =RIGHT(C15,1) -> 2 | F15: Daza | G15: Contreras | H15: Jocelyn Magdalena | I15: Femenino | J15: Subsidio | K15: 505 | L15: 2150 | M15: 425 | N15: 2150 | O15: 0.0753 | P15: 0.0060683124 | Q15: 360 | R15: 5 | S15: 0.76511628 | T15: 1645 | U15: 11.648245 | V15: 11.957505 | W15: -0.004 | X15: 0.0713 | Y15: 0.0057559073 | Z15: 45376 | AA15: 45575 | AB15: 45379 | AC15: 45575 | AD15: 56349 | AE15: 355 | AF15: 1706.059 | AG15: Camino Las Rosas 518, Edificio 12,departamento 52 | AH15: Chillán | AI15: Diguillín | AJ15: Región de Ñuble | AK15: Luis Álvarez Diaz | AL15: 0.28845392 | AM15: 0.43027696 | AN15: 1233 | AO15: OK | AP15: Firmada
A16: =A15+1 -> 15 | B16: 202403260131A033 | C16: 16415014-3 | D16: =LEFT(C16,LEN(C16)-2) -> 16415014 | E16: =RIGHT(C16,1) -> 3 | F16: Carrasco | G16: Barrientos | H16: Cesar Antonio | I16: Masculino | J16: Subsidio | K16: 750 | L16: 2600 | M16: 600 | N16: 2600 | O16: 0.0753 | P16: 0.0060683124 | Q16: 360 | R16: 5 | S16: 0.71153846 | T16: 1850 | U16: 13.09985 | V16: 13.44765 | W16: -0.004 | X16: 0.0713 | Y16: 0.0057559073 | Z16: 45377 | AA16: 45575 | AB16: 45379 | AC16: 45575 | AD16: 56349 | AE16: 355 | AF16: 1918.4013 | AG16: STELLA DIAZ VARIN 1901,departamento 1901 | AH16: Coquimbo | AI16: Elqui | AJ16: Región de Coquimbo | AK16: Juan Carlos Maturana | AL16: 0.37495021 | AM16: 0.43965438 | AN16: 638 | AO16: OK | AP16: Firmada
A17: =A16+1 -> 16 | B17: 202403250132A033 | C17: 19796943-1 | D17: =LEFT(C17,LEN(C17)-2) -> 19796943 | E17: =RIGHT(C17,1) -> 1 | F17: Yañez | G17: Gallardo | H17: Angelica Isabel | I17: Femenino | J17: Subsidio | K17: 505 | L17: 2150 | M17: 425 | N17: 2150 | O17: 0.0753 | P17: 0.0060683124 | Q17: 360 | R17: 5 | S17: 0.76511628 | T17: 1645 | U17: 11.648245 | V17: 11.957505 | W17: -0.004 | X17: 0.0713 | Y17: 0.0057559073 | Z17: 45376 | AA17: 45575 | AB17: 45379 | AC17: 45575 | AD17: 56349 | AE17: 355 | AF17: 1706.059 | AG17: Camino Las Rosas 518, Edificio 14,departamento 54 | AH17: Chillán | AI17: Diguillín | AJ17: Región de Ñuble | AK17: Luis Álvarez Diaz | AL17: 0.24543004 | AM17: 0.30375181 | AN17: 1236 | AO17: OK | AP17: Firmada
A18: =A17+1 -> 17 | B18: 202403260133A033 | C18: 18475742-7 | D18: =LEFT(C18,LEN(C18)-2) -> 18475742 | E18: =RIGHT(C18,1) -> 7 | F18: Torres | G18: Romero | H18: Evelyn Andrea | I18: Masculino | J18: Subsidio | K18: 730 | L18: 2250 | M18: 550 | N18: 2540 | O18: 0.0753 | P18: 0.0060683124 | Q18: 360 | R18: 5 | S18: 0.68932222 | T18: 1550.975 | U18: 10.982454 | V18: 11.274037 | W18: -0.004 | X18: 0.0713 | Y18: 0.0057559073 | Z18: 45377 | AA18: 45575 | AB18: 45379 | AC18: 45575 | AD18: 56349 | AE18: 355 | AF18: 1607.9421 | AG18: Calle Adriana García Ibáñez 2030, Torre F,departamento 202 | AH18: San Javier | AI18: Linares | AJ18: Región del Maule | AK18: Gabriel Guerrero González | AL18: 0.23529819 | AM18: 0.40352778 | AN18: 1135 | AO18: OK | AP18: Firmada
A19: =A18+1 -> 18 | B19: 202403250134A033 | C19: 14204102-2 | D19: =LEFT(C19,LEN(C19)-2) -> 14204102 | E19: =RIGHT(C19,1) -> 2 | F19: Nuñez | G19: Brito | H19: Fernanda Angelica | I19: Femenino | J19: Subsidio | K19: 487.6 | L19: 1400 | M19: 400 | N19: 1410 | O19: 0.0753 | P19: 0.0060683124 | Q19: 288 | R19: 5 | S19: 0.65171429 | T19: 912.4 | U19: 6.963437 | V19: 6.857598 | W19: -0.004 | X19: 0.0713 | Y19: 0.0057559073 | Z19: 45376 | AA19: 45575 | AB19: 45379 | AC19: 45575 | AD19: 54158 | AE19: 283 | AF19: 941.02322 | AG19: Avenida El Valle 199, Torre C,departamento 701 | AH19: Rancagua | AI19: Cachapoal | AJ19: Región del Libertador General Bernardo O'Higgins | AK19: Gerardo Carvallo Castillo | AL19: 0.26594348 | AM19: 0.38932645 | AN19: 802 | AO19: OK | AP19: Firmada
A20: =A19+1 -> 19 | B20: 202403250135A033 | C20: 13219684-2 | D20: =LEFT(C20,LEN(C20)-2) -> 13219684 | E20: =RIGHT(C20,1) -> 2 | F20: Cardenas | G20: Mardones | H20: Katherine Magdalena | I20: Femenino | J20: Subsidio | K20: 414 | L20: 2070 | M20: 325 | N20: 2200 | O20: 0.0753 | P20: 0.0060683124 | Q20: 360 | R20: 5 | S20: 0.8 | T20: 1656 | U20: 11.726136 | V20: 12.037464 | W20: -0.004 | X20: 0.0713 | Y20: 0.0057559073 | Z20: 45376 | AA20: 45575 | AB20: 45379 | AC20: 45575 | AD20: 56349 | AE20: 355 | AF20: 1717.7742 | AG20: Avenida El Valle 199, Torre A,departamento 303 | AH20: Rancagua | AI20: Cachapoal | AJ20: Región del Libertador General Bernardo O'Higgins | AK20: Gerardo Carvallo Castillo | AL20: 0.18073504 | AM20: 0.27390952 | AN20: 800 | AO20: OK | AP20: Firmada
A21: =A20+1 -> 20 | B21: 202403250138A033 | C21: 27097423-6 | D21: =LEFT(C21,LEN(C21)-2) -> 27097423 | E21: =RIGHT(C21,1) -> 6 | F21: Rivera | G21: De Carreño | H21: Rosmery Josefina | I21: Femenino | J21: Subsidio | K21: 940 | L21: 2800 | M21: 700 | N21: 2800 | O21: 0.0753 | P21: 0.0060683124 | Q21: 360 | R21: 5 | S21: 0.66428571 | T21: 1860 | U21: 13.17 | V21: 13.52 | W21: -0.004 | X21: 0.0713 | Y21: 0.0057559073 | Z21: 45376 | AA21: 45575 | AB21: 45379 | AC21: 45575 | AD21: 56349 | AE21: 355 | AF21: 1928.6521 | AG21: Los Libertadores 4733, Edificio H | AH21: Cerrillos | AI21: Santiago | AJ21: Región Metropolitana de Santiago | AK21: Pablo Martínez Loaiza | AL21: 0.1773358 | AM21: 0.21092959 | AN21: 5492 | AO21: OK | AP21: Firmada

Sheet Valo FX
V1: valor Creditú
I2: Monto Crédito + Cap (UF) | P2: Tasa endoso | Q2: Fecha 1er Aporte a endosar | R2: Fecha Last Aporte | S2: Fecha Corte | U2: VPN | V2: Tasa mensual de endoso | X2: Tasacion | Y2: Precio Venta/Tasación | Z2: Tasa Endoso | AA2: Monto Dividendo | AB2: Dividendo/ Renta | AC2: Carga Financiera/ Renta
A3: Nº | B3: N° Operación | C3: Apellido paterno | D3: Apellido materno | E3: Nombres | F3: Rut | G3: DV | H3: Fecha de emisión | J3: Subsidio | K3: Pie | L3: Valor Vivienda | M3: Morosidad | N3: Nº Cuotas | O3: Primera cuota a endosar | T3: 45392 | U3: 45379 | W3: Saldo insoluto Teórico | AD3: Dirección de la Propiedad | AE3: Codigo Comuna | AF3: Comuna
A4: =+Base!A2 -> 1 | B4: =+Base!B2 -> 202403250103A033 | C4: =+Base!F2 -> Diaz | D4: =+Base!G2 -> Zuñiga | E4: =+Base!H2 -> Joel Alejandro | F4: =+Base!D2 -> 18803188 | G4: =+Base!E2 -> 9 | H4: =+Base!Z2 -> 45376 | I4: =+Base!T2 -> 1595 | J4: =+Base!M2 -> 525 | K4: =+L4-J4-I4 -> 80 | L4: =+Base!L2 -> 2200 | M4: 0 | N4: =+Base!Q2 -> 300 | O4: =+Base!R2+1 -> 6 | P4: =+XIRR('Tabla desarrollo FX'!B3:MY3,'Tabla desarrollo FX'!$B$1:$MY$1) -> 0.070972547 | Q4: =+Base!AA2 -> 45575 | R4: =+Base!AD2 -> 54523 | S4: =$T$3 -> 45392 | T4: =+NPV(V4,'Tabla desarrollo FX'!D3:MY3) -> 1651.534 | U4: =+Base!AF2 -> 1647.6019 | V4: =+Base!Y2 -> 0.0057559073 | W4: =+Base!T2 -> 1595 | X4: =+Base!N2 -> 2325 | Y4: =+U4/X4 -> 0.70864598 | Z4: =+P4-Base!O2 -> -0.0043274531 | AA4: =+Base!U2 -> 11.98802 | AB4: =+Base!AL2*100 -> 25.914525 | AC4: =+Base!AM2*100 -> 32.831376 | AD4: =+Base!AG2 -> Calle 8 Sur Poniente 351,casa 351 | AE4: =+VLOOKUP(AF4,Comuna!A:B,2,0) -> #N/A | AF4: =+Base!AI2 -> Biobío
A5: =+Base!A3 -> 2 | B5: =+Base!B3 -> 202403260104A033 | C5: =+Base!F3 -> Hultazo | D5: =+Base!G3 -> Novoa | E5: =+Base!H3 -> Daniela Del Carmen | F5: =+Base!D3 -> 16265854 | G5: =+Base!E3 -> 9 | H5: =+Base!Z3 -> 45377 | I5: =+Base!T3 -> 1480.48 | J5: =+Base!M3 -> 550 | K5: =+L5-J5-I5 -> 169.52 | L5: =+Base!L3 -> 2200 | M5: 1 | N5: =+Base!Q3 -> 360 | O5: =+Base!R3+1 -> 6 | P5: =+XIRR('Tabla desarrollo FX'!B4:MY4,'Tabla desarrollo FX'!$B$1:$MY$1) -> 0.071001557 | Q5: =+Base!AA3 -> 45575 | R5: =+Base!AD3 -> 56349 | S5: =$T$3 -> 45392 | T5: =+NPV(V5,'Tabla desarrollo FX'!D4:MY4) -> 1539.1184 | U5: =+Base!AF3 -> 1534.7211 | V5: =+Base!Y3 -> 0.0057559073 | W5: =+Base!T3 -> 1480.48 | X5: =+Base!N3 -> 2560 | Y5: =+U5/X5 -> 0.59950042 | Z5: =+P5-Base!O3 -> -0.0042984435 | AA5: =+Base!U3 -> 10.483279 | AB5: =+Base!AL3*100 -> 17.374483 | AC5: =+Base!AM3*100 -> 46.168658 | AD5: =+Base!AG3 -> ADRIANA GARCIA IBAÑEZ 2030, Edificio G,departamento 303 | AE5: =+VLOOKUP(AF5,Comuna!A:B,2,0) -> 7401 | AF5: =+Base!AI3 -> Linares
A6: =+Base!A4 -> 3 | B6: =+Base!B4 -> 202403250105A033 | C6: =+Base!F4 -> Salazar | D6: =+Base!G4 -> Carvajal | E6: =+Base!H4 -> Nedier Graciela | F6: =+Base!D4 -> 24585394 | G6: =+Base!E4 -> 7 | H6: =+Base!Z4 -> 45376 | I6: =+Base!T4 -> 863.96 | J6: =+Base!M4 -> 450 | K6: =+L6-J6-I6 -> 86.04 | L6: =+Base!L4 -> 1400 | M6: 2 | N6: =+Base!Q4 -> 312 | O6: =+Base!R4+1 -> 6 | P6: =+XIRR('Tabla desarrollo FX'!B5:MY5,'Tabla desarrollo FX'!$B$1:$MY$1) -> 0.070979336 | Q6: =+Base!AA4 -> 45575 | R6: =+Base!AD4 -> 54888 | S6: =$T$3 -> 45392 | T6: =+NPV(V6,'Tabla desarrollo FX'!D5:MY5) -> 895.357 | U6: =+Base!AF4 -> 892.6874 | V6: =+Base!Y4 -> 0.0057559073 | W6: =+Base!T4 -> 863.96 | X6: =+Base!N4 -> 1400 | Y6: =+U6/X6 -> 0.63763386 | Z6: =+P6-Base!O4 -> -0.0043206641 | AA6: =+Base!U4 -> 6.402808 | AB6: =+Base!AL4*100 -> 34.565539 | AC6: =+Base!AM4*100 -> 54.730716 | AD6: =+Base!AG4 -> Camino La Vara 02600, Torre 1,departamento 406 | AE6: =+VLOOKUP(AF6,Comuna!A:B,2,0) -> #N/A | AF6: =+Base!AI4 -> Maipo
A7: =+Base!A5 -> 4 | B7: =+Base!B5 -> 202403260108A033 | C7: =+Base!F5 -> Vasquez | D7: =+Base!G5 -> Sanchez | E7: =+Base!H5 -> Bertha Ramona | F7: =+Base!D5 -> 26537872 | G7: =+Base!E5 -> 2 | H7: =+Base!Z5 -> 45377 | I7: =+Base!T5 -> 1717 | J7: =+Base!M5 -> 475 | K7: =+L7-J7-I7 -> 108 | L7: =+Base!L5 -> 2300 | M7: 3 | N7: =+Base!Q5 -> 264 | O7: =+Base!R5+1 -> 6 | P7: =+XIRR('Tabla desarrollo FX'!B6:MY6,'Tabla desarrollo FX'!$B$1:$MY$1) -> 0.070948073 | Q7: =+Base!AA5 -> 45575 | R7: =+Base!AD5 -> 53427 | S7: =$T$3 -> 45392 | T7: =+NPV(V7,'Tabla desarrollo FX'!D6:MY6) -> 1772.9012 | U7: =+Base!AF5 -> 1768.2353 | V7: =+Base!Y5 -> 0.0057559073 | W7: =+Base!T5 -> 1717 | X7: =+Base!N5 -> 2300 | Y7: =+U7/X7 -> 0.76879796 | Z7: =+P7-Base!O5 -> -0.0043519267 | AA7: =+Base!U5 -> 13.571168 | AB7: =+Base!AL5*100 -> 36.411949 | AC7: =+Base!AM5*100 -> 41.283351 | AD7: =+Base!AG5 -> Calle 38 Oriente 350, Torre 8,departamento 2804 | AE7: =+VLOOKUP(AF7,Comuna!A:B,2,0) -> 7101 | AF7: =+Base!AI5 -> Talca
A8: =+Base!A6 -> 5 | B8: =+Base!B6 -> 202403250112A033 | C8: =+Base!F6 -> Huenchul | D8: =+Base!G6 -> Colihuinca | E8: =+Base!H6 -> César Antonio | F8: =+Base!D6 -> 18188333 | G8: =+Base!E6 -> 2 | H8: =+Base!Z6 -> 45376 | I8: =+Base!T6 -> 1551.6 | J8: =+Base!M6 -> 375 | K8: =+L8-J8-I8 -> 143.4 | L8: =+Base!L6 -> 2070 | M8: 4 | N8: =+Base!Q6 -> 360 | O8: =+Base!R6+1 -> 6 | P8: =+XIRR('Tabla desarrollo FX'!B7:MY7,'Tabla desarrollo FX'!$B$1:$MY$1) -> 0.071001557 | Q8: =+Base!AA6 -> 45575 | R8: =+Base!AD6 -> 56349 | S8: =$T$3 -> 45392 | T8: =+NPV(V8,'Tabla desarrollo FX'!D7:MY7) -> 1613.0553 | U8: =+Base!AF6 -> 1609.4065 | V8: =+Base!Y6 -> 0.0057559073 | W8: =+Base!T6 -> 1551.6 | X8: =+Base!N6 -> 2400 | Y8: =+U8/X8 -> 0.67058603 | Z8: =+P8-Base!O6 -> -0.0042984435 | AA8: =+Base!U6 -> 10.98688 | AB8: =+Base!AL6*100 -> 40.025143 | AC8: =+Base!AM6*100 -> 42.269568 | AD8: =+Base!AG6 -> Camino La Vara 02600, TORRE 2,departamento 412 | AE8: =+VLOOKUP(AF8,Comuna!A:B,2,0) -> #N/A | AF8: =+Base!AI6 -> Maipo
A9: =+Base!A7 -> 6 | B9: =+Base!B7 -> 202403260115A033 | C9: =+Base!F7 -> Rojas | D9: =+Base!G7 -> Diaz | E9: =+Base!H7 -> Claudio Sebastian | F9: =+Base!D7 -> 18250306 | G9: =+Base!E7 -> 1 | H9: =+Base!Z7 -> 45377 | I9: =+Base!T7 -> 1664.23 | J9: =+Base!M7 -> 700 | K9: =+L9-J9-I9 -> 335.77 | L9: =+Base!L7 -> 2700 | M9: 5 | N9: =+Base!Q7 -> 300 | O9: =+Base!R7+1 -> 6 | P9: =+XIRR('Tabla desarrollo FX'!B8:MY8,'Tabla desarrollo FX'!$B$1:$MY$1) -> 0.070972547 | Q9: =+Base!AA7 -> 45575 | R9: =+Base!AD7 -> 54523 | S9: =$T$3 -> 45392 | T9: =+NPV(V9,'Tabla desarrollo FX'!D8:MY8) -> 1723.2178 | U9: =+Base!AF7 -> 1719.0581 | V9: =+Base!Y7 -> 0.0057559073 | W9: =+Base!T7 -> 1664.23 | X9: =+Base!N7 -> 2700 | Y9: =+U9/X9 -> 0.63668818 | Z9: =+P9-Base!O7 -> -0.0043274531 | AA9: =+Base!U7 -> 12.508353 | AB9: =+Base!AL7*100 -> 16.448389 | AC9: =+Base!AM7*100 -> 37.966625 | AD9: =+Base!AG7 -> Los Libertadores 4733, Edificio F,departamento 106 | AE9: =+VLOOKUP(AF9,Comuna!A:B,2,0) -> 13101 | AF9: =+Base!AI7 -> Santiago
A10: =+Base!A8 -> 7 | B10: =+Base!B8 -> 202403260117A033 | C10: =+Base!F8 -> Lagos | D10: =+Base!G8 -> Muñoz | E10: =+Base!H8 -> Pablo Daniel | F10: =+Base!D8 -> 17747816 | G10: =+Base!E8 -> 4 | H10: =+Base!Z8 -> 45377 | I10: =+Base!T8 -> 1630.975 | J10: =+Base!M8 -> 550 | K10: =+L10-J10-I10 -> 69.025 | L10: =+Base!L8 -> 2250 | M10: 6 | N10: =+Base!Q8 -> 360 | O10: =+Base!R8+1 -> 6 | P10: =+XIRR('Tabla desarrollo FX'!B9:MY9,'Tabla desarrollo FX'!$B$1:$MY$1) -> 0.071001557 | Q10: =+Base!AA8 -> 45575 | R10: =+Base!AD8 -> 56349 | S10: =$T$3 -> 45392 | T10: =+NPV(V10,'Tabla desarrollo FX'!D9:MY9) -> 1695.5741 | U10: =+Base!AF8 -> 1691.4151 | V10: =+Base!Y8 -> 0.0057559073 | W10: =+Base!T8 -> 1630.975 | X10: =+Base!N8 -> 2460 | Y10: =+U10/X10 -> 0.68756711 | Z10: =+P10-Base!O8 -> -0.0042984435 | AA10: =+Base!U8 -> 11.548934 | AB10: =+Base!AL8*100 -> 33.391403 | AC10: =+Base!AM8*100 -> 49.056281 | AD10: =+Base!AG8 -> ADRIANA GARCIA IBAÑEZ 2030, Torre B,departamento 401 | AE10: =+VLOOKUP(AF10,Comuna!A:B,2,0) -> 7401 | AF10: =+Base!AI8 -> Linares
A11: =+Base!A9 -> 8 | B11: =+Base!B9 -> 202403220119A033 | C11: =+Base!F9 -> Jaña | D11: =+Base!G9 -> Avila | E11: =+Base!H9 -> Francisco Javier | F11: =+Base!D9 -> 17137105 | G11: =+Base!E9 -> 8 | H11: =+Base!Z9 -> 45373 | I11: =+Base!T9 -> 781.37 | J11: =+Base!M9 -> 400 | K11: =+L11-J11-I11 -> 218.63 | L11: =+Base!L9 -> 1400 | M11: 7 | N11: =+Base!Q9 -> 360 | O11: =+Base!R9+1 -> 6 | P11: =+XIRR('Tabla desarrollo FX'!B10:MY10,'Tabla desarrollo FX'!$B$1:$MY$1) -> 0.071001557 | Q11: =+Base!AA9 -> 45575 | R11: =+Base!AD9 -> 56349 | S11: =$T$3 -> 45392 | T11: =+NPV(V11,'Tabla desarrollo FX'!D10:MY10) -> 812.31826 | U11: =+Base!AF9 -> 809.82925 | V11: =+Base!Y9 -> 0.0057559073 | W11: =+Base!T9 -> 781.37 | X11: =+Base!N9 -> 1410 | Y11: =+U11/X11 -> 0.57434698 | Z11: =+P11-Base!O9 -> -0.0042984435 | AA11: =+Base!U9 -> 5.532881 | AB11: =+Base!AL9*100 -> 38.354014 | AC11: =+Base!AM9*100 -> 50.324471 | AD11: =+Base!AG9 -> Av. El Valle 199, Torre B,departamento 101 | AE11: =+VLOOKUP(AF11,Comuna!A:B,2,0) -> #N/A | AF11: =+Base!AI9 -> Cachapoal
A12: =+Base!A10 -> 9 | B12: =+Base!B10 -> 202403260120A033 | C12: =+Base!F10 -> Oñate | D12: =+Base!G10 -> Muñoz | E12: =+Base!H10 -> Pablo Enrique | F12: =+Base!D10 -> 16995140 | G12: =+Base!E10 -> 3 | H12: =+Base!Z10 -> 45377 | I12: =+Base!T10 -> 760 | J12: =+Base!M10 -> 600 | K12: =+L12-J12-I12 -> 40 | L12: =+Base!L10 -> 1400 | M12: 8 | N12: =+Base!Q10 -> 216 | O12: =+Base!R10+1 -> 6 | P12: =+XIRR('Tabla desarrollo FX'!B11:MY11,'Tabla desarrollo FX'!$B$1:$MY$1) -> 0.070901969 | Q12: =+Base!AA10 -> 45575 | R12: =+Base!AD10 -> 51966 | S12: =$T$3 -> 45392 | T12: =+NPV(V12,'Tabla desarrollo FX'!D11:MY11) -> 781.43864 | U12: =+Base!AF10 -> 779.0959 | V12: =+Base!Y10 -> 0.0057559073 | W12: =+Base!T10 -> 760 | X12: =+Base!N10 -> 1600 | Y12: =+U12/X12 -> 0.48693494 | Z12: =+P12-Base!O10 -> -0.0043980309 | AA12: =+Base!U10 -> 6.593 | AB12: =+Base!AL10*100 -> 15.83457 | AC12: =+Base!AM10*100 -> 40.708554 | AD12: =+Base!AG10 -> PROFESOR PASCUAL PEREIRA 1324,casa 1324 | AE12: =+VLOOKUP(AF12,Comuna!A:B,2,0) -> #N/A | AF12: =+Base!AI10 -> Biobío
A13: =+Base!A11 -> 10 | B13: =+Base!B11 -> 202403250121A033 | C13: =+Base!F11 -> Aranguiz | D13: =+Base!G11 -> Arevalo | E13: =+Base!H11 -> Macarena Andrea Del Carmen | F13: =+Base!D11 -> 18645373 | G13: =+Base!E11 -> 5 | H13: =+Base!Z11 -> 45376 | I13: =+Base!T11 -> 1672 | J13: =+Base!M11 -> 325 | K13: =+L13-J13-I13 -> 93 | L13: =+Base!L11 -> 2090 | M13: 9 | N13: =+Base!Q11 -> 360 | O13: =+Base!R11+1 -> 6 | P13: =+XIRR('Tabla desarrollo FX'!B12:MY12,'Tabla desarrollo FX'!$B$1:$MY$1) -> 0.071001557 | Q13: =+Base!AA11 -> 45575 | R13: =+Base!AD11 -> 56349 | S13: =$T$3 -> 45392 | T13: =+NPV(V13,'Tabla desarrollo FX'!D12:MY12) -> 1738.224 | U13: =+Base!AF11 -> 1733.8826 | V13: =+Base!Y11 -> 0.0057559073 | W13: =+Base!T11 -> 1672 | X13: =+Base!N11 -> 2200 | Y13: =+U13/X13 -> 0.78812843 | Z13: =+P13-Base!O11 -> -0.0042984435 | AA13: =+Base!U11 -> 11.839432 | AB13: =+Base!AL11*100 -> 24.855131 | AC13: =+Base!AM11*100 -> 39.683384 | AD13: =+Base!AG11 -> Av El Valle 199, Torre B,departamento 407 | AE13: =+VLOOKUP(AF13,Comuna!A:B,2,0) -> #N/A | AF13: =+Base!AI11 -> Cachapoal
A14: =+Base!A12 -> 11 | B14: =+Base!B12 -> 202403250123A033 | C14: =+Base!F12 -> Moraga | D14: =+Base!G12 -> Carrasco | E14: =+Base!H12 -> Jenny Alejandra | F14: =+Base!D12 -> 16681463 | G14: =+Base!E12 -> 4 | H14: =+Base!Z12 -> 45376 | I14: =+Base!T12 -> 877.78 | J14: =+Base!M12 -> 450 | K14: =+L14-J14-I14 -> 72.22 | L14: =+Base!L12 -> 1400 | M14: 10 | N14: =+Base!Q12 -> 240 | O14: =+Base!R12+1 -> 6 | P14: =+XIRR('Tabla desarrollo FX'!B13:MY13,'Tabla desarrollo FX'!$B$1:$MY$1) -> 0.070927659 | Q14: =+Base!AA12 -> 45575 | R14: =+Base!AD12 -> 52697 | S14: =$T$3 -> 45392 | T14: =+NPV(V14,'Tabla desarrollo FX'!D13:MY13) -> 904.51418 | U14: =+Base!AF12 -> 902.65751 | V14: =+Base!Y12 -> 0.0057559073 | W14: =+Base!T12 -> 877.78 | X14: =+Base!N12 -> 1400 | Y14: =+U14/X14 -> 0.64475536 | Z14: =+P14-Base!O12 -> -0.0043723413 | AA14: =+Base!U12 -> 7.236418 | AB14: =+Base!AL12*100 -> 27.580802 | AC14: =+Base!AM12*100 -> 28.908034 | AD14: =+Base!AG12 -> PASAJE DEMOFILA TORREALBA (PROFESORA) 1744,casa 1744 | AE14: =+VLOOKUP(AF14,Comuna!A:B,2,0) -> #N/A | AF14: =+Base!AI12 -> Cachapoal
A15: =+Base!A13 -> 12 | B15: =+Base!B13 -> 202403250125A033 | C15: =+Base!F13 -> Pozo | D15: =+Base!G13 -> Salvatierra | E15: =+Base!H13 -> Eufronia | F15: =+Base!D13 -> 24243822 | G15: =+Base!E13 -> 1 | H15: =+Base!Z13 -> 45376 | I15: =+Base!T13 -> 766.75 | J15: =+Base!M13 -> 737.5 | K15: =+L15-J15-I15 -> 195.75 | L15: =+Base!L13 -> 1700 | M15: 11 | N15: =+Base!Q13 -> 204 | O15: =+Base!R13+1 -> 6 | P15: =+XIRR('Tabla desarrollo FX'!B14:MY14,'Tabla desarrollo FX'!$B$1:$MY$1) -> 0.070887038 | Q15: =+Base!AA13 -> 45575 | R15: =+Base!AD13 -> 51601 | S15: =$T$3 -> 45392 | T15: =+NPV(V15,'Tabla desarrollo FX'!D14:MY14) -> 787.48094 | U15: =+Base!AF13 -> 785.37074 | V15: =+Base!Y13 -> 0.0057559073 | W15: =+Base!T13 -> 766.75 | X15: =+Base!N13 -> 1700 | Y15: =+U15/X15 -> 0.46198279 | Z15: =+P15-Base!O13 -> -0.0044129619 | AA15: =+Base!U13 -> 6.850911 | AB15: =+Base!AL13*100 -> 41.766992 | AC15: =+Base!AM13*100 -> 44.378192 | AD15: =+Base!AG13 -> Los Libertadores 4733, Edificio F,departamento 808 | AE15: =+VLOOKUP(AF15,Comuna!A:B,2,0) -> 13101 | AF15: =+Base!AI13 -> Santiago
... A23: =+Base!A21 -> 20 | B23: =+Base!B21 -> 202403250138A033 | C23: =+Base!F21 -> Rivera | D23: =+Base!G21 -> De Carreño | E23: =+Base!H21 -> Rosmery Josefina | F23: =+Base!D21 -> 27097423 | G23: =+Base!E21 -> 6 | H23: =+Base!Z21 -> 45376 | I23: =+Base!T21 -> 1860 | J23: =+Base!M21 -> 700 | K23: =+L23-J23-I23 -> 240 | L23: =+Base!L21 -> 2800 | M23: 19 | N23: =+Base!Q21 -> 360 | O23: =+Base!R21+1 -> 6 | P23: =+XIRR('Tabla desarrollo FX'!B22:MY22,'Tabla desarrollo FX'!$B$1:$MY$1) -> 0.071001557 | Q23: =+Base!AA21 -> 45575 | R23: =+Base!AD21 -> 56349 | S23: =$T$3 -> 45392 | T23: =+NPV(V23,'Tabla desarrollo FX'!D22:MY22) -> 1933.5734 | U23: =+Base!AF21 -> 1928.6521 | V23: =+Base!Y21 -> 0.0057559073 | W23: =+Base!T21 -> 1860 | X23: =+Base!N21 -> 2800 | Y23: =+U23/X23 -> 0.68880432 | Z23: =+P23-Base!O21 -> -0.0042984435 | AA23: =+Base!U21 -> 13.17 | AB23: =+Base!AL21*100 -> 17.73358 | AC23: =+Base!AM21*100 -> 21.092959 | AD23: =+Base!AG21 -> Los Libertadores 4733, Edificio H | AE23: =+VLOOKUP(AF23,Comuna!A:B,2,0) -> 13101 | AF23: =+Base!AI21 -> Santiago

Sheet Valo
U1: =+SUM(U4:U23) -> 28137.957 | V1: 1 | X1: 1
I2: Monto Crédito + Cap (UF) | P2: Tasa endoso | Q2: Fecha 1er Aporte a endosar | R2: Fecha Last Aporte | S2: Fecha Corte | U2: VPN | V2: Tasa mensual de endoso | X2: Tasacion | Y2: Precio Venta/Tasación | Z2: Tasa Endoso | AA2: Monto Dividendo | AB2: Dividendo/ Renta | AC2: Carga Financiera/ Renta
A3: Nº | B3: N° Operación | C3: Apellido paterno | D3: Apellido materno | E3: Nombres | F3: Rut | G3: DV | H3: Leasing o Mutuo | J3: Subsidio | K3: Pie | L3: Valor Vivienda | M3: Morosidad | N3: Nº Cuotas | O3: Primera cuota a endosar | T3: 45392 | U3: 45379 | W3: Saldo insoluto Teórico | AD3: Dirección de la Propiedad | AE3: Codigo Comuna | AF3: Comuna
A4: 1 | B4: 202403250103A033 | C4: Diaz | D4: Zuñiga | E4: Joel Alejandro | F4: 18803188 | G4: 9 | H4: 45376 | I4: 1595 | J4: 525 | K4: 80 | L4: 2200 | M4: 0 | N4: 300 | O4: 6 | P4: 0.070972547 | Q4: 45575 | R4: 54523 | S4: 45392 | T4: 1651.534 | U4: 1647.6019 | V4: 0.0057559073 | W4: 1595 | X4: 2325 | Y4: 0.70864598 | Z4: -0.0043274531 | AA4: 11.98802 | AB4: 25.914525 | AC4: 32.831376 | AD4: Calle 8 Sur Poniente 351,casa 351 | AE4: 7401 | AF4: Biobío
A5: 2 | B5: 202403260104A033 | C5: Hultazo | D5: Novoa | E5: Daniela Del Carmen | F5: 16265854 | G5: 9 | H5: 45377 | I5: 1480.48 | J5: 550 | K5: 169.52 | L5: 2200 | M5: 1 | N5: 360 | O5: 6 | P5: 0.071001557 | Q5: 45575 | R5: 56349 | S5: 45392 | T5: 1539.1184 | U5: 1534.7211 | V5: 0.0057559073 | W5: 1480.48 | X5: 2560 | Y5: 0.59950042 | Z5: -0.0042984435 | AA5: 10.483279 | AB5: 17.374483 | AC5: 46.168658 | AD5: ADRIANA GARCIA IBAÑEZ 2030, Edificio G,departamento 303 | AE5: 7401 | AF5: Linares
A6: 3 | B6: 202403250105A033 | C6: Salazar | D6: Carvajal | E6: Nedier Graciela | F6: 24585394 | G6: 7 | H6: 45376 | I6: 863.96 | J6: 450 | K6: 86.04 | L6: 1400 | M6: 2 | N6: 312 | O6: 6 | P6: 0.070979336 | Q6: 45575 | R6: 54888 | S6: 45392 | T6: 895.357 | U6: 892.6874 | V6: 0.0057559073 | W6: 863.96 | X6: 1400 | Y6: 0.63763386 | Z6: -0.0043206641 | AA6: 6.402808 | AB6: 34.565539 | AC6: 54.730716 | AD6: Camino La Vara 02600, Torre 1,departamento 406 | AE6: 7401 | AF6: Maipo
A7: 4 | B7: 202403260108A033 | C7: Vasquez | D7: Sanchez | E7: Bertha Ramona | F7: 26537872 | G7: 2 | H7: 45377 | I7: 1717 | J7: 475 | K7: 108 | L7: 2300 | M7: 3 | N7: 264 | O7: 6 | P7: 0.070948073 | Q7: 45575 | R7: 53427 | S7: 45392 | T7: 1772.9012 | U7: 1768.2353 | V7: 0.0057559073 | W7: 1717 | X7: 2300 | Y7: 0.76879796 | Z7: -0.0043519267 | AA7: 13.571168 | AB7: 36.411949 | AC7: 41.283351 | AD7: Calle 38 Oriente 350, Torre 8,departamento 2804 | AE7: 7401 | AF7: Talca
A8: 5 | B8: 202403250112A033 | C8: Huenchul | D8: Colihuinca | E8: César Antonio | F8: 18188333 | G8: 2 | H8: 45376 | I8: 1551.6 | J8: 375 | K8: 143.4 | L8: 2070 | M8: 4 | N8: 360 | O8: 6 | P8: 0.071001557 | Q8: 45575 | R8: 56349 | S8: 45392 | T8: 1613.0553 | U8: 1609.4065 | V8: 0.0057559073 | W8: 1551.6 | X8: 2400 | Y8: 0.67058603 | Z8: -0.0042984435 | AA8: 10.98688 | AB8: 40.025143 | AC8: 42.269568 | AD8: Camino La Vara 02600, TORRE 2,departamento 412 | AE8: 7401 | AF8: Maipo
A9: 6 | B9: 202403260115A033 | C9: Rojas | D9: Diaz | E9: Claudio Sebastian | F9: 18250306 | G9: 1 | H9: 45377 | I9: 1664.23 | J9: 700 | K9: 335.77 | L9: 2700 | M9: 5 | N9: 300 | O9: 6 | P9: 0.070972547 | Q9: 45575 | R9: 54523 | S9: 45392 | T9: 1723.2178 | U9: 1719.0581 | V9: 0.0057559073 | W9: 1664.23 | X9: 2700 | Y9: 0.63668818 | Z9: -0.0043274531 | AA9: 12.508353 | AB9: 16.448389 | AC9: 37.966625 | AD9: Los Libertadores 4733, Edificio F,departamento 106 | AE9: 13101 | AF9: Santiago
A10: 7 | B10: 202403260117A033 | C10: Lagos | D10: Muñoz | E10: Pablo Daniel | F10: 17747816 | G10: 4 | H10: 45377 | I10: 1630.975 | J10: 550 | K10: 69.025 | L10: 2250 | M10: 6 | N10: 360 | O10: 6 | P10: 0.071001557 | Q10: 45575 | R10: 56349 | S10: 45392 | T10: 1695.5741 | U10: 1691.4151 | V10: 0.0057559073 | W10: 1630.975 | X10: 2460 | Y10: 0.68756711 | Z10: -0.0042984435 | AA10: 11.548934 | AB10: 33.391403 | AC10: 49.056281 | AD10: ADRIANA GARCIA IBAÑEZ 2030, Torre B,departamento 401 | AE10: 7401 | AF10: Linares
A11: 8 | B11: 202403220119A033 | C11: Jaña | D11: Avila | E11: Francisco Javier | F11: 17137105 | G11: 8 | H11: 45373 | I11: 781.37 | J11: 400 | K11: 218.63 | L11: 1400 | M11: 7 | N11: 360 | O11: 6 | P11: 0.071001557 | Q11: 45575 | R11: 56349 | S11: 45392 | T11: 812.31826 | U11: 809.82925 | V11: 0.0057559073 | W11: 781.37 | X11: 1410 | Y11: 0.57434698 | Z11: -0.0042984435 | AA11: 5.532881 | AB11: 38.354014 | AC11: 50.324471 | AD11: Av. El Valle 199, Torre B,departamento 101 | AE11: 7401 | AF11: Cachapoal
A12: 9 | B12: 202403260120A033 | C12: Oñate | D12: Muñoz | E12: Pablo Enrique | F12: 16995140 | G12: 3 | H12: 45377 | I12: 760 | J12: 600 | K12: 40 | L12: 1400 | M12: 8 | N12: 216 | O12: 6 | P12: 0.070901969 | Q12: 45575 | R12: 51966 | S12: 45392 | T12: 781.43864 | U12: 779.0959 | V12: 0.0057559073 | W12: 760 | X12: 1600 | Y12: 0.48693494 | Z12: -0.0043980309 | AA12: 6.593 | AB12: 15.83457 | AC12: 40.708554 | AD12: PROFESOR PASCUAL PEREIRA 1324,casa 1324 | AE12: 7401 | AF12: Biobío
A13: 10 | B13: 202403250121A033 | C13: Aranguiz | D13: Arevalo | E13: Macarena Andrea Del Carmen | F13: 18645373 | G13: 5 | H13: 45376 | I13: 1672 | J13: 325 | K13: 93 | L13: 2090 | M13: 9 | N13: 360 | O13: 6 | P13: 0.071001557 | Q13: 45575 | R13: 56349 | S13: 45392 | T13: 1738.224 | U13: 1733.8826 | V13: 0.0057559073 | W13: 1672 | X13: 2200 | Y13: 0.78812843 | Z13: -0.0042984435 | AA13: 11.839432 | AB13: 24.855131 | AC13: 39.683384 | AD13: Av El Valle 199, Torre B,departamento 407 | AE13: 7401 | AF13: Cachapoal
A14: 11 | B14: 202403250123A033 | C14: Moraga | D14: Carrasco | E14: Jenny Alejandra | F14: 16681463 | G14: 4 | H14: 45376 | I14: 877.78 | J14: 450 | K14: 72.22 | L14: 1400 | M14: 10 | N14: 240 | O14: 6 | P14: 0.070927659 | Q14: 45575 | R14: 52697 | S14: 45392 | T14: 904.51418 | U14: 902.65751 | V14: 0.0057559073 | W14: 877.78 | X14: 1400 | Y14: 0.64475536 | Z14: -0.0043723413 | AA14: 7.236418 | AB14: 27.580802 | AC14: 28.908034 | AD14: PASAJE DEMOFILA TORREALBA (PROFESORA) 1744,casa 1744 | AE14: 7401 | AF14: Cachapoal
A15: 12 | B15: 202403250125A033 | C15: Pozo | D15: Salvatierra | E15: Eufronia | F15: 24243822 | G15: 1 | H15: 45376 | I15: 766.75 | J15: 737.5 | K15: 195.75 | L15: 1700 | M15: 11 | N15: 204 | O15: 6 | P15: 0.070887038 | Q15: 45575 | R15: 51601 | S15: 45392 | T15: 787.48094 | U15: 785.37074 | V15: 0.0057559073 | W15: 766.75 | X15: 1700 | Y15: 0.46198279 | Z15: -0.0044129619 | AA15: 6.850911 | AB15: 41.766992 | AC15: 44.378192 | AD15: Los Libertadores 4733, Edificio F,departamento 808 | AE15: 13101 | AF15: Santiago
... A23: 20 | B23: 202403250138A033 | C23: Rivera | D23: De Carreño | E23: Rosmery Josefina | F23: 27097423 | G23: 6 | H23: 45376 | I23: 1860 | J23: 700 | K23: 240 | L23: 2800 | M23: 19 | N23: 360 | O23: 6 | P23: 0.071001557 | Q23: 45575 | R23: 56349 | S23: 45392 | T23: 1933.5734 | U23: 1928.6521 | V23: 0.0057559073 | W23: 1860 | X23: 2800 | Y23: 0.68880432 | Z23: -0.0042984435 | AA23: 13.17 | AB23: 17.73358 | AC23: 21.092959 | AD23: Los Libertadores 4733, Edificio H | AE23: 13101 | AF23: Santiago

Sheet Tabla desarrollo FX
B1: =+'Valo FX'!U3 -> 45379 | C1: ='Valo FX'!T3 -> 45392 | D1: =EDATE(C1,1) -> 45422 | E1: =EDATE(D1,1) -> 45453 | F1: =EDATE(E1,1) -> 45483 | G1: =EDATE(F1,1) -> 45514 | H1: =EDATE(G1,1) -> 45545 | I1: =EDATE(H1,1) -> 45575 | J1: =EDATE(I1,1) -> 45606 | K1: =EDATE(J1,1) -> 45636 | ... MY1: =EDATE(MX1,1) -> 56349
A2: Nº | B2: Primera cuota a endosar | C2: 1 | D2: =C2+1 -> 2 | E2: =D2+1 -> 3 | F2: =E2+1 -> 4 | G2: =F2+1 -> 5 | H2: =G2+1 -> 6 | I2: =H2+1 -> 7 | J2: =I2+1 -> 8 | K2: =J2+1 -> 9 | ... MY2: =MX2+1 -> 361
A3: =+'Valo FX'!A4 -> 1 | B3: =-'Valo FX'!T4 -> -1651.534 | C3: =IF(C$1<INDEX('Valo FX'!$Q:$Q,MATCH($A3,'Valo FX'!$A:$A,0)),0,IF(C$1<INDEX('Valo FX'!$R:$R,MATCH($A3,'Valo FX'!$A:$A,0)),INDEX(Base!$U:$U,MATCH($A3,Base!$A:$A,0)),IF(C$1=INDEX('Valo FX'!$R:$R,MATCH($A3,'Valo FX'!$A:$A,0)),INDEX(Base!$V:$V,MATCH($A3,Base!$A:$A,0)),0))) -> 0 | D3: =IF(D$1<INDEX('Valo FX'!$Q:$Q,MATCH($A3,'Valo FX'!$A:$A,0)),0,IF(D$1<INDEX('Valo FX'!$R:$R,MATCH($A3,'Valo FX'!$A:$A,0)),INDEX(Base!$U:$U,MATCH($A3,Base!$A:$A,0)),IF(D$1=INDEX('Valo FX'!$R:$R,MATCH($A3,'Valo FX'!$A:$A,0)),INDEX(Base!$V:$V,MATCH($A3,Base!$A:$A,0)),0))) -> 0 | E3: =IF(E$1<INDEX('Valo FX'!$Q:$Q,MATCH($A3,'Valo FX'!$A:$A,0)),0,IF(E$1<INDEX('Valo FX'!$R:$R,MATCH($A3,'Valo FX'!$A:$A,0)),INDEX(Base!$U:$U,MATCH($A3,Base!$A:$A,0)),IF(E$1=INDEX('Valo FX'!$R:$R,MATCH($A3,'Valo FX'!$A:$A,0)),INDEX(Base!$V:$V,MATCH($A3,Base!$A:$A,0)),0))) -> 0 | F3: =IF(F$1<INDEX('Valo FX'!$Q:$Q,MATCH($A3,'Valo FX'!$A:$A,0)),0,IF(F$1<INDEX('Valo FX'!$R:$R,MATCH($A3,'Valo FX'!$A:$A,0)),INDEX(Base!$U:$U,MATCH($A3,Base!$A:$A,0)),IF(F$1=INDEX('Valo FX'!$R:$R,MATCH($A3,'Valo FX'!$A:$A,0)),INDEX(Base!$V:$V,MATCH($A3,Base!$A:$A,0)),0))) -> 0 | G3: =IF(G$1<INDEX('Valo FX'!$Q:$Q,MATCH($A3,'Valo FX'!$A:$A,0)),0,IF(G$1<INDEX('Valo FX'!$R:$R,MATCH($A3,'Valo FX'!$A:$A,0)),INDEX(Base!$U:$U,MATCH($A3,Base!$A:$A,0)),IF(G$1=INDEX('Valo FX'!$R:$R,MATCH($A3,'Valo FX'!$A:$A,0)),INDEX(Base!$V:$V,MATCH($A3,Base!$A:$A,0)),0))) -> 0 | H3: =IF(H$1<INDEX('Valo FX'!$Q:$Q,MATCH($A3,'Valo FX'!$A:$A,0)),0,IF(H$1<INDEX('Valo FX'!$R:$R,MATCH($A3,'Valo FX'!$A:$A,0)),INDEX(Base!$U:$U,MATCH($A3,Base!$A:$A,0)),IF(H$1=INDEX('Valo FX'!$R:$R,MATCH($A3,'Valo FX'!$A:$A,0)),INDEX(Base!$V:$V,MATCH($A3,Base!$A:$A,0)),0))) -> 0 | I3: =IF(I$1<INDEX('Valo FX'!$Q:$Q,MATCH($A3,'Valo FX'!$A:$A,0)),0,IF(I$1<INDEX('Valo FX'!$R:$R,MATCH($A3,'Valo FX'!$A:$A,0)),INDEX(Base!$U:$U,MATCH($A3,Base!$A:$A,0)),IF(I$1=INDEX('Valo FX'!$R:$R,MATCH($A3,'Valo FX'!$A:$A,0)),INDEX(Base!$V:$V,MATCH($A3,Base!$A:$A,0)),0))) -> 11.98802 | J3: =IF(J$1<INDEX('Valo FX'!$Q:$Q,MATCH($A3,'Valo FX'!$A:$A,0)),0,IF(J$1<INDEX('Valo FX'!$R:$R,MATCH($A3,'Valo FX'!$A:$A,0)),INDEX(Base!$U:$U,MATCH($A3,Base!$A:$A,0)),IF(J$1=INDEX('Valo FX'!$R:$R,MATCH($A3,'Valo FX'!$A:$A,0)),INDEX(Base!$V:$V,MATCH($A3,Base!$A:$A,0)),0))) -> 11.98802 | ... MY3: =IF(MY$1<INDEX('Valo FX'!$Q:$Q,MATCH($A3,'Valo FX'!$A:$A,0)),0,IF(MY$1<INDEX('Valo FX'!$R:$R,MATCH($A3,'Valo FX'!$A:$A,0)),INDEX(Base!$U:$U,MATCH($A3,Base!$A:$A,0)),IF(MY$1=INDEX('Valo FX'!$R:$R,MATCH($A3,'Valo FX'!$A:$A,0)),INDEX(Base!$V:$V,MATCH($A3,Base!$A:$A,0)),0))) -> 0
A4: =+'Valo FX'!A5 -> 2 | B4: =-'Valo FX'!T5 -> -1539.1184 | C4: =IF(C$1<INDEX('Valo FX'!$Q:$Q,MATCH($A4,'Valo FX'!$A:$A,0)),0,IF(C$1<INDEX('Valo FX'!$R:$R,MATCH($A4,'Valo FX'!$A:$A,0)),INDEX(Base!$U:$U,MATCH($A4,Base!$A:$A,0)),IF(C$1=INDEX('Valo FX'!$R:$R,MATCH($A4,'Valo FX'!$A:$A,0)),INDEX(Base!$V:$V,MATCH($A4,Base!$A:$A,0)),0))) -> 0 | D4: =IF(D$1<INDEX('Valo FX'!$Q:$Q,MATCH($A4,'Valo FX'!$A:$A,0)),0,IF(D$1<INDEX('Valo FX'!$R:$R,MATCH($A4,'Valo FX'!$A:$A,0)),INDEX(Base!$U:$U,MATCH($A4,Base!$A:$A,0)),IF(D$1=INDEX('Valo FX'!$R:$R,MATCH($A4,'Valo FX'!$A:$A,0)),INDEX(Base!$V:$V,MATCH($A4,Base!$A:$A,0)),0))) -> 0 | E4: =IF(E$1<INDEX('Valo FX'!$Q:$Q,MATCH($A4,'Valo FX'!$A:$A,0)),0,IF(E$1<INDEX('Valo FX'!$R:$R,MATCH($A4,'Valo FX'!$A:$A,0)),INDEX(Base!$U:$U,MATCH($A4,Base!$A:$A,0)),IF(E$1=INDEX('Valo FX'!$R:$R,MATCH($A4,'Valo FX'!$A:$A,0)),INDEX(Base!$V:$V,MATCH($A4,Base!$A:$A,0)),0))) -> 0 | F4: =IF(F$1<INDEX('Valo FX'!$Q:$Q,MATCH($A4,'Valo FX'!$A:$A,0)),0,IF(F$1<INDEX('Valo FX'!$R:$R,MATCH($A4,'Valo FX'!$A:$A,0)),INDEX(Base!$U:$U,MATCH($A4,Base!$A:$A,0)),IF(F$1=INDEX('Valo FX'!$R:$R,MATCH($A4,'Valo FX'!$A:$A,0)),INDEX(Base!$V:$V,MATCH($A4,Base!$A:$A,0)),0))) -> 0 | G4: =IF(G$1<INDEX('Valo FX'!$Q:$Q,MATCH($A4,'Valo FX'!$A:$A,0)),0,IF(G$1<INDEX('Valo FX'!$R:$R,MATCH($A4,'Valo FX'!$A:$A,0)),INDEX(Base!$U:$U,MATCH($A4,Base!$A:$A,0)),IF(G$1=INDEX('Valo FX'!$R:$R,MATCH($A4,'Valo FX'!$A:$A,0)),INDEX(Base!$V:$V,MATCH($A4,Base!$A:$A,0)),0))) -> 0 | H4: =IF(H$1<INDEX('Valo FX'!$Q:$Q,MATCH($A4,'Valo FX'!$A:$A,0)),0,IF(H$1<INDEX('Valo FX'!$R:$R,MATCH($A4,'Valo FX'!$A:$A,0)),INDEX(Base!$U:$U,MATCH($A4,Base!$A:$A,0)),IF(H$1=INDEX('Valo FX'!$R:$R,MATCH($A4,'Valo FX'!$A:$A,0)),INDEX(Base!$V:$V,MATCH($A4,Base!$A:$A,0)),0))) -> 0 | I4: =IF(I$1<INDEX('Valo FX'!$Q:$Q,MATCH($A4,'Valo FX'!$A:$A,0)),0,IF(I$1<INDEX('Valo FX'!$R:$R,MATCH($A4,'Valo FX'!$A:$A,0)),INDEX(Base!$U:$U,MATCH($A4,Base!$A:$A,0)),IF(I$1=INDEX('Valo FX'!$R:$R,MATCH($A4,'Valo FX'!$A:$A,0)),INDEX(Base!$V:$V,MATCH($A4,Base!$A:$A,0)),0))) -> 10.483279 | J4: =IF(J$1<INDEX('Valo FX'!$Q:$Q,MATCH($A4,'Valo FX'!$A:$A,0)),0,IF(J$1<INDEX('Valo FX'!$R:$R,MATCH($A4,'Valo FX'!$A:$A,0)),INDEX(Base!$U:$U,MATCH($A4,Base!$A:$A,0)),IF(J$1=INDEX('Valo FX'!$R:$R,MATCH($A4,'Valo FX'!$A:$A,0)),INDEX(Base!$V:$V,MATCH($A4,Base!$A:$A,0)),0))) -> 10.483279 | ... MY4: =IF(MY$1<INDEX('Valo FX'!$Q:$Q,MATCH($A4,'Valo FX'!$A:$A,0)),0,IF(MY$1<INDEX('Valo FX'!$R:$R,MATCH($A4,'Valo FX'!$A:$A,0)),INDEX(Base!$U:$U,MATCH($A4,Base!$A:$A,0)),IF(MY$1=INDEX('Valo FX'!$R:$R,MATCH($A4,'Valo FX'!$A:$A,0)),INDEX(Base!$V:$V,MATCH($A4,Base!$A:$A,0)),0))) -> 10.761609
A5: =+'Valo FX'!A6 -> 3 | B5: =-'Valo FX'!T6 -> -895.357 | C5: =IF(C$1<INDEX('Valo FX'!$Q:$Q,MATCH($A5,'Valo FX'!$A:$A,0)),0,IF(C$1<INDEX('Valo FX'!$R:$R,MATCH($A5,'Valo FX'!$A:$A,0)),INDEX(Base!$U:$U,MATCH($A5,Base!$A:$A,0)),IF(C$1=INDEX('Valo FX'!$R:$R,MATCH($A5,'Valo FX'!$A:$A,0)),INDEX(Base!$V:$V,MATCH($A5,Base!$A:$A,0)),0))) -> 0 | D5: =IF(D$1<INDEX('Valo FX'!$Q:$Q,MATCH($A5,'Valo FX'!$A:$A,0)),0,IF(D$1<INDEX('Valo FX'!$R:$R,MATCH($A5,'Valo FX'!$A:$A,0)),INDEX(Base!$U:$U,MATCH($A5,Base!$A:$A,0)),IF(D$1=INDEX('Valo FX'!$R:$R,MATCH($A5,'Valo FX'!$A:$A,0)),INDEX(Base!$V:$V,MATCH($A5,Base!$A:$A,0)),0))) -> 0 | E5: =IF(E$1<INDEX('Valo FX'!$Q:$Q,MATCH($A5,'Valo FX'!$A:$A,0)),0,IF(E$1<INDEX('Valo FX'!$R:$R,MATCH($A5,'Valo FX'!$A:$A,0)),INDEX(Base!$U:$U,MATCH($A5,Base!$A:$A,0)),IF(E$1=INDEX('Valo FX'!$R:$R,MATCH($A5,'Valo FX'!$A:$A,0)),INDEX(Base!$V:$V,MATCH($A5,Base!$A:$A,0)),0))) -> 0 | F5: =IF(F$1<INDEX('Valo FX'!$Q:$Q,MATCH($A5,'Valo FX'!$A:$A,0)),0,IF(F$1<INDEX('Valo FX'!$R:$R,MATCH($A5,'Valo FX'!$A:$A,0)),INDEX(Base!$U:$U,MATCH($A5,Base!$A:$A,0)),IF(F$1=INDEX('Valo FX'!$R:$R,MATCH($A5,'Valo FX'!$A:$A,0)),INDEX(Base!$V:$V,MATCH($A5,Base!$A:$A,0)),0))) -> 0 | G5: =IF(G$1<INDEX('Valo FX'!$Q:$Q,MATCH($A5,'Valo FX'!$A:$A,0)),0,IF(G$1<INDEX('Valo FX'!$R:$R,MATCH($A5,'Valo FX'!$A:$A,0)),INDEX(Base!$U:$U,MATCH($A5,Base!$A:$A,0)),IF(G$1=INDEX('Valo FX'!$R:$R,MATCH($A5,'Valo FX'!$A:$A,0)),INDEX(Base!$V:$V,MATCH($A5,Base!$A:$A,0)),0))) -> 0 | H5: =IF(H$1<INDEX('Valo FX'!$Q:$Q,MATCH($A5,'Valo FX'!$A:$A,0)),0,IF(H$1<INDEX('Valo FX'!$R:$R,MATCH($A5,'Valo FX'!$A:$A,0)),INDEX(Base!$U:$U,MATCH($A5,Base!$A:$A,0)),IF(H$1=INDEX('Valo FX'!$R:$R,MATCH($A5,'Valo FX'!$A:$A,0)),INDEX(Base!$V:$V,MATCH($A5,Base!$A:$A,0)),0))) -> 0 | I5: =IF(I$1<INDEX('Valo FX'!$Q:$Q,MATCH($A5,'Valo FX'!$A:$A,0)),0,IF(I$1<INDEX('Valo FX'!$R:$R,MATCH($A5,'Valo FX'!$A:$A,0)),INDEX(Base!$U:$U,MATCH($A5,Base!$A:$A,0)),IF(I$1=INDEX('Valo FX'!$R:$R,MATCH($A5,'Valo FX'!$A:$A,0)),INDEX(Base!$V:$V,MATCH($A5,Base!$A:$A,0)),0))) -> 6.402808 | J5: =IF(J$1<INDEX('Valo FX'!$Q:$Q,MATCH($A5,'Valo FX'!$A:$A,0)),0,IF(J$1<INDEX('Valo FX'!$R:$R,MATCH($A5,'Valo FX'!$A:$A,0)),INDEX(Base!$U:$U,MATCH($A5,Base!$A:$A,0)),IF(J$1=INDEX('Valo FX'!$R:$R,MATCH($A5,'Valo FX'!$A:$A,0)),INDEX(Base!$V:$V,MATCH($A5,Base!$A:$A,0)),0))) -> 6.402808 | ... MY5: =IF(MY$1<INDEX('Valo FX'!$Q:$Q,MATCH($A5,'Valo FX'!$A:$A,0)),0,IF(MY$1<INDEX('Valo FX'!$R:$R,MATCH($A5,'Valo FX'!$A:$A,0)),INDEX(Base!$U:$U,MATCH($A5,Base!$A:$A,0)),IF(MY$1=INDEX('Valo FX'!$R:$R,MATCH($A5,'Valo FX'!$A:$A,0)),INDEX(Base!$V:$V,MATCH($A5,Base!$A:$A,0)),0))) -> 0
A6: =+'Valo FX'!A7 -> 4 | B6: =-'Valo FX'!T7 -> -1772.9012 | C6: =IF(C$1<INDEX('Valo FX'!$Q:$Q,MATCH($A6,'Valo FX'!$A:$A,0)),0,IF(C$1<INDEX('Valo FX'!$R:$R,MATCH($A6,'Valo FX'!$A:$A,0)),INDEX(Base!$U:$U,MATCH($A6,Base!$A:$A,0)),IF(C$1=INDEX('Valo FX'!$R:$R,MATCH($A6,'Valo FX'!$A:$A,0)),INDEX(Base!$V:$V,MATCH($A6,Base!$A:$A,0)),0))) -> 0 | D6: =IF(D$1<INDEX('Valo FX'!$Q:$Q,MATCH($A6,'Valo FX'!$A:$A,0)),0,IF(D$1<INDEX('Valo FX'!$R:$R,MATCH($A6,'Valo FX'!$A:$A,0)),INDEX(Base!$U:$U,MATCH($A6,Base!$A:$A,0)),IF(D$1=INDEX('Valo FX'!$R:$R,MATCH($A6,'Valo FX'!$A:$A,0)),INDEX(Base!$V:$V,MATCH($A6,Base!$A:$A,0)),0))) -> 0 | E6: =IF(E$1<INDEX('Valo FX'!$Q:$Q,MATCH($A6,'Valo FX'!$A:$A,0)),0,IF(E$1<INDEX('Valo FX'!$R:$R,MATCH($A6,'Valo FX'!$A:$A,0)),INDEX(Base!$U:$U,MATCH($A6,Base!$A:$A,0)),IF(E$1=INDEX('Valo FX'!$R:$R,MATCH($A6,'Valo FX'!$A:$A,0)),INDEX(Base!$V:$V,MATCH($A6,Base!$A:$A,0)),0))) -> 0 | F6: =IF(F$1<INDEX('Valo FX'!$Q:$Q,MATCH($A6,'Valo FX'!$A:$A,0)),0,IF(F$1<INDEX('Valo FX'!$R:$R,MATCH($A6,'Valo FX'!$A:$A,0)),INDEX(Base!$U:$U,MATCH($A6,Base!$A:$A,0)),IF(F$1=INDEX('Valo FX'!$R:$R,MATCH($A6,'Valo FX'!$A:$A,0)),INDEX(Base!$V:$V,MATCH($A6,Base!$A:$A,0)),0))) -> 0 | G6: =IF(G$1<INDEX('Valo FX'!$Q:$Q,MATCH($A6,'Valo FX'!$A:$A,0)),0,IF(G$1<INDEX('Valo FX'!$R:$R,MATCH($A6,'Valo FX'!$A:$A,0)),INDEX(Base!$U:$U,MATCH($A6,Base!$A:$A,0)),IF(G$1=INDEX('Valo FX'!$R:$R,MATCH($A6,'Valo FX'!$A:$A,0)),INDEX(Base!$V:$V,MATCH($A6,Base!$A:$A,0)),0))) -> 0 | H6: =IF(H$1<INDEX('Valo FX'!$Q:$Q,MATCH($A6,'Valo FX'!$A:$A,0)),0,IF(H$1<INDEX('Valo FX'!$R:$R,MATCH($A6,'Valo FX'!$A:$A,0)),INDEX(Base!$U:$U,MATCH($A6,Base!$A:$A,0)),IF(H$1=INDEX('Valo FX'!$R:$R,MATCH($A6,'Valo FX'!$A:$A,0)),INDEX(Base!$V:$V,MATCH($A6,Base!$A:$A,0)),0))) -> 0 | I6: =IF(I$1<INDEX('Valo FX'!$Q:$Q,MATCH($A6,'Valo FX'!$A:$A,0)),0,IF(I$1<INDEX('Valo FX'!$R:$R,MATCH($A6,'Valo FX'!$A:$A,0)),INDEX(Base!$U:$U,MATCH($A6,Base!$A:$A,0)),IF(I$1=INDEX('Valo FX'!$R:$R,MATCH($A6,'Valo FX'!$A:$A,0)),INDEX(Base!$V:$V,MATCH($A6,Base!$A:$A,0)),0))) -> 13.571168 | J6: =IF(J$1<INDEX('Valo FX'!$Q:$Q,MATCH($A6,'Valo FX'!$A:$A,0)),0,IF(J$1<INDEX('Valo FX'!$R:$R,MATCH($A6,'Valo FX'!$A:$A,0)),INDEX(Base!$U:$U,MATCH($A6,Base!$A:$A,0)),IF(J$1=INDEX('Valo FX'!$R:$R,MATCH($A6,'Valo FX'!$A:$A,0)),INDEX(Base!$V:$V,MATCH($A6,Base!$A:$A,0)),0))) -> 13.571168 | ... MY6: =IF(MY$1<INDEX('Valo FX'!$Q:$Q,MATCH($A6,'Valo FX'!$A:$A,0)),0,IF(MY$1<INDEX('Valo FX'!$R:$R,MATCH($A6,'Valo FX'!$A:$A,0)),INDEX(Base!$U:$U,MATCH($A6,Base!$A:$A,0)),IF(MY$1=INDEX('Valo FX'!$R:$R,MATCH($A6,'Valo FX'!$A:$A,0)),INDEX(Base!$V:$V,MATCH($A6,Base!$A:$A,0)),0))) -> 0
A7: =+'Valo FX'!A8 -> 5 | B7: =-'Valo FX'!T8 -> -1613.0553 | C7: =IF(C$1<INDEX('Valo FX'!$Q:$Q,MATCH($A7,'Valo FX'!$A:$A,0)),0,IF(C$1<INDEX('Valo FX'!$R:$R,MATCH($A7,'Valo FX'!$A:$A,0)),INDEX(Base!$U:$U,MATCH($A7,Base!$A:$A,0)),IF(C$1=INDEX('Valo FX'!$R:$R,MATCH($A7,'Valo FX'!$A:$A,0)),INDEX(Base!$V:$V,MATCH($A7,Base!$A:$A,0)),0))) -> 0 | D7: =IF(D$1<INDEX('Valo FX'!$Q:$Q,MATCH($A7,'Valo FX'!$A:$A,0)),0,IF(D$1<INDEX('Valo FX'!$R:$R,MATCH($A7,'Valo FX'!$A:$A,0)),INDEX(Base!$U:$U,MATCH($A7,Base!$A:$A,0)),IF(D$1=INDEX('Valo FX'!$R:$R,MATCH($A7,'Valo FX'!$A:$A,0)),INDEX(Base!$V:$V,MATCH($A7,Base!$A:$A,0)),0))) -> 0 | E7: =IF(E$1<INDEX('Valo FX'!$Q:$Q,MATCH($A7,'Valo FX'!$A:$A,0)),0,IF(E$1<INDEX('Valo FX'!$R:$R,MATCH($A7,'Valo FX'!$A:$A,0)),INDEX(Base!$U:$U,MATCH($A7,Base!$A:$A,0)),IF(E$1=INDEX('Valo FX'!$R:$R,MATCH($A7,'Valo FX'!$A:$A,0)),INDEX(Base!$V:$V,MATCH($A7,Base!$A:$A,0)),0))) -> 0 | F7: =IF(F$1<INDEX('Valo FX'!$Q:$Q,MATCH($A7,'Valo FX'!$A:$A,0)),0,IF(F$1<INDEX('Valo FX'!$R:$R,MATCH($A7,'Valo FX'!$A:$A,0)),INDEX(Base!$U:$U,MATCH($A7,Base!$A:$A,0)),IF(F$1=INDEX('Valo FX'!$R:$R,MATCH($A7,'Valo FX'!$A:$A,0)),INDEX(Base!$V:$V,MATCH($A7,Base!$A:$A,0)),0))) -> 0 | G7: =IF(G$1<INDEX('Valo FX'!$Q:$Q,MATCH($A7,'Valo FX'!$A:$A,0)),0,IF(G$1<INDEX('Valo FX'!$R:$R,MATCH($A7,'Valo FX'!$A:$A,0)),INDEX(Base!$U:$U,MATCH($A7,Base!$A:$A,0)),IF(G$1=INDEX('Valo FX'!$R:$R,MATCH($A7,'Valo FX'!$A:$A,0)),INDEX(Base!$V:$V,MATCH($A7,Base!$A:$A,0)),0))) -> 0 | H7: =IF(H$1<INDEX('Valo FX'!$Q:$Q,MATCH($A7,'Valo FX'!$A:$A,0)),0,IF(H$1<INDEX('Valo FX'!$R:$R,MATCH($A7,'Valo FX'!$A:$A,0)),INDEX(Base!$U:$U,MATCH($A7,Base!$A:$A,0)),IF(H$1=INDEX('Valo FX'!$R:$R,MATCH($A7,'Valo FX'!$A:$A,0)),INDEX(Base!$V:$V,MATCH($A7,Base!$A:$A,0)),0))) -> 0 | I7: =IF(I$1<INDEX('Valo FX'!$Q:$Q,MATCH($A7,'Valo FX'!$A:$A,0)),0,IF(I$1<INDEX('Valo FX'!$R:$R,MATCH($A7,'Valo FX'!$A:$A,0)),INDEX(Base!$U:$U,MATCH($A7,Base!$A:$A,0)),IF(I$1=INDEX('Valo FX'!$R:$R,MATCH($A7,'Valo FX'!$A:$A,0)),INDEX(Base!$V:$V,MATCH($A7,Base!$A:$A,0)),0))) -> 10.98688 | J7: =IF(J$1<INDEX('Valo FX'!$Q:$Q,MATCH($A7,'Valo FX'!$A:$A,0)),0,IF(J$1<INDEX('Valo FX'!$R:$R,MATCH($A7,'Valo FX'!$A:$A,0)),INDEX(Base!$U:$U,MATCH($A7,Base!$A:$A,0)),IF(J$1=INDEX('Valo FX'!$R:$R,MATCH($A7,'Valo FX'!$A:$A,0)),INDEX(Base!$V:$V,MATCH($A7,Base!$A:$A,0)),0))) -> 10.98688 | ... MY7: =IF(MY$1<INDEX('Valo FX'!$Q:$Q,MATCH($A7,'Valo FX'!$A:$A,0)),0,IF(MY$1<INDEX('Valo FX'!$R:$R,MATCH($A7,'Valo FX'!$A:$A,0)),INDEX(Base!$U:$U,MATCH($A7,Base!$A:$A,0)),IF(MY$1=INDEX('Valo FX'!$R:$R,MATCH($A7,'Valo FX'!$A:$A,0)),INDEX(Base!$V:$V,MATCH($A7,Base!$A:$A,0)),0))) -> 11.27858
A8: =+'Valo FX'!A9 -> 6 | B8: =-'Valo FX'!T9 -> -1723.2178 | C8: =IF(C$1<INDEX('Valo FX'!$Q:$Q,MATCH($A8,'Valo FX'!$A:$A,0)),0,IF(C$1<INDEX('Valo FX'!$R:$R,MATCH($A8,'Valo FX'!$A:$A,0)),INDEX(Base!$U:$U,MATCH($A8,Base!$A:$A,0)),IF(C$1=INDEX('Valo FX'!$R:$R,MATCH($A8,'Valo FX'!$A:$A,0)),INDEX(Base!$V:$V,MATCH($A8,Base!$A:$A,0)),0))) -> 0 | D8: =IF(D$1<INDEX('Valo FX'!$Q:$Q,MATCH($A8,'Valo FX'!$A:$A,0)),0,IF(D$1<INDEX('Valo FX'!$R:$R,MATCH($A8,'Valo FX'!$A:$A,0)),INDEX(Base!$U:$U,MATCH($A8,Base!$A:$A,0)),IF(D$1=INDEX('Valo FX'!$R:$R,MATCH($A8,'Valo FX'!$A:$A,0)),INDEX(Base!$V:$V,MATCH($A8,Base!$A:$A,0)),0))) -> 0 | E8: =IF(E$1<INDEX('Valo FX'!$Q:$Q,MATCH($A8,'Valo FX'!$A:$A,0)),0,IF(E$1<INDEX('Valo FX'!$R:$R,MATCH($A8,'Valo FX'!$A:$A,0)),INDEX(Base!$U:$U,MATCH($A8,Base!$A:$A,0)),IF(E$1=INDEX('Valo FX'!$R:$R,MATCH($A8,'Valo FX'!$A:$A,0)),INDEX(Base!$V:$V,MATCH($A8,Base!$A:$A,0)),0))) -> 0 | F8: =IF(F$1<INDEX('Valo FX'!$Q:$Q,MATCH($A8,'Valo FX'!$A:$A,0)),0,IF(F$1<INDEX('Valo FX'!$R:$R,MATCH($A8,'Valo FX'!$A:$A,0)),INDEX(Base!$U:$U,MATCH($A8,Base!$A:$A,0)),IF(F$1=INDEX('Valo FX'!$R:$R,MATCH($A8,'Valo FX'!$A:$A,0)),INDEX(Base!$V:$V,MATCH($A8,Base!$A:$A,0)),0))) -> 0 | G8: =IF(G$1<INDEX('Valo FX'!$Q:$Q,MATCH($A8,'Valo FX'!$A:$A,0)),0,IF(G$1<INDEX('Valo FX'!$R:$R,MATCH($A8,'Valo FX'!$A:$A,0)),INDEX(Base!$U:$U,MATCH($A8,Base!$A:$A,0)),IF(G$1=INDEX('Valo FX'!$R:$R,MATCH($A8,'Valo FX'!$A:$A,0)),INDEX(Base!$V:$V,MATCH($A8,Base!$A:$A,0)),0))) -> 0 | H8: =IF(H$1<INDEX('Valo FX'!$Q:$Q,MATCH($A8,'Valo FX'!$A:$A,0)),0,IF(H$1<INDEX('Valo FX'!$R:$R,MATCH($A8,'Valo FX'!$A:$A,0)),INDEX(Base!$U:$U,MATCH($A8,Base!$A:$A,0)),IF(H$1=INDEX('Valo FX'!$R:$R,MATCH($A8,'Valo FX'!$A:$A,0)),INDEX(Base!$V:$V,MATCH($A8,Base!$A:$A,0)),0))) -> 0 | I8: =IF(I$1<INDEX('Valo FX'!$Q:$Q,MATCH($A8,'Valo FX'!$A:$A,0)),0,IF(I$1<INDEX('Valo FX'!$R:$R,MATCH($A8,'Valo FX'!$A:$A,0)),INDEX(Base!$U:$U,MATCH($A8,Base!$A:$A,0)),IF(I$1=INDEX('Valo FX'!$R:$R,MATCH($A8,'Valo FX'!$A:$A,0)),INDEX(Base!$V:$V,MATCH($A8,Base!$A:$A,0)),0))) -> 12.508353 | J8: =IF(J$1<INDEX('Valo FX'!$Q:$Q,MATCH($A8,'Valo FX'!$A:$A,0)),0,IF(J$1<INDEX('Valo FX'!$R:$R,MATCH($A8,'Valo FX'!$A:$A,0)),INDEX(Base!$U:$U,MATCH($A8,Base!$A:$A,0)),IF(J$1=INDEX('Valo FX'!$R:$R,MATCH($A8,'Valo FX'!$A:$A,0)),INDEX(Base!$V:$V,MATCH($A8,Base!$A:$A,0)),0))) -> 12.508353 | ... MY8: =IF(MY$1<INDEX('Valo FX'!$Q:$Q,MATCH($A8,'Valo FX'!$A:$A,0)),0,IF(MY$1<INDEX('Valo FX'!$R:$R,MATCH($A8,'Valo FX'!$A:$A,0)),INDEX(Base!$U:$U,MATCH($A8,Base!$A:$A,0)),IF(MY$1=INDEX('Valo FX'!$R:$R,MATCH($A8,'Valo FX'!$A:$A,0)),INDEX(Base!$V:$V,MATCH($A8,Base!$A:$A,0)),0))) -> 0
A9: =+'Valo FX'!A10 -> 7 | B9: =-'Valo FX'!T10 -> -1695.5741 | C9: =IF(C$1<INDEX('Valo FX'!$Q:$Q,MATCH($A9,'Valo FX'!$A:$A,0)),0,IF(C$1<INDEX('Valo FX'!$R:$R,MATCH($A9,'Valo FX'!$A:$A,0)),INDEX(Base!$U:$U,MATCH($A9,Base!$A:$A,0)),IF(C$1=INDEX('Valo FX'!$R:$R,MATCH($A9,'Valo FX'!$A:$A,0)),INDEX(Base!$V:$V,MATCH($A9,Base!$A:$A,0)),0))) -> 0 | D9: =IF(D$1<INDEX('Valo FX'!$Q:$Q,MATCH($A9,'Valo FX'!$A:$A,0)),0,IF(D$1<INDEX('Valo FX'!$R:$R,MATCH($A9,'Valo FX'!$A:$A,0)),INDEX(Base!$U:$U,MATCH($A9,Base!$A:$A,0)),IF(D$1=INDEX('Valo FX'!$R:$R,MATCH($A9,'Valo FX'!$A:$A,0)),INDEX(Base!$V:$V,MATCH($A9,Base!$A:$A,0)),0))) -> 0 | E9: =IF(E$1<INDEX('Valo FX'!$Q:$Q,MATCH($A9,'Valo FX'!$A:$A,0)),0,IF(E$1<INDEX('Valo FX'!$R:$R,MATCH($A9,'Valo FX'!$A:$A,0)),INDEX(Base!$U:$U,MATCH($A9,Base!$A:$A,0)),IF(E$1=INDEX('Valo FX'!$R:$R,MATCH($A9,'Valo FX'!$A:$A,0)),INDEX(Base!$V:$V,MATCH($A9,Base!$A:$A,0)),0))) -> 0 | F9: =IF(F$1<INDEX('Valo FX'!$Q:$Q,MATCH($A9,'Valo FX'!$A:$A,0)),0,IF(F$1<INDEX('Valo FX'!$R:$R,MATCH($A9,'Valo FX'!$A:$A,0)),INDEX(Base!$U:$U,MATCH($A9,Base!$A:$A,0)),IF(F$1=INDEX('Valo FX'!$R:$R,MATCH($A9,'Valo FX'!$A:$A,0)),INDEX(Base!$V:$V,MATCH($A9,Base!$A:$A,0)),0))) -> 0 | G9: =IF(G$1<INDEX('Valo FX'!$Q:$Q,MATCH($A9,'Valo FX'!$A:$A,0)),0,IF(G$1<INDEX('Valo FX'!$R:$R,MATCH($A9,'Valo FX'!$A:$A,0)),INDEX(Base!$U:$U,MATCH($A9,Base!$A:$A,0)),IF(G$1=INDEX('Valo FX'!$R:$R,MATCH($A9,'Valo FX'!$A:$A,0)),INDEX(Base!$V:$V,MATCH($A9,Base!$A:$A,0)),0))) -> 0 | H9: =IF(H$1<INDEX('Valo FX'!$Q:$Q,MATCH($A9,'Valo FX'!$A:$A,0)),0,IF(H$1<INDEX('Valo FX'!$R:$R,MATCH($A9,'Valo FX'!$A:$A,0)),INDEX(Base!$U:$U,MATCH($A9,Base!$A:$A,0)),IF(H$1=INDEX('Valo FX'!$R:$R,MATCH($A9,'Valo FX'!$A:$A,0)),INDEX(Base!$V:$V,MATCH($A9,Base!$A:$A,0)),0))) -> 0 | I9: =IF(I$1<INDEX('Valo FX'!$Q:$Q,MATCH($A9,'Valo FX'!$A:$A,0)),0,IF(I$1<INDEX('Valo FX'!$R:$R,MATCH($A9,'Valo FX'!$A:$A,0)),INDEX(Base!$U:$U,MATCH($A9,Base!$A:$A,0)),IF(I$1=INDEX('Valo FX'!$R:$R,MATCH($A9,'Valo FX'!$A:$A,0)),INDEX(Base!$V:$V,MATCH($A9,Base!$A:$A,0)),0))) -> 11.548934 | J9: =IF(J$1<INDEX('Valo FX'!$Q:$Q,MATCH($A9,'Valo FX'!$A:$A,0)),0,IF(J$1<INDEX('Valo FX'!$R:$R,MATCH($A9,'Valo FX'!$A:$A,0)),INDEX(Base!$U:$U,MATCH($A9,Base!$A:$A,0)),IF(J$1=INDEX('Valo FX'!$R:$R,MATCH($A9,'Valo FX'!$A:$A,0)),INDEX(Base!$V:$V,MATCH($A9,Base!$A:$A,0)),0))) -> 11.548934 | ... MY9: =IF(MY$1<INDEX('Valo FX'!$Q:$Q,MATCH($A9,'Valo FX'!$A:$A,0)),0,IF(MY$1<INDEX('Valo FX'!$R:$R,MATCH($A9,'Valo FX'!$A:$A,0)),INDEX(Base!$U:$U,MATCH($A9,Base!$A:$A,0)),IF(MY$1=INDEX('Valo FX'!$R:$R,MATCH($A9,'Valo FX'!$A:$A,0)),INDEX(Base!$V:$V,MATCH($A9,Base!$A:$A,0)),0))) -> 11.855557
A10: =+'Valo FX'!A11 -> 8 | B10: =-'Valo FX'!T11 -> -812.31826 | C10: =IF(C$1<INDEX('Valo FX'!$Q:$Q,MATCH($A10,'Valo FX'!$A:$A,0)),0,IF(C$1<INDEX('Valo FX'!$R:$R,MATCH($A10,'Valo FX'!$A:$A,0)),INDEX(Base!$U:$U,MATCH($A10,Base!$A:$A,0)),IF(C$1=INDEX('Valo FX'!$R:$R,MATCH($A10,'Valo FX'!$A:$A,0)),INDEX(Base!$V:$V,MATCH($A10,Base!$A:$A,0)),0))) -> 0 | D10: =IF(D$1<INDEX('Valo FX'!$Q:$Q,MATCH($A10,'Valo FX'!$A:$A,0)),0,IF(D$1<INDEX('Valo FX'!$R:$R,MATCH($A10,'Valo FX'!$A:$A,0)),INDEX(Base!$U:$U,MATCH($A10,Base!$A:$A,0)),IF(D$1=INDEX('Valo FX'!$R:$R,MATCH($A10,'Valo FX'!$A:$A,0)),INDEX(Base!$V:$V,MATCH($A10,Base!$A:$A,0)),0))) -> 0 | E10: =IF(E$1<INDEX('Valo FX'!$Q:$Q,MATCH($A10,'Valo FX'!$A:$A,0)),0,IF(E$1<INDEX('Valo FX'!$R:$R,MATCH($A10,'Valo FX'!$A:$A,0)),INDEX(Base!$U:$U,MATCH($A10,Base!$A:$A,0)),IF(E$1=INDEX('Valo FX'!$R:$R,MATCH($A10,'Valo FX'!$A:$A,0)),INDEX(Base!$V:$V,MATCH($A10,Base!$A:$A,0)),0))) -> 0 | F10: =IF(F$1<INDEX('Valo FX'!$Q:$Q,MATCH($A10,'Valo FX'!$A:$A,0)),0,IF(F$1<INDEX('Valo FX'!$R:$R,MATCH($A10,'Valo FX'!$A:$A,0)),INDEX(Base!$U:$U,MATCH($A10,Base!$A:$A,0)),IF(F$1=INDEX('Valo FX'!$R:$R,MATCH($A10,'Valo FX'!$A:$A,0)),INDEX(Base!$V:$V,MATCH($A10,Base!$A:$A,0)),0))) -> 0 | G10: =IF(G$1<INDEX('Valo FX'!$Q:$Q,MATCH($A10,'Valo FX'!$A:$A,0)),0,IF(G$1<INDEX('Valo FX'!$R:$R,MATCH($A10,'Valo FX'!$A:$A,0)),INDEX(Base!$U:$U,MATCH($A10,Base!$A:$A,0)),IF(G$1=INDEX('Valo FX'!$R:$R,MATCH($A10,'Valo FX'!$A:$A,0)),INDEX(Base!$V:$V,MATCH($A10,Base!$A:$A,0)),0))) -> 0 | H10: =IF(H$1<INDEX('Valo FX'!$Q:$Q,MATCH($A10,'Valo FX'!$A:$A,0)),0,IF(H$1<INDEX('Valo FX'!$R:$R,MATCH($A10,'Valo FX'!$A:$A,0)),INDEX(Base!$U:$U,MATCH($A10,Base!$A:$A,0)),IF(H$1=INDEX('Valo FX'!$R:$R,MATCH($A10,'Valo FX'!$A:$A,0)),INDEX(Base!$V:$V,MATCH($A10,Base!$A:$A,0)),0))) -> 0 | I10: =IF(I$1<INDEX('Valo FX'!$Q:$Q,MATCH($A10,'Valo FX'!$A:$A,0)),0,IF(I$1<INDEX('Valo FX'!$R:$R,MATCH($A10,'Valo FX'!$A:$A,0)),INDEX(Base!$U:$U,MATCH($A10,Base!$A:$A,0)),IF(I$1=INDEX('Valo FX'!$R:$R,MATCH($A10,'Valo FX'!$A:$A,0)),INDEX(Base!$V:$V,MATCH($A10,Base!$A:$A,0)),0))) -> 5.532881 | J10: =IF(J$1<INDEX('Valo FX'!$Q:$Q,MATCH($A10,'Valo FX'!$A:$A,0)),0,IF(J$1<INDEX('Valo FX'!$R:$R,MATCH($A10,'Valo FX'!$A:$A,0)),INDEX(Base!$U:$U,MATCH($A10,Base!$A:$A,0)),IF(J$1=INDEX('Valo FX'!$R:$R,MATCH($A10,'Valo FX'!$A:$A,0)),INDEX(Base!$V:$V,MATCH($A10,Base!$A:$A,0)),0))) -> 5.532881 | ... MY10: =IF(MY$1<INDEX('Valo FX'!$Q:$Q,MATCH($A10,'Valo FX'!$A:$A,0)),0,IF(MY$1<INDEX('Valo FX'!$R:$R,MATCH($A10,'Valo FX'!$A:$A,0)),INDEX(Base!$U:$U,MATCH($A10,Base!$A:$A,0)),IF(MY$1=INDEX('Valo FX'!$R:$R,MATCH($A10,'Valo FX'!$A:$A,0)),INDEX(Base!$V:$V,MATCH($A10,Base!$A:$A,0)),0))) -> 5.679779
A11: =+'Valo FX'!A12 -> 9 | B11: =-'Valo FX'!T12 -> -781.43864 | C11: =IF(C$1<INDEX('Valo FX'!$Q:$Q,MATCH($A11,'Valo FX'!$A:$A,0)),0,IF(C$1<INDEX('Valo FX'!$R:$R,MATCH($A11,'Valo FX'!$A:$A,0)),INDEX(Base!$U:$U,MATCH($A11,Base!$A:$A,0)),IF(C$1=INDEX('Valo FX'!$R:$R,MATCH($A11,'Valo FX'!$A:$A,0)),INDEX(Base!$V:$V,MATCH($A11,Base!$A:$A,0)),0))) -> 0 | D11: =IF(D$1<INDEX('Valo FX'!$Q:$Q,MATCH($A11,'Valo FX'!$A:$A,0)),0,IF(D$1<INDEX('Valo FX'!$R:$R,MATCH($A11,'Valo FX'!$A:$A,0)),INDEX(Base!$U:$U,MATCH($A11,Base!$A:$A,0)),IF(D$1=INDEX('Valo FX'!$R:$R,MATCH($A11,'Valo FX'!$A:$A,0)),INDEX(Base!$V:$V,MATCH($A11,Base!$A:$A,0)),0))) -> 0 | E11: =IF(E$1<INDEX('Valo FX'!$Q:$Q,MATCH($A11,'Valo FX'!$A:$A,0)),0,IF(E$1<INDEX('Valo FX'!$R:$R,MATCH($A11,'Valo FX'!$A:$A,0)),INDEX(Base!$U:$U,MATCH($A11,Base!$A:$A,0)),IF(E$1=INDEX('Valo FX'!$R:$R,MATCH($A11,'Valo FX'!$A:$A,0)),INDEX(Base!$V:$V,MATCH($A11,Base!$A:$A,0)),0))) -> 0 | F11: =IF(F$1<INDEX('Valo FX'!$Q:$Q,MATCH($A11,'Valo FX'!$A:$A,0)),0,IF(F$1<INDEX('Valo FX'!$R:$R,MATCH($A11,'Valo FX'!$A:$A,0)),INDEX(Base!$U:$U,MATCH($A11,Base!$A:$A,0)),IF(F$1=INDEX('Valo FX'!$R:$R,MATCH($A11,'Valo FX'!$A:$A,0)),INDEX(Base!$V:$V,MATCH($A11,Base!$A:$A,0)),0))) -> 0 | G11: =IF(G$1<INDEX('Valo FX'!$Q:$Q,MATCH($A11,'Valo FX'!$A:$A,0)),0,IF(G$1<INDEX('Valo FX'!$R:$R,MATCH($A11,'Valo FX'!$A:$A,0)),INDEX(Base!$U:$U,MATCH($A11,Base!$A:$A,0)),IF(G$1=INDEX('Valo FX'!$R:$R,MATCH($A11,'Valo FX'!$A:$A,0)),INDEX(Base!$V:$V,MATCH($A11,Base!$A:$A,0)),0))) -> 0 | H11: =IF(H$1<INDEX('Valo FX'!$Q:$Q,MATCH($A11,'Valo FX'!$A:$A,0)),0,IF(H$1<INDEX('Valo FX'!$R:$R,MATCH($A11,'Valo FX'!$A:$A,0)),INDEX(Base!$U:$U,MATCH($A11,Base!$A:$A,0)),IF(H$1=INDEX('Valo FX'!$R:$R,MATCH($A11,'Valo FX'!$A:$A,0)),INDEX(Base!$V:$V,MATCH($A11,Base!$A:$A,0)),0))) -> 0 | I11: =IF(I$1<INDEX('Valo FX'!$Q:$Q,MATCH($A11,'Valo FX'!$A:$A,0)),0,IF(I$1<INDEX('Valo FX'!$R:$R,MATCH($A11,'Valo FX'!$A:$A,0)),INDEX(Base!$U:$U,MATCH($A11,Base!$A:$A,0)),IF(I$1=INDEX('Valo FX'!$R:$R,MATCH($A11,'Valo FX'!$A:$A,0)),INDEX(Base!$V:$V,MATCH($A11,Base!$A:$A,0)),0))) -> 6.593 | J11: =IF(J$1<INDEX('Valo FX'!$Q:$Q,MATCH($A11,'Valo FX'!$A:$A,0)),0,IF(J$1<INDEX('Valo FX'!$R:$R,MATCH($A11,'Valo FX'!$A:$A,0)),INDEX(Base!$U:$U,MATCH($A11,Base!$A:$A,0)),IF(J$1=INDEX('Valo FX'!$R:$R,MATCH($A11,'Valo FX'!$A:$A,0)),INDEX(Base!$V:$V,MATCH($A11,Base!$A:$A,0)),0))) -> 6.593 | ... MY11: =IF(MY$1<INDEX('Valo FX'!$Q:$Q,MATCH($A11,'Valo FX'!$A:$A,0)),0,IF(MY$1<INDEX('Valo FX'!$R:$R,MATCH($A11,'Valo FX'!$A:$A,0)),INDEX(Base!$U:$U,MATCH($A11,Base!$A:$A,0)),IF(MY$1=INDEX('Valo FX'!$R:$R,MATCH($A11,'Valo FX'!$A:$A,0)),INDEX(Base!$V:$V,MATCH($A11,Base!$A:$A,0)),0))) -> 0
A12: =+'Valo FX'!A13 -> 10 | B12: =-'Valo FX'!T13 -> -1738.224 | C12: =IF(C$1<INDEX('Valo FX'!$Q:$Q,MATCH($A12,'Valo FX'!$A:$A,0)),0,IF(C$1<INDEX('Valo FX'!$R:$R,MATCH($A12,'Valo FX'!$A:$A,0)),INDEX(Base!$U:$U,MATCH($A12,Base!$A:$A,0)),IF(C$1=INDEX('Valo FX'!$R:$R,MATCH($A12,'Valo FX'!$A:$A,0)),INDEX(Base!$V:$V,MATCH($A12,Base!$A:$A,0)),0))) -> 0 | D12: =IF(D$1<INDEX('Valo FX'!$Q:$Q,MATCH($A12,'Valo FX'!$A:$A,0)),0,IF(D$1<INDEX('Valo FX'!$R:$R,MATCH($A12,'Valo FX'!$A:$A,0)),INDEX(Base!$U:$U,MATCH($A12,Base!$A:$A,0)),IF(D$1=INDEX('Valo FX'!$R:$R,MATCH($A12,'Valo FX'!$A:$A,0)),INDEX(Base!$V:$V,MATCH($A12,Base!$A:$A,0)),0))) -> 0 | E12: =IF(E$1<INDEX('Valo FX'!$Q:$Q,MATCH($A12,'Valo FX'!$A:$A,0)),0,IF(E$1<INDEX('Valo FX'!$R:$R,MATCH($A12,'Valo FX'!$A:$A,0)),INDEX(Base!$U:$U,MATCH($A12,Base!$A:$A,0)),IF(E$1=INDEX('Valo FX'!$R:$R,MATCH($A12,'Valo FX'!$A:$A,0)),INDEX(Base!$V:$V,MATCH($A12,Base!$A:$A,0)),0))) -> 0 | F12: =IF(F$1<INDEX('Valo FX'!$Q:$Q,MATCH($A12,'Valo FX'!$A:$A,0)),0,IF(F$1<INDEX('Valo FX'!$R:$R,MATCH($A12,'Valo FX'!$A:$A,0)),INDEX(Base!$U:$U,MATCH($A12,Base!$A:$A,0)),IF(F$1=INDEX('Valo FX'!$R:$R,MATCH($A12,'Valo FX'!$A:$A,0)),INDEX(Base!$V:$V,MATCH($A12,Base!$A:$A,0)),0))) -> 0 | G12: =IF(G$1<INDEX('Valo FX'!$Q:$Q,MATCH($A12,'Valo FX'!$A:$A,0)),0,IF(G$1<INDEX('Valo FX'!$R:$R,MATCH($A12,'Valo FX'!$A:$A,0)),INDEX(Base!$U:$U,MATCH($A12,Base!$A:$A,0)),IF(G$1=INDEX('Valo FX'!$R:$R,MATCH($A12,'Valo FX'!$A:$A,0)),INDEX(Base!$V:$V,MATCH($A12,Base!$A:$A,0)),0))) -> 0 | H12: =IF(H$1<INDEX('Valo FX'!$Q:$Q,MATCH($A12,'Valo FX'!$A:$A,0)),0,IF(H$1<INDEX('Valo FX'!$R:$R,MATCH($A12,'Valo FX'!$A:$A,0)),INDEX(Base!$U:$U,MATCH($A12,Base!$A:$A,0)),IF(H$1=INDEX('Valo FX'!$R:$R,MATCH($A12,'Valo FX'!$A:$A,0)),INDEX(Base!$V:$V,MATCH($A12,Base!$A:$A,0)),0))) -> 0 | I12: =IF(I$1<INDEX('Valo FX'!$Q:$Q,MATCH($A12,'Valo FX'!$A:$A,0)),0,IF(I$1<INDEX('Valo FX'!$R:$R,MATCH($A12,'Valo FX'!$A:$A,0)),INDEX(Base!$U:$U,MATCH($A12,Base!$A:$A,0)),IF(I$1=INDEX('Valo FX'!$R:$R,MATCH($A12,'Valo FX'!$A:$A,0)),INDEX(Base!$V:$V,MATCH($A12,Base!$A:$A,0)),0))) -> 11.839432 | J12: =IF(J$1<INDEX('Valo FX'!$Q:$Q,MATCH($A12,'Valo FX'!$A:$A,0)),0,IF(J$1<INDEX('Valo FX'!$R:$R,MATCH($A12,'Valo FX'!$A:$A,0)),INDEX(Base!$U:$U,MATCH($A12,Base!$A:$A,0)),IF(J$1=INDEX('Valo FX'!$R:$R,MATCH($A12,'Valo FX'!$A:$A,0)),INDEX(Base!$V:$V,MATCH($A12,Base!$A:$A,0)),0))) -> 11.839432 | ... MY12: =IF(MY$1<INDEX('Valo FX'!$Q:$Q,MATCH($A12,'Valo FX'!$A:$A,0)),0,IF(MY$1<INDEX('Valo FX'!$R:$R,MATCH($A12,'Valo FX'!$A:$A,0)),INDEX(Base!$U:$U,MATCH($A12,Base!$A:$A,0)),IF(MY$1=INDEX('Valo FX'!$R:$R,MATCH($A12,'Valo FX'!$A:$A,0)),INDEX(Base!$V:$V,MATCH($A12,Base!$A:$A,0)),0))) -> 12.153768
A13: =+'Valo FX'!A14 -> 11 | B13: =-'Valo FX'!T14 -> -904.51418 | C13: =IF(C$1<INDEX('Valo FX'!$Q:$Q,MATCH($A13,'Valo FX'!$A:$A,0)),0,IF(C$1<INDEX('Valo FX'!$R:$R,MATCH($A13,'Valo FX'!$A:$A,0)),INDEX(Base!$U:$U,MATCH($A13,Base!$A:$A,0)),IF(C$1=INDEX('Valo FX'!$R:$R,MATCH($A13,'Valo FX'!$A:$A,0)),INDEX(Base!$V:$V,MATCH($A13,Base!$A:$A,0)),0))) -> 0 | D13: =IF(D$1<INDEX('Valo FX'!$Q:$Q,MATCH($A13,'Valo FX'!$A:$A,0)),0,IF(D$1<INDEX('Valo FX'!$R:$R,MATCH($A13,'Valo FX'!$A:$A,0)),INDEX(Base!$U:$U,MATCH($A13,Base!$A:$A,0)),IF(D$1=INDEX('Valo FX'!$R:$R,MATCH($A13,'Valo FX'!$A:$A,0)),INDEX(Base!$V:$V,MATCH($A13,Base!$A:$A,0)),0))) -> 0 | E13: =IF(E$1<INDEX('Valo FX'!$Q:$Q,MATCH($A13,'Valo FX'!$A:$A,0)),0,IF(E$1<INDEX('Valo FX'!$R:$R,MATCH($A13,'Valo FX'!$A:$A,0)),INDEX(Base!$U:$U,MATCH($A13,Base!$A:$A,0)),IF(E$1=INDEX('Valo FX'!$R:$R,MATCH($A13,'Valo FX'!$A:$A,0)),INDEX(Base!$V:$V,MATCH($A13,Base!$A:$A,0)),0))) -> 0 | F13: =IF(F$1<INDEX('Valo FX'!$Q:$Q,MATCH($A13,'Valo FX'!$A:$A,0)),0,IF(F$1<INDEX('Valo FX'!$R:$R,MATCH($A13,'Valo FX'!$A:$A,0)),INDEX(Base!$U:$U,MATCH($A13,Base!$A:$A,0)),IF(F$1=INDEX('Valo FX'!$R:$R,MATCH($A13,'Valo FX'!$A:$A,0)),INDEX(Base!$V:$V,MATCH($A13,Base!$A:$A,0)),0))) -> 0 | G13: =IF(G$1<INDEX('Valo FX'!$Q:$Q,MATCH($A13,'Valo FX'!$A:$A,0)),0,IF(G$1<INDEX('Valo FX'!$R:$R,MATCH($A13,'Valo FX'!$A:$A,0)),INDEX(Base!$U:$U,MATCH($A13,Base!$A:$A,0)),IF(G$1=INDEX('Valo FX'!$R:$R,MATCH($A13,'Valo FX'!$A:$A,0)),INDEX(Base!$V:$V,MATCH($A13,Base!$A:$A,0)),0))) -> 0 | H13: =IF(H$1<INDEX('Valo FX'!$Q:$Q,MATCH($A13,'Valo FX'!$A:$A,0)),0,IF(H$1<INDEX('Valo FX'!$R:$R,MATCH($A13,'Valo FX'!$A:$A,0)),INDEX(Base!$U:$U,MATCH($A13,Base!$A:$A,0)),IF(H$1=INDEX('Valo FX'!$R:$R,MATCH($A13,'Valo FX'!$A:$A,0)),INDEX(Base!$V:$V,MATCH($A13,Base!$A:$A,0)),0))) -> 0 | I13: =IF(I$1<INDEX('Valo FX'!$Q:$Q,MATCH($A13,'Valo FX'!$A:$A,0)),0,IF(I$1<INDEX('Valo FX'!$R:$R,MATCH($A13,'Valo FX'!$A:$A,0)),INDEX(Base!$U:$U,MATCH($A13,Base!$A:$A,0)),IF(I$1=INDEX('Valo FX'!$R:$R,MATCH($A13,'Valo FX'!$A:$A,0)),INDEX(Base!$V:$V,MATCH($A13,Base!$A:$A,0)),0))) -> 7.236418 | J13: =IF(J$1<INDEX('Valo FX'!$Q:$Q,MATCH($A13,'Valo FX'!$A:$A,0)),0,IF(J$1<INDEX('Valo FX'!$R:$R,MATCH($A13,'Valo FX'!$A:$A,0)),INDEX(Base!$U:$U,MATCH($A13,Base!$A:$A,0)),IF(J$1=INDEX('Valo FX'!$R:$R,MATCH($A13,'Valo FX'!$A:$A,0)),INDEX(Base!$V:$V,MATCH($A13,Base!$A:$A,0)),0))) -> 7.236418 | ... MY13: =IF(MY$1<INDEX('Valo FX'!$Q:$Q,MATCH($A13,'Valo FX'!$A:$A,0)),0,IF(MY$1<INDEX('Valo FX'!$R:$R,MATCH($A13,'Valo FX'!$A:$A,0)),INDEX(Base!$U:$U,MATCH($A13,Base!$A:$A,0)),IF(MY$1=INDEX('Valo FX'!$R:$R,MATCH($A13,'Valo FX'!$A:$A,0)),INDEX(Base!$V:$V,MATCH($A13,Base!$A:$A,0)),0))) -> 0
A14: =+'Valo FX'!A15 -> 12 | B14: =-'Valo FX'!T15 -> -787.48094 | C14: =IF(C$1<INDEX('Valo FX'!$Q:$Q,MATCH($A14,'Valo FX'!$A:$A,0)),0,IF(C$1<INDEX('Valo FX'!$R:$R,MATCH($A14,'Valo FX'!$A:$A,0)),INDEX(Base!$U:$U,MATCH($A14,Base!$A:$A,0)),IF(C$1=INDEX('Valo FX'!$R:$R,MATCH($A14,'Valo FX'!$A:$A,0)),INDEX(Base!$V:$V,MATCH($A14,Base!$A:$A,0)),0))) -> 0 | D14: =IF(D$1<INDEX('Valo FX'!$Q:$Q,MATCH($A14,'Valo FX'!$A:$A,0)),0,IF(D$1<INDEX('Valo FX'!$R:$R,MATCH($A14,'Valo FX'!$A:$A,0)),INDEX(Base!$U:$U,MATCH($A14,Base!$A:$A,0)),IF(D$1=INDEX('Valo FX'!$R:$R,MATCH($A14,'Valo FX'!$A:$A,0)),INDEX(Base!$V:$V,MATCH($A14,Base!$A:$A,0)),0))) -> 0 | E14: =IF(E$1<INDEX('Valo FX'!$Q:$Q,MATCH($A14,'Valo FX'!$A:$A,0)),0,IF(E$1<INDEX('Valo FX'!$R:$R,MATCH($A14,'Valo FX'!$A:$A,0)),INDEX(Base!$U:$U,MATCH($A14,Base!$A:$A,0)),IF(E$1=INDEX('Valo FX'!$R:$R,MATCH($A14,'Valo FX'!$A:$A,0)),INDEX(Base!$V:$V,MATCH($A14,Base!$A:$A,0)),0))) -> 0 | F14: =IF(F$1<INDEX('Valo FX'!$Q:$Q,MATCH($A14,'Valo FX'!$A:$A,0)),0,IF(F$1<INDEX('Valo FX'!$R:$R,MATCH($A14,'Valo FX'!$A:$A,0)),INDEX(Base!$U:$U,MATCH($A14,Base!$A:$A,0)),IF(F$1=INDEX('Valo FX'!$R:$R,MATCH($A14,'Valo FX'!$A:$A,0)),INDEX(Base!$V:$V,MATCH($A14,Base!$A:$A,0)),0))) -> 0 | G14: =IF(G$1<INDEX('Valo FX'!$Q:$Q,MATCH($A14,'Valo FX'!$A:$A,0)),0,IF(G$1<INDEX('Valo FX'!$R:$R,MATCH($A14,'Valo FX'!$A:$A,0)),INDEX(Base!$U:$U,MATCH($A14,Base!$A:$A,0)),IF(G$1=INDEX('Valo FX'!$R:$R,MATCH($A14,'Valo FX'!$A:$A,0)),INDEX(Base!$V:$V,MATCH($A14,Base!$A:$A,0)),0))) -> 0 | H14: =IF(H$1<INDEX('Valo FX'!$Q:$Q,MATCH($A14,'Valo FX'!$A:$A,0)),0,IF(H$1<INDEX('Valo FX'!$R:$R,MATCH($A14,'Valo FX'!$A:$A,0)),INDEX(Base!$U:$U,MATCH($A14,Base!$A:$A,0)),IF(H$1=INDEX('Valo FX'!$R:$R,MATCH($A14,'Valo FX'!$A:$A,0)),INDEX(Base!$V:$V,MATCH($A14,Base!$A:$A,0)),0))) -> 0 | I14: =IF(I$1<INDEX('Valo FX'!$Q:$Q,MATCH($A14,'Valo FX'!$A:$A,0)),0,IF(I$1<INDEX('Valo FX'!$R:$R,MATCH($A14,'Valo FX'!$A:$A,0)),INDEX(Base!$U:$U,MATCH($A14,Base!$A:$A,0)),IF(I$1=INDEX('Valo FX'!$R:$R,MATCH($A14,'Valo FX'!$A:$A,0)),INDEX(Base!$V:$V,MATCH($A14,Base!$A:$A,0)),0))) -> 6.850911 | J14: =IF(J$1<INDEX('Valo FX'!$Q:$Q,MATCH($A14,'Valo FX'!$A:$A,0)),0,IF(J$1<INDEX('Valo FX'!$R:$R,MATCH($A14,'Valo FX'!$A:$A,0)),INDEX(Base!$U:$U,MATCH($A14,Base!$A:$A,0)),IF(J$1=INDEX('Valo FX'!$R:$R,MATCH($A14,'Valo FX'!$A:$A,0)),INDEX(Base!$V:$V,MATCH($A14,Base!$A:$A,0)),0))) -> 6.850911 | ... MY14: =IF(MY$1<INDEX('Valo FX'!$Q:$Q,MATCH($A14,'Valo FX'!$A:$A,0)),0,IF(MY$1<INDEX('Valo FX'!$R:$R,MATCH($A14,'Valo FX'!$A:$A,0)),INDEX(Base!$U:$U,MATCH($A14,Base!$A:$A,0)),IF(MY$1=INDEX('Valo FX'!$R:$R,MATCH($A14,'Valo FX'!$A:$A,0)),INDEX(Base!$V:$V,MATCH($A14,Base!$A:$A,0)),0))) -> 0
... A22: =+'Valo FX'!A23 -> 20 | B22: =-'Valo FX'!T23 -> -1933.5734 | C22: =IF(C$1<INDEX('Valo FX'!$Q:$Q,MATCH($A22,'Valo FX'!$A:$A,0)),0,IF(C$1<INDEX('Valo FX'!$R:$R,MATCH($A22,'Valo FX'!$A:$A,0)),INDEX(Base!$U:$U,MATCH($A22,Base!$A:$A,0)),IF(C$1=INDEX('Valo FX'!$R:$R,MATCH($A22,'Valo FX'!$A:$A,0)),INDEX(Base!$V:$V,MATCH($A22,Base!$A:$A,0)),0))) -> 0 | D22: =IF(D$1<INDEX('Valo FX'!$Q:$Q,MATCH($A22,'Valo FX'!$A:$A,0)),0,IF(D$1<INDEX('Valo FX'!$R:$R,MATCH($A22,'Valo FX'!$A:$A,0)),INDEX(Base!$U:$U,MATCH($A22,Base!$A:$A,0)),IF(D$1=INDEX('Valo FX'!$R:$R,MATCH($A22,'Valo FX'!$A:$A,0)),INDEX(Base!$V:$V,MATCH($A22,Base!$A:$A,0)),0))) -> 0 | E22: =IF(E$1<INDEX('Valo FX'!$Q:$Q,MATCH($A22,'Valo FX'!$A:$A,0)),0,IF(E$1<INDEX('Valo FX'!$R:$R,MATCH($A22,'Valo FX'!$A:$A,0)),INDEX(Base!$U:$U,MATCH($A22,Base!$A:$A,0)),IF(E$1=INDEX('Valo FX'!$R:$R,MATCH($A22,'Valo FX'!$A:$A,0)),INDEX(Base!$V:$V,MATCH($A22,Base!$A:$A,0)),0))) -> 0 | F22: =IF(F$1<INDEX('Valo FX'!$Q:$Q,MATCH($A22,'Valo FX'!$A:$A,0)),0,IF(F$1<INDEX('Valo FX'!$R:$R,MATCH($A22,'Valo FX'!$A:$A,0)),INDEX(Base!$U:$U,MATCH($A22,Base!$A:$A,0)),IF(F$1=INDEX('Valo FX'!$R:$R,MATCH($A22,'Valo FX'!$A:$A,0)),INDEX(Base!$V:$V,MATCH($A22,Base!$A:$A,0)),0))) -> 0 | G22: =IF(G$1<INDEX('Valo FX'!$Q:$Q,MATCH($A22,'Valo FX'!$A:$A,0)),0,IF(G$1<INDEX('Valo FX'!$R:$R,MATCH($A22,'Valo FX'!$A:$A,0)),INDEX(Base!$U:$U,MATCH($A22,Base!$A:$A,0)),IF(G$1=INDEX('Valo FX'!$R:$R,MATCH($A22,'Valo FX'!$A:$A,0)),INDEX(Base!$V:$V,MATCH($A22,Base!$A:$A,0)),0))) -> 0 | H22: =IF(H$1<INDEX('Valo FX'!$Q:$Q,MATCH($A22,'Valo FX'!$A:$A,0)),0,IF(H$1<INDEX('Valo FX'!$R:$R,MATCH($A22,'Valo FX'!$A:$A,0)),INDEX(Base!$U:$U,MATCH($A22,Base!$A:$A,0)),IF(H$1=INDEX('Valo FX'!$R:$R,MATCH($A22,'Valo FX'!$A:$A,0)),INDEX(Base!$V:$V,MATCH($A22,Base!$A:$A,0)),0))) -> 0 | I22: =IF(I$1<INDEX('Valo FX'!$Q:$Q,MATCH($A22,'Valo FX'!$A:$A,0)),0,IF(I$1<INDEX('Valo FX'!$R:$R,MATCH($A22,'Valo FX'!$A:$A,0)),INDEX(Base!$U:$U,MATCH($A22,Base!$A:$A,0)),IF(I$1=INDEX('Valo FX'!$R:$R,MATCH($A22,'Valo FX'!$A:$A,0)),INDEX(Base!$V:$V,MATCH($A22,Base!$A:$A,0)),0))) -> 13.17 | J22: =IF(J$1<INDEX('Valo FX'!$Q:$Q,MATCH($A22,'Valo FX'!$A:$A,0)),0,IF(J$1<INDEX('Valo FX'!$R:$R,MATCH($A22,'Valo FX'!$A:$A,0)),INDEX(Base!$U:$U,MATCH($A22,Base!$A:$A,0)),IF(J$1=INDEX('Valo FX'!$R:$R,MATCH($A22,'Valo FX'!$A:$A,0)),INDEX(Base!$V:$V,MATCH($A22,Base!$A:$A,0)),0))) -> 13.17 | ... MY22: =IF(MY$1<INDEX('Valo FX'!$Q:$Q,MATCH($A22,'Valo FX'!$A:$A,0)),0,IF(MY$1<INDEX('Valo FX'!$R:$R,MATCH($A22,'Valo FX'!$A:$A,0)),INDEX(Base!$U:$U,MATCH($A22,Base!$A:$A,0)),IF(MY$1=INDEX('Valo FX'!$R:$R,MATCH($A22,'Valo FX'!$A:$A,0)),INDEX(Base!$V:$V,MATCH($A22,Base!$A:$A,0)),0))) -> 13.52

Sheet Tabla desarrollo
D1: 45392 | E1: 45422 | F1: 45453 | G1: 45483 | H1: 45514 | I1: 45545 | J1: 45575 | K1: 45606 | L1: 45636 | M1: 45667 | N1: 45698 | O1: 45726 | P1: 45757 | Q1: 45787 | R1: 45818 | S1: 45848 | T1: 45879 | U1: 45910 | V1: 45940 | W1: 45971 | X1: 46001 | Y1: 46032 | Z1: 46063 | AA1: 46091 | AB1: 46122 | AC1: 46152 | AD1: 46183 | AE1: 46213 | AF1: 46244 | AG1: 46275 | AH1: 46305 | AI1: 46336 | AJ1: 46366 | AK1: 46397 | AL1: 46428 | AM1: 46456 | AN1: 46487 | AO1: 46517 | AP1: 46548 | AQ1: 46578 | AR1: 46609 | AS1: 46640 | AT1: 46670 | AU1: 46701 | AV1: 46731 | AW1: 46762 | AX1: 46793 | AY1: 46822 | AZ1: 46853 | BA1: 46883 | BB1: 46914 | BC1: 46944 | BD1: 46975 | BE1: 47006 | BF1: 47036 | BG1: 47067 | BH1: 47097 | BI1: 47128 | BJ1: 47159 | BK1: 47187 | BL1: 47218 | BM1: 47248 | BN1: 47279 | BO1: 47309 | BP1: 47340 | BQ1: 47371 | BR1: 47401 | BS1: 47432 | BT1: 47462 | BU1: 47493 | BV1: 47524 | BW1: 47552 | BX1: 47583 | BY1: 47613 | BZ1: 47644 | CA1: 47674 | CB1: 47705 | CC1: 47736 | CD1: 47766 | CE1: 47797 | CF1: 47827 | CG1: 47858 | CH1: 47889 | CI1: 47917 | CJ1: 47948 | CK1: 47978 | CL1: 48009 | CM1: 48039 | CN1: 48070 | CO1: 48101 | CP1: 48131 | CQ1: 48162 | CR1: 48192 | CS1: 48223 | CT1: 48254 | CU1: 48283 | CV1: 48314 | CW1: 48344 | CX1: 48375 | CY1: 48405 | CZ1: 48436 | DA1: 48467 | DB1: 48497 | DC1: 48528 | DD1: 48558 | DE1: 48589 | DF1: 48620 | DG1: 48648 | DH1: 48679 | DI1: 48709 | DJ1: 48740 | DK1: 48770 | DL1: 48801 | DM1: 48832 | DN1: 48862 | DO1: 48893 | DP1: 48923 | DQ1: 48954 | DR1: 48985 | DS1: 49013 | DT1: 49044 | DU1: 49074 | DV1: 49105 | DW1: 49135 | DX1: 49166 | DY1: 49197 | DZ1: 49227 | EA1: 49258 | EB1: 49288 | EC1: 49319 | ED1: 49350 | EE1: 49378 | EF1: 49409 | EG1: 49439 | EH1: 49470 | EI1: 49500 | EJ1: 49531 | EK1: 49562 | EL1: 49592 | EM1: 49623 | EN1: 49653 | EO1: 49684 | EP1: 49715 | EQ1: 49744 | ER1: 49775 | ES1: 49805 | ET1: 49836 | EU1: 49866 | EV1: 49897 | EW1: 49928 | EX1: 49958 | EY1: 49989 | EZ1: 50019 | FA1: 50050 | FB1: 50081 | FC1: 50109 | FD1: 50140 | FE1: 50170 | FF1: 50201 | FG1: 50231 | FH1: 50262 | FI1: 50293 | FJ1: 50323 | FK1: 50354 | FL1: 50384 | FM1: 50415 | FN1: 50446 | FO1: 50474 | FP1: 50505 | FQ1: 50535 | FR1: 50566 | FS1: 50596 | FT1: 50627 | FU1: 50658 | FV1: 50688 | FW1: 50719 | FX1: 50749 | FY1: 50780 | FZ1: 50811 | GA1: 50839 | GB1: 50870 | GC1: 50900 | GD1: 50931 | GE1: 50961 | GF1: 50992 | GG1: 51023 | GH1: 51053 | GI1: 51084 | GJ1: 51114 | GK1: 51145 | GL1: 51176 | GM1: 51205 | GN1: 51236 | GO1: 51266 | GP1: 51297 | GQ1: 51327 | GR1: 51358 | GS1: 51389 | GT1: 51419 | GU1: 51450 | GV1: 51480 | GW1: 51511 | GX1: 51542 | GY1: 51570 | GZ1: 51601 | HA1: 51631 | HB1: 51662 | HC1: 51692 | HD1: 51723 | HE1: 51754 | HF1: 51784 | HG1: 51815 | HH1: 51845 | HI1: 51876 | HJ1: 51907 | HK1: 51935 | HL1: 51966 | HM1: 51996 | HN1: 52027 | HO1: 52057 | HP1: 52088 | HQ1: 52119 | HR1: 52149 | HS1: 52180 | HT1: 52210 | HU1: 52241 | HV1: 52272 | HW1: 52300 | HX1: 52331 | HY1: 52361 | HZ1: 52392 | IA1: 52422 | IB1: 52453 | IC1: 52484 | ID1: 52514 | IE1: 52545 | IF1: 52575 | IG1: 52606 | IH1: 52637 | II1: 52666 | IJ1: 52697 | IK1: 52727 | IL1: 52758 | IM1: 52788 | IN1: 52819 | IO1: 52850 | IP1: 52880 | IQ1: 52911 | IR1: 52941 | IS1: 52972 | IT1: 53003 | IU1: 53031 | IV1: 53062 | IW1: 53092 | IX1: 53123 | IY1: 53153 | IZ1: 53184 | JA1: 53215 | JB1: 53245 | JC1: 53276 | JD1: 53306 | JE1: 53337 | JF1: 53368 | JG1: 53396 | JH1: 53427 | JI1: 53457 | JJ1: 53488 | JK1: 53518 | JL1: 53549 | JM1: 53580 | JN1: 53610 | JO1: 53641 | JP1: 53671 | JQ1: 53702 | JR1: 53733 | JS1: 53761 | JT1: 53792 | JU1: 53822 | JV1: 53853 | JW1: 53883 | JX1: 53914 | JY1: 53945 | JZ1: 53975 | KA1: 54006 | KB1: 54036 | KC1: 54067 | KD1: 54098 | KE1: 54127 | KF1: 54158 | KG1: 54188 | KH1: 54219 | KI1: 54249 | KJ1: 54280 | KK1: 54311 | KL1: 54341 | KM1: 54372 | KN1: 54402 | KO1: 54433 | KP1: 54464 | KQ1: 54492 | KR1: 54523 | KS1: 54553 | KT1: 54584 | KU1: 54614 | KV1: 54645 | KW1: 54676 | KX1: 54706 | KY1: 54737 | KZ1: 54767 | LA1: 54798 | LB1: 54829 | LC1: 54857 | LD1: 54888 | LE1: 54918 | LF1: 54949 | LG1: 54979 | LH1: 55010 | LI1: 55041 | LJ1: 55071 | LK1: 55102 | LL1: 55132 | LM1: 55163 | LN1: 55194 | LO1: 55222 | LP1: 55253 | LQ1: 55283 | LR1: 55314 | LS1: 55344 | LT1: 55375 | LU1: 55406 | LV1: 55436 | LW1: 55467 | LX1: 55497 | LY1: 55528 | LZ1: 55559 | MA1: 55588 | MB1: 55619 | MC1: 55649 | MD1: 55680 | ME1: 55710 | MF1: 55741 | MG1: 55772 | MH1: 55802 | MI1: 55833 | MJ1: 55863 | MK1: 55894 | ML1: 55925 | MM1: 55953 | MN1: 55984 | MO1: 56014 | MP1: 56045 | MQ1: 56075 | MR1: 56106 | MS1: 56137 | MT1: 56167 | MU1: 56198 | MV1: 56228 | MW1: 56259 | MX1: 56290 | MY1: 56318 | MZ1: 56349
A2: Nº | B2: N° Operación | C2: Primera cuota a endosar | D2: 1 | E2: 2 | F2: 3 | G2: 4 | H2: 5 | I2: 6 | J2: 7 | K2: 8 | L2: 9 | M2: 10 | N2: 11 | O2: 12 | P2: 13 | Q2: 14 | R2: 15 | S2: 16 | T2: 17 | U2: 18 | V2: 19 | W2: 20 | X2: 21 | Y2: 22 | Z2: 23 | AA2: 24 | AB2: 25 | AC2: 26 | AD2: 27 | AE2: 28 | AF2: 29 | AG2: 30 | AH2: 31 | AI2: 32 | AJ2: 33 | AK2: 34 | AL2: 35 | AM2: 36 | AN2: 37 | AO2: 38 | AP2: 39 | AQ2: 40 | AR2: 41 | AS2: 42 | AT2: 43 | AU2: 44 | AV2: 45 | AW2: 46 | AX2: 47 | AY2: 48 | AZ2: 49 | BA2: 50 | BB2: 51 | BC2: 52 | BD2: 53 | BE2: 54 | BF2: 55 | BG2: 56 | BH2: 57 | BI2: 58 | BJ2: 59 | BK2: 60 | BL2: 61 | BM2: 62 | BN2: 63 | BO2: 64 | BP2: 65 | BQ2: 66 | BR2: 67 | BS2: 68 | BT2: 69 | BU2: 70 | BV2: 71 | BW2: 72 | BX2: 73 | BY2: 74 | BZ2: 75 | CA2: 76 | CB2: 77 | CC2: 78 | CD2: 79 | CE2: 80 | CF2: 81 | CG2: 82 | CH2: 83 | CI2: 84 | CJ2: 85 | CK2: 86 | CL2: 87 | CM2: 88 | CN2: 89 | CO2: 90 | CP2: 91 | CQ2: 92 | CR2: 93 | CS2: 94 | CT2: 95 | CU2: 96 | CV2: 97 | CW2: 98 | CX2: 99 | CY2: 100 | CZ2: 101 | DA2: 102 | DB2: 103 | DC2: 104 | DD2: 105 | DE2: 106 | DF2: 107 | DG2: 108 | DH2: 109 | DI2: 110 | DJ2: 111 | DK2: 112 | DL2: 113 | DM2: 114 | DN2: 115 | DO2: 116 | DP2: 117 | DQ2: 118 | DR2: 119 | DS2: 120 | DT2: 121 | DU2: 122 | DV2: 123 | DW2: 124 | DX2: 125 | DY2: 126 | DZ2: 127 | EA2: 128 | EB2: 129 | EC2: 130 | ED2: 131 | EE2: 132 | EF2: 133 | EG2: 134 | EH2: 135 | EI2: 136 | EJ2: 137 | EK2: 138 | EL2: 139 | EM2: 140 | EN2: 141 | EO2: 142 | EP2: 143 | EQ2: 144 | ER2: 145 | ES2: 146 | ET2: 147 | EU2: 148 | EV2: 149 | EW2: 150 | EX2: 151 | EY2: 152 | EZ2: 153 | FA2: 154 | FB2: 155 | FC2: 156 | FD2: 157 | FE2: 158 | FF2: 159 | FG2: 160 | FH2: 161 | FI2: 162 | FJ2: 163 | FK2: 164 | FL2: 165 | FM2: 166 | FN2: 167 | FO2: 168 | FP2: 169 | FQ2: 170 | FR2: 171 | FS2: 172 | FT2: 173 | FU2: 174 | FV2: 175 | FW2: 176 | FX2: 177 | FY2: 178 | FZ2: 179 | GA2: 180 | GB2: 181 | GC2: 182 | GD2: 183 | GE2: 184 | GF2: 185 | GG2: 186 | GH2: 187 | GI2: 188 | GJ2: 189 | GK2: 190 | GL2: 191 | GM2: 192 | GN2: 193 | GO2: 194 | GP2: 195 | GQ2: 196 | GR2: 197 | GS2: 198 | GT2: 199 | GU2: 200 | GV2: 201 | GW2: 202 | GX2: 203 | GY2: 204 | GZ2: 205 | HA2: 206 | HB2: 207 | HC2: 208 | HD2: 209 | HE2: 210 | HF2: 211 | HG2: 212 | HH2: 213 | HI2: 214 | HJ2: 215 | HK2: 216 | HL2: 217 | HM2: 218 | HN2: 219 | HO2: 220 | HP2: 221 | HQ2: 222 | HR2: 223 | HS2: 224 | HT2: 225 | HU2: 226 | HV2: 227 | HW2: 228 | HX2: 229 | HY2: 230 | HZ2: 231 | IA2: 232 | IB2: 233 | IC2: 234 | ID2: 235 | IE2: 236 | IF2: 237 | IG2: 238 | IH2: 239 | II2: 240 | IJ2: 241 | IK2: 242 | IL2: 243 | IM2: 244 | IN2: 245 | IO2: 246 | IP2: 247 | IQ2: 248 | IR2: 249 | IS2: 250 | IT2: 251 | IU2: 252 | IV2: 253 | IW2: 254 | IX2: 255 | IY2: 256 | IZ2: 257 | JA2: 258 | JB2: 259 | JC2: 260 | JD2: 261 | JE2: 262 | JF2: 263 | JG2: 264 | JH2: 265 | JI2: 266 | JJ2: 267 | JK2: 268 | JL2: 269 | JM2: 270 | JN2: 271 | JO2: 272 | JP2: 273 | JQ2: 274 | JR2: 275 | JS2: 276 | JT2: 277 | JU2: 278 | JV2: 279 | JW2: 280 | JX2: 281 | JY2: 282 | JZ2: 283 | KA2: 284 | KB2: 285 | KC2: 286 | KD2: 287 | KE2: 288 | KF2: 289 | KG2: 290 | KH2: 291 | KI2: 292 | KJ2: 293 | KK2: 294 | KL2: 295 | KM2: 296 | KN2: 297 | KO2: 298 | KP2: 299 | KQ2: 300 | KR2: 301 | KS2: 302 | KT2: 303 | KU2: 304 | KV2: 305 | KW2: 306 | KX2: 307 | KY2: 308 | KZ2: 309 | LA2: 310 | LB2: 311 | LC2: 312 | LD2: 313 | LE2: 314 | LF2: 315 | LG2: 316 | LH2: 317 | LI2: 318 | LJ2: 319 | LK2: 320 | LL2: 321 | LM2: 322 | LN2: 323 | LO2: 324 | LP2: 325 | LQ2: 326 | LR2: 327 | LS2: 328 | LT2: 329 | LU2: 330 | LV2: 331 | LW2: 332 | LX2: 333 | LY2: 334 | LZ2: 335 | MA2: 336 | MB2: 337 | MC2: 338 | MD2: 339 | ME2: 340 | MF2: 341 | MG2: 342 | MH2: 343 | MI2: 344 | MJ2: 345 | MK2: 346 | ML2: 347 | MM2: 348 | MN2: 349 | MO2: 350 | MP2: 351 | MQ2: 352 | MR2: 353 | MS2: 354 | MT2: 355 | MU2: 356 | MV2: 357 | MW2: 358 | MX2: 359 | MY2: 360 | MZ2: 361
A3: 1 | B3: 202403250103A033 | C3: 6 | D3: 0 | E3: 0 | F3: 0 | G3: 0 | H3: 0 | I3: 0 | J3: 11.98802 | K3: 11.98802 | L3: 11.98802 | M3: 11.98802 | N3: 11.98802 | O3: 11.98802 | P3: 11.98802 | Q3: 11.98802 | R3: 11.98802 | S3: 11.98802 | T3: 11.98802 | U3: 11.98802 | V3: 11.98802 | W3: 11.98802 | X3: 11.98802 | Y3: 11.98802 | Z3: 11.98802 | AA3: 11.98802 | AB3: 11.98802 | AC3: 11.98802 | AD3: 11.98802 | AE3: 11.98802 | AF3: 11.98802 | AG3: 11.98802 | AH3: 11.98802 | AI3: 11.98802 | AJ3: 11.98802 | AK3: 11.98802 | AL3: 11.98802 | AM3: 11.98802 | AN3: 11.98802 | AO3: 11.98802 | AP3: 11.98802 | AQ3: 11.98802 | AR3: 11.98802 | AS3: 11.98802 | AT3: 11.98802 | AU3: 11.98802 | AV3: 11.98802 | AW3: 11.98802 | AX3: 11.98802 | AY3: 11.98802 | AZ3: 11.98802 | BA3: 11.98802 | BB3: 11.98802 | BC3: 11.98802 | BD3: 11.98802 | BE3: 11.98802 | BF3: 11.98802 | BG3: 11.98802 | BH3: 11.98802 | BI3: 11.98802 | BJ3: 11.98802 | BK3: 11.98802 | BL3: 11.98802 | BM3: 11.98802 | BN3: 11.98802 | BO3: 11.98802 | BP3: 11.98802 | BQ3: 11.98802 | BR3: 11.98802 | BS3: 11.98802 | BT3: 11.98802 | BU3: 11.98802 | BV3: 11.98802 | BW3: 11.98802 | BX3: 11.98802 | BY3: 11.98802 | BZ3: 11.98802 | CA3: 11.98802 | CB3: 11.98802 | CC3: 11.98802 | CD3: 11.98802 | CE3: 11.98802 | CF3: 11.98802 | CG3: 11.98802 | CH3: 11.98802 | CI3: 11.98802 | CJ3: 11.98802 | CK3: 11.98802 | CL3: 11.98802 | CM3: 11.98802 | CN3: 11.98802 | CO3: 11.98802 | CP3: 11.98802 | CQ3: 11.98802 | CR3: 11.98802 | CS3: 11.98802 | CT3: 11.98802 | CU3: 11.98802 | CV3: 11.98802 | CW3: 11.98802 | CX3: 11.98802 | CY3: 11.98802 | CZ3: 11.98802 | DA3: 11.98802 | DB3: 11.98802 | DC3: 11.98802 | DD3: 11.98802 | DE3: 11.98802 | DF3: 11.98802 | DG3: 11.98802 | DH3: 11.98802 | DI3: 11.98802 | DJ3: 11.98802 | DK3: 11.98802 | DL3: 11.98802 | DM3: 11.98802 | DN3: 11.98802 | DO3: 11.98802 | DP3: 11.98802 | DQ3: 11.98802 | DR3: 11.98802 | DS3: 11.98802 | DT3: 11.98802 | DU3: 11.98802 | DV3: 11.98802 | DW3: 11.98802 | DX3: 11.98802 | DY3: 11.98802 | DZ3: 11.98802 | EA3: 11.98802 | EB3: 11.98802 | EC3: 11.98802 | ED3: 11.98802 | EE3: 11.98802 | EF3: 11.98802 | EG3: 11.98802 | EH3: 11.98802 | EI3: 11.98802 | EJ3: 11.98802 | EK3: 11.98802 | EL3: 11.98802 | EM3: 11.98802 | EN3: 11.98802 | EO3: 11.98802 | EP3: 11.98802 | EQ3: 11.98802 | ER3: 11.98802 | ES3: 11.98802 | ET3: 11.98802 | EU3: 11.98802 | EV3: 11.98802 | EW3: 11.98802 | EX3: 11.98802 | EY3: 11.98802 | EZ3: 11.98802 | FA3: 11.98802 | FB3: 11.98802 | FC3: 11.98802 | FD3: 11.98802 | FE3: 11.98802 | FF3: 11.98802 | FG3: 11.98802 | FH3: 11.98802 | FI3: 11.98802 | FJ3: 11.98802 | FK3: 11.98802 | FL3: 11.98802 | FM3: 11.98802 | FN3: 11.98802 | FO3: 11.98802 | FP3: 11.98802 | FQ3: 11.98802 | FR3: 11.98802 | FS3: 11.98802 | FT3: 11.98802 | FU3: 11.98802 | FV3: 11.98802 | FW3: 11.98802 | FX3: 11.98802 | FY3: 11.98802 | FZ3: 11.98802 | GA3: 11.98802 | GB3: 11.98802 | GC3: 11.98802 | GD3: 11.98802 | GE3: 11.98802 | GF3: 11.98802 | GG3: 11.98802 | GH3: 11.98802 | GI3: 11.98802 | GJ3: 11.98802 | GK3: 11.98802 | GL3: 11.98802 | GM3: 11.98802 | GN3: 11.98802 | GO3: 11.98802 | GP3: 11.98802 | GQ3: 11.98802 | GR3: 11.98802 | GS3: 11.98802 | GT3: 11.98802 | GU3: 11.98802 | GV3: 11.98802 | GW3: 11.98802 | GX3: 11.98802 | GY3: 11.98802 | GZ3: 11.98802 | HA3: 11.98802 | HB3: 11.98802 | HC3: 11.98802 | HD3: 11.98802 | HE3: 11.98802 | HF3: 11.98802 | HG3: 11.98802 | HH3: 11.98802 | HI3: 11.98802 | HJ3: 11.98802 | HK3: 11.98802 | HL3: 11.98802 | HM3: 11.98802 | HN3: 11.98802 | HO3: 11.98802 | HP3: 11.98802 | HQ3: 11.98802 | HR3: 11.98802 | HS3: 11.98802 | HT3: 11.98802 | HU3: 11.98802 | HV3: 11.98802 | HW3: 11.98802 | HX3: 11.98802 | HY3: 11.98802 | HZ3: 11.98802 | IA3: 11.98802 | IB3: 11.98802 | IC3: 11.98802 | ID3: 11.98802 | IE3: 11.98802 | IF3: 11.98802 | IG3: 11.98802 | IH3: 11.98802 | II3: 11.98802 | IJ3: 11.98802 | IK3: 11.98802 | IL3: 11.98802 | IM3: 11.98802 | IN3: 11.98802 | IO3: 11.98802 | IP3: 11.98802 | IQ3: 11.98802 | IR3: 11.98802 | IS3: 11.98802 | IT3: 11.98802 | IU3: 11.98802 | IV3: 11.98802 | IW3: 11.98802 | IX3: 11.98802 | IY3: 11.98802 | IZ3: 11.98802 | JA3: 11.98802 | JB3: 11.98802 | JC3: 11.98802 | JD3: 11.98802 | JE3: 11.98802 | JF3: 11.98802 | JG3: 11.98802 | JH3: 11.98802 | JI3: 11.98802 | JJ3: 11.98802 | JK3: 11.98802 | JL3: 11.98802 | JM3: 11.98802 | JN3: 11.98802 | JO3: 11.98802 | JP3: 11.98802 | JQ3: 11.98802 | JR3: 11.98802 | JS3: 11.98802 | JT3: 11.98802 | JU3: 11.98802 | JV3: 11.98802 | JW3: 11.98802 | JX3: 11.98802 | JY3: 11.98802 | JZ3: 11.98802 | KA3: 11.98802 | KB3: 11.98802 | KC3: 11.98802 | KD3: 11.98802 | KE3: 11.98802 | KF3: 11.98802 | KG3: 11.98802 | KH3: 11.98802 | KI3: 11.98802 | KJ3: 11.98802 | KK3: 11.98802 | KL3: 11.98802 | KM3: 11.98802 | KN3: 11.98802 | KO3: 11.98802 | KP3: 11.98802 | KQ3: 11.98802 | KR3: 11.919435 | KS3: 0 | KT3: 0 | KU3: 0 | KV3: 0 | KW3: 0 | KX3: 0 | KY3: 0 | KZ3: 0 | LA3: 0 | LB3: 0 | LC3: 0 | LD3: 0 | LE3: 0 | LF3: 0 | LG3: 0 | LH3: 0 | LI3: 0 | LJ3: 0 | LK3: 0 | LL3: 0 | LM3: 0 | LN3: 0 | LO3: 0 | LP3: 0 | LQ3: 0 | LR3: 0 | LS3: 0 | LT3: 0 | LU3: 0 | LV3: 0 | LW3: 0 | LX3: 0 | LY3: 0 | LZ3: 0 | MA3: 0 | MB3: 0 | MC3: 0 | MD3: 0 | ME3: 0 | MF3: 0 | MG3: 0 | MH3: 0 | MI3: 0 | MJ3: 0 | MK3: 0 | ML3: 0 | MM3: 0 | MN3: 0 | MO3: 0 | MP3: 0 | MQ3: 0 | MR3: 0 | MS3: 0 | MT3: 0 | MU3: 0 | MV3: 0 | MW3: 0 | MX3: 0 | MY3: 0 | MZ3: 0
A4: 2 | B4: 202403260104A033 | C4: 6 | D4: 0 | E4: 0 | F4: 0 | G4: 0 | H4: 0 | I4: 0 | J4: 10.483279 | K4: 10.483279 | L4: 10.483279 | M4: 10.483279 | N4: 10.483279 | O4: 10.483279 | P4: 10.483279 | Q4: 10.483279 | R4: 10.483279 | S4: 10.483279 | T4: 10.483279 | U4: 10.483279 | V4: 10.483279 | W4: 10.483279 | X4: 10.483279 | Y4: 10.483279 | Z4: 10.483279 | AA4: 10.483279 | AB4: 10.483279 | AC4: 10.483279 | AD4: 10.483279 | AE4: 10.483279 | AF4: 10.483279 | AG4: 10.483279 | AH4: 10.483279 | AI4: 10.483279 | AJ4: 10.483279 | AK4: 10.483279 | AL4: 10.483279 | AM4: 10.483279 | AN4: 10.483279 | AO4: 10.483279 | AP4: 10.483279 | AQ4: 10.483279 | AR4: 10.483279 | AS4: 10.483279 | AT4: 10.483279 | AU4: 10.483279 | AV4: 10.483279 | AW4: 10.483279 | AX4: 10.483279 | AY4: 10.483279 | AZ4: 10.483279 | BA4: 10.483279 | BB4: 10.483279 | BC4: 10.483279 | BD4: 10.483279 | BE4: 10.483279 | BF4: 10.483279 | BG4: 10.483279 | BH4: 10.483279 | BI4: 10.483279 | BJ4: 10.483279 | BK4: 10.483279 | BL4: 10.483279 | BM4: 10.483279 | BN4: 10.483279 | BO4: 10.483279 | BP4: 10.483279 | BQ4: 10.483279 | BR4: 10.483279 | BS4: 10.483279 | BT4: 10.483279 | BU4: 10.483279 | BV4: 10.483279 | BW4: 10.483279 | BX4: 10.483279 | BY4: 10.483279 | BZ4: 10.483279 | CA4: 10.483279 | CB4: 10.483279 | CC4: 10.483279 | CD4: 10.483279 | CE4: 10.483279 | CF4: 10.483279 | CG4: 10.483279 | CH4: 10.483279 | CI4: 10.483279 | CJ4: 10.483279 | CK4: 10.483279 | CL4: 10.483279 | CM4: 10.483279 | CN4: 10.483279 | CO4: 10.483279 | CP4: 10.483279 | CQ4: 10.483279 | CR4: 10.483279 | CS4: 10.483279 | CT4: 10.483279 | CU4: 10.483279 | CV4: 10.483279 | CW4: 10.483279 | CX4: 10.483279 | CY4: 10.483279 | CZ4: 10.483279 | DA4: 10.483279 | DB4: 10.483279 | DC4: 10.483279 | DD4: 10.483279 | DE4: 10.483279 | DF4: 10.483279 | DG4: 10.483279 | DH4: 10.483279 | DI4: 10.483279 | DJ4: 10.483279 | DK4: 10.483279 | DL4: 10.483279 | DM4: 10.483279 | DN4: 10.483279 | DO4: 10.483279 | DP4: 10.483279 | DQ4: 10.483279 | DR4: 10.483279 | DS4: 10.483279 | DT4: 10.483279 | DU4: 10.483279 | DV4: 10.483279 | DW4: 10.483279 | DX4: 10.483279 | DY4: 10.483279 | DZ4: 10.483279 | EA4: 10.483279 | EB4: 10.483279 | EC4: 10.483279 | ED4: 10.483279 | EE4: 10.483279 | EF4: 10.483279 | EG4: 10.483279 | EH4: 10.483279 | EI4: 10.483279 | EJ4: 10.483279 | EK4: 10.483279 | EL4: 10.483279 | EM4: 10.483279 | EN4: 10.483279 | EO4: 10.483279 | EP4: 10.483279 | EQ4: 10.483279 | ER4: 10.483279 | ES4: 10.483279 | ET4: 10.483279 | EU4: 10.483279 | EV4: 10.483279 | EW4: 10.483279 | EX4: 10.483279 | EY4: 10.483279 | EZ4: 10.483279 | FA4: 10.483279 | FB4: 10.483279 | FC4: 10.483279 | FD4: 10.483279 | FE4: 10.483279 | FF4: 10.483279 | FG4: 10.483279 | FH4: 10.483279 | FI4: 10.483279 | FJ4: 10.483279 | FK4: 10.483279 | FL4: 10.483279 | FM4: 10.483279 | FN4: 10.483279 | FO4: 10.483279 | FP4: 10.483279 | FQ4: 10.483279 | FR4: 10.483279 | FS4: 10.483279 | FT4: 10.483279 | FU4: 10.483279 | FV4: 10.483279 | FW4: 10.483279 | FX4: 10.483279 | FY4: 10.483279 | FZ4: 10.483279 | GA4: 10.483279 | GB4: 10.483279 | GC4: 10.483279 | GD4: 10.483279 | GE4: 10.483279 | GF4: 10.483279 | GG4: 10.483279 | GH4: 10.483279 | GI4: 10.483279 | GJ4: 10.483279 | GK4: 10.483279 | GL4: 10.483279 | GM4: 10.483279 | GN4: 10.483279 | GO4: 10.483279 | GP4: 10.483279 | GQ4: 10.483279 | GR4: 10.483279 | GS4: 10.483279 | GT4: 10.483279 | GU4: 10.483279 | GV4: 10.483279 | GW4: 10.483279 | GX4: 10.483279 | GY4: 10.483279 | GZ4: 10.483279 | HA4: 10.483279 | HB4: 10.483279 | HC4: 10.483279 | HD4: 10.483279 | HE4: 10.483279 | HF4: 10.483279 | HG4: 10.483279 | HH4: 10.483279 | HI4: 10.483279 | HJ4: 10.483279 | HK4: 10.483279 | HL4: 10.483279 | HM4: 10.483279 | HN4: 10.483279 | HO4: 10.483279 | HP4: 10.483279 | HQ4: 10.483279 | HR4: 10.483279 | HS4: 10.483279 | HT4: 10.483279 | HU4: 10.483279 | HV4: 10.483279 | HW4: 10.483279 | HX4: 10.483279 | HY4: 10.483279 | HZ4: 10.483279 | IA4: 10.483279 | IB4: 10.483279 | IC4: 10.483279 | ID4: 10.483279 | IE4: 10.483279 | IF4: 10.483279 | IG4: 10.483279 | IH4: 10.483279 | II4: 10.483279 | IJ4: 10.483279 | IK4: 10.483279 | IL4: 10.483279 | IM4: 10.483279 | IN4: 10.483279 | IO4: 10.483279 | IP4: 10.483279 | IQ4: 10.483279 | IR4: 10.483279 | IS4: 10.483279 | IT4: 10.483279 | IU4: 10.483279 | IV4: 10.483279 | IW4: 10.483279 | IX4: 10.483279 | IY4: 10.483279 | IZ4: 10.483279 | JA4: 10.483279 | JB4: 10.483279 | JC4: 10.483279 | JD4: 10.483279 | JE4: 10.483279 | JF4: 10.483279 | JG4: 10.483279 | JH4: 10.483279 | JI4: 10.483279 | JJ4: 10.483279 | JK4: 10.483279 | JL4: 10.483279 | JM4: 10.483279 | JN4: 10.483279 | JO4: 10.483279 | JP4: 10.483279 | JQ4: 10.483279 | JR4: 10.483279 | JS4: 10.483279 | JT4: 10.483279 | JU4: 10.483279 | JV4: 10.483279 | JW4: 10.483279 | JX4: 10.483279 | JY4: 10.483279 | JZ4: 10.483279 | KA4: 10.483279 | KB4: 10.483279 | KC4: 10.483279 | KD4: 10.483279 | KE4: 10.483279 | KF4: 10.483279 | KG4: 10.483279 | KH4: 10.483279 | KI4: 10.483279 | KJ4: 10.483279 | KK4: 10.483279 | KL4: 10.483279 | KM4: 10.483279 | KN4: 10.483279 | KO4: 10.483279 | KP4: 10.483279 | KQ4: 10.483279 | KR4: 10.483279 | KS4: 10.483279 | KT4: 10.483279 | KU4: 10.483279 | KV4: 10.483279 | KW4: 10.483279 | KX4: 10.483279 | KY4: 10.483279 | KZ4: 10.483279 | LA4: 10.483279 | LB4: 10.483279 | LC4: 10.483279 | LD4: 10.483279 | LE4: 10.483279 | LF4: 10.483279 | LG4: 10.483279 | LH4: 10.483279 | LI4: 10.483279 | LJ4: 10.483279 | LK4: 10.483279 | LL4: 10.483279 | LM4: 10.483279 | LN4: 10.483279 | LO4: 10.483279 | LP4: 10.483279 | LQ4: 10.483279 | LR4: 10.483279 | LS4: 10.483279 | LT4: 10.483279 | LU4: 10.483279 | LV4: 10.483279 | LW4: 10.483279 | LX4: 10.483279 | LY4: 10.483279 | LZ4: 10.483279 | MA4: 10.483279 | MB4: 10.483279 | MC4: 10.483279 | MD4: 10.483279 | ME4: 10.483279 | MF4: 10.483279 | MG4: 10.483279 | MH4: 10.483279 | MI4: 10.483279 | MJ4: 10.483279 | MK4: 10.483279 | ML4: 10.483279 | MM4: 10.483279 | MN4: 10.483279 | MO4: 10.483279 | MP4: 10.483279 | MQ4: 10.483279 | MR4: 10.483279 | MS4: 10.483279 | MT4: 10.483279 | MU4: 10.483279 | MV4: 10.483279 | MW4: 10.483279 | MX4: 10.483279 | MY4: 10.483279 | MZ4: 10.761609
A5: 3 | B5: 202403250105A033 | C5: 6 | D5: 0 | E5: 0 | F5: 0 | G5: 0 | H5: 0 | I5: 0 | J5: 6.402808 | K5: 6.402808 | L5: 6.402808 | M5: 6.402808 | N5: 6.402808 | O5: 6.402808 | P5: 6.402808 | Q5: 6.402808 | R5: 6.402808 | S5: 6.402808 | T5: 6.402808 | U5: 6.402808 | V5: 6.402808 | W5: 6.402808 | X5: 6.402808 | Y5: 6.402808 | Z5: 6.402808 | AA5: 6.402808 | AB5: 6.402808 | AC5: 6.402808 | AD5: 6.402808 | AE5: 6.402808 | AF5: 6.402808 | AG5: 6.402808 | AH5: 6.402808 | AI5: 6.402808 | AJ5: 6.402808 | AK5: 6.402808 | AL5: 6.402808 | AM5: 6.402808 | AN5: 6.402808 | AO5: 6.402808 | AP5: 6.402808 | AQ5: 6.402808 | AR5: 6.402808 | AS5: 6.402808 | AT5: 6.402808 | AU5: 6.402808 | AV5: 6.402808 | AW5: 6.402808 | AX5: 6.402808 | AY5: 6.402808 | AZ5: 6.402808 | BA5: 6.402808 | BB5: 6.402808 | BC5: 6.402808 | BD5: 6.402808 | BE5: 6.402808 | BF5: 6.402808 | BG5: 6.402808 | BH5: 6.402808 | BI5: 6.402808 | BJ5: 6.402808 | BK5: 6.402808 | BL5: 6.402808 | BM5: 6.402808 | BN5: 6.402808 | BO5: 6.402808 | BP5: 6.402808 | BQ5: 6.402808 | BR5: 6.402808 | BS5: 6.402808 | BT5: 6.402808 | BU5: 6.402808 | BV5: 6.402808 | BW5: 6.402808 | BX5: 6.402808 | BY5: 6.402808 | BZ5: 6.402808 | CA5: 6.402808 | CB5: 6.402808 | CC5: 6.402808 | CD5: 6.402808 | CE5: 6.402808 | CF5: 6.402808 | CG5: 6.402808 | CH5: 6.402808 | CI5: 6.402808 | CJ5: 6.402808 | CK5: 6.402808 | CL5: 6.402808 | CM5: 6.402808 | CN5: 6.402808 | CO5: 6.402808 | CP5: 6.402808 | CQ5: 6.402808 | CR5: 6.402808 | CS5: 6.402808 | CT5: 6.402808 | CU5: 6.402808 | CV5: 6.402808 | CW5: 6.402808 | CX5: 6.402808 | CY5: 6.402808 | CZ5: 6.402808 | DA5: 6.402808 | DB5: 6.402808 | DC5: 6.402808 | DD5: 6.402808 | DE5: 6.402808 | DF5: 6.402808 | DG5: 6.402808 | DH5: 6.402808 | DI5: 6.402808 | DJ5: 6.402808 | DK5: 6.402808 | DL5: 6.402808 | DM5: 6.402808 | DN5: 6.402808 | DO5: 6.402808 | DP5: 6.402808 | DQ5: 6.402808 | DR5: 6.402808 | DS5: 6.402808 | DT5: 6.402808 | DU5: 6.402808 | DV5: 6.402808 | DW5: 6.402808 | DX5: 6.402808 | DY5: 6.402808 | DZ5: 6.402808 | EA5: 6.402808 | EB5: 6.402808 | EC5: 6.402808 | ED5: 6.402808 | EE5: 6.402808 | EF5: 6.402808 | EG5: 6.402808 | EH5: 6.402808 | EI5: 6.402808 | EJ5: 6.402808 | EK5: 6.402808 | EL5: 6.402808 | EM5: 6.402808 | EN5: 6.402808 | EO5: 6.402808 | EP5: 6.402808 | EQ5: 6.402808 | ER5: 6.402808 | ES5: 6.402808 | ET5: 6.402808 | EU5: 6.402808 | EV5: 6.402808 | EW5: 6.402808 | EX5: 6.402808 | EY5: 6.402808 | EZ5: 6.402808 | FA5: 6.402808 | FB5: 6.402808 | FC5: 6.402808 | FD5: 6.402808 | FE5: 6.402808 | FF5: 6.402808 | FG5: 6.402808 | FH5: 6.402808 | FI5: 6.402808 | FJ5: 6.402808 | FK5: 6.402808 | FL5: 6.402808 | FM5: 6.402808 | FN5: 6.402808 | FO5: 6.402808 | FP5: 6.402808 | FQ5: 6.402808 | FR5: 6.402808 | FS5: 6.402808 | FT5: 6.402808 | FU5: 6.402808 | FV5: 6.402808 | FW5: 6.402808 | FX5: 6.402808 | FY5: 6.402808 | FZ5: 6.402808 | GA5: 6.402808 | GB5: 6.402808 | GC5: 6.402808 | GD5: 6.402808 | GE5: 6.402808 | GF5: 6.402808 | GG5: 6.402808 | GH5: 6.402808 | GI5: 6.402808 | GJ5: 6.402808 | GK5: 6.402808 | GL5: 6.402808 | GM5: 6.402808 | GN5: 6.402808 | GO5: 6.402808 | GP5: 6.402808 | GQ5: 6.402808 | GR5: 6.402808 | GS5: 6.402808 | GT5: 6.402808 | GU5: 6.402808 | GV5: 6.402808 | GW5: 6.402808 | GX5: 6.402808 | GY5: 6.402808 | GZ5: 6.402808 | HA5: 6.402808 | HB5: 6.402808 | HC5: 6.402808 | HD5: 6.402808 | HE5: 6.402808 | HF5: 6.402808 | HG5: 6.402808 | HH5: 6.402808 | HI5: 6.402808 | HJ5: 6.402808 | HK5: 6.402808 | HL5: 6.402808 | HM5: 6.402808 | HN5: 6.402808 | HO5: 6.402808 | HP5: 6.402808 | HQ5: 6.402808 | HR5: 6.402808 | HS5: 6.402808 | HT5: 6.402808 | HU5: 6.402808 | HV5: 6.402808 | HW5: 6.402808 | HX5: 6.402808 | HY5: 6.402808 | HZ5: 6.402808 | IA5: 6.402808 | IB5: 6.402808 | IC5: 6.402808 | ID5: 6.402808 | IE5: 6.402808 | IF5: 6.402808 | IG5: 6.402808 | IH5: 6.402808 | II5: 6.402808 | IJ5: 6.402808 | IK5: 6.402808 | IL5: 6.402808 | IM5: 6.402808 | IN5: 6.402808 | IO5: 6.402808 | IP5: 6.402808 | IQ5: 6.402808 | IR5: 6.402808 | IS5: 6.402808 | IT5: 6.402808 | IU5: 6.402808 | IV5: 6.402808 | IW5: 6.402808 | IX5: 6.402808 | IY5: 6.402808 | IZ5: 6.402808 | JA5: 6.402808 | JB5: 6.402808 | JC5: 6.402808 | JD5: 6.402808 | JE5: 6.402808 | JF5: 6.402808 | JG5: 6.402808 | JH5: 6.402808 | JI5: 6.402808 | JJ5: 6.402808 | JK5: 6.402808 | JL5: 6.402808 | JM5: 6.402808 | JN5: 6.402808 | JO5: 6.402808 | JP5: 6.402808 | JQ5: 6.402808 | JR5: 6.402808 | JS5: 6.402808 | JT5: 6.402808 | JU5: 6.402808 | JV5: 6.402808 | JW5: 6.402808 | JX5: 6.402808 | JY5: 6.402808 | JZ5: 6.402808 | KA5: 6.402808 | KB5: 6.402808 | KC5: 6.402808 | KD5: 6.402808 | KE5: 6.402808 | KF5: 6.402808 | KG5: 6.402808 | KH5: 6.402808 | KI5: 6.402808 | KJ5: 6.402808 | KK5: 6.402808 | KL5: 6.402808 | KM5: 6.402808 | KN5: 6.402808 | KO5: 6.402808 | KP5: 6.402808 | KQ5: 6.402808 | KR5: 6.402808 | KS5: 6.402808 | KT5: 6.402808 | KU5: 6.402808 | KV5: 6.402808 | KW5: 6.402808 | KX5: 6.402808 | KY5: 6.402808 | KZ5: 6.402808 | LA5: 6.402808 | LB5: 6.402808 | LC5: 6.402808 | LD5: 6.596335 | LE5: 0 | LF5: 0 | LG5: 0 | LH5: 0 | LI5: 0 | LJ5: 0 | LK5: 0 | LL5: 0 | LM5: 0 | LN5: 0 | LO5: 0 | LP5: 0 | LQ5: 0 | LR5: 0 | LS5: 0 | LT5: 0 | LU5: 0 | LV5: 0 | LW5: 0 | LX5: 0 | LY5: 0 | LZ5: 0 | MA5: 0 | MB5: 0 | MC5: 0 | MD5: 0 | ME5: 0 | MF5: 0 | MG5: 0 | MH5: 0 | MI5: 0 | MJ5: 0 | MK5: 0 | ML5: 0 | MM5: 0 | MN5: 0 | MO5: 0 | MP5: 0 | MQ5: 0 | MR5: 0 | MS5: 0 | MT5: 0 | MU5: 0 | MV5: 0 | MW5: 0 | MX5: 0 | MY5: 0 | MZ5: 0
A6: 4 | B6: 202403260108A033 | C6: 6 | D6: 0 | E6: 0 | F6: 0 | G6: 0 | H6: 0 | I6: 0 | J6: 13.571168 | K6: 13.571168 | L6: 13.571168 | M6: 13.571168 | N6: 13.571168 | O6: 13.571168 | P6: 13.571168 | Q6: 13.571168 | R6: 13.571168 | S6: 13.571168 | T6: 13.571168 | U6: 13.571168 | V6: 13.571168 | W6: 13.571168 | X6: 13.571168 | Y6: 13.571168 | Z6: 13.571168 | AA6: 13.571168 | AB6: 13.571168 | AC6: 13.571168 | AD6: 13.571168 | AE6: 13.571168 | AF6: 13.571168 | AG6: 13.571168 | AH6: 13.571168 | AI6: 13.571168 | AJ6: 13.571168 | AK6: 13.571168 | AL6: 13.571168 | AM6: 13.571168 | AN6: 13.571168 | AO6: 13.571168 | AP6: 13.571168 | AQ6: 13.571168 | AR6: 13.571168 | AS6: 13.571168 | AT6: 13.571168 | AU6: 13.571168 | AV6: 13.571168 | AW6: 13.571168 | AX6: 13.571168 | AY6: 13.571168 | AZ6: 13.571168 | BA6: 13.571168 | BB6: 13.571168 | BC6: 13.571168 | BD6: 13.571168 | BE6: 13.571168 | BF6: 13.571168 | BG6: 13.571168 | BH6: 13.571168 | BI6: 13.571168 | BJ6: 13.571168 | BK6: 13.571168 | BL6: 13.571168 | BM6: 13.571168 | BN6: 13.571168 | BO6: 13.571168 | BP6: 13.571168 | BQ6: 13.571168 | BR6: 13.571168 | BS6: 13.571168 | BT6: 13.571168 | BU6: 13.571168 | BV6: 13.571168 | BW6: 13.571168 | BX6: 13.571168 | BY6: 13.571168 | BZ6: 13.571168 | CA6: 13.571168 | CB6: 13.571168 | CC6: 13.571168 | CD6: 13.571168 | CE6: 13.571168 | CF6: 13.571168 | CG6: 13.571168 | CH6: 13.571168 | CI6: 13.571168 | CJ6: 13.571168 | CK6: 13.571168 | CL6: 13.571168 | CM6: 13.571168 | CN6: 13.571168 | CO6: 13.571168 | CP6: 13.571168 | CQ6: 13.571168 | CR6: 13.571168 | CS6: 13.571168 | CT6: 13.571168 | CU6: 13.571168 | CV6: 13.571168 | CW6: 13.571168 | CX6: 13.571168 | CY6: 13.571168 | CZ6: 13.571168 | DA6: 13.571168 | DB6: 13.571168 | DC6: 13.571168 | DD6: 13.571168 | DE6: 13.571168 | DF6: 13.571168 | DG6: 13.571168 | DH6: 13.571168 | DI6: 13.571168 | DJ6: 13.571168 | DK6: 13.571168 | DL6: 13.571168 | DM6: 13.571168 | DN6: 13.571168 | DO6: 13.571168 | DP6: 13.571168 | DQ6: 13.571168 | DR6: 13.571168 | DS6: 13.571168 | DT6: 13.571168 | DU6: 13.571168 | DV6: 13.571168 | DW6: 13.571168 | DX6: 13.571168 | DY6: 13.571168 | DZ6: 13.571168 | EA6: 13.571168 | EB6: 13.571168 | EC6: 13.571168 | ED6: 13.571168 | EE6: 13.571168 | EF6: 13.571168 | EG6: 13.571168 | EH6: 13.571168 | EI6: 13.571168 | EJ6: 13.571168 | EK6: 13.571168 | EL6: 13.571168 | EM6: 13.571168 | EN6: 13.571168 | EO6: 13.571168 | EP6: 13.571168 | EQ6: 13.571168 | ER6: 13.571168 | ES6: 13.571168 | ET6: 13.571168 | EU6: 13.571168 | EV6: 13.571168 | EW6: 13.571168 | EX6: 13.571168 | EY6: 13.571168 | EZ6: 13.571168 | FA6: 13.571168 | FB6: 13.571168 | FC6: 13.571168 | FD6: 13.571168 | FE6: 13.571168 | FF6: 13.571168 | FG6: 13.571168 | FH6: 13.571168 | FI6: 13.571168 | FJ6: 13.571168 | FK6: 13.571168 | FL6: 13.571168 | FM6: 13.571168 | FN6: 13.571168 | FO6: 13.571168 | FP6: 13.571168 | FQ6: 13.571168 | FR6: 13.571168 | FS6: 13.571168 | FT6: 13.571168 | FU6: 13.571168 | FV6: 13.571168 | FW6: 13.571168 | FX6: 13.571168 | FY6: 13.571168 | FZ6: 13.571168 | GA6: 13.571168 | GB6: 13.571168 | GC6: 13.571168 | GD6: 13.571168 | GE6: 13.571168 | GF6: 13.571168 | GG6: 13.571168 | GH6: 13.571168 | GI6: 13.571168 | GJ6: 13.571168 | GK6: 13.571168 | GL6: 13.571168 | GM6: 13.571168 | GN6: 13.571168 | GO6: 13.571168 | GP6: 13.571168 | GQ6: 13.571168 | GR6: 13.571168 | GS6: 13.571168 | GT6: 13.571168 | GU6: 13.571168 | GV6: 13.571168 | GW6: 13.571168 | GX6: 13.571168 | GY6: 13.571168 | GZ6: 13.571168 | HA6: 13.571168 | HB6: 13.571168 | HC6: 13.571168 | HD6: 13.571168 | HE6: 13.571168 | HF6: 13.571168 | HG6: 13.571168 | HH6: 13.571168 | HI6: 13.571168 | HJ6: 13.571168 | HK6: 13.571168 | HL6: 13.571168 | HM6: 13.571168 | HN6: 13.571168 | HO6: 13.571168 | HP6: 13.571168 | HQ6: 13.571168 | HR6: 13.571168 | HS6: 13.571168 | HT6: 13.571168 | HU6: 13.571168 | HV6: 13.571168 | HW6: 13.571168 | HX6: 13.571168 | HY6: 13.571168 | HZ6: 13.571168 | IA6: 13.571168 | IB6: 13.571168 | IC6: 13.571168 | ID6: 13.571168 | IE6: 13.571168 | IF6: 13.571168 | IG6: 13.571168 | IH6: 13.571168 | II6: 13.571168 | IJ6: 13.571168 | IK6: 13.571168 | IL6: 13.571168 | IM6: 13.571168 | IN6: 13.571168 | IO6: 13.571168 | IP6: 13.571168 | IQ6: 13.571168 | IR6: 13.571168 | IS6: 13.571168 | IT6: 13.571168 | IU6: 13.571168 | IV6: 13.571168 | IW6: 13.571168 | IX6: 13.571168 | IY6: 13.571168 | IZ6: 13.571168 | JA6: 13.571168 | JB6: 13.571168 | JC6: 13.571168 | JD6: 13.571168 | JE6: 13.571168 | JF6: 13.571168 | JG6: 13.571168 | JH6: 13.454412 | JI6: 0 | JJ6: 0 | JK6: 0 | JL6: 0 | JM6: 0 | JN6: 0 | JO6: 0 | JP6: 0 | JQ6: 0 | JR6: 0 | JS6: 0 | JT6: 0 | JU6: 0 | JV6: 0 | JW6: 0 | JX6: 0 | JY6: 0 | JZ6: 0 | KA6: 0 | KB6: 0 | KC6: 0 | KD6: 0 | KE6: 0 | KF6: 0 | KG6: 0 | KH6: 0 | KI6: 0 | KJ6: 0 | KK6: 0 | KL6: 0 | KM6: 0 | KN6: 0 | KO6: 0 | KP6: 0 | KQ6: 0 | KR6: 0 | KS6: 0 | KT6: 0 | KU6: 0 | KV6: 0 | KW6: 0 | KX6: 0 | KY6: 0 | KZ6: 0 | LA6: 0 | LB6: 0 | LC6: 0 | LD6: 0 | LE6: 0 | LF6: 0 | LG6: 0 | LH6: 0 | LI6: 0 | LJ6: 0 | LK6: 0 | LL6: 0 | LM6: 0 | LN6: 0 | LO6: 0 | LP6: 0 | LQ6: 0 | LR6: 0 | LS6: 0 | LT6: 0 | LU6: 0 | LV6: 0 | LW6: 0 | LX6: 0 | LY6: 0 | LZ6: 0 | MA6: 0 | MB6: 0 | MC6: 0 | MD6: 0 | ME6: 0 | MF6: 0 | MG6: 0 | MH6: 0 | MI6: 0 | MJ6: 0 | MK6: 0 | ML6: 0 | MM6: 0 | MN6: 0 | MO6: 0 | MP6: 0 | MQ6: 0 | MR6: 0 | MS6: 0 | MT6: 0 | MU6: 0 | MV6: 0 | MW6: 0 | MX6: 0 | MY6: 0 | MZ6: 0
A7: 5 | B7: 202403250112A033 | C7: 6 | D7: 0 | E7: 0 | F7: 0 | G7: 0 | H7: 0 | I7: 0 | J7: 10.98688 | K7: 10.98688 | L7: 10.98688 | M7: 10.98688 | N7: 10.98688 | O7: 10.98688 | P7: 10.98688 | Q7: 10.98688 | R7: 10.98688 | S7: 10.98688 | T7: 10.98688 | U7: 10.98688 | V7: 10.98688 | W7: 10.98688 | X7: 10.98688 | Y7: 10.98688 | Z7: 10.98688 | AA7: 10.98688 | AB7: 10.98688 | AC7: 10.98688 | AD7: 10.98688 | AE7: 10.98688 | AF7: 10.98688 | AG7: 10.98688 | AH7: 10.98688 | AI7: 10.98688 | AJ7: 10.98688 | AK7: 10.98688 | AL7: 10.98688 | AM7: 10.98688 | AN7: 10.98688 | AO7: 10.98688 | AP7: 10.98688 | AQ7: 10.98688 | AR7: 10.98688 | AS7: 10.98688 | AT7: 10.98688 | AU7: 10.98688 | AV7: 10.98688 | AW7: 10.98688 | AX7: 10.98688 | AY7: 10.98688 | AZ7: 10.98688 | BA7: 10.98688 | BB7: 10.98688 | BC7: 10.98688 | BD7: 10.98688 | BE7: 10.98688 | BF7: 10.98688 | BG7: 10.98688 | BH7: 10.98688 | BI7: 10.98688 | BJ7: 10.98688 | BK7: 10.98688 | BL7: 10.98688 | BM7: 10.98688 | BN7: 10.98688 | BO7: 10.98688 | BP7: 10.98688 | BQ7: 10.98688 | BR7: 10.98688 | BS7: 10.98688 | BT7: 10.98688 | BU7: 10.98688 | BV7: 10.98688 | BW7: 10.98688 | BX7: 10.98688 | BY7: 10.98688 | BZ7: 10.98688 | CA7: 10.98688 | CB7: 10.98688 | CC7: 10.98688 | CD7: 10.98688 | CE7: 10.98688 | CF7: 10.98688 | CG7: 10.98688 | CH7: 10.98688 | CI7: 10.98688 | CJ7: 10.98688 | CK7: 10.98688 | CL7: 10.98688 | CM7: 10.98688 | CN7: 10.98688 | CO7: 10.98688 | CP7: 10.98688 | CQ7: 10.98688 | CR7: 10.98688 | CS7: 10.98688 | CT7: 10.98688 | CU7: 10.98688 | CV7: 10.98688 | CW7: 10.98688 | CX7: 10.98688 | CY7: 10.98688 | CZ7: 10.98688 | DA7: 10.98688 | DB7: 10.98688 | DC7: 10.98688 | DD7: 10.98688 | DE7: 10.98688 | DF7: 10.98688 | DG7: 10.98688 | DH7: 10.98688 | DI7: 10.98688 | DJ7: 10.98688 | DK7: 10.98688 | DL7: 10.98688 | DM7: 10.98688 | DN7: 10.98688 | DO7: 10.98688 | DP7: 10.98688 | DQ7: 10.98688 | DR7: 10.98688 | DS7: 10.98688 | DT7: 10.98688 | DU7: 10.98688 | DV7: 10.98688 | DW7: 10.98688 | DX7: 10.98688 | DY7: 10.98688 | DZ7: 10.98688 | EA7: 10.98688 | EB7: 10.98688 | EC7: 10.98688 | ED7: 10.98688 | EE7: 10.98688 | EF7: 10.98688 | EG7: 10.98688 | EH7: 10.98688 | EI7: 10.98688 | EJ7: 10.98688 | EK7: 10.98688 | EL7: 10.98688 | EM7: 10.98688 | EN7: 10.98688 | EO7: 10.98688 | EP7: 10.98688 | EQ7: 10.98688 | ER7: 10.98688 | ES7: 10.98688 | ET7: 10.98688 | EU7: 10.98688 | EV7: 10.98688 | EW7: 10.98688 | EX7: 10.98688 | EY7: 10.98688 | EZ7: 10.98688 | FA7: 10.98688 | FB7: 10.98688 | FC7: 10.98688 | FD7: 10.98688 | FE7: 10.98688 | FF7: 10.98688 | FG7: 10.98688 | FH7: 10.98688 | FI7: 10.98688 | FJ7: 10.98688 | FK7: 10.98688 | FL7: 10.98688 | FM7: 10.98688 | FN7: 10.98688 | FO7: 10.98688 | FP7: 10.98688 | FQ7: 10.98688 | FR7: 10.98688 | FS7: 10.98688 | FT7: 10.98688 | FU7: 10.98688 | FV7: 10.98688 | FW7: 10.98688 | FX7: 10.98688 | FY7: 10.98688 | FZ7: 10.98688 | GA7: 10.98688 | GB7: 10.98688 | GC7: 10.98688 | GD7: 10.98688 | GE7: 10.98688 | GF7: 10.98688 | GG7: 10.98688 | GH7: 10.98688 | GI7: 10.98688 | GJ7: 10.98688 | GK7: 10.98688 | GL7: 10.98688 | GM7: 10.98688 | GN7: 10.98688 | GO7: 10.98688 | GP7: 10.98688 | GQ7: 10.98688 | GR7: 10.98688 | GS7: 10.98688 | GT7: 10.98688 | GU7: 10.98688 | GV7: 10.98688 | GW7: 10.98688 | GX7: 10.98688 | GY7: 10.98688 | GZ7: 10.98688 | HA7: 10.98688 | HB7: 10.98688 | HC7: 10.98688 | HD7: 10.98688 | HE7: 10.98688 | HF7: 10.98688 | HG7: 10.98688 | HH7: 10.98688 | HI7: 10.98688 | HJ7: 10.98688 | HK7: 10.98688 | HL7: 10.98688 | HM7: 10.98688 | HN7: 10.98688 | HO7: 10.98688 | HP7: 10.98688 | HQ7: 10.98688 | HR7: 10.98688 | HS7: 10.98688 | HT7: 10.98688 | HU7: 10.98688 | HV7: 10.98688 | HW7: 10.98688 | HX7: 10.98688 | HY7: 10.98688 | HZ7: 10.98688 | IA7: 10.98688 | IB7: 10.98688 | IC7: 10.98688 | ID7: 10.98688 | IE7: 10.98688 | IF7: 10.98688 | IG7: 10.98688 | IH7: 10.98688 | II7: 10.98688 | IJ7: 10.98688 | IK7: 10.98688 | IL7: 10.98688 | IM7: 10.98688 | IN7: 10.98688 | IO7: 10.98688 | IP7: 10.98688 | IQ7: 10.98688 | IR7: 10.98688 | IS7: 10.98688 | IT7: 10.98688 | IU7: 10.98688 | IV7: 10.98688 | IW7: 10.98688 | IX7: 10.98688 | IY7: 10.98688 | IZ7: 10.98688 | JA7: 10.98688 | JB7: 10.98688 | JC7: 10.98688 | JD7: 10.98688 | JE7: 10.98688 | JF7: 10.98688 | JG7: 10.98688 | JH7: 10.98688 | JI7: 10.98688 | JJ7: 10.98688 | JK7: 10.98688 | JL7: 10.98688 | JM7: 10.98688 | JN7: 10.98688 | JO7: 10.98688 | JP7: 10.98688 | JQ7: 10.98688 | JR7: 10.98688 | JS7: 10.98688 | JT7: 10.98688 | JU7: 10.98688 | JV7: 10.98688 | JW7: 10.98688 | JX7: 10.98688 | JY7: 10.98688 | JZ7: 10.98688 | KA7: 10.98688 | KB7: 10.98688 | KC7: 10.98688 | KD7: 10.98688 | KE7: 10.98688 | KF7: 10.98688 | KG7: 10.98688 | KH7: 10.98688 | KI7: 10.98688 | KJ7: 10.98688 | KK7: 10.98688 | KL7: 10.98688 | KM7: 10.98688 | KN7: 10.98688 | KO7: 10.98688 | KP7: 10.98688 | KQ7: 10.98688 | KR7: 10.98688 | KS7: 10.98688 | KT7: 10.98688 | KU7: 10.98688 | KV7: 10.98688 | KW7: 10.98688 | KX7: 10.98688 | KY7: 10.98688 | KZ7: 10.98688 | LA7: 10.98688 | LB7: 10.98688 | LC7: 10.98688 | LD7: 10.98688 | LE7: 10.98688 | LF7: 10.98688 | LG7: 10.98688 | LH7: 10.98688 | LI7: 10.98688 | LJ7: 10.98688 | LK7: 10.98688 | LL7: 10.98688 | LM7: 10.98688 | LN7: 10.98688 | LO7: 10.98688 | LP7: 10.98688 | LQ7: 10.98688 | LR7: 10.98688 | LS7: 10.98688 | LT7: 10.98688 | LU7: 10.98688 | LV7: 10.98688 | LW7: 10.98688 | LX7: 10.98688 | LY7: 10.98688 | LZ7: 10.98688 | MA7: 10.98688 | MB7: 10.98688 | MC7: 10.98688 | MD7: 10.98688 | ME7: 10.98688 | MF7: 10.98688 | MG7: 10.98688 | MH7: 10.98688 | MI7: 10.98688 | MJ7: 10.98688 | MK7: 10.98688 | ML7: 10.98688 | MM7: 10.98688 | MN7: 10.98688 | MO7: 10.98688 | MP7: 10.98688 | MQ7: 10.98688 | MR7: 10.98688 | MS7: 10.98688 | MT7: 10.98688 | MU7: 10.98688 | MV7: 10.98688 | MW7: 10.98688 | MX7: 10.98688 | MY7: 10.98688 | MZ7: 11.27858
A8: 6 | B8: 202403260115A033 | C8: 6 | D8: 0 | E8: 0 | F8: 0 | G8: 0 | H8: 0 | I8: 0 | J8: 12.508353 | K8: 12.508353 | L8: 12.508353 | M8: 12.508353 | N8: 12.508353 | O8: 12.508353 | P8: 12.508353 | Q8: 12.508353 | R8: 12.508353 | S8: 12.508353 | T8: 12.508353 | U8: 12.508353 | V8: 12.508353 | W8: 12.508353 | X8: 12.508353 | Y8: 12.508353 | Z8: 12.508353 | AA8: 12.508353 | AB8: 12.508353 | AC8: 12.508353 | AD8: 12.508353 | AE8: 12.508353 | AF8: 12.508353 | AG8: 12.508353 | AH8: 12.508353 | AI8: 12.508353 | AJ8: 12.508353 | AK8: 12.508353 | AL8: 12.508353 | AM8: 12.508353 | AN8: 12.508353 | AO8: 12.508353 | AP8: 12.508353 | AQ8: 12.508353 | AR8: 12.508353 | AS8: 12.508353 | AT8: 12.508353 | AU8: 12.508353 | AV8: 12.508353 | AW8: 12.508353 | AX8: 12.508353 | AY8: 12.508353 | AZ8: 12.508353 | BA8: 12.508353 | BB8: 12.508353 | BC8: 12.508353 | BD8: 12.508353 | BE8: 12.508353 | BF8: 12.508353 | BG8: 12.508353 | BH8: 12.508353 | BI8: 12.508353 | BJ8: 12.508353 | BK8: 12.508353 | BL8: 12.508353 | BM8: 12.508353 | BN8: 12.508353 | BO8: 12.508353 | BP8: 12.508353 | BQ8: 12.508353 | BR8: 12.508353 | BS8: 12.508353 | BT8: 12.508353 | BU8: 12.508353 | BV8: 12.508353 | BW8: 12.508353 | BX8: 12.508353 | BY8: 12.508353 | BZ8: 12.508353 | CA8: 12.508353 | CB8: 12.508353 | CC8: 12.508353 | CD8: 12.508353 | CE8: 12.508353 | CF8: 12.508353 | CG8: 12.508353 | CH8: 12.508353 | CI8: 12.508353 | CJ8: 12.508353 | CK8: 12.508353 | CL8: 12.508353 | CM8: 12.508353 | CN8: 12.508353 | CO8: 12.508353 | CP8: 12.508353 | CQ8: 12.508353 | CR8: 12.508353 | CS8: 12.508353 | CT8: 12.508353 | CU8: 12.508353 | CV8: 12.508353 | CW8: 12.508353 | CX8: 12.508353 | CY8: 12.508353 | CZ8: 12.508353 | DA8: 12.508353 | DB8: 12.508353 | DC8: 12.508353 | DD8: 12.508353 | DE8: 12.508353 | DF8: 12.508353 | DG8: 12.508353 | DH8: 12.508353 | DI8: 12.508353 | DJ8: 12.508353 | DK8: 12.508353 | DL8: 12.508353 | DM8: 12.508353 | DN8: 12.508353 | DO8: 12.508353 | DP8: 12.508353 | DQ8: 12.508353 | DR8: 12.508353 | DS8: 12.508353 | DT8: 12.508353 | DU8: 12.508353 | DV8: 12.508353 | DW8: 12.508353 | DX8: 12.508353 | DY8: 12.508353 | DZ8: 12.508353 | EA8: 12.508353 | EB8: 12.508353 | EC8: 12.508353 | ED8: 12.508353 | EE8: 12.508353 | EF8: 12.508353 | EG8: 12.508353 | EH8: 12.508353 | EI8: 12.508353 | EJ8: 12.508353 | EK8: 12.508353 | EL8: 12.508353 | EM8: 12.508353 | EN8: 12.508353 | EO8: 12.508353 | EP8: 12.508353 | EQ8: 12.508353 | ER8: 12.508353 | ES8: 12.508353 | ET8: 12.508353 | EU8: 12.508353 | EV8: 12.508353 | EW8: 12.508353 | EX8: 12.508353 | EY8: 12.508353 | EZ8: 12.508353 | FA8: 12.508353 | FB8: 12.508353 | FC8: 12.508353 | FD8: 12.508353 | FE8: 12.508353 | FF8: 12.508353 | FG8: 12.508353 | FH8: 12.508353 | FI8: 12.508353 | FJ8: 12.508353 | FK8: 12.508353 | FL8: 12.508353 | FM8: 12.508353 | FN8: 12.508353 | FO8: 12.508353 | FP8: 12.508353 | FQ8: 12.508353 | FR8: 12.508353 | FS8: 12.508353 | FT8: 12.508353 | FU8: 12.508353 | FV8: 12.508353 | FW8: 12.508353 | FX8: 12.508353 | FY8: 12.508353 | FZ8: 12.508353 | GA8: 12.508353 | GB8: 12.508353 | GC8: 12.508353 | GD8: 12.508353 | GE8: 12.508353 | GF8: 12.508353 | GG8: 12.508353 | GH8: 12.508353 | GI8: 12.508353 | GJ8: 12.508353 | GK8: 12.508353 | GL8: 12.508353 | GM8: 12.508353 | GN8: 12.508353 | GO8: 12.508353 | GP8: 12.508353 | GQ8: 12.508353 | GR8: 12.508353 | GS8: 12.508353 | GT8: 12.508353 | GU8: 12.508353 | GV8: 12.508353 | GW8: 12.508353 | GX8: 12.508353 | GY8: 12.508353 | GZ8: 12.508353 | HA8: 12.508353 | HB8: 12.508353 | HC8: 12.508353 | HD8: 12.508353 | HE8: 12.508353 | HF8: 12.508353 | HG8: 12.508353 | HH8: 12.508353 | HI8: 12.508353 | HJ8: 12.508353 | HK8: 12.508353 | HL8: 12.508353 | HM8: 12.508353 | HN8: 12.508353 | HO8: 12.508353 | HP8: 12.508353 | HQ8: 12.508353 | HR8: 12.508353 | HS8: 12.508353 | HT8: 12.508353 | HU8: 12.508353 | HV8: 12.508353 | HW8: 12.508353 | HX8: 12.508353 | HY8: 12.508353 | HZ8: 12.508353 | IA8: 12.508353 | IB8: 12.508353 | IC8: 12.508353 | ID8: 12.508353 | IE8: 12.508353 | IF8: 12.508353 | IG8: 12.508353 | IH8: 12.508353 | II8: 12.508353 | IJ8: 12.508353 | IK8: 12.508353 | IL8: 12.508353 | IM8: 12.508353 | IN8: 12.508353 | IO8: 12.508353 | IP8: 12.508353 | IQ8: 12.508353 | IR8: 12.508353 | IS8: 12.508353 | IT8: 12.508353 | IU8: 12.508353 | IV8: 12.508353 | IW8: 12.508353 | IX8: 12.508353 | IY8: 12.508353 | IZ8: 12.508353 | JA8: 12.508353 | JB8: 12.508353 | JC8: 12.508353 | JD8: 12.508353 | JE8: 12.508353 | JF8: 12.508353 | JG8: 12.508353 | JH8: 12.508353 | JI8: 12.508353 | JJ8: 12.508353 | JK8: 12.508353 | JL8: 12.508353 | JM8: 12.508353 | JN8: 12.508353 | JO8: 12.508353 | JP8: 12.508353 | JQ8: 12.508353 | JR8: 12.508353 | JS8: 12.508353 | JT8: 12.508353 | JU8: 12.508353 | JV8: 12.508353 | JW8: 12.508353 | JX8: 12.508353 | JY8: 12.508353 | JZ8: 12.508353 | KA8: 12.508353 | KB8: 12.508353 | KC8: 12.508353 | KD8: 12.508353 | KE8: 12.508353 | KF8: 12.508353 | KG8: 12.508353 | KH8: 12.508353 | KI8: 12.508353 | KJ8: 12.508353 | KK8: 12.508353 | KL8: 12.508353 | KM8: 12.508353 | KN8: 12.508353 | KO8: 12.508353 | KP8: 12.508353 | KQ8: 12.508353 | KR8: 12.436791 | KS8: 0 | KT8: 0 | KU8: 0 | KV8: 0 | KW8: 0 | KX8: 0 | KY8: 0 | KZ8: 0 | LA8: 0 | LB8: 0 | LC8: 0 | LD8: 0 | LE8: 0 | LF8: 0 | LG8: 0 | LH8: 0 | LI8: 0 | LJ8: 0 | LK8: 0 | LL8: 0 | LM8: 0 | LN8: 0 | LO8: 0 | LP8: 0 | LQ8: 0 | LR8: 0 | LS8: 0 | LT8: 0 | LU8: 0 | LV8: 0 | LW8: 0 | LX8: 0 | LY8: 0 | LZ8: 0 | MA8: 0 | MB8: 0 | MC8: 0 | MD8: 0 | ME8: 0 | MF8: 0 | MG8: 0 | MH8: 0 | MI8: 0 | MJ8: 0 | MK8: 0 | ML8: 0 | MM8: 0 | MN8: 0 | MO8: 0 | MP8: 0 | MQ8: 0 | MR8: 0 | MS8: 0 | MT8: 0 | MU8: 0 | MV8: 0 | MW8: 0 | MX8: 0 | MY8: 0 | MZ8: 0
A9: 7 | B9: 202403260117A033 | C9: 6 | D9: 0 | E9: 0 | F9: 0 | G9: 0 | H9: 0 | I9: 0 | J9: 11.548934 | K9: 11.548934 | L9: 11.548934 | M9: 11.548934 | N9: 11.548934 | O9: 11.548934 | P9: 11.548934 | Q9: 11.548934 | R9: 11.548934 | S9: 11.548934 | T9: 11.548934 | U9: 11.548934 | V9: 11.548934 | W9: 11.548934 | X9: 11.548934 | Y9: 11.548934 | Z9: 11.548934 | AA9: 11.548934 | AB9: 11.548934 | AC9: 11.548934 | AD9: 11.548934 | AE9: 11.548934 | AF9: 11.548934 | AG9: 11.548934 | AH9: 11.548934 | AI9: 11.548934 | AJ9: 11.548934 | AK9: 11.548934 | AL9: 11.548934 | AM9: 11.548934 | AN9: 11.548934 | AO9: 11.548934 | AP9: 11.548934 | AQ9: 11.548934 | AR9: 11.548934 | AS9: 11.548934 | AT9: 11.548934 | AU9: 11.548934 | AV9: 11.548934 | AW9: 11.548934 | AX9: 11.548934 | AY9: 11.548934 | AZ9: 11.548934 | BA9: 11.548934 | BB9: 11.548934 | BC9: 11.548934 | BD9: 11.548934 | BE9: 11.548934 | BF9: 11.548934 | BG9: 11.548934 | BH9: 11.548934 | BI9: 11.548934 | BJ9: 11.548934 | BK9: 11.548934 | BL9: 11.548934 | BM9: 11.548934 | BN9: 11.548934 | BO9: 11.548934 | BP9: 11.548934 | BQ9: 11.548934 | BR9: 11.548934 | BS9: 11.548934 | BT9: 11.548934 | BU9: 11.548934 | BV9: 11.548934 | BW9: 11.548934 | BX9: 11.548934 | BY9: 11.548934 | BZ9: 11.548934 | CA9: 11.548934 | CB9: 11.548934 | CC9: 11.548934 | CD9: 11.548934 | CE9: 11.548934 | CF9: 11.548934 | CG9: 11.548934 | CH9: 11.548934 | CI9: 11.548934 | CJ9: 11.548934 | CK9: 11.548934 | CL9: 11.548934 | CM9: 11.548934 | CN9: 11.548934 | CO9: 11.548934 | CP9: 11.548934 | CQ9: 11.548934 | CR9: 11.548934 | CS9: 11.548934 | CT9: 11.548934 | CU9: 11.548934 | CV9: 11.548934 | CW9: 11.548934 | CX9: 11.548934 | CY9: 11.548934 | CZ9: 11.548934 | DA9: 11.548934 | DB9: 11.548934 | DC9: 11.548934 | DD9: 11.548934 | DE9: 11.548934 | DF9: 11.548934 | DG9: 11.548934 | DH9: 11.548934 | DI9: 11.548934 | DJ9: 11.548934 | DK9: 11.548934 | DL9: 11.548934 | DM9: 11.548934 | DN9: 11.548934 | DO9: 11.548934 | DP9: 11.548934 | DQ9: 11.548934 | DR9: 11.548934 | DS9: 11.548934 | DT9: 11.548934 | DU9: 11.548934 | DV9: 11.548934 | DW9: 11.548934 | DX9: 11.548934 | DY9: 11.548934 | DZ9: 11.548934 | EA9: 11.548934 | EB9: 11.548934 | EC9: 11.548934 | ED9: 11.548934 | EE9: 11.548934 | EF9: 11.548934 | EG9: 11.548934 | EH9: 11.548934 | EI9: 11.548934 | EJ9: 11.548934 | EK9: 11.548934 | EL9: 11.548934 | EM9: 11.548934 | EN9: 11.548934 | EO9: 11.548934 | EP9: 11.548934 | EQ9: 11.548934 | ER9: 11.548934 | ES9: 11.548934 | ET9: 11.548934 | EU9: 11.548934 | EV9: 11.548934 | EW9: 11.548934 | EX9: 11.548934 | EY9: 11.548934 | EZ9: 11.548934 | FA9: 11.548934 | FB9: 11.548934 | FC9: 11.548934 | FD9: 11.548934 | FE9: 11.548934 | FF9: 11.548934 | FG9: 11.548934 | FH9: 11.548934 | FI9: 11.548934 | FJ9: 11.548934 | FK9: 11.548934 | FL9: 11.548934 | FM9: 11.548934 | FN9: 11.548934 | FO9: 11.548934 | FP9: 11.548934 | FQ9: 11.548934 | FR9: 11.548934 | FS9: 11.548934 | FT9: 11.548934 | FU9: 11.548934 | FV9: 11.548934 | FW9: 11.548934 | FX9: 11.548934 | FY9: 11.548934 | FZ9: 11.548934 | GA9: 11.548934 | GB9: 11.548934 | GC9: 11.548934 | GD9: 11.548934 | GE9: 11.548934 | GF9: 11.548934 | GG9: 11.548934 | GH9: 11.548934 | GI9: 11.548934 | GJ9: 11.548934 | GK9: 11.548934 | GL9: 11.548934 | GM9: 11.548934 | GN9: 11.548934 | GO9: 11.548934 | GP9: 11.548934 | GQ9: 11.548934 | GR9: 11.548934 | GS9: 11.548934 | GT9: 11.548934 | GU9: 11.548934 | GV9: 11.548934 | GW9: 11.548934 | GX9: 11.548934 | GY9: 11.548934 | GZ9: 11.548934 | HA9: 11.548934 | HB9: 11.548934 | HC9: 11.548934 | HD9: 11.548934 | HE9: 11.548934 | HF9: 11.548934 | HG9: 11.548934 | HH9: 11.548934 | HI9: 11.548934 | HJ9: 11.548934 | HK9: 11.548934 | HL9: 11.548934 | HM9: 11.548934 | HN9: 11.548934 | HO9: 11.548934 | HP9: 11.548934 | HQ9: 11.548934 | HR9: 11.548934 | HS9: 11.548934 | HT9: 11.548934 | HU9: 11.548934 | HV9: 11.548934 | HW9: 11.548934 | HX9: 11.548934 | HY9: 11.548934 | HZ9: 11.548934 | IA9: 11.548934 | IB9: 11.548934 | IC9: 11.548934 | ID9: 11.548934 | IE9: 11.548934 | IF9: 11.548934 | IG9: 11.548934 | IH9: 11.548934 | II9: 11.548934 | IJ9: 11.548934 | IK9: 11.548934 | IL9: 11.548934 | IM9: 11.548934 | IN9: 11.548934 | IO9: 11.548934 | IP9: 11.548934 | IQ9: 11.548934 | IR9: 11.548934 | IS9: 11.548934 | IT9: 11.548934 | IU9: 11.548934 | IV9: 11.548934 | IW9: 11.548934 | IX9: 11.548934 | IY9: 11.548934 | IZ9: 11.548934 | JA9: 11.548934 | JB9: 11.548934 | JC9: 11.548934 | JD9: 11.548934 | JE9: 11.548934 | JF9: 11.548934 | JG9: 11.548934 | JH9: 11.548934 | JI9: 11.548934 | JJ9: 11.548934 | JK9: 11.548934 | JL9: 11.548934 | JM9: 11.548934 | JN9: 11.548934 | JO9: 11.548934 | JP9: 11.548934 | JQ9: 11.548934 | JR9: 11.548934 | JS9: 11.548934 | JT9: 11.548934 | JU9: 11.548934 | JV9: 11.548934 | JW9: 11.548934 | JX9: 11.548934 | JY9: 11.548934 | JZ9: 11.548934 | KA9: 11.548934 | KB9: 11.548934 | KC9: 11.548934 | KD9: 11.548934 | KE9: 11.548934 | KF9: 11.548934 | KG9: 11.548934 | KH9: 11.548934 | KI9: 11.548934 | KJ9: 11.548934 | KK9: 11.548934 | KL9: 11.548934 | KM9: 11.548934 | KN9: 11.548934 | KO9: 11.548934 | KP9: 11.548934 | KQ9: 11.548934 | KR9: 11.548934 | KS9: 11.548934 | KT9: 11.548934 | KU9: 11.548934 | KV9: 11.548934 | KW9: 11.548934 | KX9: 11.548934 | KY9: 11.548934 | KZ9: 11.548934 | LA9: 11.548934 | LB9: 11.548934 | LC9: 11.548934 | LD9: 11.548934 | LE9: 11.548934 | LF9: 11.548934 | LG9: 11.548934 | LH9: 11.548934 | LI9: 11.548934 | LJ9: 11.548934 | LK9: 11.548934 | LL9: 11.548934 | LM9: 11.548934 | LN9: 11.548934 | LO9: 11.548934 | LP9: 11.548934 | LQ9: 11.548934 | LR9: 11.548934 | LS9: 11.548934 | LT9: 11.548934 | LU9: 11.548934 | LV9: 11.548934 | LW9: 11.548934 | LX9: 11.548934 | LY9: 11.548934 | LZ9: 11.548934 | MA9: 11.548934 | MB9: 11.548934 | MC9: 11.548934 | MD9: 11.548934 | ME9: 11.548934 | MF9: 11.548934 | MG9: 11.548934 | MH9: 11.548934 | MI9: 11.548934 | MJ9: 11.548934 | MK9: 11.548934 | ML9: 11.548934 | MM9: 11.548934 | MN9: 11.548934 | MO9: 11.548934 | MP9: 11.548934 | MQ9: 11.548934 | MR9: 11.548934 | MS9: 11.548934 | MT9: 11.548934 | MU9: 11.548934 | MV9: 11.548934 | MW9: 11.548934 | MX9: 11.548934 | MY9: 11.548934 | MZ9: 11.855557
A10: 8 | B10: 202403220119A033 | C10: 6 | D10: 0 | E10: 0 | F10: 0 | G10: 0 | H10: 0 | I10: 0 | J10: 5.532881 | K10: 5.532881 | L10: 5.532881 | M10: 5.532881 | N10: 5.532881 | O10: 5.532881 | P10: 5.532881 | Q10: 5.532881 | R10: 5.532881 | S10: 5.532881 | T10: 5.532881 | U10: 5.532881 | V10: 5.532881 | W10: 5.532881 | X10: 5.532881 | Y10: 5.532881 | Z10: 5.532881 | AA10: 5.532881 | AB10: 5.532881 | AC10: 5.532881 | AD10: 5.532881 | AE10: 5.532881 | AF10: 5.532881 | AG10: 5.532881 | AH10: 5.532881 | AI10: 5.532881 | AJ10: 5.532881 | AK10: 5.532881 | AL10: 5.532881 | AM10: 5.532881 | AN10: 5.532881 | AO10: 5.532881 | AP10: 5.532881 | AQ10: 5.532881 | AR10: 5.532881 | AS10: 5.532881 | AT10: 5.532881 | AU10: 5.532881 | AV10: 5.532881 | AW10: 5.532881 | AX10: 5.532881 | AY10: 5.532881 | AZ10: 5.532881 | BA10: 5.532881 | BB10: 5.532881 | BC10: 5.532881 | BD10: 5.532881 | BE10: 5.532881 | BF10: 5.532881 | BG10: 5.532881 | BH10: 5.532881 | BI10: 5.532881 | BJ10: 5.532881 | BK10: 5.532881 | BL10: 5.532881 | BM10: 5.532881 | BN10: 5.532881 | BO10: 5.532881 | BP10: 5.532881 | BQ10: 5.532881 | BR10: 5.532881 | BS10: 5.532881 | BT10: 5.532881 | BU10: 5.532881 | BV10: 5.532881 | BW10: 5.532881 | BX10: 5.532881 | BY10: 5.532881 | BZ10: 5.532881 | CA10: 5.532881 | CB10: 5.532881 | CC10: 5.532881 | CD10: 5.532881 | CE10: 5.532881 | CF10: 5.532881 | CG10: 5.532881 | CH10: 5.532881 | CI10: 5.532881 | CJ10: 5.532881 | CK10: 5.532881 | CL10: 5.532881 | CM10: 5.532881 | CN10: 5.532881 | CO10: 5.532881 | CP10: 5.532881 | CQ10: 5.532881 | CR10: 5.532881 | CS10: 5.532881 | CT10: 5.532881 | CU10: 5.532881 | CV10: 5.532881 | CW10: 5.532881 | CX10: 5.532881 | CY10: 5.532881 | CZ10: 5.532881 | DA10: 5.532881 | DB10: 5.532881 | DC10: 5.532881 | DD10: 5.532881 | DE10: 5.532881 | DF10: 5.532881 | DG10: 5.532881 | DH10: 5.532881 | DI10: 5.532881 | DJ10: 5.532881 | DK10: 5.532881 | DL10: 5.532881 | DM10: 5.532881 | DN10: 5.532881 | DO10: 5.532881 | DP10: 5.532881 | DQ10: 5.532881 | DR10: 5.532881 | DS10: 5.532881 | DT10: 5.532881 | DU10: 5.532881 | DV10: 5.532881 | DW10: 5.532881 | DX10: 5.532881 | DY10: 5.532881 | DZ10: 5.532881 | EA10: 5.532881 | EB10: 5.532881 | EC10: 5.532881 | ED10: 5.532881 | EE10: 5.532881 | EF10: 5.532881 | EG10: 5.532881 | EH10: 5.532881 | EI10: 5.532881 | EJ10: 5.532881 | EK10: 5.532881 | EL10: 5.532881 | EM10: 5.532881 | EN10: 5.532881 | EO10: 5.532881 | EP10: 5.532881 | EQ10: 5.532881 | ER10: 5.532881 | ES10: 5.532881 | ET10: 5.532881 | EU10: 5.532881 | EV10: 5.532881 | EW10: 5.532881 | EX10: 5.532881 | EY10: 5.532881 | EZ10: 5.532881 | FA10: 5.532881 | FB10: 5.532881 | FC10: 5.532881 | FD10: 5.532881 | FE10: 5.532881 | FF10: 5.532881 | FG10: 5.532881 | FH10: 5.532881 | FI10: 5.532881 | FJ10: 5.532881 | FK10: 5.532881 | FL10: 5.532881 | FM10: 5.532881 | FN10: 5.532881 | FO10: 5.532881 | FP10: 5.532881 | FQ10: 5.532881 | FR10: 5.532881 | FS10: 5.532881 | FT10: 5.532881 | FU10: 5.532881 | FV10: 5.532881 | FW10: 5.532881 | FX10: 5.532881 | FY10: 5.532881 | FZ10: 5.532881 | GA10: 5.532881 | GB10: 5.532881 | GC10: 5.532881 | GD10: 5.532881 | GE10: 5.532881 | GF10: 5.532881 | GG10: 5.532881 | GH10: 5.532881 | GI10: 5.532881 | GJ10: 5.532881 | GK10: 5.532881 | GL10: 5.532881 | GM10: 5.532881 | GN10: 5.532881 | GO10: 5.532881 | GP10: 5.532881 | GQ10: 5.532881 | GR10: 5.532881 | GS10: 5.532881 | GT10: 5.532881 | GU10: 5.532881 | GV10: 5.532881 | GW10: 5.532881 | GX10: 5.532881 | GY10: 5.532881 | GZ10: 5.532881 | HA10: 5.532881 | HB10: 5.532881 | HC10: 5.532881 | HD10: 5.532881 | HE10: 5.532881 | HF10: 5.532881 | HG10: 5.532881 | HH10: 5.532881 | HI10: 5.532881 | HJ10: 5.532881 | HK10: 5.532881 | HL10: 5.532881 | HM10: 5.532881 | HN10: 5.532881 | HO10: 5.532881 | HP10: 5.532881 | HQ10: 5.532881 | HR10: 5.532881 | HS10: 5.532881 | HT10: 5.532881 | HU10: 5.532881 | HV10: 5.532881 | HW10: 5.532881 | HX10: 5.532881 | HY10: 5.532881 | HZ10: 5.532881 | IA10: 5.532881 | IB10: 5.532881 | IC10: 5.532881 | ID10: 5.532881 | IE10: 5.532881 | IF10: 5.532881 | IG10: 5.532881 | IH10: 5.532881 | II10: 5.532881 | IJ10: 5.532881 | IK10: 5.532881 | IL10: 5.532881 | IM10: 5.532881 | IN10: 5.532881 | IO10: 5.532881 | IP10: 5.532881 | IQ10: 5.532881 | IR10: 5.532881 | IS10: 5.532881 | IT10: 5.532881 | IU10: 5.532881 | IV10: 5.532881 | IW10: 5.532881 | IX10: 5.532881 | IY10: 5.532881 | IZ10: 5.532881 | JA10: 5.532881 | JB10: 5.532881 | JC10: 5.532881 | JD10: 5.532881 | JE10: 5.532881 | JF10: 5.532881 | JG10: 5.532881 | JH10: 5.532881 | JI10: 5.532881 | JJ10: 5.532881 | JK10: 5.532881 | JL10: 5.532881 | JM10: 5.532881 | JN10: 5.532881 | JO10: 5.532881 | JP10: 5.532881 | JQ10: 5.532881 | JR10: 5.532881 | JS10: 5.532881 | JT10: 5.532881 | JU10: 5.532881 | JV10: 5.532881 | JW10: 5.532881 | JX10: 5.532881 | JY10: 5.532881 | JZ10: 5.532881 | KA10: 5.532881 | KB10: 5.532881 | KC10: 5.532881 | KD10: 5.532881 | KE10: 5.532881 | KF10: 5.532881 | KG10: 5.532881 | KH10: 5.532881 | KI10: 5.532881 | KJ10: 5.532881 | KK10: 5.532881 | KL10: 5.532881 | KM10: 5.532881 | KN10: 5.532881 | KO10: 5.532881 | KP10: 5.532881 | KQ10: 5.532881 | KR10: 5.532881 | KS10: 5.532881 | KT10: 5.532881 | KU10: 5.532881 | KV10: 5.532881 | KW10: 5.532881 | KX10: 5.532881 | KY10: 5.532881 | KZ10: 5.532881 | LA10: 5.532881 | LB10: 5.532881 | LC10: 5.532881 | LD10: 5.532881 | LE10: 5.532881 | LF10: 5.532881 | LG10: 5.532881 | LH10: 5.532881 | LI10: 5.532881 | LJ10: 5.532881 | LK10: 5.532881 | LL10: 5.532881 | LM10: 5.532881 | LN10: 5.532881 | LO10: 5.532881 | LP10: 5.532881 | LQ10: 5.532881 | LR10: 5.532881 | LS10: 5.532881 | LT10: 5.532881 | LU10: 5.532881 | LV10: 5.532881 | LW10: 5.532881 | LX10: 5.532881 | LY10: 5.532881 | LZ10: 5.532881 | MA10: 5.532881 | MB10: 5.532881 | MC10: 5.532881 | MD10: 5.532881 | ME10: 5.532881 | MF10: 5.532881 | MG10: 5.532881 | MH10: 5.532881 | MI10: 5.532881 | MJ10: 5.532881 | MK10: 5.532881 | ML10: 5.532881 | MM10: 5.532881 | MN10: 5.532881 | MO10: 5.532881 | MP10: 5.532881 | MQ10: 5.532881 | MR10: 5.532881 | MS10: 5.532881 | MT10: 5.532881 | MU10: 5.532881 | MV10: 5.532881 | MW10: 5.532881 | MX10: 5.532881 | MY10: 5.532881 | MZ10: 5.679779
A11: 9 | B11: 202403260120A033 | C11: 6 | D11: 0 | E11: 0 | F11: 0 | G11: 0 | H11: 0 | I11: 0 | J11: 6.593 | K11: 6.593 | L11: 6.593 | M11: 6.593 | N11: 6.593 | O11: 6.593 | P11: 6.593 | Q11: 6.593 | R11: 6.593 | S11: 6.593 | T11: 6.593 | U11: 6.593 | V11: 6.593 | W11: 6.593 | X11: 6.593 | Y11: 6.593 | Z11: 6.593 | AA11: 6.593 | AB11: 6.593 | AC11: 6.593 | AD11: 6.593 | AE11: 6.593 | AF11: 6.593 | AG11: 6.593 | AH11: 6.593 | AI11: 6.593 | AJ11: 6.593 | AK11: 6.593 | AL11: 6.593 | AM11: 6.593 | AN11: 6.593 | AO11: 6.593 | AP11: 6.593 | AQ11: 6.593 | AR11: 6.593 | AS11: 6.593 | AT11: 6.593 | AU11: 6.593 | AV11: 6.593 | AW11: 6.593 | AX11: 6.593 | AY11: 6.593 | AZ11: 6.593 | BA11: 6.593 | BB11: 6.593 | BC11: 6.593 | BD11: 6.593 | BE11: 6.593 | BF11: 6.593 | BG11: 6.593 | BH11: 6.593 | BI11: 6.593 | BJ11: 6.593 | BK11: 6.593 | BL11: 6.593 | BM11: 6.593 | BN11: 6.593 | BO11: 6.593 | BP11: 6.593 | BQ11: 6.593 | BR11: 6.593 | BS11: 6.593 | BT11: 6.593 | BU11: 6.593 | BV11: 6.593 | BW11: 6.593 | BX11: 6.593 | BY11: 6.593 | BZ11: 6.593 | CA11: 6.593 | CB11: 6.593 | CC11: 6.593 | CD11: 6.593 | CE11: 6.593 | CF11: 6.593 | CG11: 6.593 | CH11: 6.593 | CI11: 6.593 | CJ11: 6.593 | CK11: 6.593 | CL11: 6.593 | CM11: 6.593 | CN11: 6.593 | CO11: 6.593 | CP11: 6.593 | CQ11: 6.593 | CR11: 6.593 | CS11: 6.593 | CT11: 6.593 | CU11: 6.593 | CV11: 6.593 | CW11: 6.593 | CX11: 6.593 | CY11: 6.593 | CZ11: 6.593 | DA11: 6.593 | DB11: 6.593 | DC11: 6.593 | DD11: 6.593 | DE11: 6.593 | DF11: 6.593 | DG11: 6.593 | DH11: 6.593 | DI11: 6.593 | DJ11: 6.593 | DK11: 6.593 | DL11: 6.593 | DM11: 6.593 | DN11: 6.593 | DO11: 6.593 | DP11: 6.593 | DQ11: 6.593 | DR11: 6.593 | DS11: 6.593 | DT11: 6.593 | DU11: 6.593 | DV11: 6.593 | DW11: 6.593 | DX11: 6.593 | DY11: 6.593 | DZ11: 6.593 | EA11: 6.593 | EB11: 6.593 | EC11: 6.593 | ED11: 6.593 | EE11: 6.593 | EF11: 6.593 | EG11: 6.593 | EH11: 6.593 | EI11: 6.593 | EJ11: 6.593 | EK11: 6.593 | EL11: 6.593 | EM11: 6.593 | EN11: 6.593 | EO11: 6.593 | EP11: 6.593 | EQ11: 6.593 | ER11: 6.593 | ES11: 6.593 | ET11: 6.593 | EU11: 6.593 | EV11: 6.593 | EW11: 6.593 | EX11: 6.593 | EY11: 6.593 | EZ11: 6.593 | FA11: 6.593 | FB11: 6.593 | FC11: 6.593 | FD11: 6.593 | FE11: 6.593 | FF11: 6.593 | FG11: 6.593 | FH11: 6.593 | FI11: 6.593 | FJ11: 6.593 | FK11: 6.593 | FL11: 6.593 | FM11: 6.593 | FN11: 6.593 | FO11: 6.593 | FP11: 6.593 | FQ11: 6.593 | FR11: 6.593 | FS11: 6.593 | FT11: 6.593 | FU11: 6.593 | FV11: 6.593 | FW11: 6.593 | FX11: 6.593 | FY11: 6.593 | FZ11: 6.593 | GA11: 6.593 | GB11: 6.593 | GC11: 6.593 | GD11: 6.593 | GE11: 6.593 | GF11: 6.593 | GG11: 6.593 | GH11: 6.593 | GI11: 6.593 | GJ11: 6.593 | GK11: 6.593 | GL11: 6.593 | GM11: 6.593 | GN11: 6.593 | GO11: 6.593 | GP11: 6.593 | GQ11: 6.593 | GR11: 6.593 | GS11: 6.593 | GT11: 6.593 | GU11: 6.593 | GV11: 6.593 | GW11: 6.593 | GX11: 6.593 | GY11: 6.593 | GZ11: 6.593 | HA11: 6.593 | HB11: 6.593 | HC11: 6.593 | HD11: 6.593 | HE11: 6.593 | HF11: 6.593 | HG11: 6.593 | HH11: 6.593 | HI11: 6.593 | HJ11: 6.593 | HK11: 6.593 | HL11: 6.50864 | HM11: 0 | HN11: 0 | HO11: 0 | HP11: 0 | HQ11: 0 | HR11: 0 | HS11: 0 | HT11: 0 | HU11: 0 | HV11: 0 | HW11: 0 | HX11: 0 | HY11: 0 | HZ11: 0 | IA11: 0 | IB11: 0 | IC11: 0 | ID11: 0 | IE11: 0 | IF11: 0 | IG11: 0 | IH11: 0 | II11: 0 | IJ11: 0 | IK11: 0 | IL11: 0 | IM11: 0 | IN11: 0 | IO11: 0 | IP11: 0 | IQ11: 0 | IR11: 0 | IS11: 0 | IT11: 0 | IU11: 0 | IV11: 0 | IW11: 0 | IX11: 0 | IY11: 0 | IZ11: 0 | JA11: 0 | JB11: 0 | JC11: 0 | JD11: 0 | JE11: 0 | JF11: 0 | JG11: 0 | JH11: 0 | JI11: 0 | JJ11: 0 | JK11: 0 | JL11: 0 | JM11: 0 | JN11: 0 | JO11: 0 | JP11: 0 | JQ11: 0 | JR11: 0 | JS11: 0 | JT11: 0 | JU11: 0 | JV11: 0 | JW11: 0 | JX11: 0 | JY11: 0 | JZ11: 0 | KA11: 0 | KB11: 0 | KC11: 0 | KD11: 0 | KE11: 0 | KF11: 0 | KG11: 0 | KH11: 0 | KI11: 0 | KJ11: 0 | KK11: 0 | KL11: 0 | KM11: 0 | KN11: 0 | KO11: 0 | KP11: 0 | KQ11: 0 | KR11: 0 | KS11: 0 | KT11: 0 | KU11: 0 | KV11: 0 | KW11: 0 | KX11: 0 | KY11: 0 | KZ11: 0 | LA11: 0 | LB11: 0 | LC11: 0 | LD11: 0 | LE11: 0 | LF11: 0 | LG11: 0 | LH11: 0 | LI11: 0 | LJ11: 0 | LK11: 0 | LL11: 0 | LM11: 0 | LN11: 0 | LO11: 0 | LP11: 0 | LQ11: 0 | LR11: 0 | LS11: 0 | LT11: 0 | LU11: 0 | LV11: 0 | LW11: 0 | LX11: 0 | LY11: 0 | LZ11: 0 | MA11: 0 | MB11: 0 | MC11: 0 | MD11: 0 | ME11: 0 | MF11: 0 | MG11: 0 | MH11: 0 | MI11: 0 | MJ11: 0 | MK11: 0 | ML11: 0 | MM11: 0 | MN11: 0 | MO11: 0 | MP11: 0 | MQ11: 0 | MR11: 0 | MS11: 0 | MT11: 0 | MU11: 0 | MV11: 0 | MW11: 0 | MX11: 0 | MY11: 0 | MZ11: 0
A12: 10 | B12: 202403250121A033 | C12: 6 | D12: 0 | E12: 0 | F12: 0 | G12: 0 | H12: 0 | I12: 0 | J12: 11.839432 | K12: 11.839432 | L12: 11.839432 | M12: 11.839432 | N12: 11.839432 | O12: 11.839432 | P12: 11.839432 | Q12: 11.839432 | R12: 11.839432 | S12: 11.839432 | T12: 11.839432 | U12: 11.839432 | V12: 11.839432 | W12: 11.839432 | X12: 11.839432 | Y12: 11.839432 | Z12: 11.839432 | AA12: 11.839432 | AB12: 11.839432 | AC12: 11.839432 | AD12: 11.839432 | AE12: 11.839432 | AF12: 11.839432 | AG12: 11.839432 | AH12: 11.839432 | AI12: 11.839432 | AJ12: 11.839432 | AK12: 11.839432 | AL12: 11.839432 | AM12: 11.839432 | AN12: 11.839432 | AO12: 11.839432 | AP12: 11.839432 | AQ12: 11.839432 | AR12: 11.839432 | AS12: 11.839432 | AT12: 11.839432 | AU12: 11.839432 | AV12: 11.839432 | AW12: 11.839432 | AX12: 11.839432 | AY12: 11.839432 | AZ12: 11.839432 | BA12: 11.839432 | BB12: 11.839432 | BC12: 11.839432 | BD12: 11.839432 | BE12: 11.839432 | BF12: 11.839432 | BG12: 11.839432 | BH12: 11.839432 | BI12: 11.839432 | BJ12: 11.839432 | BK12: 11.839432 | BL12: 11.839432 | BM12: 11.839432 | BN12: 11.839432 | BO12: 11.839432 | BP12: 11.839432 | BQ12: 11.839432 | BR12: 11.839432 | BS12: 11.839432 | BT12: 11.839432 | BU12: 11.839432 | BV12: 11.839432 | BW12: 11.839432 | BX12: 11.839432 | BY12: 11.839432 | BZ12: 11.839432 | CA12: 11.839432 | CB12: 11.839432 | CC12: 11.839432 | CD12: 11.839432 | CE12: 11.839432 | CF12: 11.839432 | CG12: 11.839432 | CH12: 11.839432 | CI12: 11.839432 | CJ12: 11.839432 | CK12: 11.839432 | CL12: 11.839432 | CM12: 11.839432 | CN12: 11.839432 | CO12: 11.839432 | CP12: 11.839432 | CQ12: 11.839432 | CR12: 11.839432 | CS12: 11.839432 | CT12: 11.839432 | CU12: 11.839432 | CV12: 11.839432 | CW12: 11.839432 | CX12: 11.839432 | CY12: 11.839432 | CZ12: 11.839432 | DA12: 11.839432 | DB12: 11.839432 | DC12: 11.839432 | DD12: 11.839432 | DE12: 11.839432 | DF12: 11.839432 | DG12: 11.839432 | DH12: 11.839432 | DI12: 11.839432 | DJ12: 11.839432 | DK12: 11.839432 | DL12: 11.839432 | DM12: 11.839432 | DN12: 11.839432 | DO12: 11.839432 | DP12: 11.839432 | DQ12: 11.839432 | DR12: 11.839432 | DS12: 11.839432 | DT12: 11.839432 | DU12: 11.839432 | DV12: 11.839432 | DW12: 11.839432 | DX12: 11.839432 | DY12: 11.839432 | DZ12: 11.839432 | EA12: 11.839432 | EB12: 11.839432 | EC12: 11.839432 | ED12: 11.839432 | EE12: 11.839432 | EF12: 11.839432 | EG12: 11.839432 | EH12: 11.839432 | EI12: 11.839432 | EJ12: 11.839432 | EK12: 11.839432 | EL12: 11.839432 | EM12: 11.839432 | EN12: 11.839432 | EO12: 11.839432 | EP12: 11.839432 | EQ12: 11.839432 | ER12: 11.839432 | ES12: 11.839432 | ET12: 11.839432 | EU12: 11.839432 | EV12: 11.839432 | EW12: 11.839432 | EX12: 11.839432 | EY12: 11.839432 | EZ12: 11.839432 | FA12: 11.839432 | FB12: 11.839432 | FC12: 11.839432 | FD12: 11.839432 | FE12: 11.839432 | FF12: 11.839432 | FG12: 11.839432 | FH12: 11.839432 | FI12: 11.839432 | FJ12: 11.839432 | FK12: 11.839432 | FL12: 11.839432 | FM12: 11.839432 | FN12: 11.839432 | FO12: 11.839432 | FP12: 11.839432 | FQ12: 11.839432 | FR12: 11.839432 | FS12: 11.839432 | FT12: 11.839432 | FU12: 11.839432 | FV12: 11.839432 | FW12: 11.839432 | FX12: 11.839432 | FY12: 11.839432 | FZ12: 11.839432 | GA12: 11.839432 | GB12: 11.839432 | GC12: 11.839432 | GD12: 11.839432 | GE12: 11.839432 | GF12: 11.839432 | GG12: 11.839432 | GH12: 11.839432 | GI12: 11.839432 | GJ12: 11.839432 | GK12: 11.839432 | GL12: 11.839432 | GM12: 11.839432 | GN12: 11.839432 | GO12: 11.839432 | GP12: 11.839432 | GQ12: 11.839432 | GR12: 11.839432 | GS12: 11.839432 | GT12: 11.839432 | GU12: 11.839432 | GV12: 11.839432 | GW12: 11.839432 | GX12: 11.839432 | GY12: 11.839432 | GZ12: 11.839432 | HA12: 11.839432 | HB12: 11.839432 | HC12: 11.839432 | HD12: 11.839432 | HE12: 11.839432 | HF12: 11.839432 | HG12: 11.839432 | HH12: 11.839432 | HI12: 11.839432 | HJ12: 11.839432 | HK12: 11.839432 | HL12: 11.839432 | HM12: 11.839432 | HN12: 11.839432 | HO12: 11.839432 | HP12: 11.839432 | HQ12: 11.839432 | HR12: 11.839432 | HS12: 11.839432 | HT12: 11.839432 | HU12: 11.839432 | HV12: 11.839432 | HW12: 11.839432 | HX12: 11.839432 | HY12: 11.839432 | HZ12: 11.839432 | IA12: 11.839432 | IB12: 11.839432 | IC12: 11.839432 | ID12: 11.839432 | IE12: 11.839432 | IF12: 11.839432 | IG12: 11.839432 | IH12: 11.839432 | II12: 11.839432 | IJ12: 11.839432 | IK12: 11.839432 | IL12: 11.839432 | IM12: 11.839432 | IN12: 11.839432 | IO12: 11.839432 | IP12: 11.839432 | IQ12: 11.839432 | IR12: 11.839432 | IS12: 11.839432 | IT12: 11.839432 | IU12: 11.839432 | IV12: 11.839432 | IW12: 11.839432 | IX12: 11.839432 | IY12: 11.839432 | IZ12: 11.839432 | JA12: 11.839432 | JB12: 11.839432 | JC12: 11.839432 | JD12: 11.839432 | JE12: 11.839432 | JF12: 11.839432 | JG12: 11.839432 | JH12: 11.839432 | JI12: 11.839432 | JJ12: 11.839432 | JK12: 11.839432 | JL12: 11.839432 | JM12: 11.839432 | JN12: 11.839432 | JO12: 11.839432 | JP12: 11.839432 | JQ12: 11.839432 | JR12: 11.839432 | JS12: 11.839432 | JT12: 11.839432 | JU12: 11.839432 | JV12: 11.839432 | JW12: 11.839432 | JX12: 11.839432 | JY12: 11.839432 | JZ12: 11.839432 | KA12: 11.839432 | KB12: 11.839432 | KC12: 11.839432 | KD12: 11.839432 | KE12: 11.839432 | KF12: 11.839432 | KG12: 11.839432 | KH12: 11.839432 | KI12: 11.839432 | KJ12: 11.839432 | KK12: 11.839432 | KL12: 11.839432 | KM12: 11.839432 | KN12: 11.839432 | KO12: 11.839432 | KP12: 11.839432 | KQ12: 11.839432 | KR12: 11.839432 | KS12: 11.839432 | KT12: 11.839432 | KU12: 11.839432 | KV12: 11.839432 | KW12: 11.839432 | KX12: 11.839432 | KY12: 11.839432 | KZ12: 11.839432 | LA12: 11.839432 | LB12: 11.839432 | LC12: 11.839432 | LD12: 11.839432 | LE12: 11.839432 | LF12: 11.839432 | LG12: 11.839432 | LH12: 11.839432 | LI12: 11.839432 | LJ12: 11.839432 | LK12: 11.839432 | LL12: 11.839432 | LM12: 11.839432 | LN12: 11.839432 | LO12: 11.839432 | LP12: 11.839432 | LQ12: 11.839432 | LR12: 11.839432 | LS12: 11.839432 | LT12: 11.839432 | LU12: 11.839432 | LV12: 11.839432 | LW12: 11.839432 | LX12: 11.839432 | LY12: 11.839432 | LZ12: 11.839432 | MA12: 11.839432 | MB12: 11.839432 | MC12: 11.839432 | MD12: 11.839432 | ME12: 11.839432 | MF12: 11.839432 | MG12: 11.839432 | MH12: 11.839432 | MI12: 11.839432 | MJ12: 11.839432 | MK12: 11.839432 | ML12: 11.839432 | MM12: 11.839432 | MN12: 11.839432 | MO12: 11.839432 | MP12: 11.839432 | MQ12: 11.839432 | MR12: 11.839432 | MS12: 11.839432 | MT12: 11.839432 | MU12: 11.839432 | MV12: 11.839432 | MW12: 11.839432 | MX12: 11.839432 | MY12: 11.839432 | MZ12: 12.153768
A13: 11 | B13: 202403250123A033 | C13: 6 | D13: 0 | E13: 0 | F13: 0 | G13: 0 | H13: 0 | I13: 0 | J13: 7.236418 | K13: 7.236418 | L13: 7.236418 | M13: 7.236418 | N13: 7.236418 | O13: 7.236418 | P13: 7.236418 | Q13: 7.236418 | R13: 7.236418 | S13: 7.236418 | T13: 7.236418 | U13: 7.236418 | V13: 7.236418 | W13: 7.236418 | X13: 7.236418 | Y13: 7.236418 | Z13: 7.236418 | AA13: 7.236418 | AB13: 7.236418 | AC13: 7.236418 | AD13: 7.236418 | AE13: 7.236418 | AF13: 7.236418 | AG13: 7.236418 | AH13: 7.236418 | AI13: 7.236418 | AJ13: 7.236418 | AK13: 7.236418 | AL13: 7.236418 | AM13: 7.236418 | AN13: 7.236418 | AO13: 7.236418 | AP13: 7.236418 | AQ13: 7.236418 | AR13: 7.236418 | AS13: 7.236418 | AT13: 7.236418 | AU13: 7.236418 | AV13: 7.236418 | AW13: 7.236418 | AX13: 7.236418 | AY13: 7.236418 | AZ13: 7.236418 | BA13: 7.236418 | BB13: 7.236418 | BC13: 7.236418 | BD13: 7.236418 | BE13: 7.236418 | BF13: 7.236418 | BG13: 7.236418 | BH13: 7.236418 | BI13: 7.236418 | BJ13: 7.236418 | BK13: 7.236418 | BL13: 7.236418 | BM13: 7.236418 | BN13: 7.236418 | BO13: 7.236418 | BP13: 7.236418 | BQ13: 7.236418 | BR13: 7.236418 | BS13: 7.236418 | BT13: 7.236418 | BU13: 7.236418 | BV13: 7.236418 | BW13: 7.236418 | BX13: 7.236418 | BY13: 7.236418 | BZ13: 7.236418 | CA13: 7.236418 | CB13: 7.236418 | CC13: 7.236418 | CD13: 7.236418 | CE13: 7.236418 | CF13: 7.236418 | CG13: 7.236418 | CH13: 7.236418 | CI13: 7.236418 | CJ13: 7.236418 | CK13: 7.236418 | CL13: 7.236418 | CM13: 7.236418 | CN13: 7.236418 | CO13: 7.236418 | CP13: 7.236418 | CQ13: 7.236418 | CR13: 7.236418 | CS13: 7.236418 | CT13: 7.236418 | CU13: 7.236418 | CV13: 7.236418 | CW13: 7.236418 | CX13: 7.236418 | CY13: 7.236418 | CZ13: 7.236418 | DA13: 7.236418 | DB13: 7.236418 | DC13: 7.236418 | DD13: 7.236418 | DE13: 7.236418 | DF13: 7.236418 | DG13: 7.236418 | DH13: 7.236418 | DI13: 7.236418 | DJ13: 7.236418 | DK13: 7.236418 | DL13: 7.236418 | DM13: 7.236418 | DN13: 7.236418 | DO13: 7.236418 | DP13: 7.236418 | DQ13: 7.236418 | DR13: 7.236418 | DS13: 7.236418 | DT13: 7.236418 | DU13: 7.236418 | DV13: 7.236418 | DW13: 7.236418 | DX13: 7.236418 | DY13: 7.236418 | DZ13: 7.236418 | EA13: 7.236418 | EB13: 7.236418 | EC13: 7.236418 | ED13: 7.236418 | EE13: 7.236418 | EF13: 7.236418 | EG13: 7.236418 | EH13: 7.236418 | EI13: 7.236418 | EJ13: 7.236418 | EK13: 7.236418 | EL13: 7.236418 | EM13: 7.236418 | EN13: 7.236418 | EO13: 7.236418 | EP13: 7.236418 | EQ13: 7.236418 | ER13: 7.236418 | ES13: 7.236418 | ET13: 7.236418 | EU13: 7.236418 | EV13: 7.236418 | EW13: 7.236418 | EX13: 7.236418 | EY13: 7.236418 | EZ13: 7.236418 | FA13: 7.236418 | FB13: 7.236418 | FC13: 7.236418 | FD13: 7.236418 | FE13: 7.236418 | FF13: 7.236418 | FG13: 7.236418 | FH13: 7.236418 | FI13: 7.236418 | FJ13: 7.236418 | FK13: 7.236418 | FL13: 7.236418 | FM13: 7.236418 | FN13: 7.236418 | FO13: 7.236418 | FP13: 7.236418 | FQ13: 7.236418 | FR13: 7.236418 | FS13: 7.236418 | FT13: 7.236418 | FU13: 7.236418 | FV13: 7.236418 | FW13: 7.236418 | FX13: 7.236418 | FY13: 7.236418 | FZ13: 7.236418 | GA13: 7.236418 | GB13: 7.236418 | GC13: 7.236418 | GD13: 7.236418 | GE13: 7.236418 | GF13: 7.236418 | GG13: 7.236418 | GH13: 7.236418 | GI13: 7.236418 | GJ13: 7.236418 | GK13: 7.236418 | GL13: 7.236418 | GM13: 7.236418 | GN13: 7.236418 | GO13: 7.236418 | GP13: 7.236418 | GQ13: 7.236418 | GR13: 7.236418 | GS13: 7.236418 | GT13: 7.236418 | GU13: 7.236418 | GV13: 7.236418 | GW13: 7.236418 | GX13: 7.236418 | GY13: 7.236418 | GZ13: 7.236418 | HA13: 7.236418 | HB13: 7.236418 | HC13: 7.236418 | HD13: 7.236418 | HE13: 7.236418 | HF13: 7.236418 | HG13: 7.236418 | HH13: 7.236418 | HI13: 7.236418 | HJ13: 7.236418 | HK13: 7.236418 | HL13: 7.236418 | HM13: 7.236418 | HN13: 7.236418 | HO13: 7.236418 | HP13: 7.236418 | HQ13: 7.236418 | HR13: 7.236418 | HS13: 7.236418 | HT13: 7.236418 | HU13: 7.236418 | HV13: 7.236418 | HW13: 7.236418 | HX13: 7.236418 | HY13: 7.236418 | HZ13: 7.236418 | IA13: 7.236418 | IB13: 7.236418 | IC13: 7.236418 | ID13: 7.236418 | IE13: 7.236418 | IF13: 7.236418 | IG13: 7.236418 | IH13: 7.236418 | II13: 7.236418 | IJ13: 7.068762 | IK13: 0 | IL13: 0 | IM13: 0 | IN13: 0 | IO13: 0 | IP13: 0 | IQ13: 0 | IR13: 0 | IS13: 0 | IT13: 0 | IU13: 0 | IV13: 0 | IW13: 0 | IX13: 0 | IY13: 0 | IZ13: 0 | JA13: 0 | JB13: 0 | JC13: 0 | JD13: 0 | JE13: 0 | JF13: 0 | JG13: 0 | JH13: 0 | JI13: 0 | JJ13: 0 | JK13: 0 | JL13: 0 | JM13: 0 | JN13: 0 | JO13: 0 | JP13: 0 | JQ13: 0 | JR13: 0 | JS13: 0 | JT13: 0 | JU13: 0 | JV13: 0 | JW13: 0 | JX13: 0 | JY13: 0 | JZ13: 0 | KA13: 0 | KB13: 0 | KC13: 0 | KD13: 0 | KE13: 0 | KF13: 0 | KG13: 0 | KH13: 0 | KI13: 0 | KJ13: 0 | KK13: 0 | KL13: 0 | KM13: 0 | KN13: 0 | KO13: 0 | KP13: 0 | KQ13: 0 | KR13: 0 | KS13: 0 | KT13: 0 | KU13: 0 | KV13: 0 | KW13: 0 | KX13: 0 | KY13: 0 | KZ13: 0 | LA13: 0 | LB13: 0 | LC13: 0 | LD13: 0 | LE13: 0 | LF13: 0 | LG13: 0 | LH13: 0 | LI13: 0 | LJ13: 0 | LK13: 0 | LL13: 0 | LM13: 0 | LN13: 0 | LO13: 0 | LP13: 0 | LQ13: 0 | LR13: 0 | LS13: 0 | LT13: 0 | LU13: 0 | LV13: 0 | LW13: 0 | LX13: 0 | LY13: 0 | LZ13: 0 | MA13: 0 | MB13: 0 | MC13: 0 | MD13: 0 | ME13: 0 | MF13: 0 | MG13: 0 | MH13: 0 | MI13: 0 | MJ13: 0 | MK13: 0 | ML13: 0 | MM13: 0 | MN13: 0 | MO13: 0 | MP13: 0 | MQ13: 0 | MR13: 0 | MS13: 0 | MT13: 0 | MU13: 0 | MV13: 0 | MW13: 0 | MX13: 0 | MY13: 0 | MZ13: 0
A14: 12 | B14: 202403250125A033 | C14: 6 | D14: 0 | E14: 0 | F14: 0 | G14: 0 | H14: 0 | I14: 0 | J14: 6.850911 | K14: 6.850911 | L14: 6.850911 | M14: 6.850911 | N14: 6.850911 | O14: 6.850911 | P14: 6.850911 | Q14: 6.850911 | R14: 6.850911 | S14: 6.850911 | T14: 6.850911 | U14: 6.850911 | V14: 6.850911 | W14: 6.850911 | X14: 6.850911 | Y14: 6.850911 | Z14: 6.850911 | AA14: 6.850911 | AB14: 6.850911 | AC14: 6.850911 | AD14: 6.850911 | AE14: 6.850911 | AF14: 6.850911 | AG14: 6.850911 | AH14: 6.850911 | AI14: 6.850911 | AJ14: 6.850911 | AK14: 6.850911 | AL14: 6.850911 | AM14: 6.850911 | AN14: 6.850911 | AO14: 6.850911 | AP14: 6.850911 | AQ14: 6.850911 | AR14: 6.850911 | AS14: 6.850911 | AT14: 6.850911 | AU14: 6.850911 | AV14: 6.850911 | AW14: 6.850911 | AX14: 6.850911 | AY14: 6.850911 | AZ14: 6.850911 | BA14: 6.850911 | BB14: 6.850911 | BC14: 6.850911 | BD14: 6.850911 | BE14: 6.850911 | BF14: 6.850911 | BG14: 6.850911 | BH14: 6.850911 | BI14: 6.850911 | BJ14: 6.850911 | BK14: 6.850911 | BL14: 6.850911 | BM14: 6.850911 | BN14: 6.850911 | BO14: 6.850911 | BP14: 6.850911 | BQ14: 6.850911 | BR14: 6.850911 | BS14: 6.850911 | BT14: 6.850911 | BU14: 6.850911 | BV14: 6.850911 | BW14: 6.850911 | BX14: 6.850911 | BY14: 6.850911 | BZ14: 6.850911 | CA14: 6.850911 | CB14: 6.850911 | CC14: 6.850911 | CD14: 6.850911 | CE14: 6.850911 | CF14: 6.850911 | CG14: 6.850911 | CH14: 6.850911 | CI14: 6.850911 | CJ14: 6.850911 | CK14: 6.850911 | CL14: 6.850911 | CM14: 6.850911 | CN14: 6.850911 | CO14: 6.850911 | CP14: 6.850911 | CQ14: 6.850911 | CR14: 6.850911 | CS14: 6.850911 | CT14: 6.850911 | CU14: 6.850911 | CV14: 6.850911 | CW14: 6.850911 | CX14: 6.850911 | CY14: 6.850911 | CZ14: 6.850911 | DA14: 6.850911 | DB14: 6.850911 | DC14: 6.850911 | DD14: 6.850911 | DE14: 6.850911 | DF14: 6.850911 | DG14: 6.850911 | DH14: 6.850911 | DI14: 6.850911 | DJ14: 6.850911 | DK14: 6.850911 | DL14: 6.850911 | DM14: 6.850911 | DN14: 6.850911 | DO14: 6.850911 | DP14: 6.850911 | DQ14: 6.850911 | DR14: 6.850911 | DS14: 6.850911 | DT14: 6.850911 | DU14: 6.850911 | DV14: 6.850911 | DW14: 6.850911 | DX14: 6.850911 | DY14: 6.850911 | DZ14: 6.850911 | EA14: 6.850911 | EB14: 6.850911 | EC14: 6.850911 | ED14: 6.850911 | EE14: 6.850911 | EF14: 6.850911 | EG14: 6.850911 | EH14: 6.850911 | EI14: 6.850911 | EJ14: 6.850911 | EK14: 6.850911 | EL14: 6.850911 | EM14: 6.850911 | EN14: 6.850911 | EO14: 6.850911 | EP14: 6.850911 | EQ14: 6.850911 | ER14: 6.850911 | ES14: 6.850911 | ET14: 6.850911 | EU14: 6.850911 | EV14: 6.850911 | EW14: 6.850911 | EX14: 6.850911 | EY14: 6.850911 | EZ14: 6.850911 | FA14: 6.850911 | FB14: 6.850911 | FC14: 6.850911 | FD14: 6.850911 | FE14: 6.850911 | FF14: 6.850911 | FG14: 6.850911 | FH14: 6.850911 | FI14: 6.850911 | FJ14: 6.850911 | FK14: 6.850911 | FL14: 6.850911 | FM14: 6.850911 | FN14: 6.850911 | FO14: 6.850911 | FP14: 6.850911 | FQ14: 6.850911 | FR14: 6.850911 | FS14: 6.850911 | FT14: 6.850911 | FU14: 6.850911 | FV14: 6.850911 | FW14: 6.850911 | FX14: 6.850911 | FY14: 6.850911 | FZ14: 6.850911 | GA14: 6.850911 | GB14: 6.850911 | GC14: 6.850911 | GD14: 6.850911 | GE14: 6.850911 | GF14: 6.850911 | GG14: 6.850911 | GH14: 6.850911 | GI14: 6.850911 | GJ14: 6.850911 | GK14: 6.850911 | GL14: 6.850911 | GM14: 6.850911 | GN14: 6.850911 | GO14: 6.850911 | GP14: 6.850911 | GQ14: 6.850911 | GR14: 6.850911 | GS14: 6.850911 | GT14: 6.850911 | GU14: 6.850911 | GV14: 6.850911 | GW14: 6.850911 | GX14: 6.850911 | GY14: 6.850911 | GZ14: 6.893849 | HA14: 0 | HB14: 0 | HC14: 0 | HD14: 0 | HE14: 0 | HF14: 0 | HG14: 0 | HH14: 0 | HI14: 0 | HJ14: 0 | HK14: 0 | HL14: 0 | HM14: 0 | HN14: 0 | HO14: 0 | HP14: 0 | HQ14: 0 | HR14: 0 | HS14: 0 | HT14: 0 | HU14: 0 | HV14: 0 | HW14: 0 | HX14: 0 | HY14: 0 | HZ14: 0 | IA14: 0 | IB14: 0 | IC14: 0 | ID14: 0 | IE14: 0 | IF14: 0 | IG14: 0 | IH14: 0 | II14: 0 | IJ14: 0 | IK14: 0 | IL14: 0 | IM14: 0 | IN14: 0 | IO14: 0 | IP14: 0 | IQ14: 0 | IR14: 0 | IS14: 0 | IT14: 0 | IU14: 0 | IV14: 0 | IW14: 0 | IX14: 0 | IY14: 0 | IZ14: 0 | JA14: 0 | JB14: 0 | JC14: 0 | JD14: 0 | JE14: 0 | JF14: 0 | JG14: 0 | JH14: 0 | JI14: 0 | JJ14: 0 | JK14: 0 | JL14: 0 | JM14: 0 | JN14: 0 | JO14: 0 | JP14: 0 | JQ14: 0 | JR14: 0 | JS14: 0 | JT14: 0 | JU14: 0 | JV14: 0 | JW14: 0 | JX14: 0 | JY14: 0 | JZ14: 0 | KA14: 0 | KB14: 0 | KC14: 0 | KD14: 0 | KE14: 0 | KF14: 0 | KG14: 0 | KH14: 0 | KI14: 0 | KJ14: 0 | KK14: 0 | KL14: 0 | KM14: 0 | KN14: 0 | KO14: 0 | KP14: 0 | KQ14: 0 | KR14: 0 | KS14: 0 | KT14: 0 | KU14: 0 | KV14: 0 | KW14: 0 | KX14: 0 | KY14: 0 | KZ14: 0 | LA14: 0 | LB14: 0 | LC14: 0 | LD14: 0 | LE14: 0 | LF14: 0 | LG14: 0 | LH14: 0 | LI14: 0 | LJ14: 0 | LK14: 0 | LL14: 0 | LM14: 0 | LN14: 0 | LO14: 0 | LP14: 0 | LQ14: 0 | LR14: 0 | LS14: 0 | LT14: 0 | LU14: 0 | LV14: 0 | LW14: 0 | LX14: 0 | LY14: 0 | LZ14: 0 | MA14: 0 | MB14: 0 | MC14: 0 | MD14: 0 | ME14: 0 | MF14: 0 | MG14: 0 | MH14: 0 | MI14: 0 | MJ14: 0 | MK14: 0 | ML14: 0 | MM14: 0 | MN14: 0 | MO14: 0 | MP14: 0 | MQ14: 0 | MR14: 0 | MS14: 0 | MT14: 0 | MU14: 0 | MV14: 0 | MW14: 0 | MX14: 0 | MY14: 0 | MZ14: 0
... A22: 20 | B22: 202403250138A033 | C22: 6 | D22: 0 | E22: 0 | F22: 0 | G22: 0 | H22: 0 | I22: 0 | J22: 13.17 | K22: 13.17 | L22: 13.17 | M22: 13.17 | N22: 13.17 | O22: 13.17 | P22: 13.17 | Q22: 13.17 | R22: 13.17 | S22: 13.17 | T22: 13.17 | U22: 13.17 | V22: 13.17 | W22: 13.17 | X22: 13.17 | Y22: 13.17 | Z22: 13.17 | AA22: 13.17 | AB22: 13.17 | AC22: 13.17 | AD22: 13.17 | AE22: 13.17 | AF22: 13.17 | AG22: 13.17 | AH22: 13.17 | AI22: 13.17 | AJ22: 13.17 | AK22: 13.17 | AL22: 13.17 | AM22: 13.17 | AN22: 13.17 | AO22: 13.17 | AP22: 13.17 | AQ22: 13.17 | AR22: 13.17 | AS22: 13.17 | AT22: 13.17 | AU22: 13.17 | AV22: 13.17 | AW22: 13.17 | AX22: 13.17 | AY22: 13.17 | AZ22: 13.17 | BA22: 13.17 | BB22: 13.17 | BC22: 13.17 | BD22: 13.17 | BE22: 13.17 | BF22: 13.17 | BG22: 13.17 | BH22: 13.17 | BI22: 13.17 | BJ22: 13.17 | BK22: 13.17 | BL22: 13.17 | BM22: 13.17 | BN22: 13.17 | BO22: 13.17 | BP22: 13.17 | BQ22: 13.17 | BR22: 13.17 | BS22: 13.17 | BT22: 13.17 | BU22: 13.17 | BV22: 13.17 | BW22: 13.17 | BX22: 13.17 | BY22: 13.17 | BZ22: 13.17 | CA22: 13.17 | CB22: 13.17 | CC22: 13.17 | CD22: 13.17 | CE22: 13.17 | CF22: 13.17 | CG22: 13.17 | CH22: 13.17 | CI22: 13.17 | CJ22: 13.17 | CK22: 13.17 | CL22: 13.17 | CM22: 13.17 | CN22: 13.17 | CO22: 13.17 | CP22: 13.17 | CQ22: 13.17 | CR22: 13.17 | CS22: 13.17 | CT22: 13.17 | CU22: 13.17 | CV22: 13.17 | CW22: 13.17 | CX22: 13.17 | CY22: 13.17 | CZ22: 13.17 | DA22: 13.17 | DB22: 13.17 | DC22: 13.17 | DD22: 13.17 | DE22: 13.17 | DF22: 13.17 | DG22: 13.17 | DH22: 13.17 | DI22: 13.17 | DJ22: 13.17 | DK22: 13.17 | DL22: 13.17 | DM22: 13.17 | DN22: 13.17 | DO22: 13.17 | DP22: 13.17 | DQ22: 13.17 | DR22: 13.17 | DS22: 13.17 | DT22: 13.17 | DU22: 13.17 | DV22: 13.17 | DW22: 13.17 | DX22: 13.17 | DY22: 13.17 | DZ22: 13.17 | EA22: 13.17 | EB22: 13.17 | EC22: 13.17 | ED22: 13.17 | EE22: 13.17 | EF22: 13.17 | EG22: 13.17 | EH22: 13.17 | EI22: 13.17 | EJ22: 13.17 | EK22: 13.17 | EL22: 13.17 | EM22: 13.17 | EN22: 13.17 | EO22: 13.17 | EP22: 13.17 | EQ22: 13.17 | ER22: 13.17 | ES22: 13.17 | ET22: 13.17 | EU22: 13.17 | EV22: 13.17 | EW22: 13.17 | EX22: 13.17 | EY22: 13.17 | EZ22: 13.17 | FA22: 13.17 | FB22: 13.17 | FC22: 13.17 | FD22: 13.17 | FE22: 13.17 | FF22: 13.17 | FG22: 13.17 | FH22: 13.17 | FI22: 13.17 | FJ22: 13.17 | FK22: 13.17 | FL22: 13.17 | FM22: 13.17 | FN22: 13.17 | FO22: 13.17 | FP22: 13.17 | FQ22: 13.17 | FR22: 13.17 | FS22: 13.17 | FT22: 13.17 | FU22: 13.17 | FV22: 13.17 | FW22: 13.17 | FX22: 13.17 | FY22: 13.17 | FZ22: 13.17 | GA22: 13.17 | GB22: 13.17 | GC22: 13.17 | GD22: 13.17 | GE22: 13.17 | GF22: 13.17 | GG22: 13.17 | GH22: 13.17 | GI22: 13.17 | GJ22: 13.17 | GK22: 13.17 | GL22: 13.17 | GM22: 13.17 | GN22: 13.17 | GO22: 13.17 | GP22: 13.17 | GQ22: 13.17 | GR22: 13.17 | GS22: 13.17 | GT22: 13.17 | GU22: 13.17 | GV22: 13.17 | GW22: 13.17 | GX22: 13.17 | GY22: 13.17 | GZ22: 13.17 | HA22: 13.17 | HB22: 13.17 | HC22: 13.17 | HD22: 13.17 | HE22: 13.17 | HF22: 13.17 | HG22: 13.17 | HH22: 13.17 | HI22: 13.17 | HJ22: 13.17 | HK22: 13.17 | HL22: 13.17 | HM22: 13.17 | HN22: 13.17 | HO22: 13.17 | HP22: 13.17 | HQ22: 13.17 | HR22: 13.17 | HS22: 13.17 | HT22: 13.17 | HU22: 13.17 | HV22: 13.17 | HW22: 13.17 | HX22: 13.17 | HY22: 13.17 | HZ22: 13.17 | IA22: 13.17 | IB22: 13.17 | IC22: 13.17 | ID22: 13.17 | IE22: 13.17 | IF22: 13.17 | IG22: 13.17 | IH22: 13.17 | II22: 13.17 | IJ22: 13.17 | IK22: 13.17 | IL22: 13.17 | IM22: 13.17 | IN22: 13.17 | IO22: 13.17 | IP22: 13.17 | IQ22: 13.17 | IR22: 13.17 | IS22: 13.17 | IT22: 13.17 | IU22: 13.17 | IV22: 13.17 | IW22: 13.17 | IX22: 13.17 | IY22: 13.17 | IZ22: 13.17 | JA22: 13.17 | JB22: 13.17 | JC22: 13.17 | JD22: 13.17 | JE22: 13.17 | JF22: 13.17 | JG22: 13.17 | JH22: 13.17 | JI22: 13.17 | JJ22: 13.17 | JK22: 13.17 | JL22: 13.17 | JM22: 13.17 | JN22: 13.17 | JO22: 13.17 | JP22: 13.17 | JQ22: 13.17 | JR22: 13.17 | JS22: 13.17 | JT22: 13.17 | JU22: 13.17 | JV22: 13.17 | JW22: 13.17 | JX22: 13.17 | JY22: 13.17 | JZ22: 13.17 | KA22: 13.17 | KB22: 13.17 | KC22: 13.17 | KD22: 13.17 | KE22: 13.17 | KF22: 13.17 | KG22: 13.17 | KH22: 13.17 | KI22: 13.17 | KJ22: 13.17 | KK22: 13.17 | KL22: 13.17 | KM22: 13.17 | KN22: 13.17 | KO22: 13.17 | KP22: 13.17 | KQ22: 13.17 | KR22: 13.17 | KS22: 13.17 | KT22: 13.17 | KU22: 13.17 | KV22: 13.17 | KW22: 13.17 | KX22: 13.17 | KY22: 13.17 | KZ22: 13.17 | LA22: 13.17 | LB22: 13.17 | LC22: 13.17 | LD22: 13.17 | LE22: 13.17 | LF22: 13.17 | LG22: 13.17 | LH22: 13.17 | LI22: 13.17 | LJ22: 13.17 | LK22: 13.17 | LL22: 13.17 | LM22: 13.17 | LN22: 13.17 | LO22: 13.17 | LP22: 13.17 | LQ22: 13.17 | LR22: 13.17 | LS22: 13.17 | LT22: 13.17 | LU22: 13.17 | LV22: 13.17 | LW22: 13.17 | LX22: 13.17 | LY22: 13.17 | LZ22: 13.17 | MA22: 13.17 | MB22: 13.17 | MC22: 13.17 | MD22: 13.17 | ME22: 13.17 | MF22: 13.17 | MG22: 13.17 | MH22: 13.17 | MI22: 13.17 | MJ22: 13.17 | MK22: 13.17 | ML22: 13.17 | MM22: 13.17 | MN22: 13.17 | MO22: 13.17 | MP22: 13.17 | MQ22: 13.17 | MR22: 13.17 | MS22: 13.17 | MT22: 13.17 | MU22: 13.17 | MV22: 13.17 | MW22: 13.17 | MX22: 13.17 | MY22: 13.17 | MZ22: 13.52

Sheet Comuna
A1: COMUNA | B1: CODCOMUNA
A2: Algarrobo | B2: 5602
A3: Alhué | B3: 13502
A4: Alto Biobío | B4: 8314
A5: Alto del Carmen | B5: 3302
A6: Alto Hospicio | B6: 1107
A7: Ancud | B7: 10202
A8: Andacollo | B8: 4103
A9: Angol | B9: 9201
A10: Antártica | B10: 12202
A11: Antofagasta | B11: 2101
A12: Antuco | B12: 8302
A13: Arauco | B13: 8202
... A348: Zapallar | B348: 5405

Sheet Contrato
A1: N° | B1: Día_contrato | C1: Mes_contrato | D1: año_contrato | F1: día_firma | G1: mes_firma | H1: año_firma | I1: Prefijo 1 | J1: Cliente | K1: Rut | L1: DV | M1: Valor_Credito | N1: Plazo_Meses | O1: Dirección_Gtia | P1: Comuna | Q1: Región | R1: Prefijo 2 | S1: Notaria | T1: Repertorio | U1: Valorización | V1: Comuna notario
A2: 1 | B2: 8 | C2: Julio | D2: 2019 | E2: =Base!Y2 -> 0.0057559073 | F2: =DAY(E2) -> 0 | G2: =TEXT(E2,"mmmm") -> enero | H2: =YEAR(E2) -> 1900 | I2: Doña | J2: =Base!H2&" "&Base!F2&" "&Base!G2 -> Joel Alejandro Diaz Zuñiga | K2: 17993152 | L2: =Base!E2 -> 9 | M2: =Base!S2 -> 0.725 | N2: =Base!P2 -> 0.0060683124 | O2: =Base!AF2 -> 1647.6019 | P2: =Base!AG2 -> Calle 8 Sur Poniente 351,casa 351 | Q2: =Base!AI2 -> Biobío | R2: Doña | S2: Maria Soledad Lascar | T2: 17455 | U2: 1216,27 | V2: Santiago
A3: 2 | B3: 8 | C3: Julio | D3: 2019 | E3: =Base!Y3 -> 0.0057559073 | F3: =DAY(E3) -> 0 | G3: =TEXT(E3,"mmmm") -> enero | H3: =YEAR(E3) -> 1900 | I3: Don | J3: =Base!H3&" "&Base!F3&" "&Base!G3 -> Daniela Del Carmen Hultazo Novoa | K3: 17621952 | L3: =Base!E3 -> 9 | M3: =Base!S3 -> 0.67294545 | N3: =Base!P3 -> 0.0060683124 | O3: =Base!AF3 -> 1534.7211 | P3: =Base!AG3 -> ADRIANA GARCIA IBAÑEZ 2030, Edificio G,departamento 303 | Q3: =Base!AI3 -> Linares | R3: Doña | S3: Lorena Jorquera | T3: 20884 | U3: 2448,23 | V3: Antofagasta
A4: 3 | B4: 8 | C4: Julio | D4: 2019 | E4: =Base!Y4 -> 0.0057559073 | F4: =DAY(E4) -> 0 | G4: =TEXT(E4,"mmmm") -> enero | H4: =YEAR(E4) -> 1900 | I4: Doña | J4: =Base!H4&" "&Base!F4&" "&Base!G4 -> Nedier Graciela Salazar Carvajal | K4: 11660191 | L4: =Base!E4 -> 7 | M4: =Base!S4 -> 0.61711429 | N4: =Base!P4 -> 0.0060683124 | O4: =Base!AF4 -> 892.6874 | P4: =Base!AG4 -> Camino La Vara 02600, Torre 1,departamento 406 | Q4: =Base!AI4 -> Maipo | R4: Doña | S4: Elena Leyton Carvajal | T4: 1437 | U4: 1775,24 | V4: La Serena
A5: 4 | B5: 8 | C5: Julio | D5: 2019 | E5: =Base!Y5 -> 0.0057559073 | F5: =DAY(E5) -> 0 | G5: =TEXT(E5,"mmmm") -> enero | H5: =YEAR(E5) -> 1900 | I5: Don | J5: =Base!#REF!&" "&Base!#REF!&" "&Base!#REF! -> #REF! | K5: 13289022 | L5: =Base!E5 -> 2 | M5: =Base!S5 -> 0.74652174 | N5: =Base!P5 -> 0.0060683124 | O5: =Base!AF5 -> 1768.2353 | P5: =Base!AG5 -> Calle 38 Oriente 350, Torre 8,departamento 2804 | Q5: =Base!AI5 -> Talca | R5: Doña | S5: Maria Soledad Lascar | T5: 22222 | U5: 1717,81 | V5: Santiago
A6: 5 | B6: 8 | C6: Julio | D6: 2019 | E6: =Base!Y6 -> 0.0057559073 | F6: =DAY(E6) -> 0 | G6: =TEXT(E6,"mmmm") -> enero | H6: =YEAR(E6) -> 1900 | I6: Doña | J6: =Base!H6&" "&Base!F6&" "&Base!G6 -> César Antonio Huenchul Colihuinca | K6: 17914896 | L6: =Base!E6 -> 2 | M6: =Base!S6 -> 0.74956522 | N6: =Base!P6 -> 0.0060683124 | O6: =Base!AF6 -> 1609.4065 | P6: =Base!AG6 -> Camino La Vara 02600, TORRE 2,departamento 412 | Q6: =Base!AI6 -> Maipo | R6: Doña | S6: Elena Leyton Carvajal | T6: 1520 | U6: 1301,63 | V6: La Serena
A7: 6 | B7: 8 | C7: Julio | D7: 2019 | E7: =Base!Y7 -> 0.0057559073 | F7: =DAY(E7) -> 0 | G7: =TEXT(E7,"mmmm") -> enero | H7: =YEAR(E7) -> 1900 | I7: Doña | J7: =Base!H7&" "&Base!F7&" "&Base!G7 -> Claudio Sebastian Rojas Diaz | K7: 14277619 | L7: =Base!E7 -> 1 | M7: =Base!S7 -> 0.61638148 | N7: =Base!P7 -> 0.0060683124 | O7: =Base!AF7 -> 1719.0581 | P7: =Base!AG7 -> Los Libertadores 4733, Edificio F,departamento 106 | Q7: =Base!AI7 -> Santiago | R7: Doña | S7: Maria Soledad Lascar | T7: 22710 | U7: 1240,37 | V7: Santiago
A8: 7 | B8: 8 | C8: Julio | D8: 2019 | E8: =Base!Y8 -> 0.0057559073 | F8: =DAY(E8) -> 0 | G8: =TEXT(E8,"mmmm") -> enero | H8: =YEAR(E8) -> 1900 | I8: Don | J8: =Base!H8&" "&Base!F8&" "&Base!G8 -> Pablo Daniel Lagos Muñoz | K8: 15449863 | L8: =Base!E8 -> 4 | M8: =Base!S8 -> 0.72487778 | N8: =Base!P8 -> 0.0060683124 | O8: =Base!AF8 -> 1691.4151 | P8: =Base!AG8 -> ADRIANA GARCIA IBAÑEZ 2030, Torre B,departamento 401 | Q8: =Base!AI8 -> Linares | R8: Doña | S8: Maria Soledad Lascar | T8: 23038 | U8: 1706,31 | V8: Santiago
A9: 8 | B9: 8 | C9: Julio | D9: 2019 | E9: =Base!#REF! -> #REF! | F9: =DAY(E9) -> #REF! | G9: =TEXT(E9,"mmmm") -> #REF! | H9: =YEAR(E9) -> #REF! | I9: Don | J9: =Base!#REF!&" "&Base!#REF!&" "&Base!#REF! -> #REF! | K9: 15028168 | L9: =Base!#REF! -> #REF! | M9: =Base!#REF! -> #REF! | N9: =Base!#REF! -> #REF! | O9: =Base!#REF! -> #REF! | P9: =Base!#REF! -> #REF! | Q9: =Base!#REF! -> #REF! | R9: Doña | S9: Maria Soledad Lascar | T9: 23061 | U9: 1972,12 | V9: Santiago
A10: 9 | B10: 8 | C10: Julio | D10: 2019 | E10: =Base!#REF! -> #REF! | F10: =DAY(E10) -> #REF! | G10: =TEXT(E10,"mmmm") -> #REF! | H10: =YEAR(E10) -> #REF! | I10: Don | J10: =Base!#REF!&" "&Base!#REF!&" "&Base!#REF! -> #REF! | K10: 11619168 | L10: =Base!#REF! -> #REF! | M10: =Base!#REF! -> #REF! | N10: =Base!#REF! -> #REF! | O10: =Base!#REF! -> #REF! | P10: =Base!#REF! -> #REF! | Q10: =Base!#REF! -> #REF! | R10: Don | S10: Ruben Reinoso Herrera | T10: 4236 | U10: 2295,88 | V10: La Serena
A11: 10 | B11: 8 | C11: Julio | D11: 2019 | E11: =Base!#REF! -> #REF! | F11: =DAY(E11) -> #REF! | G11: =TEXT(E11,"mmmm") -> #REF! | H11: =YEAR(E11) -> #REF! | I11: Doña | J11: =Base!#REF!&" "&Base!#REF!&" "&Base!#REF! -> #REF! | K11: 10083891 | L11: =Base!#REF! -> #REF! | M11: =Base!#REF! -> #REF! | N11: =Base!#REF! -> #REF! | O11: =Base!#REF! -> #REF! | P11: =Base!#REF! -> #REF! | Q11: =Base!#REF! -> #REF! | R11: Doña | S11: Maria Soledad Lascar | T11: 25520 | U11: 2533,70 | V11: Santiago
A12: 11 | B12: 8 | C12: Julio | D12: 2019 | E12: =Base!#REF! -> #REF! | F12: =DAY(E12) -> #REF! | G12: =TEXT(E12,"mmmm") -> #REF! | H12: =YEAR(E12) -> #REF! | I12: Doña | J12: =Base!#REF!&" "&Base!#REF!&" "&Base!#REF! -> #REF! | K12: 9612906 | L12: =Base!#REF! -> #REF! | M12: =Base!#REF! -> #REF! | N12: =Base!#REF! -> #REF! | O12: =Base!#REF! -> #REF! | P12: =Base!#REF! -> #REF! | Q12: =Base!#REF! -> #REF! | R12: Doña | S12: Maria Soledad Lascar | T12: 25605 | U12: 2728,43 | V12: Santiago
A13: 12 | B13: 8 | C13: Julio | D13: 2019 | E13: =Base!#REF! -> #REF! | F13: =DAY(E13) -> #REF! | G13: =TEXT(E13,"mmmm") -> #REF! | H13: =YEAR(E13) -> #REF! | I13: Don | J13: =Base!#REF!&" "&Base!#REF!&" "&Base!#REF! -> #REF! | K13: 17794314 | L13: =Base!#REF! -> #REF! | M13: =Base!#REF! -> #REF! | N13: =Base!#REF! -> #REF! | O13: =Base!#REF! -> #REF! | P13: =Base!#REF! -> #REF! | Q13: =Base!#REF! -> #REF! | R13: Doña | S13: Maria Soledad Lascar | T13: 25633 | U13: 2476,26 | V13: Santiago
A14: 13 | B14: 8 | C14: Julio | D14: 2019 | E14: =Base!#REF! -> #REF! | F14: =DAY(E14) -> #REF! | G14: =TEXT(E14,"mmmm") -> #REF! | H14: =YEAR(E14) -> #REF! | I14: Don | J14: =Base!#REF!&" "&Base!#REF!&" "&Base!#REF! -> #REF! | K14: 12739972 | L14: =Base!#REF! -> #REF! | M14: =Base!#REF! -> #REF! | N14: =Base!#REF! -> #REF! | O14: =Base!#REF! -> #REF! | P14: =Base!#REF! -> #REF! | Q14: =Base!#REF! -> #REF! | R14: Doña | S14: Esmirna Vidal Moraga | T14: 2904 | U14: 1160,37 | V14: Temuco
A15: 14 | B15: 8 | C15: Julio | D15: 2019 | E15: =Base!#REF! -> #REF! | F15: =DAY(E15) -> #REF! | G15: =TEXT(E15,"mmmm") -> #REF! | H15: =YEAR(E15) -> #REF! | I15: Don | J15: =Base!#REF!&" "&Base!#REF!&" "&Base!#REF! -> #REF! | K15: 16147502 | L15: =Base!#REF! -> #REF! | M15: =Base!#REF! -> #REF! | N15: =Base!#REF! -> #REF! | O15: =Base!#REF! -> #REF! | P15: =Base!#REF! -> #REF! | Q15: =Base!#REF! -> #REF! | R15: Doña | S15: Maria Soledad Lascar | T15: 25868 | U15: 1900,39 | V15: Santiago
A16: 15 | B16: 8 | C16: Julio | D16: 2019 | E16: =Base!#REF! -> #REF! | F16: =DAY(E16) -> #REF! | G16: =TEXT(E16,"mmmm") -> #REF! | H16: =YEAR(E16) -> #REF! | I16: Doña | J16: =Base!#REF!&" "&Base!#REF!&" "&Base!#REF! -> #REF! | K16: 23697529 | L16: =Base!#REF! -> #REF! | M16: =Base!#REF! -> #REF! | N16: =Base!#REF! -> #REF! | O16: =Base!#REF! -> #REF! | P16: =Base!#REF! -> #REF! | Q16: =Base!#REF! -> #REF! | R16: Doña | S16: Maria Soledad Lascar | T16: 26037 | U16: 1814,58 | V16: Santiago
A17: 16 | B17: 8 | C17: Julio | D17: 2019 | E17: =Base!#REF! -> #REF! | F17: =DAY(E17) -> #REF! | G17: =TEXT(E17,"mmmm") -> #REF! | H17: =YEAR(E17) -> #REF! | I17: Doña | J17: =Base!#REF!&" "&Base!#REF!&" "&Base!#REF! -> #REF! | K17: 19074840 | L17: =Base!#REF! -> #REF! | M17: =Base!#REF! -> #REF! | N17: =Base!#REF! -> #REF! | O17: =Base!#REF! -> #REF! | P17: =Base!#REF! -> #REF! | Q17: =Base!#REF! -> #REF! | R17: Doña | S17: Esmirna Vidal Moraga | T17: 2692 | U17: 1168,03 | V17: Temuco
A18: 17 | B18: 8 | C18: Julio | D18: 2019 | E18: =Base!#REF! -> #REF! | F18: =DAY(E18) -> #REF! | G18: =TEXT(E18,"mmmm") -> #REF! | H18: =YEAR(E18) -> #REF! | I18: Don | J18: =Base!#REF!&" "&Base!#REF!&" "&Base!#REF! -> #REF! | K18: 17758777 | L18: =Base!#REF! -> #REF! | M18: =Base!#REF! -> #REF! | N18: =Base!#REF! -> #REF! | O18: =Base!#REF! -> #REF! | P18: =Base!#REF! -> #REF! | Q18: =Base!#REF! -> #REF! | R18: Don | S18: Juan Loyola Opazo | T18: 2979 | U18: 1526,22 | V18: Temuco
A19: 18 | B19: 8 | C19: Julio | D19: 2019 | E19: =Base!#REF! -> #REF! | F19: =DAY(E19) -> #REF! | G19: =TEXT(E19,"mmmm") -> #REF! | H19: =YEAR(E19) -> #REF! | I19: Doña | J19: =Base!#REF!&" "&Base!#REF!&" "&Base!#REF! -> #REF! | K19: 10679812 | L19: =Base!#REF! -> #REF! | M19: =Base!#REF! -> #REF! | N19: =Base!#REF! -> #REF! | O19: =Base!#REF! -> #REF! | P19: =Base!#REF! -> #REF! | Q19: =Base!#REF! -> #REF! | R19: Doña | S19: Elena Leyton Carvajal | T19: 1816 | U19: 1747,94 | V19: La Serena
A20: 19 | B20: 8 | C20: Julio | D20: 2019 | E20: =Base!#REF! -> #REF! | F20: =DAY(E20) -> #REF! | G20: =TEXT(E20,"mmmm") -> #REF! | H20: =YEAR(E20) -> #REF! | I20: Don | J20: =Base!#REF!&" "&Base!#REF!&" "&Base!#REF! -> #REF! | K20: 15373272 | L20: =Base!#REF! -> #REF! | M20: =Base!#REF! -> #REF! | N20: =Base!#REF! -> #REF! | O20: =Base!#REF! -> #REF! | P20: =Base!#REF! -> #REF! | Q20: =Base!#REF! -> #REF! | R20: Don | S20: Carlos Miranda Jimenez | T20: 3700 | U20: 3746,14 | V20: Concepción
... A49: 48 | B49: 8 | C49: Julio | D49: 2019 | E49: =Base!#REF! -> #REF! | F49: =DAY(E49) -> #REF! | G49: =TEXT(E49,"mmmm") -> #REF! | H49: =YEAR(E49) -> #REF! | I49: Doña | J49: =Base!#REF!&" "&Base!#REF!&" "&Base!#REF! -> #REF! | K49: 17144755 | L49: =Base!#REF! -> #REF! | M49: =Base!#REF! -> #REF! | N49: =Base!#REF! -> #REF! | O49: =Base!#REF! -> #REF! | P49: =Base!#REF! -> #REF! | Q49: =Base!#REF! -> #REF! | R49: Don | S49: Teodoro Duran Palma | T49: 3176 | U49: 840,76 | V49: Talca
